Workbook

Sheet Trades
A1: window_id | B1: stock1 | C1: stock2 | D1: entry_minute | E1: entry_timestamp | F1: entry_price_1 | G1: entry_price_2 | H1: entry_price_1_slipped | I1: entry_price_2_slipped | J1: entry_zscore | K1: hedge_ratio_entry | L1: position_size_1 | M1: position_size_2 | N1: direction | O1: holding_minutes | P1: exit_reason | Q1: exit_minute | R1: exit_timestamp | S1: exit_price_1 | T1: exit_price_2 | U1: exit_zscore | V1: gross_pnl | W1: gross_pnl_slipped | X1: transaction_costs | Y1: cfd_financing | Z1: net_pnl | AA1: exit_price_age_1 | AB1: exit_price_age_2 | AC1: exit_price_age_3 | AD1: market open | AE1: time since market open
A2: 0 | B2: XOM | C2: PSX | D2: 24473 | E2: 45960.76 | F2: 115.98 | G2: 138.85 | H2: 115.9684 | I2: 138.86389 | J2: 3.5371 | K2: 0.6000914 | L2: -862.21762 | M2: 432.18682 | N2: SHORT | O2: =(Table8[[#This Row],[exit_timestamp]]-Table8[[#This Row],[entry_timestamp]])*1440 -> 8 | P2: signal | Q2: 24481 | R2: 45960.765 | S2: 115.79 | T2: 138.93 | U2: 0.32285626 | V2: 198.39629 | W2: 166.40739 | X2: 0 | Y2: 12.944044 | Z2: 153.46335 | AA2: 0 | AB2: 0 | AC2: =TEXT(E2,"dddd") -> Thursday | AD2: =INT(E2)+TIME(14,30,0) -> 45960.604 | AE2: =(E2-AD2)*1440 -> 224 | AG2: Average early winner | AH2: =AVERAGEIFS(Z:Z,AE:AE,"<=10",Z:Z,">0") -> 570.67884
A3: 0 | B3: XOM | C3: PSX | D3: 24579 | E3: 45961.604 | F3: 113.765 | G3: 137.19 | H3: 113.77638 | I3: 137.17628 | J3: -4.250111 | K3: 0.6000914 | L3: 879.00497 | M3: -437.41628 | N3: LONG | O3: =(Table8[[#This Row],[exit_timestamp]]-Table8[[#This Row],[entry_timestamp]])*1440 -> -54 | P3: signal | Q3: 24585 | R3: 45961.567 | S3: 114 | T3: 135.72 | U3: 0.27504599 | V3: 849.5681 | W3: 817.60992 | X3: 0 | Y3: 13.164212 | Z3: 804.4457 | AA3: 0 | AB3: 2 | AC3: =TEXT(E3,"dddd") -> Friday | AD3: =INT(E3)+TIME(14,30,0) -> 45961.604 | AE3: =(E3-AD3)*1440 -> 0 | AG3: Average early loser | AH3: =AVERAGEIFS(Z:Z,AE:AE,"<=10",Z:Z,"<0") -> -441.76439
A4: 0 | B4: XOM | C4: PSX | D4: 24969 | E4: 45964.604 | F4: 114.475 | G4: 137.13 | H4: 114.48645 | I4: 137.11629 | J4: -3.72219 | K4: 0.6000914 | L4: 873.55318 | M4: -437.60767 | N4: LONG | O4: =(Table8[[#This Row],[exit_timestamp]]-Table8[[#This Row],[entry_timestamp]])*1440 -> 5 | P4: signal | Q4: 24974 | R4: 45964.608 | S4: 114.18 | T4: 135.39 | U4: -0.093952476 | V4: 503.73916 | W4: 471.83924 | X4: 0 | Y4: 13.111608 | Z4: 458.72763 | AA4: 0 | AB4: 0 | AC4: =TEXT(E4,"dddd") -> Monday | AD4: =INT(E4)+TIME(14,30,0) -> 45964.604 | AE4: =(E4-AD4)*1440 -> -1.0477379e-08
A5: 0 | B5: XOM | C5: PSX | D5: 25119 | E5: 45964.708 | F5: 114.235 | G5: 135.93 | H5: 114.24642 | I5: 135.91641 | J5: -3.5526752 | K5: 0.6000914 | L5: 875.38845 | M5: -441.4709 | N5: LONG | O5: =(Table8[[#This Row],[exit_timestamp]]-Table8[[#This Row],[entry_timestamp]])*1440 -> 14 | P5: signal | Q5: 25133 | R5: 45964.718 | S5: 114.44 | T5: 136.04 | U5: -0.31514174 | V5: 130.89283 | W5: 98.868204 | X5: 0 | Y5: 13.168594 | Z5: 85.699611 | AA5: 0 | AB5: 1 | AC5: =TEXT(E5,"dddd") -> Monday | AD5: =INT(E5)+TIME(14,30,0) -> 45964.604 | AE5: =(E5-AD5)*1440 -> 150 | AG5: Average later winner | AH5: =AVERAGEIFS(Z:Z,AE:AE,">10",Z:Z,">0") -> 225.43317
A6: 0 | B6: XOM | C6: PSX | D6: 25359 | E6: 45965.604 | F6: 113.59 | G6: 135.04 | H6: 113.57864 | I6: 135.0535 | J6: 4.7787487 | K6: 0.6000914 | L6: -880.35919 | M6: 444.38048 | N6: SHORT | O6: =(Table8[[#This Row],[exit_timestamp]]-Table8[[#This Row],[entry_timestamp]])*1440 -> 19 | P6: signal | Q6: 25378 | R6: 45965.617 | S6: 112.89 | T6: 134.45 | U6: 0.29820064 | V6: 354.06695 | W6: 322.15297 | X6: 0 | Y6: 13.247397 | Z6: 308.90557 | AA6: 0 | AB6: 0 | AC6: =TEXT(E6,"dddd") -> Tuesday | AD6: =INT(E6)+TIME(14,30,0) -> 45965.604 | AE6: =(E6-AD6)*1440 -> -1.0477379e-08 | AG6: Average later loser | AH6: =AVERAGEIFS(Z:Z,AE:AE,">10",Z:Z,"<0") -> -205.03526
A7: 0 | B7: XOM | C7: PSX | D7: 26048 | E7: 45966.812 | F7: 114.35 | G7: 135.92 | H7: 114.33857 | I7: 135.93359 | J7: 3.9356146 | K7: 0.6000914 | L7: -874.50809 | M7: 441.50338 | N7: SHORT | O7: =(Table8[[#This Row],[exit_timestamp]]-Table8[[#This Row],[entry_timestamp]])*1440 -> 10 | P7: signal | Q7: 26058 | R7: 45966.819 | S7: 114.05 | T7: 136.065 | U7: 0.0053672066 | V7: 326.37042 | W7: 294.38842 | X7: 0 | Y7: 13.160115 | Z7: 281.22831 | AA7: 0 | AB7: 0 | AC7: =TEXT(E7,"dddd") -> Wednesday | AD7: =INT(E7)+TIME(14,30,0) -> 45966.604 | AE7: =(E7-AD7)*1440 -> 299
A8: 0 | B8: XOM | C8: PSX | D8: 26142 | E8: 45967.605 | F8: 113.81 | G8: 137.595 | H8: 113.82138 | I8: 137.58124 | J8: -3.9977948 | K8: 0.6000914 | L8: 878.65741 | M8: -436.12878 | N8: LONG | O8: =(Table8[[#This Row],[exit_timestamp]]-Table8[[#This Row],[entry_timestamp]])*1440 -> 26 | P8: signal | Q8: 26168 | R8: 45967.623 | S8: 114.61 | T8: 139.61 | U8: -0.31825981 | V8: -175.87356 | W8: -208.03356 | X8: 0 | Y8: 13.147862 | Z8: -221.18143 | AA8: 0 | AB8: 0 | AC8: =TEXT(E8,"dddd") -> Thursday | AD8: =INT(E8)+TIME(14,30,0) -> 45967.604 | AE8: =(E8-AD8)*1440 -> 1 | AG8: Overall PF | AH8: =SUMIF(Z:Z,">0",Z:Z)/ABS(SUMIF(Z:Z,"<0",Z:Z)) -> 2.028852
A9: 0 | B9: XOM | C9: PSX | D9: 26919 | E9: 45968.874 | F9: 117.19 | G9: 137.81 | H9: 117.20172 | I9: 137.79622 | J9: -3.5891554 | K9: 0.6000914 | L9: 853.31513 | M9: -435.44837 | N9: LONG | O9: =(Table8[[#This Row],[exit_timestamp]]-Table8[[#This Row],[entry_timestamp]])*1440 -> 3932 | P9: signal | Q9: 26921 | R9: 45971.604 | S9: 117.255 | T9: 137.445 | U9: 0.32409789 | V9: 214.40414 | W9: 182.41266 | X9: 0 | Y9: 12.887635 | Z9: 169.52502 | AA9: 3931 | AB9: 0 | AC9: =TEXT(E9,"dddd") -> Friday | AD9: =INT(E9)+TIME(14,30,0) -> 45968.604 | AE9: =(E9-AD9)*1440 -> 388 | AG9: early PF | AH9: =SUMIFS(Z:Z,Z:Z,">0",AE:AE,"<=10")/ABS(SUMIFS(Z:Z,Z:Z,"<0",AE:AE,"<=10")) -> 1.8454531
A10: 0 | B10: XOM | C10: PSX | D10: 26929 | E10: 45971.61 | F10: 116.21 | G10: 136.64 | H10: 116.22162 | I10: 136.62634 | J10: -3.5199101 | K10: 0.6000914 | L10: 860.51114 | M10: -439.17696 | N10: LONG | O10: =(Table8[[#This Row],[exit_timestamp]]-Table8[[#This Row],[entry_timestamp]])*1440 -> 25 | P10: signal | Q10: 26954 | R10: 45971.627 | S10: 115.75 | T10: 136.67 | U10: -0.37814933 | V10: -409.01043 | W10: -440.974 | X10: 0 | Y10: 12.996881 | Z10: -453.97088 | AA10: 0 | AB10: 0 | AC10: =TEXT(E10,"dddd") -> Monday | AD10: =INT(E10)+TIME(14,30,0) -> 45971.604 | AE10: =(E10-AD10)*1440 -> 8 | AG10: later PF | AH10: =SUMIFS(Z:Z,Z:Z,">0",AE:AE,">10")/ABS(SUMIFS(Z:Z,Z:Z,"<0",AE:AE,">10")) -> 2.8586607
A11: 0 | B11: XOM | C11: PSX | D11: 27521 | E11: 45972.75 | F11: 120.23 | G11: 142.635 | H11: 120.24202 | I11: 142.62074 | J11: -3.7233017 | K11: 0.6000914 | L11: 831.73917 | M11: -420.71819 | N11: LONG | O11: =(Table8[[#This Row],[exit_timestamp]]-Table8[[#This Row],[entry_timestamp]])*1440 -> 13 | P11: signal | Q11: 27534 | R11: 45972.759 | S11: 120.31 | T11: 142.33 | U11: 0.12835184 | V11: 194.85818 | W11: 162.86253 | X11: 0 | Y11: 12.524574 | Z11: 150.33796 | AA11: 0 | AB11: 0 | AC11: =TEXT(E11,"dddd") -> Tuesday | AD11: =INT(E11)+TIME(14,30,0) -> 45972.604 | AE11: =(E11-AD11)*1440 -> 210 | AG11: overall PF no 2k loss | AH11: =SUMIF(Z:Z,">0",Z:Z)/ABS(SUMIF(Z:Z,"<0",Z:Z)-MIN(Z:Z)) -> 2.4713189
A12: 0 | B12: XOM | C12: PSX | D12: 27703 | E12: 45973.605 | F12: 118.99 | G12: 140.56 | H12: 119.0019 | I12: 140.54594 | J12: -4.666632 | K12: 0.6000914 | L12: 840.40676 | M12: -426.929 | N12: LONG | O12: =(Table8[[#This Row],[exit_timestamp]]-Table8[[#This Row],[entry_timestamp]])*1440 -> 29 | P12: signal | Q12: 27732 | R12: 45973.625 | S12: 118.385 | T12: 140.41 | U12: -0.27059819 | V12: -444.40674 | W12: -476.35132 | X12: 0 | Y12: 12.673358 | Z12: -489.02468 | AA12: 0 | AB12: 0 | AC12: =TEXT(E12,"dddd") -> Wednesday | AD12: =INT(E12)+TIME(14,30,0) -> 45973.604 | AE12: =(E12-AD12)*1440 -> 1 | AG12: early PF no 2k loss | AH12: =SUMIFS(Z:Z,Z:Z,">0",AE:AE,"<=10")/ABS(SUMIFS(Z:Z,Z:Z,"<0",AE:AE,"<=10")-_xlfn.MINIFS(Z:Z,AE:AE,"<=10")) -> 2.3617605
A13: 1 | B13: MPC | C13: VLO | D13: 28242 | E13: 45974.708 | F13: 197.25 | G13: 177.885 | H13: 197.26972 | I13: 177.86721 | J13: -3.8222828 | K13: 0.74400122 | L13: 506.97085 | M13: -418.24843 | N13: LONG | O13: =(Table8[[#This Row],[exit_timestamp]]-Table8[[#This Row],[entry_timestamp]])*1440 -> 18 | P13: signal | Q13: 28260 | R13: 45974.721 | S13: 197.4 | T13: 177.71 | U13: -0.35008483 | V13: 149.2391 | W13: 114.35879 | X13: 0 | Y13: 9.2521928 | Z13: 105.1066 | AA13: 8 | AB13: 0 | AC13: =TEXT(E13,"dddd") -> Thursday | AD13: =INT(E13)+TIME(14,30,0) -> 45974.604 | AE13: =(E13-AD13)*1440 -> 150
A14: 1 | B14: MPC | C14: VLO | D14: 28284 | E14: 45974.738 | F14: 197 | G14: 177.81 | H14: 197.0197 | I14: 177.79222 | J14: -3.5148436 | K14: 0.74400122 | L14: 507.61421 | M14: -418.42485 | N14: LONG | O14: =(Table8[[#This Row],[exit_timestamp]]-Table8[[#This Row],[entry_timestamp]])*1440 -> 20 | P14: signal | Q14: 28304 | R14: 45974.751 | S14: 196.78 | T14: 177.43 | U14: -0.48620068 | V14: 47.326315 | W14: 12.473358 | X14: 0 | Y14: 9.2603906 | Z14: 3.2129677 | AA14: 3 | AB14: 3 | AC14: =TEXT(E14,"dddd") -> Thursday | AD14: =INT(E14)+TIME(14,30,0) -> 45974.604 | AE14: =(E14-AD14)*1440 -> 192
A15: 1 | B15: MPC | C15: VLO | D15: 28872 | E15: 45978.604 | F15: 197.88 | G15: 181.15 | H15: 197.89979 | I15: 181.13189 | J15: -4.8288594 | K15: 0.74400122 | L15: 505.35678 | M15: -410.71003 | N15: LONG | O15: =(Table8[[#This Row],[exit_timestamp]]-Table8[[#This Row],[entry_timestamp]])*1440 -> 18 | P15: signal | Q15: 28890 | R15: 45978.617 | S15: 198.03 | T15: 181.65 | U15: -0.26763876 | V15: -129.5515 | W15: -164.45964 | X15: 0 | Y15: 9.1606681 | Z15: -173.62031 | AA15: 0 | AB15: 0 | AC15: =TEXT(E15,"dddd") -> Monday | AD15: =INT(E15)+TIME(14,30,0) -> 45978.604 | AE15: =(E15-AD15)*1440 -> -1.0477379e-08
A16: 1 | B16: MPC | C16: VLO | D16: 29264 | E16: 45979.606 | F16: 197.315 | G16: 179.195 | H16: 197.29527 | I16: 179.21292 | J16: 3.7196131 | K16: 0.74400122 | L16: -506.80384 | M16: 415.19084 | N16: SHORT | O16: =(Table8[[#This Row],[exit_timestamp]]-Table8[[#This Row],[entry_timestamp]])*1440 -> 2 | P16: signal | Q16: 29266 | R16: 45979.607 | S16: 197.315 | T16: 180.135 | U16: 0.37237201 | V16: 390.27939 | W16: 355.36033 | X16: 0 | Y16: 9.2199468 | Z16: 346.14039 | AA16: 0 | AB16: 0 | AC16: =TEXT(E16,"dddd") -> Tuesday | AD16: =INT(E16)+TIME(14,30,0) -> 45979.604 | AE16: =(E16-AD16)*1440 -> 2
A17: 1 | B17: MPC | C17: VLO | D17: 29654 | E17: 45980.605 | F17: 193.33 | G17: 179.17 | H17: 193.34933 | I17: 179.15208 | J17: -4.2799968 | K17: 0.74400122 | L17: 517.2503 | M17: -415.24877 | N17: LONG | O17: =(Table8[[#This Row],[exit_timestamp]]-Table8[[#This Row],[entry_timestamp]])*1440 -> 4 | P17: signal | Q17: 29658 | R17: 45980.608 | S17: 192.99 | T17: 177.47 | U17: -0.13015378 | V17: 530.05781 | W17: 495.26596 | X17: 0 | Y17: 9.3249907 | Z17: 485.94097 | AA17: 0 | AB17: 0 | AC17: =TEXT(E17,"dddd") -> Wednesday | AD17: =INT(E17)+TIME(14,30,0) -> 45980.604 | AE17: =(E17-AD17)*1440 -> 1
A18: 1 | B18: MPC | C18: VLO | D18: 30043 | E18: 45981.604 | F18: 194.56 | G18: 176.91 | H18: 194.54054 | I18: 176.92769 | J18: 4.5088765 | K18: 0.74400122 | L18: -513.98026 | M18: 420.55351 | N18: SHORT | O18: =(Table8[[#This Row],[exit_timestamp]]-Table8[[#This Row],[entry_timestamp]])*1440 -> 4 | P18: signal | Q18: 30047 | R18: 45981.607 | S18: 194.64 | T18: 178.57 | U18: 0.36065798 | V18: 657.00041 | W18: 622.04646 | X18: 0 | Y18: 9.3453378 | Z18: 612.70113 | AA18: 0 | AB18: 0 | AC18: =TEXT(E18,"dddd") -> Thursday | AD18: =INT(E18)+TIME(14,30,0) -> 45981.604 | AE18: =(E18-AD18)*1440 -> -1.0477379e-08
A19: 1 | B19: MPC | C19: VLO | D19: 30399 | E19: 45981.851 | F19: 189.76 | G19: 172.77 | H19: 189.77898 | I19: 172.75272 | J19: -3.733946 | K19: 0.74400122 | L19: 526.98145 | M19: -430.63102 | N19: LONG | O19: =(Table8[[#This Row],[exit_timestamp]]-Table8[[#This Row],[entry_timestamp]])*1440 -> 3 | P19: signal | Q19: 30402 | R19: 45981.853 | S19: 189.76 | T19: 172.24 | U19: -0.27390705 | V19: 228.23444 | W19: 193.37724 | X19: 0 | Y19: 9.5761247 | Z19: 183.80112 | AA19: 0 | AB19: 0 | AC19: =TEXT(E19,"dddd") -> Thursday | AD19: =INT(E19)+TIME(14,30,0) -> 45981.604 | AE19: =(E19-AD19)*1440 -> 356
A20: 2 | B20: XOM | C20: VLO | D20: 32204 | E20: 45992.605 | F20: 116.59 | G20: 177.4 | H20: 116.57834 | I20: 177.41774 | J20: 3.8872681 | K20: 0.36784501 | L20: -857.70649 | M20: 207.35344 | N20: SHORT | O20: =(Table8[[#This Row],[exit_timestamp]]-Table8[[#This Row],[entry_timestamp]])*1440 -> 1 | P20: signal | Q20: 32205 | R20: 45992.606 | S20: 116.46 | T20: 178.41 | U20: 0.12682432 | V20: 320.92882 | W20: 293.56213 | X20: 0 | Y20: 10.650599 | Z20: 282.91153 | AA20: 0 | AB20: 0 | AC20: =TEXT(E20,"dddd") -> Monday | AD20: =INT(E20)+TIME(14,30,0) -> 45992.604 | AE20: =(E20-AD20)*1440 -> 1
A21: 2 | B21: XOM | C21: VLO | D21: 34155 | E21: 45999.604 | F21: 115.5 | G21: 172.15 | H21: 115.51155 | I21: 172.13279 | J21: -4.035499 | K21: 0.36784501 | L21: 865.80087 | M21: -213.67703 | N21: LONG | O21: =(Table8[[#This Row],[exit_timestamp]]-Table8[[#This Row],[entry_timestamp]])*1440 -> 6 | P21: signal | Q21: 34161 | R21: 45999.608 | S21: 115.945 | T21: 172.62 | U21: -0.22128585 | V21: 284.85318 | W21: 257.44771 | X21: 0 | Y21: 10.794779 | Z21: 246.65293 | AA21: 0 | AB21: 1 | AC21: =TEXT(E21,"dddd") -> Monday | AD21: =INT(E21)+TIME(14,30,0) -> 45999.604 | AE21: =(E21-AD21)*1440 -> -1.0477379e-08
A22: 2 | B22: XOM | C22: VLO | D22: 34545 | E22: 46000.604 | F22: 117.48 | G22: 173.21 | H22: 117.46825 | I22: 173.22732 | J22: 4.9944444 | K22: 0.36784501 | L22: -851.20872 | M22: 212.36938 | N22: SHORT | O22: =(Table8[[#This Row],[exit_timestamp]]-Table8[[#This Row],[entry_timestamp]])*1440 -> 32 | P22: signal | Q22: 34577 | R22: 46000.626 | S22: 119.91 | T22: 173.58 | U22: 0.49101009 | V22: -1989.8605 | W22: -2017.4321 | X22: 0 | Y22: 10.635781 | Z22: -2028.0679 | AA22: 0 | AB22: 2 | AC22: =TEXT(E22,"dddd") -> Tuesday | AD22: =INT(E22)+TIME(14,30,0) -> 46000.604 | AE22: =(E22-AD22)*1440 -> -1.0477379e-08
A23: 2 | B23: XOM | C23: VLO | D23: 34935 | E23: 46001.604 | F23: 118.5 | G23: 174.52 | H23: 118.48815 | I23: 174.53745 | J23: 4.7268624 | K23: 0.36784501 | L23: -843.88186 | M23: 210.77527 | N23: SHORT | O23: =(Table8[[#This Row],[exit_timestamp]]-Table8[[#This Row],[entry_timestamp]])*1440 -> 26 | P23: signal | Q23: 34961 | R23: 46001.622 | S23: 118.88 | T23: 174.055 | U23: 0.14350041 | V23: -418.68561 | W23: -446.06477 | X23: 0 | Y23: 10.546571 | Z23: -456.61135 | AA23: 0 | AB23: 0 | AC23: =TEXT(E23,"dddd") -> Wednesday | AD23: =INT(E23)+TIME(14,30,0) -> 46001.604 | AE23: =(E23-AD23)*1440 -> -1.0477379e-08
A24: 2 | B24: XOM | C24: VLO | D24: 35130 | E24: 46001.74 | F24: 119.15 | G24: 176.14 | H24: 119.16191 | I24: 176.12239 | J24: -3.7745396 | K24: 0.36784501 | L24: 839.27822 | M24: -208.83673 | N24: LONG | O24: =(Table8[[#This Row],[exit_timestamp]]-Table8[[#This Row],[entry_timestamp]])*1440 -> 19 | P24: signal | Q24: 35149 | R24: 46001.753 | S24: 119.26 | T24: 176.52 | U24: -0.44079237 | V24: 12.962649 | W24: -14.411419 | X24: 0 | Y24: 10.481149 | Z24: -24.892569 | AA24: 0 | AB24: 0 | AC24: =TEXT(E24,"dddd") -> Wednesday | AD24: =INT(E24)+TIME(14,30,0) -> 46001.604 | AE24: =(E24-AD24)*1440 -> 195
... A66: 12 | B66: CVX | C66: PSX | D66: 72207 | E66: 46141.795 | F66: 191.72 | G66: 174.39 | H66: 191.70083 | I66: 174.40744 | J66: 3.8070158 | K66: 0.71286786 | L66: -521.59399 | M66: 408.77794 | N66: SHORT | O66: =(Table8[[#This Row],[exit_timestamp]]-Table8[[#This Row],[entry_timestamp]])*1440 -> 43 | P66: signal | Q66: 72250 | R66: 46141.825 | S66: 191.16 | T66: 172.12 | U66: 0.18707846 | V66: -635.8333 | W66: -669.96865 | X66: 0 | Y66: 9.3037194 | Z66: -679.27237 | AA66: 1 | AB66: 0 | AC66: =TEXT(E66,"dddd") -> Wednesday | AD66: =INT(E66)+TIME(14,30,0) -> 46141.604 | AE66: =(E66-AD66)*1440 -> 275
A67: 12 | B67: CVX | C67: PSX | D67: 72322 | E67: 46142.604 | F67: 188.88 | G67: 172.295 | H67: 188.89889 | I67: 172.27777 | J67: -4.9768744 | K67: 0.71286786 | L67: 529.43668 | M67: -413.74843 | N67: LONG | O67: =(Table8[[#This Row],[exit_timestamp]]-Table8[[#This Row],[entry_timestamp]])*1440 -> 19 | P67: signal | Q67: 72341 | R67: 46142.617 | S67: 191.975 | T67: 175.73 | U67: -0.4362697 | V67: 217.38066 | W67: 182.81732 | X67: 0 | Y67: 9.4318511 | Z67: 173.38547 | AA67: 0 | AB67: 0 | AC67: =TEXT(E67,"dddd") -> Thursday | AD67: =INT(E67)+TIME(14,30,0) -> 46142.604 | AE67: =(E67-AD67)*1440 -> -1.0477379e-08 | AH67: was 1.30 but changed as DST in this trade!
A68: 12 | B68: CVX | C68: PSX | D68: 72712 | E68: 46143.604 | F68: 191.07 | G68: 178.46 | H68: 191.08911 | I68: 178.44215 | J68: -4.1504488 | K68: 0.71286786 | L68: 523.3684 | M68: -399.45526 | N68: LONG | O68: =(Table8[[#This Row],[exit_timestamp]]-Table8[[#This Row],[entry_timestamp]])*1440 -> 2 | P68: signal | Q68: 72714 | R68: 46143.606 | S68: 193.64 | T68: 178.32 | U68: -0.038092521 | V68: 1400.9805 | W68: 1366.5943 | X68: 0 | Y68: 9.2282366 | Z68: 1357.366 | AA68: 0 | AB68: 0 | AC68: =TEXT(E68,"dddd") -> Friday | AD68: =INT(E68)+TIME(14,30,0) -> 46143.604 | AE68: =(E68-AD68)*1440 -> -1.0477379e-08
A69: 12 | B69: CVX | C69: PSX | D69: 73493 | E69: 46147.605 | F69: 191.09 | G69: 178.75 | H69: 191.10911 | I69: 178.73212 | J69: -4.7311466 | K69: 0.71286786 | L69: 523.31362 | M69: -398.80719 | N69: LONG | O69: =(Table8[[#This Row],[exit_timestamp]]-Table8[[#This Row],[entry_timestamp]])*1440 -> 22 | P69: signal | Q69: 73515 | R69: 46147.62 | S69: 191.61 | T69: 179.42 | U69: 0.055007164 | V69: 4.9222639 | W69: -29.389026 | X69: 0 | Y69: 9.2212082 | Z69: -38.610234 | AA69: 0 | AB69: 0 | AC69: =TEXT(E69,"dddd") -> Tuesday | AD69: =INT(E69)+TIME(14,30,0) -> 46147.604 | AE69: =(E69-AD69)*1440 -> 1
A70: 12 | B70: CVX | C70: PSX | D70: 74276 | E70: 46149.604 | F70: 180.4 | G70: 168.22 | H70: 180.41804 | I70: 168.20318 | J70: -5.1146144 | K70: 0.71286786 | L70: 554.32373 | M70: -423.77117 | N70: LONG | O70: =(Table8[[#This Row],[exit_timestamp]]-Table8[[#This Row],[entry_timestamp]])*1440 -> 15 | P70: signal | Q70: 74291 | R70: 46149.615 | S70: 181.92 | T70: 168.615 | U70: -0.37728469 | V70: 675.18245 | W70: 640.8241 | X70: 0 | Y70: 9.7809489 | Z70: 631.04315 | AA70: 0 | AB70: 2 | AC70: =TEXT(E70,"dddd") -> Thursday | AD70: =INT(E70)+TIME(14,30,0) -> 46149.604 | AE70: =(E70-AD70)*1440 -> -1.0477379e-08
A71: 12 | B71: CVX | C71: PSX | D71: 74669 | E71: 46150.606 | F71: 181.375 | G71: 168.385 | H71: 181.39314 | I71: 168.36816 | J71: -4.4009746 | K71: 0.71286786 | L71: 551.3439 | M71: -423.35592 | N71: LONG | O71: =(Table8[[#This Row],[exit_timestamp]]-Table8[[#This Row],[entry_timestamp]])*1440 -> 3 | P71: signal | Q71: 74672 | R71: 46150.608 | S71: 181.41 | T71: 167.2 | U71: 0.11498237 | V71: 520.9738 | W71: 486.76468 | X71: 0 | Y71: 9.7469982 | Z71: 477.01768 | AA71: 0 | AB71: 0 | AC71: =TEXT(E71,"dddd") -> Friday | AD71: =INT(E71)+TIME(14,30,0) -> 46150.604 | AE71: =(E71-AD71)*1440 -> 2
A72: 14 | B72: COP | C72: OXY | D72: 78971 | E72: 46168.604 | F72: 118.565 | G72: 57.96 | H72: 118.57686 | I72: 57.954204 | J72: -4.3587421 | K72: 0.75386183 | L72: 843.41922 | M72: -1300.6588 | N72: LONG | O72: =(Table8[[#This Row],[exit_timestamp]]-Table8[[#This Row],[entry_timestamp]])*1440 -> 25 | P72: signal | Q72: 78996 | R72: 46168.622 | S72: 119.83 | T72: 58.98 | U72: -0.3136961 | V72: -259.74664 | W72: -295.06324 | X72: 0 | Y72: 21.44078 | Z72: -316.50402 | AA72: 0 | AB72: 0 | AC72: =TEXT(E72,"dddd") -> Tuesday | AD72: =INT(E72)+TIME(14,30,0) -> 46168.604 | AE72: =(E72-AD72)*1440 -> -1.0477379e-08
A73: 14 | B73: COP | C73: OXY | D73: 79363 | E73: 46169.604 | F73: 114.795 | G73: 56 | H73: 114.78352 | I73: 56.0056 | J73: 3.5076662 | K73: 0.75386183 | L73: -871.11808 | M73: 1346.1818 | N73: SHORT | O73: =(Table8[[#This Row],[exit_timestamp]]-Table8[[#This Row],[entry_timestamp]])*1440 -> 31 | P73: signal | Q73: 79394 | R73: 46169.626 | S73: 115.59 | T73: 56.225 | U73: 0.18525492 | V73: -389.64796 | W73: -424.82474 | X73: 0 | Y73: 22.172999 | Z73: -446.99774 | AA73: 0 | AB73: 0 | AC73: =TEXT(E73,"dddd") -> Wednesday | AD73: =INT(E73)+TIME(14,30,0) -> 46169.604 | AE73: =(E73-AD73)*1440 -> -1.0477379e-08
A74: 14 | B74: COP | C74: OXY | D74: 80775 | E74: 46174.768 | F74: 116.1 | G74: 59.075 | H74: 116.11161 | I74: 59.069092 | J74: -3.5422808 | K74: 0.75386183 | L74: 861.32644 | M74: -1276.1097 | N74: LONG | O74: =(Table8[[#This Row],[exit_timestamp]]-Table8[[#This Row],[entry_timestamp]])*1440 -> 17 | P74: signal | Q74: 80792 | R74: 46174.78 | S74: 115.82 | T74: 58.89 | U74: -0.1633968 | V74: -5.0911022 | W74: -40.120614 | X74: 0 | Y74: 21.374362 | Z74: -61.494975 | AA74: 0 | AB74: 0 | AC74: =TEXT(E74,"dddd") -> Monday | AD74: =INT(E74)+TIME(14,30,0) -> 46174.604 | AE74: =(E74-AD74)*1440 -> 236
A75: 14 | B75: COP | C75: OXY | D75: 80931 | E75: 46175.605 | F75: 116.065 | G75: 58.52 | H75: 116.05339 | I75: 58.525852 | J75: 4.223299 | K75: 0.75386183 | L75: -861.58618 | M75: 1288.2123 | N75: SHORT | O75: =(Table8[[#This Row],[exit_timestamp]]-Table8[[#This Row],[entry_timestamp]])*1440 -> 19 | P75: signal | Q75: 80950 | R75: 46175.618 | S75: 116.84 | T75: 59.015 | U75: 0.37396195 | V75: -30.064209 | W75: -65.271985 | X75: 0 | Y75: 21.497985 | Z75: -86.76997 | AA75: 1 | AB75: 0 | AC75: =TEXT(E75,"dddd") -> Tuesday | AD75: =INT(E75)+TIME(14,30,0) -> 46175.604 | AE75: =(E75-AD75)*1440 -> 1
A76: 14 | B76: COP | C76: OXY | D76: 81501 | E76: 46176.727 | F76: 119.52 | G76: 60.47 | H76: 119.50805 | I76: 60.476047 | J76: 3.6388854 | K76: 0.75386183 | L76: -836.68005 | M76: 1246.6708 | N76: SHORT | O76: =(Table8[[#This Row],[exit_timestamp]]-Table8[[#This Row],[entry_timestamp]])*1440 -> 20 | P76: signal | Q76: 81521 | R76: 46176.741 | S76: 119.285 | T76: 60.295 | U76: 0.20365692 | V76: -21.547576 | W76: -56.583334 | X76: 0 | Y76: 20.833508 | Z76: -77.416842 | AA76: 0 | AB76: 0 | AC76: =TEXT(E76,"dddd") -> Wednesday | AD76: =INT(E76)+TIME(14,30,0) -> 46176.604 | AE76: =(E76-AD76)*1440 -> 177
A77: 14 | B77: COP | C77: OXY | D77: 81716 | E77: 46177.604 | F77: 117.95 | G77: 58.64 | H77: 117.9382 | I77: 58.645864 | J77: 3.5236732 | K77: 0.75386183 | L77: -847.81687 | M77: 1285.5761 | N77: SHORT | O77: =(Table8[[#This Row],[exit_timestamp]]-Table8[[#This Row],[entry_timestamp]])*1440 -> 25 | P77: signal | Q77: 81741 | R77: 46177.622 | S77: 118.38 | T77: 58.44 | U77: 0.49579825 | V77: -621.67648 | W77: -656.76446 | X77: 0 | Y77: 21.33393 | Z77: -678.09839 | AA77: 0 | AB77: 0 | AC77: =TEXT(E77,"dddd") -> Thursday | AD77: =INT(E77)+TIME(14,30,0) -> 46177.604 | AE77: =(E77-AD77)*1440 -> -1.0477379e-08
A78: 14 | B78: COP | C78: OXY | D78: 81978 | E78: 46177.786 | F78: 118.75 | G78: 58.43 | H78: 118.76188 | I78: 58.424157 | J78: -4.1258414 | K78: 0.75386183 | L78: 842.10526 | M78: -1290.1965 | N78: LONG | O78: =(Table8[[#This Row],[exit_timestamp]]-Table8[[#This Row],[entry_timestamp]])*1440 -> 23 | P78: signal | Q78: 82001 | R78: 46177.802 | S78: 118.9 | T78: 58.51 | U78: -0.054157033 | V78: 23.100068 | W78: -12.000122 | X78: 0 | Y78: 21.323018 | Z78: -33.32314 | AA78: 0 | AB78: 0 | AC78: =TEXT(E78,"dddd") -> Thursday | AD78: =INT(E78)+TIME(14,30,0) -> 46177.604 | AE78: =(E78-AD78)*1440 -> 262
A79: 14 | B79: COP | C79: OXY | D79: 82497 | E79: 46181.605 | F79: 118.24 | G79: 57.45 | H79: 118.22818 | I79: 57.455745 | J79: 3.5356335 | K79: 0.75386183 | L79: -845.73748 | M79: 1312.2051 | N79: SHORT | O79: =(Table8[[#This Row],[exit_timestamp]]-Table8[[#This Row],[entry_timestamp]])*1440 -> 3 | P79: forced | Q79: 82500 | R79: 46181.607 | S79: 118.27 | T79: 57.335 | V79: -176.27571 | W79: -211.34039 | X79: 0 | Y79: 21.579426 | Z79: -232.91982 | AA79: 0 | AB79: 0 | AC79: =TEXT(E79,"dddd") -> Monday | AD79: =INT(E79)+TIME(14,30,0) -> 46181.604 | AE79: =(E79-AD79)*1440 -> 1
A80: 16 | B80: CVX | C80: OXY | D80: 87588 | E80: 46199.604 | F80: 171.89 | G80: 50.77 | H80: 171.87281 | I80: 50.775077 | J80: 3.83551 | K80: 0.72444379 | L80: -581.76741 | M80: 1426.9131 | N80: SHORT | O80: =(Table8[[#This Row],[exit_timestamp]]-Table8[[#This Row],[entry_timestamp]])*1440 -> 11 | P80: signal | Q80: 87599 | R80: 46199.612 | S80: 170.91 | T80: 50.545 | U80: 0.37643066 | V80: 249.07661 | W80: 214.67685 | X80: 0 | Y80: 20.086805 | Z80: 194.59005 | AA80: 0 | AB80: 0 | AC80: =TEXT(E80,"dddd") -> Friday | AD80: =INT(E80)+TIME(14,30,0) -> 46199.604 | AE80: =(E80-AD80)*1440 -> -1.0477379e-08
A81: 16 | B81: CVX | C81: OXY | D81: 88142 | E81: 46202.718 | F81: 169.3 | G81: 49.85 | H81: 169.28307 | I81: 49.854985 | J81: 3.860869 | K81: 0.72444379 | L81: -590.66745 | M81: 1453.2473 | N81: SHORT | O81: =(Table8[[#This Row],[exit_timestamp]]-Table8[[#This Row],[entry_timestamp]])*1440 -> 2 | P81: signal | Q81: 88144 | R81: 46202.719 | S81: 169.21 | T81: 49.915 | U81: 0.2904448 | V81: 147.62115 | W81: 113.12814 | X81: 0 | Y81: 20.439148 | Z81: 92.688994 | AA81: 0 | AB81: 0 | AC81: =TEXT(E81,"dddd") -> Monday | AD81: =INT(E81)+TIME(14,30,0) -> 46202.604 | AE81: =(E81-AD81)*1440 -> 164
A82: 16 | B82: CVX | C82: OXY | D82: 88359 | E82: 46202.869 | F82: 168.88 | G82: 49.21 | H82: 168.86311 | I82: 49.214921 | J82: 3.6250364 | K82: 0.72444379 | L82: -592.13643 | M82: 1472.1475 | N82: SHORT | O82: =(Table8[[#This Row],[exit_timestamp]]-Table8[[#This Row],[entry_timestamp]])*1440 -> 1064 | P82: signal | Q82: 88373 | R82: 46203.608 | S82: 169.19 | T82: 49.5 | U82: -0.49331685 | V82: 243.36049 | W82: 208.81056 | X82: 0 | Y82: 20.642839 | Z82: 188.16772 | AA82: 0 | AB82: 0 | AC82: =TEXT(E82,"dddd") -> Monday | AD82: =INT(E82)+TIME(14,30,0) -> 46202.604 | AE82: =(E82-AD82)*1440 -> 381
A83: 16 | B83: CVX | C83: OXY | D83: 88760 | E83: 46204.605 | F83: 166.28 | G83: 48.45 | H83: 166.26337 | I83: 48.454845 | J83: 3.9236625 | K83: 0.72444379 | L83: -601.39524 | M83: 1495.24 | N83: SHORT | O83: =(Table8[[#This Row],[exit_timestamp]]-Table8[[#This Row],[entry_timestamp]])*1440 -> 20 | P83: signal | Q83: 88780 | R83: 46204.619 | S83: 166.5 | T83: 48.445 | U83: 0.36516037 | V83: -139.78315 | W83: -174.28451 | X83: 0 | Y83: 20.966353 | Z83: -195.25086 | AA83: 0 | AB83: 0 | AC83: =TEXT(E83,"dddd") -> Wednesday | AD83: =INT(E83)+TIME(14,30,0) -> 46204.604 | AE83: =(E83-AD83)*1440 -> 1
A84: 16 | B84: CVX | C84: OXY | D84: 89149 | E84: 46205.604 | F84: 168.05 | G84: 48.43 | H84: 168.0332 | I84: 48.434843 | J84: 4.7332451 | K84: 0.72444379 | L84: -595.06099 | M84: 1495.8575 | N84: SHORT | O84: =(Table8[[#This Row],[exit_timestamp]]-Table8[[#This Row],[entry_timestamp]])*1440 -> 21 | P84: signal | Q84: 89170 | R84: 46205.619 | S84: 169.14 | T84: 48.93 | U84: 0.4371205 | V84: 99.312274 | W84: 64.683744 | X84: 0 | Y84: 20.909185 | Z84: 43.774559 | AA84: 0 | AB84: 0 | AC84: =TEXT(E84,"dddd") -> Thursday | AD84: =INT(E84)+TIME(14,30,0) -> 46205.604 | AE84: =(E84-AD84)*1440 -> -1.0477379e-08
A85: 16 | B85: CVX | C85: OXY | D85: 89430 | E85: 46205.799 | F85: 168.04 | G85: 48.48 | H85: 168.0568 | I85: 48.475152 | J85: -4.0112115 | K85: 0.72444379 | L85: 595.09641 | M85: -1494.3148 | N85: LONG | O85: =(Table8[[#This Row],[exit_timestamp]]-Table8[[#This Row],[entry_timestamp]])*1440 -> 15 | P85: signal | Q85: 89445 | R85: 46205.81 | S85: 168.46 | T85: 48.57 | U85: -0.4559868 | V85: 115.45216 | W85: 80.924843 | X85: 0 | Y85: 20.894112 | Z85: 60.030732 | AA85: 0 | AB85: 0 | AC85: =TEXT(E85,"dddd") -> Thursday | AD85: =INT(E85)+TIME(14,30,0) -> 46205.604 | AE85: =(E85-AD85)*1440 -> 281
A86: 16 | B86: CVX | C86: OXY | D86: 89540 | E86: 46209.604 | F86: 168.685 | G86: 48.845 | H86: 168.70187 | I86: 48.840116 | J86: -3.6460094 | K86: 0.72444379 | L86: 592.82094 | M86: -1483.1483 | N86: LONG | O86: =(Table8[[#This Row],[exit_timestamp]]-Table8[[#This Row],[entry_timestamp]])*1440 -> 24 | P86: signal | Q86: 89564 | R86: 46209.621 | S86: 169.075 | T86: 49.235 | U86: -0.16300201 | V86: -347.22768 | W86: -381.79752 | X86: 0 | Y86: 20.759693 | Z86: -402.55721 | AA86: 0 | AB86: 0 | AC86: =TEXT(E86,"dddd") -> Monday | AD86: =INT(E86)+TIME(14,30,0) -> 46209.604 | AE86: =(E86-AD86)*1440 -> -1.0477379e-08
A87: 16 | B87: CVX | C87: OXY | D87: 89880 | E87: 46209.84 | F87: 167.68 | G87: 48.725 | H87: 167.66323 | I87: 48.729872 | J87: 3.5505425 | K87: 0.72444379 | L87: -596.37405 | M87: 1486.801 | N87: SHORT | O87: =(Table8[[#This Row],[exit_timestamp]]-Table8[[#This Row],[entry_timestamp]])*1440 -> 2 | P87: signal | Q87: 89882 | R87: 46209.842 | S87: 167.56 | T87: 48.75 | U87: 0.18551903 | V87: 108.73491 | W87: 74.249474 | X87: 0 | Y87: 20.831751 | Z87: 53.417724 | AA87: 0 | AB87: 0 | AC87: =TEXT(E87,"dddd") -> Monday | AD87: =INT(E87)+TIME(14,30,0) -> 46209.604 | AE87: =(E87-AD87)*1440 -> 340
A88: 16 | B88: CVX | C88: OXY | D88: 89930 | E88: 46210.604 | F88: 170.925 | G88: 49.57 | H88: 170.90791 | I88: 49.574957 | J88: 4.2075241 | K88: 0.72444379 | L88: -585.05192 | M88: 1461.4561 | N88: SHORT | O88: =(Table8[[#This Row],[exit_timestamp]]-Table8[[#This Row],[entry_timestamp]])*1440 -> 2 | P88: signal | Q88: 89932 | R88: 46210.606 | S88: 171.37 | T88: 50.19 | U88: 0.032782292 | V88: 645.75468 | W88: 611.14916 | X88: 0 | Y88: 20.46508 | Z88: 590.68408 | AA88: 0 | AB88: 0 | AC88: =TEXT(E88,"dddd") -> Tuesday | AD88: =INT(E88)+TIME(14,30,0) -> 46210.604 | AE88: =(E88-AD88)*1440 -> -1.0477379e-08
R92: PnL within 1 hr of closing | U92: 1239.3579 | AC92: =26/36 -> 0.72222222 | AD92: win rate of later trades
R93: number | U93: 9 | AC93: =30/51 -> 0.58823529 | AD93: win rate of early trades
R94: average | U94: =U92/U93 -> 137.70644 | AC94: =51/87 -> 0.5862069 | AD94: within 10 mins of 2.30 (market open)
R95: perc PnL | U95: =1239.357916/11654.22266 -> 0.10634411 | AC95: 153.79045 | AD95: mean PnL of these trades
AC96: 105.85861 | AD96: mean PnL of other trades
AC98: =7843.312845/11654.22266 -> 0.6730018 | AD98: percentage of total PnL of early trades
AC99: =(AC96*36)/11654.22266 -> 0.3269982 | AD99: percentage of total PnL of non-early trades

Sheet trade study
B2: Field | C2: What you're looking for | G2: A — Genuine temporary dislocation
B3: Date | C3: Event/news lookup | G3: Large overnight divergence followed by actual convergence.
B4: Pair | C4: Whether certain pairs dominate tails
B5: P&L | C5: Winner/loser magnitude | G5: B — Fundamental divergence
B6: Entry time | C6: How close to open | G6: Large divergence followed by continued divergence, with evidence that one leg was genuinely being repriced.
B7: Entry ( | C7: z
B8: Holding time | C8: Rapid convergence vs prolonged divergence | G8: C — Statistical artefact
B9: Hedge ratio | C9: Any extreme sizing/beta effects | G9: Z-score reverted primarily because the rolling mean/std caught up rather than because the spread converged.
B10: Overnight spread change | C10: Very important
B11: Spread change after entry | C11: Genuine convergence/divergence | G11: D — Unclear/normal statistical loss.
B12: Pair-specific news? | C12: Fundamental repricing
B13: Sector/macro event? | C13: Common shock | G13: Then compare winners versus losers.
B14: Earnings nearby? | C14: Elevated event risk
B15: Interpretation | C15: Temporary dislocation / fundamental repricing / unclear

Sheet trades edited
A1: window_id | B1: stock1 | C1: stock2 | D1: entry_minute | E1: entry_timestamp | F1: entry_price_1 | G1: entry_price_2 | H1: entry_price_1_slipped | I1: entry_price_2_slipped | J1: entry_zscore | K1: hedge_ratio_entry | L1: position_size_1 | M1: position_size_2 | N1: direction | O1: holding_minutes | P1: exit_reason | Q1: exit_minute | R1: exit_timestamp | S1: exit_price_1 | T1: exit_price_2 | U1: exit_zscore | V1: gross_pnl | W1: gross_pnl_slipped | X1: transaction_costs | Y1: cfd_financing | Z1: net_pnl | AA1: exit_price_age_1 | AB1: exit_price_age_2 | AC1: int R | AE1: UK Date | AF1: US DATE | AG1: VIX ON ENTRY
A2: 0 | B2: XOM | C2: PSX | D2: 24473 | E2: 45960.76 | F2: 115.98 | G2: 138.85 | H2: 115.9684 | I2: 138.86389 | J2: 3.5371 | K2: 0.6000914 | L2: -862.21762 | M2: 432.18682 | N2: SHORT | O2: 480000000000 | P2: signal | Q2: 24481 | R2: 45960.765 | S2: 115.79 | T2: 138.93 | U2: 0.32285626 | V2: 198.39629 | W2: 166.40739 | X2: 0 | Y2: 12.944044 | Z2: 153.46335 | AA2: 0 | AB2: 0 | AC2: =INT(R2) -> 45960 | AE2: =IF(ISNUMBER(AF2),DATE(YEAR(AF2),DAY(AF2),MONTH(AF2)),DATE(RIGHT(AF2,4),LEFT(AF2,2),MID(AF2,4,2))) -> 45870 | AF2: 45665 | AG2: 20.38 | AJ2: VIX at entry | AK2: Net PnL | AL2: Trades | AM2: Avg Net P&L | AN2: Win rate
A3: 0 | B3: XOM | C3: PSX | D3: 24579 | E3: 45961.562 | F3: 113.765 | G3: 137.19 | H3: 113.77638 | I3: 137.17628 | J3: -4.250111 | K3: 0.6000914 | L3: 879.00497 | M3: -437.41628 | N3: LONG | O3: 360000000000 | P3: signal | Q3: 24585 | R3: 45961.567 | S3: 114 | T3: 135.72 | U3: 0.27504599 | V3: 849.5681 | W3: 817.60992 | X3: 0 | Y3: 13.164212 | Z3: 804.4457 | AA3: 0 | AB3: 2 | AC3: =INT(R3) -> 45961 | AE3: =IF(ISNUMBER(AF3),DATE(YEAR(AF3),DAY(AF3),MONTH(AF3)),DATE(RIGHT(AF3,4),LEFT(AF3,2),MID(AF3,4,2))) -> 45873 | AF3: 45755 | AG3: 17.52 | AJ3: <15 | AK3: =AL3*AM3 -> -10781.59 | AL3: =COUNTIF(Z:Z,"<15") -> 32 | AM3: =AVERAGEIF(Z:Z,"<15",W:W) -> -336.9247 | AN3: =COUNTIFS(Z:Z,"<15",T:T,">0")/COUNTIFS(Z:Z,"<15") -> 1
A4: 0 | B4: XOM | C4: PSX | D4: 24969 | E4: 45964.604 | F4: 114.475 | G4: 137.13 | H4: 114.48645 | I4: 137.11629 | J4: -3.72219 | K4: 0.6000914 | L4: 873.55318 | M4: -437.60767 | N4: LONG | O4: 300000000000 | P4: signal | Q4: 24974 | R4: 45964.608 | S4: 114.18 | T4: 135.39 | U4: -0.093952476 | V4: 503.73916 | W4: 471.83924 | X4: 0 | Y4: 13.111608 | Z4: 458.72763 | AA4: 0 | AB4: 0 | AC4: =INT(R4) -> 45964 | AE4: =IF(ISNUMBER(AF4),DATE(YEAR(AF4),DAY(AF4),MONTH(AF4)),DATE(RIGHT(AF4,4),LEFT(AF4,2),MID(AF4,4,2))) -> 45874 | AF4: 45785 | AG4: 17.85 | AJ4: 15–20 | AK4: =AL4*AM4 -> #DIV/0! | AL4: =COUNTIFS(Z:Z,">=15",Z:Z,"<20") -> 0 | AM4: =AVERAGEIFS(W:W,Z:Z,">=15",Z:Z,"<20") -> #DIV/0! | AN4: =COUNTIFS(Z:Z,">=15",Z:Z,"<20",T:T,">0")/COUNTIFS(Z:Z,">=15",Z:Z,"<20") -> #DIV/0!
A5: 0 | B5: XOM | C5: PSX | D5: 25119 | E5: 45964.708 | F5: 114.235 | G5: 135.93 | H5: 114.24642 | I5: 135.91641 | J5: -3.5526752 | K5: 0.6000914 | L5: 875.38845 | M5: -441.4709 | N5: LONG | O5: 840000000000 | P5: signal | Q5: 25133 | R5: 45964.718 | S5: 114.44 | T5: 136.04 | U5: -0.31514174 | V5: 130.89283 | W5: 98.868204 | X5: 0 | Y5: 13.168594 | Z5: 85.699611 | AA5: 0 | AB5: 1 | AC5: =INT(R5) -> 45964 | AE5: =IF(ISNUMBER(AF5),DATE(YEAR(AF5),DAY(AF5),MONTH(AF5)),DATE(RIGHT(AF5,4),LEFT(AF5,2),MID(AF5,4,2))) -> 45875 | AF5: 45816 | AG5: 16.77 | AJ5: >=20 | AK5: =AL5*AM5 -> 23908.53 | AL5: =COUNTIFS(Z:Z,">=20") -> 55 | AM5: =AVERAGEIFS(W:W,Z:Z,">=20") -> 434.70055 | AN5: =COUNTIFS(Z:Z,">=20",T:T,">0")/COUNTIFS(Z:Z,">=20") -> 1
A6: 0 | B6: XOM | C6: PSX | D6: 25359 | E6: 45965.604 | F6: 113.59 | G6: 135.04 | H6: 113.57864 | I6: 135.0535 | J6: 4.7787487 | K6: 0.6000914 | L6: -880.35919 | M6: 444.38048 | N6: SHORT | O6: 1140000000000 | P6: signal | Q6: 25378 | R6: 45965.617 | S6: 112.89 | T6: 134.45 | U6: 0.29820064 | V6: 354.06695 | W6: 322.15297 | X6: 0 | Y6: 13.247397 | Z6: 308.90557 | AA6: 0 | AB6: 0 | AC6: =INT(R6) -> 45965 | AE6: =IF(ISNUMBER(AF6),DATE(YEAR(AF6),DAY(AF6),MONTH(AF6)),DATE(RIGHT(AF6,4),LEFT(AF6,2),MID(AF6,4,2))) -> 45876 | AF6: 45846 | AG6: 16.57
A7: 0 | B7: XOM | C7: PSX | D7: 26048 | E7: 45966.812 | F7: 114.35 | G7: 135.92 | H7: 114.33857 | I7: 135.93359 | J7: 3.9356146 | K7: 0.6000914 | L7: -874.50809 | M7: 441.50338 | N7: SHORT | O7: 600000000000 | P7: signal | Q7: 26058 | R7: 45966.819 | S7: 114.05 | T7: 136.065 | U7: 0.0053672066 | V7: 326.37042 | W7: 294.38842 | X7: 0 | Y7: 13.160115 | Z7: 281.22831 | AA7: 0 | AB7: 0 | AC7: =INT(R7) -> 45966 | AE7: =IF(ISNUMBER(AF7),DATE(YEAR(AF7),DAY(AF7),MONTH(AF7)),DATE(RIGHT(AF7,4),LEFT(AF7,2),MID(AF7,4,2))) -> 45877 | AF7: 45877 | AG7: 15.15
A8: 0 | B8: XOM | C8: PSX | D8: 26142 | E8: 45967.605 | F8: 113.81 | G8: 137.595 | H8: 113.82138 | I8: 137.58124 | J8: -3.9977948 | K8: 0.6000914 | L8: 878.65741 | M8: -436.12878 | N8: LONG | O8: 1560000000000 | P8: signal | Q8: 26168 | R8: 45967.623 | S8: 114.61 | T8: 139.61 | U8: -0.31825981 | V8: -175.87356 | W8: -208.03356 | X8: 0 | Y8: 13.147862 | Z8: -221.18143 | AA8: 0 | AB8: 0 | AC8: =INT(R8) -> 45967 | AE8: =IF(ISNUMBER(AF8),DATE(YEAR(AF8),DAY(AF8),MONTH(AF8)),DATE(RIGHT(AF8,4),LEFT(AF8,2),MID(AF8,4,2))) -> 45880 | AF8: 45969 | AG8: 16.25
A9: 0 | B9: XOM | C9: PSX | D9: 26919 | E9: 45968.874 | F9: 117.19 | G9: 137.81 | H9: 117.20172 | I9: 137.79622 | J9: -3.5891554 | K9: 0.6000914 | L9: 853.31513 | M9: -435.44837 | N9: LONG | O9: 235920000000000 | P9: signal | Q9: 26921 | R9: 45971.604 | S9: 117.255 | T9: 137.445 | U9: 0.32409789 | V9: 214.40414 | W9: 182.41266 | X9: 0 | Y9: 12.887635 | Z9: 169.52502 | AA9: 3931 | AB9: 0 | AC9: =INT(R9) -> 45971 | AE9: =IF(ISNUMBER(AF9),DATE(YEAR(AF9),DAY(AF9),MONTH(AF9)),DATE(RIGHT(AF9,4),LEFT(AF9,2),MID(AF9,4,2))) -> 45881 | AF9: 45999 | AG9: 14.73
A10: 0 | B10: XOM | C10: PSX | D10: 26929 | E10: 45971.61 | F10: 116.21 | G10: 136.64 | H10: 116.22162 | I10: 136.62634 | J10: -3.5199101 | K10: 0.6000914 | L10: 860.51114 | M10: -439.17696 | N10: LONG | O10: 1500000000000 | P10: signal | Q10: 26954 | R10: 45971.627 | S10: 115.75 | T10: 136.67 | U10: -0.37814933 | V10: -409.01043 | W10: -440.974 | X10: 0 | Y10: 12.996881 | Z10: -453.97088 | AA10: 0 | AB10: 0 | AC10: =INT(R10) -> 45971 | AE10: =IF(ISNUMBER(AF10),DATE(YEAR(AF10),DAY(AF10),MONTH(AF10)),DATE(RIGHT(AF10,4),LEFT(AF10,2),MID(AF10,4,2))) -> 45882 | AF10: 08/13/2025 | AG10: 14.49 | AJ10: Metric | AK10: OOS H1 | AL10: OOS H2
A11: 0 | B11: XOM | C11: PSX | D11: 27521 | E11: 45972.75 | F11: 120.23 | G11: 142.635 | H11: 120.24202 | I11: 142.62074 | J11: -3.7233017 | K11: 0.6000914 | L11: 831.73917 | M11: -420.71819 | N11: LONG | O11: 780000000000 | P11: signal | Q11: 27534 | R11: 45972.759 | S11: 120.31 | T11: 142.33 | U11: 0.12835184 | V11: 194.85818 | W11: 162.86253 | X11: 0 | Y11: 12.524574 | Z11: 150.33796 | AA11: 0 | AB11: 0 | AC11: =INT(R11) -> 45972 | AE11: =IF(ISNUMBER(AF11),DATE(YEAR(AF11),DAY(AF11),MONTH(AF11)),DATE(RIGHT(AF11,4),LEFT(AF11,2),MID(AF11,4,2))) -> 45883 | AF11: 08/14/2025 | AG11: 14.83 | AJ11: Trades
A12: 0 | B12: XOM | C12: PSX | D12: 27703 | E12: 45973.605 | F12: 118.99 | G12: 140.56 | H12: 119.0019 | I12: 140.54594 | J12: -4.666632 | K12: 0.6000914 | L12: 840.40676 | M12: -426.929 | N12: LONG | O12: 1740000000000 | P12: signal | Q12: 27732 | R12: 45973.625 | S12: 118.385 | T12: 140.41 | U12: -0.27059819 | V12: -444.40674 | W12: -476.35132 | X12: 0 | Y12: 12.673358 | Z12: -489.02468 | AA12: 0 | AB12: 0 | AC12: =INT(R12) -> 45973 | AE12: =IF(ISNUMBER(AF12),DATE(YEAR(AF12),DAY(AF12),MONTH(AF12)),DATE(RIGHT(AF12,4),LEFT(AF12,2),MID(AF12,4,2))) -> 45884 | AF12: 08/15/2025 | AG12: 15.09 | AJ12: Gross P&L
A13: 1 | B13: MPC | C13: VLO | D13: 28242 | E13: 45974.708 | F13: 197.25 | G13: 177.885 | H13: 197.26972 | I13: 177.86721 | J13: -3.8222828 | K13: 0.74400122 | L13: 506.97085 | M13: -418.24843 | N13: LONG | O13: 1080000000000 | P13: signal | Q13: 28260 | R13: 45974.721 | S13: 197.4 | T13: 177.71 | U13: -0.35008483 | V13: 149.2391 | W13: 114.35879 | X13: 0 | Y13: 9.2521928 | Z13: 105.1066 | AA13: 8 | AB13: 0 | AC13: =INT(R13) -> 45974 | AE13: =IF(ISNUMBER(AF13),DATE(YEAR(AF13),DAY(AF13),MONTH(AF13)),DATE(RIGHT(AF13,4),LEFT(AF13,2),MID(AF13,4,2))) -> 45887 | AF13: 08/18/2025 | AG13: 14.99 | AJ13: Net P&L
A14: 1 | B14: MPC | C14: VLO | D14: 28284 | E14: 45974.738 | F14: 197 | G14: 177.81 | H14: 197.0197 | I14: 177.79222 | J14: -3.5148436 | K14: 0.74400122 | L14: 507.61421 | M14: -418.42485 | N14: LONG | O14: 1200000000000 | P14: signal | Q14: 28304 | R14: 45974.751 | S14: 196.78 | T14: 177.43 | U14: -0.48620068 | V14: 47.326315 | W14: 12.473358 | X14: 0 | Y14: 9.2603906 | Z14: 3.2129677 | AA14: 3 | AB14: 3 | AC14: =INT(R14) -> 45974 | AE14: =IF(ISNUMBER(AF14),DATE(YEAR(AF14),DAY(AF14),MONTH(AF14)),DATE(RIGHT(AF14,4),LEFT(AF14,2),MID(AF14,4,2))) -> 45888 | AF14: 08/19/2025 | AG14: 15.57 | AJ14: Avg gross P&L/trade
A15: 1 | B15: MPC | C15: VLO | D15: 28872 | E15: 45978.604 | F15: 197.88 | G15: 181.15 | H15: 197.89979 | I15: 181.13189 | J15: -4.8288594 | K15: 0.74400122 | L15: 505.35678 | M15: -410.71003 | N15: LONG | O15: 1080000000000 | P15: signal | Q15: 28890 | R15: 45978.617 | S15: 198.03 | T15: 181.65 | U15: -0.26763876 | V15: -129.5515 | W15: -164.45964 | X15: 0 | Y15: 9.1606681 | Z15: -173.62031 | AA15: 0 | AB15: 0 | AC15: =INT(R15) -> 45978 | AE15: =IF(ISNUMBER(AF15),DATE(YEAR(AF15),DAY(AF15),MONTH(AF15)),DATE(RIGHT(AF15,4),LEFT(AF15,2),MID(AF15,4,2))) -> 45889 | AF15: 08/20/2025 | AG15: 15.69 | AJ15: Avg net P&L/trade
A16: 1 | B16: MPC | C16: VLO | D16: 29264 | E16: 45979.606 | F16: 197.315 | G16: 179.195 | H16: 197.29527 | I16: 179.21292 | J16: 3.7196131 | K16: 0.74400122 | L16: -506.80384 | M16: 415.19084 | N16: SHORT | O16: 120000000000 | P16: signal | Q16: 29266 | R16: 45979.607 | S16: 197.315 | T16: 180.135 | U16: 0.37237201 | V16: 390.27939 | W16: 355.36033 | X16: 0 | Y16: 9.2199468 | Z16: 346.14039 | AA16: 0 | AB16: 0 | AC16: =INT(R16) -> 45979 | AE16: =IF(ISNUMBER(AF16),DATE(YEAR(AF16),DAY(AF16),MONTH(AF16)),DATE(RIGHT(AF16,4),LEFT(AF16,2),MID(AF16,4,2))) -> 45890 | AF16: 08/21/2025 | AG16: 16.6 | AJ16: Net PF
A17: 1 | B17: MPC | C17: VLO | D17: 29654 | E17: 45980.605 | F17: 193.33 | G17: 179.17 | H17: 193.34933 | I17: 179.15208 | J17: -4.2799968 | K17: 0.74400122 | L17: 517.2503 | M17: -415.24877 | N17: LONG | O17: 240000000000 | P17: signal | Q17: 29658 | R17: 45980.608 | S17: 192.99 | T17: 177.47 | U17: -0.13015378 | V17: 530.05781 | W17: 495.26596 | X17: 0 | Y17: 9.3249907 | Z17: 485.94097 | AA17: 0 | AB17: 0 | AC17: =INT(R17) -> 45980 | AE17: =IF(ISNUMBER(AF17),DATE(YEAR(AF17),DAY(AF17),MONTH(AF17)),DATE(RIGHT(AF17,4),LEFT(AF17,2),MID(AF17,4,2))) -> 45891 | AF17: 08/22/2025 | AG17: 14.22 | AJ17: Win rate
A18: 1 | B18: MPC | C18: VLO | D18: 30043 | E18: 45981.604 | F18: 194.56 | G18: 176.91 | H18: 194.54054 | I18: 176.92769 | J18: 4.5088765 | K18: 0.74400122 | L18: -513.98026 | M18: 420.55351 | N18: SHORT | O18: 240000000000 | P18: signal | Q18: 30047 | R18: 45981.607 | S18: 194.64 | T18: 178.57 | U18: 0.36065798 | V18: 657.00041 | W18: 622.04646 | X18: 0 | Y18: 9.3453378 | Z18: 612.70113 | AA18: 0 | AB18: 0 | AC18: =INT(R18) -> 45981 | AE18: =IF(ISNUMBER(AF18),DATE(YEAR(AF18),DAY(AF18),MONTH(AF18)),DATE(RIGHT(AF18,4),LEFT(AF18,2),MID(AF18,4,2))) -> 45894 | AF18: 08/25/2025 | AG18: 14.79 | AJ18: Avg winner
A19: 1 | B19: MPC | C19: VLO | D19: 30399 | E19: 45981.851 | F19: 189.76 | G19: 172.77 | H19: 189.77898 | I19: 172.75272 | J19: -3.733946 | K19: 0.74400122 | L19: 526.98145 | M19: -430.63102 | N19: LONG | O19: 180000000000 | P19: signal | Q19: 30402 | R19: 45981.853 | S19: 189.76 | T19: 172.24 | U19: -0.27390705 | V19: 228.23444 | W19: 193.37724 | X19: 0 | Y19: 9.5761247 | Z19: 183.80112 | AA19: 0 | AB19: 0 | AC19: =INT(R19) -> 45981 | AE19: =IF(ISNUMBER(AF19),DATE(YEAR(AF19),DAY(AF19),MONTH(AF19)),DATE(RIGHT(AF19,4),LEFT(AF19,2),MID(AF19,4,2))) -> 45895 | AF19: 08/26/2025 | AG19: 14.62 | AJ19: Avg loser
A20: 2 | B20: XOM | C20: VLO | D20: 32204 | E20: 45992.605 | F20: 116.59 | G20: 177.4 | H20: 116.57834 | I20: 177.41774 | J20: 3.8872681 | K20: 0.36784501 | L20: -857.70649 | M20: 207.35344 | N20: SHORT | O20: 60000000000 | P20: signal | Q20: 32205 | R20: 45992.606 | S20: 116.46 | T20: 178.41 | U20: 0.12682432 | V20: 320.92882 | W20: 293.56213 | X20: 0 | Y20: 10.650599 | Z20: 282.91153 | AA20: 0 | AB20: 0 | AC20: =INT(R20) -> 45992 | AE20: =IF(ISNUMBER(AF20),DATE(YEAR(AF20),DAY(AF20),MONTH(AF20)),DATE(RIGHT(AF20,4),LEFT(AF20,2),MID(AF20,4,2))) -> 45896 | AF20: 08/27/2025 | AG20: 14.85 | AJ20: Avg holding time
A21: 2 | B21: XOM | C21: VLO | D21: 34155 | E21: 45999.604 | F21: 115.5 | G21: 172.15 | H21: 115.51155 | I21: 172.13279 | J21: -4.035499 | K21: 0.36784501 | L21: 865.80087 | M21: -213.67703 | N21: LONG | O21: 360000000000 | P21: signal | Q21: 34161 | R21: 45999.608 | S21: 115.945 | T21: 172.62 | U21: -0.22128585 | V21: 284.85318 | W21: 257.44771 | X21: 0 | Y21: 10.794779 | Z21: 246.65293 | AA21: 0 | AB21: 1 | AC21: =INT(R21) -> 45999 | AE21: =IF(ISNUMBER(AF21),DATE(YEAR(AF21),DAY(AF21),MONTH(AF21)),DATE(RIGHT(AF21,4),LEFT(AF21,2),MID(AF21,4,2))) -> 45897 | AF21: 08/28/2025 | AG21: 14.43 | AJ21: Avg |entry Z|
A22: 2 | B22: XOM | C22: VLO | D22: 34545 | E22: 46000.604 | F22: 117.48 | G22: 173.21 | H22: 117.46825 | I22: 173.22732 | J22: 4.9944444 | K22: 0.36784501 | L22: -851.20872 | M22: 212.36938 | N22: SHORT | O22: 1920000000000 | P22: signal | Q22: 34577 | R22: 46000.626 | S22: 119.91 | T22: 173.58 | U22: 0.49101009 | V22: -1989.8605 | W22: -2017.4321 | X22: 0 | Y22: 10.635781 | Z22: -2028.0679 | AA22: 0 | AB22: 2 | AC22: =INT(R22) -> 46000 | AE22: =IF(ISNUMBER(AF22),DATE(YEAR(AF22),DAY(AF22),MONTH(AF22)),DATE(RIGHT(AF22,4),LEFT(AF22,2),MID(AF22,4,2))) -> 45898 | AF22: 08/29/2025 | AG22: 15.36
A23: 2 | B23: XOM | C23: VLO | D23: 34935 | E23: 46001.604 | F23: 118.5 | G23: 174.52 | H23: 118.48815 | I23: 174.53745 | J23: 4.7268624 | K23: 0.36784501 | L23: -843.88186 | M23: 210.77527 | N23: SHORT | O23: 1560000000000 | P23: signal | Q23: 34961 | R23: 46001.622 | S23: 118.88 | T23: 174.055 | U23: 0.14350041 | V23: -418.68561 | W23: -446.06477 | X23: 0 | Y23: 10.546571 | Z23: -456.61135 | AA23: 0 | AB23: 0 | AC23: =INT(R23) -> 46001 | AE23: =IF(ISNUMBER(AF23),DATE(YEAR(AF23),DAY(AF23),MONTH(AF23)),DATE(RIGHT(AF23,4),LEFT(AF23,2),MID(AF23,4,2))) -> 45901 | AF23: 45666 | AG23: 16.12
A24: 2 | B24: XOM | C24: VLO | D24: 35130 | E24: 46001.74 | F24: 119.15 | G24: 176.14 | H24: 119.16191 | I24: 176.12239 | J24: -3.7745396 | K24: 0.36784501 | L24: 839.27822 | M24: -208.83673 | N24: LONG | O24: 1140000000000 | P24: signal | Q24: 35149 | R24: 46001.753 | S24: 119.26 | T24: 176.52 | U24: -0.44079237 | V24: 12.962649 | W24: -14.411419 | X24: 0 | Y24: 10.481149 | Z24: -24.892569 | AA24: 0 | AB24: 0 | AC24: =INT(R24) -> 46001 | AE24: =IF(ISNUMBER(AF24),DATE(YEAR(AF24),DAY(AF24),MONTH(AF24)),DATE(RIGHT(AF24,4),LEFT(AF24,2),MID(AF24,4,2))) -> 45902 | AF24: 45697 | AG24: 17.17
A25: 2 | B25: XOM | C25: VLO | D25: 35182 | E25: 46001.776 | F25: 118.91 | G25: 176.165 | H25: 118.92189 | I25: 176.14738 | J25: -3.5847301 | K25: 0.36784501 | L25: 840.97216 | M25: -208.80709 | N25: LONG | O25: 720000000000 | P25: signal | Q25: 35194 | R25: 46001.784 | S25: 119.01 | T25: 176.03 | U25: -0.31300551 | V25: 112.28617 | W25: 84.923682 | X25: 0 | Y25: 10.497793 | Z25: 74.42589 | AA25: 0 | AB25: 3 | AC25: =INT(R25) -> 46001 | AE25: =IF(ISNUMBER(AF25),DATE(YEAR(AF25),DAY(AF25),MONTH(AF25)),DATE(RIGHT(AF25,4),LEFT(AF25,2),MID(AF25,4,2))) -> 45903 | AF25: 45725 | AG25: 16.35
A26: 2 | B26: XOM | C26: VLO | D26: 35325 | E26: 46002.604 | F26: 119.33 | G26: 172.46 | H26: 119.31807 | I26: 172.47725 | J26: 3.7928468 | K26: 0.36784501 | L26: -838.01223 | M26: 213.29294 | N26: SHORT | O26: 1380000000000 | P26: signal | Q26: 35348 | R26: 46002.62 | S26: 119.57 | T26: 173.01 | U26: 0.49766276 | V26: -83.811818 | W26: -111.20056 | X26: 0 | Y26: 10.513052 | Z26: -121.71361 | AA26: 0 | AB26: 1 | AC26: =INT(R26) -> 46002 | AE26: =IF(ISNUMBER(AF26),DATE(YEAR(AF26),DAY(AF26),MONTH(AF26)),DATE(RIGHT(AF26,4),LEFT(AF26,2),MID(AF26,4,2))) -> 45904 | AF26: 45756 | AG26: 15.3
A27: 6 | B27: VLO | C27: OXY | D27: 47473 | E27: 46050.749 | F27: 183.31 | G27: 44.55 | H27: 183.29167 | I27: 44.554455 | J27: 4.5653092 | K27: 1.2052444 | L27: -545.52398 | M27: 2705.3746 | N27: SHORT | O27: 360000000000 | P27: signal | Q27: 47479 | R27: 46050.753 | S27: 183.485 | T27: 44.88 | U27: -0.030997425 | V27: 797.30692 | W27: 753.10321 | X27: 0 | Y27: 32.508986 | Z27: 720.59422 | AA27: 0 | AB27: 0 | AC27: =INT(R27) -> 46050 | AE27: =IF(ISNUMBER(AF27),DATE(YEAR(AF27),DAY(AF27),MONTH(AF27)),DATE(RIGHT(AF27,4),LEFT(AF27,2),MID(AF27,4,2))) -> 45905 | AF27: 45786 | AG27: 15.18
A28: 6 | B28: VLO | C28: OXY | D28: 47563 | E28: 46050.812 | F28: 184.03 | G28: 44.625 | H28: 184.0116 | I28: 44.629463 | J28: 4.6243819 | K28: 1.2052444 | L28: -543.38966 | M28: 2700.8277 | N28: SHORT | O28: 300000000000 | P28: signal | Q28: 47568 | R28: 46050.815 | S28: 183.25 | T28: 44.69 | U28: 0.38506806 | V28: 599.39774 | W28: 555.31768 | X28: 0 | Y28: 32.442174 | Z28: 522.87551 | AA28: 0 | AB28: 0 | AC28: =INT(R28) -> 46050 | AE28: =IF(ISNUMBER(AF28),DATE(YEAR(AF28),DAY(AF28),MONTH(AF28)),DATE(RIGHT(AF28,4),LEFT(AF28,2),MID(AF28,4,2))) -> 45908 | AF28: 45878 | AG28: 15.11
A29: 6 | B29: VLO | C29: OXY | D29: 48053 | E29: 46052.604 | F29: 182.23 | G29: 45.13 | H29: 182.21178 | I29: 45.134513 | J29: 3.5331525 | K29: 1.2052444 | L29: -548.75707 | M29: 2670.6058 | N29: SHORT | O29: 900000000000 | P29: signal | Q29: 48068 | R29: 46052.615 | S29: 179.91 | T29: 45.08 | U29: -0.37197442 | V29: 1139.5861 | W29: 1095.6219 | X29: 0 | Y29: 32.193628 | Z29: 1063.4283 | AA29: 0 | AB29: 0 | AC29: =INT(R29) -> 46052 | AE29: =IF(ISNUMBER(AF29),DATE(YEAR(AF29),DAY(AF29),MONTH(AF29)),DATE(RIGHT(AF29,4),LEFT(AF29,2),MID(AF29,4,2))) -> 45909 | AF29: 45909 | AG29: 15.04
A30: 6 | B30: VLO | C30: OXY | D30: 48232 | E30: 46052.728 | F30: 179.75 | G30: 44.48 | H30: 179.73202 | I30: 44.484448 | J30: 3.8548011 | K30: 1.2052444 | L30: -556.32823 | M30: 2709.6322 | N30: SHORT | O30: 60000000000 | P30: signal | Q30: 48233 | R30: 46052.729 | S30: 179.605 | T30: 44.735 | U30: 0.36551607 | V30: 771.62379 | W30: 727.45788 | X30: 0 | Y30: 32.659604 | Z30: 694.79827 | AA30: 0 | AB30: 0 | AC30: =INT(R30) -> 46052 | AE30: =IF(ISNUMBER(AF30),DATE(YEAR(AF30),DAY(AF30),MONTH(AF30)),DATE(RIGHT(AF30,4),LEFT(AF30,2),MID(AF30,4,2))) -> 45910 | AF30: 45939 | AG30: 15.35
A31: 6 | B31: VLO | C31: OXY | D31: 48443 | E31: 46055.604 | F31: 177.26 | G31: 43.86 | H31: 177.24227 | I31: 43.864386 | J31: 5.0309057 | K31: 1.2052444 | L31: -564.14307 | M31: 2747.9352 | N31: SHORT | O31: 1200000000000 | P31: signal | Q31: 48463 | R31: 46055.618 | S31: 179.165 | T31: 44.185 | U31: 0.34203641 | V31: -181.6136 | W31: -225.91526 | X31: 0 | Y31: 33.120783 | Z31: -259.03605 | AA31: 0 | AB31: 0 | AC31: =INT(R31) -> 46055 | AE31: =IF(ISNUMBER(AF31),DATE(YEAR(AF31),DAY(AF31),MONTH(AF31)),DATE(RIGHT(AF31,4),LEFT(AF31,2),MID(AF31,4,2))) -> 45911 | AF31: 45970 | AG31: 14.71
A32: 6 | B32: VLO | C32: OXY | D32: 48834 | E32: 46056.605 | F32: 183.15 | G32: 43.45 | H32: 183.13169 | I32: 43.454345 | J32: 4.9565441 | K32: 1.2052444 | L32: -546.00055 | M32: 2773.8651 | N32: SHORT | O32: 720000000000 | P32: signal | Q32: 48846 | R32: 46056.613 | S32: 182.64 | T32: 43.83 | U32: 0.41656835 | V32: 1332.529 | W32: 1288.3466 | X32: 0 | Y32: 33.198656 | Z32: 1255.1479 | AA32: 0 | AB32: 0 | AC32: =INT(R32) -> 46056 | AE32: =IF(ISNUMBER(AF32),DATE(YEAR(AF32),DAY(AF32),MONTH(AF32)),DATE(RIGHT(AF32,4),LEFT(AF32,2),MID(AF32,4,2))) -> 45912 | AF32: 46000 | AG32: 14.76
A33: 6 | B33: VLO | C33: OXY | D33: 49615 | E33: 46058.606 | F33: 192.23 | G33: 45.3 | H33: 192.21078 | I33: 45.30453 | J33: 3.9188714 | K33: 1.2052444 | L33: -520.21016 | M33: 2660.5836 | N33: SHORT | O33: 60000000000 | P33: signal | Q33: 49616 | R33: 46058.606 | S33: 192.23 | T33: 45.61 | U33: -0.084991222 | V33: 824.78092 | W33: 780.59356 | X33: 0 | Y33: 31.807938 | Z33: 748.78562 | AA33: 1 | AB33: 0 | AC33: =INT(R33) -> 46058 | AE33: =IF(ISNUMBER(AF33),DATE(YEAR(AF33),DAY(AF33),MONTH(AF33)),DATE(RIGHT(AF33,4),LEFT(AF33,2),MID(AF33,4,2))) -> 45915 | AF33: 09/15/2025 | AG33: 15.69
A34: 6 | B34: VLO | C34: OXY | D34: 50999 | E34: 46063.753 | F34: 198.93 | G34: 46.255 | H34: 198.91011 | I34: 46.259625 | J34: 3.971554 | K34: 1.2052444 | L34: -502.68939 | M34: 2605.6521 | N34: SHORT | O34: 1020000000000 | P34: signal | Q34: 51016 | R34: 46063.765 | S34: 199.125 | T34: 46.27 | U34: 0.37032833 | V34: -58.939649 | W34: -103.05825 | X34: 0 | Y34: 31.083415 | Z34: -134.14166 | AA34: 0 | AB34: 0 | AC34: =INT(R34) -> 46063 | AE34: =IF(ISNUMBER(AF34),DATE(YEAR(AF34),DAY(AF34),MONTH(AF34)),DATE(RIGHT(AF34,4),LEFT(AF34,2),MID(AF34,4,2))) -> 45916 | AF34: 09/16/2025 | AG34: 16.36
A35: 7 | B35: VLO | C35: OXY | D35: 51565 | E35: 46065.605 | F35: 204.33 | G35: 46.84 | H35: 204.30957 | I35: 46.844684 | J35: 3.975705 | K35: 1.1584421 | L35: -489.40439 | M35: 2473.1898 | N35: SHORT | O35: 1500000000000 | P35: signal | Q35: 51590 | R35: 46065.622 | S35: 205.27 | T35: 46.76 | U35: 0.27202683 | V35: -657.89531 | W35: -701.09038 | X35: 0 | Y35: 29.625942 | Z35: -730.71632 | AA35: 0 | AB35: 0 | AC35: =INT(R35) -> 46065 | AE35: =IF(ISNUMBER(AF35),DATE(YEAR(AF35),DAY(AF35),MONTH(AF35)),DATE(RIGHT(AF35,4),LEFT(AF35,2),MID(AF35,4,2))) -> 45917 | AF35: 09/17/2025 | AG35: 15.72
A36: 7 | B36: VLO | C36: OXY | D36: 51853 | E36: 46065.805 | F36: 197.09 | G36: 45.56 | H36: 197.10971 | I36: 45.555444 | J36: -3.5570165 | K36: 1.1584421 | L36: 507.38241 | M36: -2542.6736 | N36: LONG | O36: 900000000000 | P36: signal | Q36: 51868 | R36: 46065.815 | S36: 197.16 | T36: 45.455 | U36: 0.20745407 | V36: 302.4975 | W36: 259.3518 | X36: 0 | Y36: 30.50056 | Z36: 228.85124 | AA36: 0 | AB36: 0 | AC36: =INT(R36) -> 46065 | AE36: =IF(ISNUMBER(AF36),DATE(YEAR(AF36),DAY(AF36),MONTH(AF36)),DATE(RIGHT(AF36,4),LEFT(AF36,2),MID(AF36,4,2))) -> 45918 | AF36: 09/18/2025 | AG36: 15.7
A37: 7 | B37: VLO | C37: OXY | D37: 51957 | E37: 46066.606 | F37: 197.265 | G37: 45.345 | H37: 197.24527 | I37: 45.349534 | J37: 3.5481635 | K37: 1.1584421 | L37: -506.9323 | M37: 2554.7295 | N37: SHORT | O37: 60000000000 | P37: signal | Q37: 51958 | R37: 46066.606 | S37: 197.265 | T37: 45.6 | U37: -0.49856161 | V37: 651.45603 | W37: 608.22204 | X37: 0 | Y37: 30.616618 | Z37: 577.60542 | AA37: 1 | AB37: 0 | AC37: =INT(R37) -> 46066 | AE37: =IF(ISNUMBER(AF37),DATE(YEAR(AF37),DAY(AF37),MONTH(AF37)),DATE(RIGHT(AF37,4),LEFT(AF37,2),MID(AF37,4,2))) -> 45919 | AF37: 09/19/2025 | AG37: 15.45
A38: 7 | B38: VLO | C38: OXY | D38: 52349 | E38: 46070.606 | F38: 202.8 | G38: 46.35 | H38: 202.77972 | I38: 46.354635 | J38: 3.7187851 | K38: 1.1584421 | L38: -493.09665 | M38: 2499.3357 | N38: SHORT | O38: 660000000000 | P38: signal | Q38: 52360 | R38: 46070.614 | S38: 200.47 | T38: 45.93 | U38: 0.19221352 | V38: 99.194192 | W38: 56.245213 | X38: 0 | Y38: 29.924324 | Z38: 26.32089 | AA38: 0 | AB38: 0 | AC38: =INT(R38) -> 46070 | AE38: =IF(ISNUMBER(AF38),DATE(YEAR(AF38),DAY(AF38),MONTH(AF38)),DATE(RIGHT(AF38,4),LEFT(AF38,2),MID(AF38,4,2))) -> 45922 | AF38: 09/22/2025 | AG38: 16.1
A39: 7 | B39: VLO | C39: OXY | D39: 52706 | E39: 46070.854 | F39: 197.15 | G39: 45.855 | H39: 197.16971 | I39: 45.850414 | J39: -3.5601937 | K39: 1.1584421 | L39: 507.228 | M39: -2526.3158 | N39: LONG | O39: 360000000000 | P39: signal | Q39: 52712 | R39: 46070.858 | S39: 197.46 | T39: 45.79 | U39: -0.050450418 | V39: 321.45121 | W39: 278.28306 | X39: 0 | Y39: 30.335438 | Z39: 247.94762 | AA39: 0 | AB39: 0 | AC39: =INT(R39) -> 46070 | AE39: =IF(ISNUMBER(AF39),DATE(YEAR(AF39),DAY(AF39),MONTH(AF39)),DATE(RIGHT(AF39,4),LEFT(AF39,2),MID(AF39,4,2))) -> 45923 | AF39: 09/23/2025 | AG39: 16.64
A40: 7 | B40: VLO | C40: OXY | D40: 52737 | E40: 46071.604 | F40: 198.83 | G40: 46.725 | H40: 198.84988 | I40: 46.720328 | J40: -4.6988719 | K40: 1.1584421 | L40: 502.94221 | M40: -2479.2768 | N40: LONG | O40: 720000000000 | P40: signal | Q40: 52749 | R40: 46071.613 | S40: 197.73 | T40: 46.27 | U40: -0.47052163 | V40: 574.83452 | W40: 531.83381 | X40: 0 | Y40: 29.82219 | Z40: 502.01162 | AA40: 9 | AB40: 0 | AC40: =INT(R40) -> 46071 | AE40: =IF(ISNUMBER(AF40),DATE(YEAR(AF40),DAY(AF40),MONTH(AF40)),DATE(RIGHT(AF40,4),LEFT(AF40,2),MID(AF40,4,2))) -> 45924 | AF40: 09/24/2025 | AG40: 16.18
A41: 7 | B41: VLO | C41: OXY | D41: 53078 | E41: 46071.841 | F41: 199.005 | G41: 47.19 | H41: 198.9851 | I41: 47.194719 | J41: 3.5675 | K41: 1.1584421 | L41: -502.49994 | M41: 2454.8466 | N41: SHORT | O41: 720000000000 | P41: signal | Q41: 53090 | R41: 46071.849 | S41: 198.88 | T41: 47.225 | U41: -0.025827999 | V41: 148.73212 | W41: 105.56097 | X41: 0 | Y41: 29.573465 | Z41: 75.987504 | AA41: 0 | AB41: 0 | AC41: =INT(R41) -> 46071 | AE41: =IF(ISNUMBER(AF41),DATE(YEAR(AF41),DAY(AF41),MONTH(AF41)),DATE(RIGHT(AF41,4),LEFT(AF41,2),MID(AF41,4,2))) -> 45925 | AF41: 09/25/2025 | AG41: 16.74
A42: 7 | B42: VLO | C42: OXY | D42: 54305 | E42: 46077.608 | F42: 196.52 | G42: 51.38 | H42: 196.50035 | I42: 51.385138 | J42: 3.7348129 | K42: 1.1584421 | L42: -508.85406 | M42: 2254.6557 | N42: SHORT | O42: 600000000000 | P42: signal | Q42: 54315 | R42: 46077.615 | S42: 195.11 | T42: 51.38 | U42: 0.34825929 | V42: 717.48423 | W42: 674.38713 | X42: 0 | Y42: 27.635098 | Z42: 646.75203 | AA42: 1 | AB42: 0 | AC42: =INT(R42) -> 46077 | AE42: =IF(ISNUMBER(AF42),DATE(YEAR(AF42),DAY(AF42),MONTH(AF42)),DATE(RIGHT(AF42,4),LEFT(AF42,2),MID(AF42,4,2))) -> 45926 | AF42: 09/26/2025 | AG42: 15.29
A43: 7 | B43: VLO | C43: OXY | D43: 54691 | E43: 46078.605 | F43: 200.5 | G43: 51.8 | H43: 200.47995 | I43: 51.80518 | J43: 3.5805076 | K43: 1.1584421 | L43: -498.75312 | M43: 2236.3747 | N43: SHORT | O43: 1200000000000 | P43: signal | Q43: 54711 | R43: 46078.619 | S43: 197.835 | T43: 51.04 | U43: 0.39904308 | V43: -370.46772 | W43: -413.33368 | X43: 0 | Y43: 27.351278 | Z43: -440.68496 | AA43: 0 | AB43: 0 | AC43: =INT(R43) -> 46078 | AE43: =IF(ISNUMBER(AF43),DATE(YEAR(AF43),DAY(AF43),MONTH(AF43)),DATE(RIGHT(AF43,4),LEFT(AF43,2),MID(AF43,4,2))) -> 45929 | AF43: 09/29/2025 | AG43: 16.12
A44: 7 | B44: VLO | C44: OXY | D44: 55080 | E44: 46079.604 | F44: 197.15 | G44: 49.93 | H44: 197.13028 | I44: 49.934993 | J44: 4.3926995 | K44: 1.1584421 | L44: -507.228 | M44: 2320.1324 | N44: SHORT | O44: 1140000000000 | P44: signal | Q44: 55099 | R44: 46079.617 | S44: 199.2 | T44: 50.1 | U44: 0.3792561 | V44: -645.39489 | W44: -688.70716 | X44: 0 | Y44: 28.273604 | Z44: -716.98076 | AA44: 4 | AB44: 0 | AC44: =INT(R44) -> 46079 | AE44: =IF(ISNUMBER(AF44),DATE(YEAR(AF44),DAY(AF44),MONTH(AF44)),DATE(RIGHT(AF44,4),LEFT(AF44,2),MID(AF44,4,2))) -> 45930 | AF44: 09/30/2025 | AG44: 16.28
A45: 10 | B45: MPC | C45: PSX | D45: 63235 | E45: 46107.782 | F45: 249.025 | G45: 185.45 | H45: 249.0001 | I45: 185.46855 | J45: 4.9104081 | K45: 1.2206218 | L45: -401.56611 | M45: 658.19456 | N45: SHORT | O45: 660000000000 | P45: signal | Q45: 63246 | R45: 46107.79 | S45: 248.34 | T45: 185.55 | U45: 0.48475149 | V45: 340.89224 | W45: 296.50073 | X45: 0 | Y45: 10.597607 | Z45: 285.90312 | AA45: 7 | AB45: 1 | AC45: =INT(R45) -> 46107 | AE45: =IF(ISNUMBER(AF45),DATE(YEAR(AF45),DAY(AF45),MONTH(AF45)),DATE(RIGHT(AF45,4),LEFT(AF45,2),MID(AF45,4,2))) -> 45931 | AF45: 45667 | AG45: 16.29
A46: 10 | B46: MPC | C46: PSX | D46: 63449 | E46: 46108.658 | F46: 251.585 | G46: 187.325 | H46: 251.61016 | I46: 187.30627 | J46: -3.5737317 | K46: 1.2206218 | L46: 397.47998 | M46: -651.60647 | N46: LONG | O46: 1980000000000 | P46: signal | Q46: 63482 | R46: 46108.681 | S46: 251.31 | T46: 187.5 | U46: -0.13489631 | V46: -223.33813 | W46: -267.75103 | X46: 0 | Y46: 10.490864 | Z46: -278.2419 | AA46: 3 | AB46: 0 | AC46: =INT(R46) -> 46108 | AE46: =IF(ISNUMBER(AF46),DATE(YEAR(AF46),DAY(AF46),MONTH(AF46)),DATE(RIGHT(AF46,4),LEFT(AF46,2),MID(AF46,4,2))) -> 45932 | AF46: 45698 | AG46: 16.63
A47: 10 | B47: MPC | C47: PSX | D47: 64198 | E47: 46112.676 | F47: 250.155 | G47: 185.48 | H47: 250.12998 | I47: 185.49855 | J47: 3.6542911 | K47: 1.2206218 | L47: -399.75215 | M47: 658.08811 | N47: SHORT | O47: 540000000000 | P47: signal | Q47: 64207 | R47: 46112.682 | S47: 248.85 | T47: 185.13 | U47: 0.49074797 | V47: 291.34572 | W47: 247.00849 | X47: 0 | Y47: 10.578403 | Z47: 236.43009 | AA47: 1 | AB47: 0 | AC47: =INT(R47) -> 46112 | AE47: =IF(ISNUMBER(AF47),DATE(YEAR(AF47),DAY(AF47),MONTH(AF47)),DATE(RIGHT(AF47,4),LEFT(AF47,2),MID(AF47,4,2))) -> 45933 | AF47: 45726 | AG47: 16.65
A48: 10 | B48: MPC | C48: PSX | D48: 64285 | E48: 46112.736 | F48: 248.09 | G48: 184.095 | H48: 248.06519 | I48: 184.11341 | J48: 3.6647745 | K48: 1.2206218 | L48: -403.07953 | M48: 663.03909 | N48: SHORT | O48: 360000000000 | P48: signal | Q48: 64291 | R48: 46112.74 | S48: 245.85 | T48: 183.83 | U48: -0.29327375 | V48: 727.19278 | W48: 682.88821 | X48: 0 | Y48: 10.661186 | Z48: 672.22702 | AA48: 0 | AB48: 0 | AC48: =INT(R48) -> 46112 | AE48: =IF(ISNUMBER(AF48),DATE(YEAR(AF48),DAY(AF48),MONTH(AF48)),DATE(RIGHT(AF48,4),LEFT(AF48,2),MID(AF48,4,2))) -> 45936 | AF48: 45818 | AG48: 16.37
A49: 10 | B49: MPC | C49: PSX | D49: 64782 | E49: 46113.804 | F49: 234.19 | G49: 173.37 | H49: 234.16658 | I49: 173.38734 | J49: 3.5816792 | K49: 1.2206218 | L49: -427.00371 | M49: 704.05596 | N49: SHORT | O49: 120000000000 | P49: signal | Q49: 64784 | R49: 46113.806 | S49: 234.19 | T49: 173.81 | U49: 0.11875679 | V49: 309.78462 | W49: 265.34121 | X49: 0 | Y49: 11.310597 | Z49: 254.03061 | AA49: 6 | AB49: 0 | AC49: =INT(R49) -> 46113 | AE49: =IF(ISNUMBER(AF49),DATE(YEAR(AF49),DAY(AF49),MONTH(AF49)),DATE(RIGHT(AF49,4),LEFT(AF49,2),MID(AF49,4,2))) -> 45937 | AF49: 45848 | AG49: 17.24
A50: 10 | B50: MPC | C50: PSX | D50: 65579 | E50: 46118.812 | F50: 241.45 | G50: 176.55 | H50: 241.47414 | I50: 176.53234 | J50: -3.7413073 | K50: 1.2206218 | L50: 414.16442 | M50: -691.37458 | N50: LONG | O50: 1860000000000 | P50: signal | Q50: 65610 | R50: 46118.834 | S50: 241.24 | T50: 176.43 | U50: -0.020030022 | V50: -4.0095794 | W50: -48.405022 | X50: 0 | Y50: 11.05539 | Z50: -59.460412 | AA50: 0 | AB50: 1 | AC50: =INT(R50) -> 46118 | AE50: =IF(ISNUMBER(AF50),DATE(YEAR(AF50),DAY(AF50),MONTH(AF50)),DATE(RIGHT(AF50,4),LEFT(AF50,2),MID(AF50,4,2))) -> 45938 | AF50: 45879 | AG50: 16.3
A51: 10 | B51: MPC | C51: PSX | D51: 65670 | E51: 46119.605 | F51: 242.74 | G51: 173.615 | H51: 242.71573 | I51: 173.63236 | J51: 3.5116199 | K51: 1.2206218 | L51: -411.96342 | M51: 703.06242 | N51: SHORT | O51: 300000000000 | P51: signal | Q51: 65675 | R51: 46119.608 | S51: 242.74 | T51: 176.41 | U51: 0.43486104 | V51: 1965.0595 | W51: 1920.4505 | X51: 0 | Y51: 11.150258 | Z51: 1909.3003 | AA51: 5 | AB51: 0 | AC51: =INT(R51) -> 46119 | AE51: =IF(ISNUMBER(AF51),DATE(YEAR(AF51),DAY(AF51),MONTH(AF51)),DATE(RIGHT(AF51,4),LEFT(AF51,2),MID(AF51,4,2))) -> 45939 | AF51: 45910 | AG51: 16.43
A52: 10 | B52: MPC | C52: PSX | D52: 66064 | E52: 46120.605 | F52: 231.02 | G52: 164.185 | H52: 230.9969 | I52: 164.20142 | J52: 3.9772965 | K52: 1.2206218 | L52: -432.86296 | M52: 743.44296 | N52: SHORT | O52: 420000000000 | P52: signal | Q52: 66071 | R52: 46120.61 | S52: 229.735 | T52: 165.06 | U52: -0.44118601 | V52: 1206.7415 | W52: 1162.3196 | X52: 0 | Y52: 11.763059 | Z52: 1150.5566 | AA52: 0 | AB52: 0 | AC52: =INT(R52) -> 46120 | AE52: =IF(ISNUMBER(AF52),DATE(YEAR(AF52),DAY(AF52),MONTH(AF52)),DATE(RIGHT(AF52,4),LEFT(AF52,2),MID(AF52,4,2))) -> 45940 | AF52: 45940 | AG52: 21.66
A53: 10 | B53: MPC | C53: PSX | D53: 66820 | E53: 46121.858 | F53: 223.8 | G53: 160.91 | H53: 223.77762 | I53: 160.92609 | J53: 4.0550521 | K53: 1.2206218 | L53: -446.82752 | M53: 758.57425 | N53: SHORT | O53: 840000000000 | P53: signal | Q53: 66834 | R53: 46121.867 | S53: 222.645 | T53: 160.415 | U53: 0.44230669 | V53: 140.59154 | W53: 96.268261 | X53: 0 | Y53: 12.054018 | Z53: 84.214243 | AA53: 1 | AB53: 0 | AC53: =INT(R53) -> 46121 | AE53: =IF(ISNUMBER(AF53),DATE(YEAR(AF53),DAY(AF53),MONTH(AF53)),DATE(RIGHT(AF53,4),LEFT(AF53,2),MID(AF53,4,2))) -> 45943 | AF53: 10/13/2025 | AG53: 19.03
A54: 10 | B54: MPC | C54: PSX | D54: 66845 | E54: 46122.604 | F54: 221.54 | G54: 160.94 | H54: 221.56215 | I54: 160.92391 | J54: -3.8854422 | K54: 1.2206218 | L54: 451.38575 | M54: -758.43284 | N54: LONG | O54: 900000000000 | P54: signal | Q54: 66860 | R54: 46122.615 | S54: 221.565 | T54: 160.62 | U54: -0.48827037 | V54: 253.98315 | W54: 209.59386 | X54: 0 | Y54: 12.098186 | Z54: 197.49567 | AA54: 2 | AB54: 0 | AC54: =INT(R54) -> 46122 | AE54: =IF(ISNUMBER(AF54),DATE(YEAR(AF54),DAY(AF54),MONTH(AF54)),DATE(RIGHT(AF54,4),LEFT(AF54,2),MID(AF54,4,2))) -> 45944 | AF54: 10/14/2025 | AG54: 20.81
A55: 11 | B55: CVX | C55: PSX | D55: 67195 | E55: 46122.847 | F55: 187.9 | G55: 158.25 | H55: 187.88121 | I55: 158.26583 | J55: 3.7449559 | K55: 0.77505102 | L55: -532.19798 | M55: 489.76368 | N55: SHORT | O55: 600000000000 | P55: signal | Q55: 67205 | R55: 46122.854 | S55: 188.055 | T55: 158.6 | U55: 0.44766662 | V55: 88.926601 | W55: 53.40019 | X55: 0 | Y55: 10.219617 | Z55: 43.180573 | AA55: 0 | AB55: 0 | AC55: =INT(R55) -> 46122 | AE55: =IF(ISNUMBER(AF55),DATE(YEAR(AF55),DAY(AF55),MONTH(AF55)),DATE(RIGHT(AF55,4),LEFT(AF55,2),MID(AF55,4,2))) -> 45945 | AF55: 10/15/2025 | AG55: 20.64
A56: 11 | B56: CVX | C56: PSX | D56: 67243 | E56: 46125.607 | F56: 191.305 | G56: 160.7 | H56: 191.28587 | I56: 160.71607 | J56: 3.5145051 | K56: 0.77505102 | L56: -522.72549 | M56: 482.29684 | N56: SHORT | O56: 1020000000000 | P56: signal | Q56: 67260 | R56: 46125.619 | S56: 191.36 | T56: 160.27 | U56: 0.37838138 | V56: -236.13754 | W56: -271.6207 | X56: 0 | Y56: 10.050223 | Z56: -281.67092 | AA56: 0 | AB56: 5 | AC56: =INT(R56) -> 46125 | AE56: =IF(ISNUMBER(AF56),DATE(YEAR(AF56),DAY(AF56),MONTH(AF56)),DATE(RIGHT(AF56,4),LEFT(AF56,2),MID(AF56,4,2))) -> 45946 | AF56: 10/16/2025 | AG56: 25.31
A57: 11 | B57: CVX | C57: PSX | D57: 68026 | E57: 46127.608 | F57: 185.79 | G57: 158.87 | H57: 185.80858 | I57: 158.85411 | J57: -3.769357 | K57: 0.77505102 | L57: 538.2421 | M57: -487.85235 | N57: LONG | O57: 540000000000 | P57: signal | Q57: 68035 | R57: 46127.614 | S57: 185.59 | T57: 157.69 | U57: -0.03733207 | V57: 468.01735 | W57: 432.58466 | X57: 0 | Y57: 10.260944 | Z57: 422.32371 | AA57: 0 | AB57: 0 | AC57: =INT(R57) -> 46127 | AE57: =IF(ISNUMBER(AF57),DATE(YEAR(AF57),DAY(AF57),MONTH(AF57)),DATE(RIGHT(AF57,4),LEFT(AF57,2),MID(AF57,4,2))) -> 45947 | AF57: 10/17/2025 | AG57: 20.78
A58: 11 | B58: CVX | C58: PSX | D58: 68807 | E58: 46129.605 | F58: 180.27 | G58: 157.51 | H58: 180.28803 | I58: 157.49425 | J58: -4.6436545 | K58: 0.77505102 | L58: 554.72347 | M58: -492.06464 | N58: LONG | O58: 660000000000 | P58: signal | Q58: 68818 | R58: 46129.613 | S58: 180.73 | T58: 156.75 | U58: -0.41466816 | V58: 629.14193 | W58: 593.65279 | X58: 0 | Y58: 10.467881 | Z58: 583.1849 | AA58: 0 | AB58: 0 | AC58: =INT(R58) -> 46129 | AE58: =IF(ISNUMBER(AF58),DATE(YEAR(AF58),DAY(AF58),MONTH(AF58)),DATE(RIGHT(AF58,4),LEFT(AF58,2),MID(AF58,4,2))) -> 45950 | AF58: 10/20/2025 | AG58: 18.23
A59: 11 | B59: CVX | C59: PSX | D59: 69198 | E59: 46132.605 | F59: 184.66 | G59: 155.86 | H59: 184.64153 | I59: 155.87559 | J59: 3.5344592 | K59: 0.77505102 | L59: -541.5358 | M59: 497.27385 | N59: SHORT | O59: 180000000000 | P59: signal | Q59: 69201 | R59: 46132.607 | S59: 183.98 | T59: 156.06 | U59: -0.069036553 | V59: 467.69911 | W59: 432.22497 | X59: 0 | Y59: 10.388096 | Z59: 421.83687 | AA59: 0 | AB59: 2 | AC59: =INT(R59) -> 46132 | AE59: =IF(ISNUMBER(AF59),DATE(YEAR(AF59),DAY(AF59),MONTH(AF59)),DATE(RIGHT(AF59,4),LEFT(AF59,2),MID(AF59,4,2))) -> 45951 | AF59: 10/21/2025 | AG59: 17.87
A60: 11 | B60: CVX | C60: PSX | D60: 69297 | E60: 46132.674 | F60: 184.97 | G60: 156.69 | H60: 184.9885 | I60: 156.67433 | J60: -3.6146245 | K60: 0.77505102 | L60: 540.62821 | M60: -494.63975 | N60: LONG | O60: 1260000000000 | P60: signal | Q60: 69318 | R60: 46132.688 | S60: 184.42 | T60: 156.275 | U60: -0.43904364 | V60: -92.07002 | W60: -127.52078 | X60: 0 | Y60: 10.35268 | Z60: -137.87346 | AA60: 0 | AB60: 2 | AC60: =INT(R60) -> 46132 | AE60: =IF(ISNUMBER(AF60),DATE(YEAR(AF60),DAY(AF60),MONTH(AF60)),DATE(RIGHT(AF60,4),LEFT(AF60,2),MID(AF60,4,2))) -> 45952 | AF60: 10/22/2025 | AG60: 18.6
A61: 11 | B61: CVX | C61: PSX | D61: 69977 | E61: 46134.604 | F61: 188.505 | G61: 160.8 | H61: 188.48615 | I61: 160.81608 | J61: 3.7915397 | K61: 0.77505102 | L61: -530.48991 | M61: 481.9969 | N61: SHORT | O61: 1080000000000 | P61: signal | Q61: 69995 | R61: 46134.617 | S61: 188.34 | T61: 160.865 | U61: 0.45065045 | V61: 118.86063 | W61: 83.365233 | X61: 0 | Y61: 10.124868 | Z61: 73.240365 | AA61: 0 | AB61: 0 | AC61: =INT(R61) -> 46134 | AE61: =IF(ISNUMBER(AF61),DATE(YEAR(AF61),DAY(AF61),MONTH(AF61)),DATE(RIGHT(AF61,4),LEFT(AF61,2),MID(AF61,4,2))) -> 45953 | AF61: 10/23/2025 | AG61: 17.3
A62: 11 | B62: CVX | C62: PSX | D62: 70362 | E62: 46134.872 | F62: 186.215 | G62: 160.78 | H62: 186.23362 | I62: 160.76392 | J62: -3.5252704 | K62: 0.77505102 | L62: 537.01367 | M62: -482.05686 | N62: LONG | O62: 63420000000000 | P62: signal | Q62: 70370 | R62: 46135.606 | S62: 187.8 | T62: 162.05 | U62: -0.19480949 | V62: 238.95445 | W62: 203.30709 | X62: 0 | Y62: 10.190705 | Z62: 193.11639 | AA62: 0 | AB62: 1 | AC62: =INT(R62) -> 46135 | AE62: =IF(ISNUMBER(AF62),DATE(YEAR(AF62),DAY(AF62),MONTH(AF62)),DATE(RIGHT(AF62,4),LEFT(AF62,2),MID(AF62,4,2))) -> 45954 | AF62: 10/24/2025 | AG62: 16.37
A63: 11 | B63: CVX | C63: PSX | D63: 70759 | E63: 46136.605 | F63: 185.9 | G63: 160.645 | H63: 185.91859 | I63: 160.62894 | J63: -4.2259717 | K63: 0.77505102 | L63: 537.92361 | M63: -482.46196 | N63: LONG | O63: 1380000000000 | P63: signal | Q63: 70782 | R63: 46136.621 | S63: 185.69 | T63: 161.365 | U63: -0.40759844 | V63: -460.33657 | W63: -495.86103 | X63: 0 | Y63: 10.203856 | Z63: -506.06489 | AA63: 0 | AB63: 1 | AC63: =INT(R63) -> 46136 | AE63: =IF(ISNUMBER(AF63),DATE(YEAR(AF63),DAY(AF63),MONTH(AF63)),DATE(RIGHT(AF63,4),LEFT(AF63,2),MID(AF63,4,2))) -> 45957 | AF63: 10/27/2025 | AG63: 15.79
A64: 12 | B64: CVX | C64: PSX | D64: 71148 | E64: 46139.604 | F64: 186.99 | G64: 163.615 | H64: 186.9713 | I64: 163.63136 | J64: 4.5965719 | K64: 0.71286786 | L64: -534.78796 | M64: 435.69835 | N64: SHORT | O64: 300000000000 | P64: signal | Q64: 71153 | R64: 46139.608 | S64: 187.24 | T64: 165.235 | U64: 0.29119212 | V64: 572.13434 | W64: 537.79303 | X64: 0 | Y64: 9.7048631 | Z64: 528.08817 | AA64: 0 | AB64: 1 | AC64: =INT(R64) -> 46139 | AE64: =IF(ISNUMBER(AF64),DATE(YEAR(AF64),DAY(AF64),MONTH(AF64)),DATE(RIGHT(AF64,4),LEFT(AF64,2),MID(AF64,4,2))) -> 45958 | AF64: 10/28/2025 | AG64: 16.42
... A67: 12 | B67: CVX | C67: PSX | D67: 72322 | E67: 46142.604 | F67: 188.88 | G67: 172.295 | H67: 188.89889 | I67: 172.27777 | J67: -4.9768744 | K67: 0.71286786 | L67: 529.43668 | M67: -413.74843 | N67: LONG | O67: 1140000000000 | P67: signal | Q67: 72341 | R67: 46142.617 | S67: 191.975 | T67: 175.73 | U67: -0.4362697 | V67: 217.38066 | W67: 182.81732 | X67: 0 | Y67: 9.4318511 | Z67: 173.38547 | AA67: 0 | AB67: 0 | AC67: =INT(R67) -> 46142 | AE67: =IF(ISNUMBER(AF67),DATE(YEAR(AF67),DAY(AF67),MONTH(AF67)),DATE(RIGHT(AF67,4),LEFT(AF67,2),MID(AF67,4,2))) -> 45961 | AF67: 10/31/2025 | AG67: 17.44
A68: 12 | B68: CVX | C68: PSX | D68: 72712 | E68: 46143.604 | F68: 191.07 | G68: 178.46 | H68: 191.08911 | I68: 178.44215 | J68: -4.1504488 | K68: 0.71286786 | L68: 523.3684 | M68: -399.45526 | N68: LONG | O68: 120000000000 | P68: signal | Q68: 72714 | R68: 46143.606 | S68: 193.64 | T68: 178.32 | U68: -0.038092521 | V68: 1400.9805 | W68: 1366.5943 | X68: 0 | Y68: 9.2282366 | Z68: 1357.366 | AA68: 0 | AB68: 0 | AC68: =INT(R68) -> 46143 | AE68: =IF(ISNUMBER(AF68),DATE(YEAR(AF68),DAY(AF68),MONTH(AF68)),DATE(RIGHT(AF68,4),LEFT(AF68,2),MID(AF68,4,2))) -> 45964 | AF68: 45727 | AG68: 17.17
A69: 12 | B69: CVX | C69: PSX | D69: 73493 | E69: 46147.605 | F69: 191.09 | G69: 178.75 | H69: 191.10911 | I69: 178.73212 | J69: -4.7311466 | K69: 0.71286786 | L69: 523.31362 | M69: -398.80719 | N69: LONG | O69: 1320000000000 | P69: signal | Q69: 73515 | R69: 46147.62 | S69: 191.61 | T69: 179.42 | U69: 0.055007164 | V69: 4.9222639 | W69: -29.389026 | X69: 0 | Y69: 9.2212082 | Z69: -38.610234 | AA69: 0 | AB69: 0 | AC69: =INT(R69) -> 46147 | AE69: =IF(ISNUMBER(AF69),DATE(YEAR(AF69),DAY(AF69),MONTH(AF69)),DATE(RIGHT(AF69,4),LEFT(AF69,2),MID(AF69,4,2))) -> 45965 | AF69: 45758 | AG69: 19
A70: 12 | B70: CVX | C70: PSX | D70: 74276 | E70: 46149.604 | F70: 180.4 | G70: 168.22 | H70: 180.41804 | I70: 168.20318 | J70: -5.1146144 | K70: 0.71286786 | L70: 554.32373 | M70: -423.77117 | N70: LONG | O70: 900000000000 | P70: signal | Q70: 74291 | R70: 46149.615 | S70: 181.92 | T70: 168.615 | U70: -0.37728469 | V70: 675.18245 | W70: 640.8241 | X70: 0 | Y70: 9.7809489 | Z70: 631.04315 | AA70: 0 | AB70: 2 | AC70: =INT(R70) -> 46149 | AE70: =IF(ISNUMBER(AF70),DATE(YEAR(AF70),DAY(AF70),MONTH(AF70)),DATE(RIGHT(AF70,4),LEFT(AF70,2),MID(AF70,4,2))) -> 45966 | AF70: 45788 | AG70: 18.01
A71: 12 | B71: CVX | C71: PSX | D71: 74669 | E71: 46150.606 | F71: 181.375 | G71: 168.385 | H71: 181.39314 | I71: 168.36816 | J71: -4.4009746 | K71: 0.71286786 | L71: 551.3439 | M71: -423.35592 | N71: LONG | O71: 180000000000 | P71: signal | Q71: 74672 | R71: 46150.608 | S71: 181.41 | T71: 167.2 | U71: 0.11498237 | V71: 520.9738 | W71: 486.76468 | X71: 0 | Y71: 9.7469982 | Z71: 477.01768 | AA71: 0 | AB71: 0 | AC71: =INT(R71) -> 46150 | AE71: =IF(ISNUMBER(AF71),DATE(YEAR(AF71),DAY(AF71),MONTH(AF71)),DATE(RIGHT(AF71,4),LEFT(AF71,2),MID(AF71,4,2))) -> 45967 | AF71: 45819 | AG71: 19.5
A72: 14 | B72: COP | C72: OXY | D72: 78971 | E72: 46168.604 | F72: 118.565 | G72: 57.96 | H72: 118.57686 | I72: 57.954204 | J72: -4.3587421 | K72: 0.75386183 | L72: 843.41922 | M72: -1300.6588 | N72: LONG | O72: 1500000000000 | P72: signal | Q72: 78996 | R72: 46168.622 | S72: 119.83 | T72: 58.98 | U72: -0.3136961 | V72: -259.74664 | W72: -295.06324 | X72: 0 | Y72: 21.44078 | Z72: -316.50402 | AA72: 0 | AB72: 0 | AC72: =INT(R72) -> 46168 | AE72: =IF(ISNUMBER(AF72),DATE(YEAR(AF72),DAY(AF72),MONTH(AF72)),DATE(RIGHT(AF72,4),LEFT(AF72,2),MID(AF72,4,2))) -> 45968 | AF72: 45849 | AG72: 19.08
A73: 14 | B73: COP | C73: OXY | D73: 79363 | E73: 46169.604 | F73: 114.795 | G73: 56 | H73: 114.78352 | I73: 56.0056 | J73: 3.5076662 | K73: 0.75386183 | L73: -871.11808 | M73: 1346.1818 | N73: SHORT | O73: 1860000000000 | P73: signal | Q73: 79394 | R73: 46169.626 | S73: 115.59 | T73: 56.225 | U73: 0.18525492 | V73: -389.64796 | W73: -424.82474 | X73: 0 | Y73: 22.172999 | Z73: -446.99774 | AA73: 0 | AB73: 0 | AC73: =INT(R73) -> 46169 | AE73: =IF(ISNUMBER(AF73),DATE(YEAR(AF73),DAY(AF73),MONTH(AF73)),DATE(RIGHT(AF73,4),LEFT(AF73,2),MID(AF73,4,2))) -> 45971 | AF73: 45941 | AG73: 17.6
A74: 14 | B74: COP | C74: OXY | D74: 80775 | E74: 46174.768 | F74: 116.1 | G74: 59.075 | H74: 116.11161 | I74: 59.069092 | J74: -3.5422808 | K74: 0.75386183 | L74: 861.32644 | M74: -1276.1097 | N74: LONG | O74: 1020000000000 | P74: signal | Q74: 80792 | R74: 46174.78 | S74: 115.82 | T74: 58.89 | U74: -0.1633968 | V74: -5.0911022 | W74: -40.120614 | X74: 0 | Y74: 21.374362 | Z74: -61.494975 | AA74: 0 | AB74: 0 | AC74: =INT(R74) -> 46174 | AE74: =IF(ISNUMBER(AF74),DATE(YEAR(AF74),DAY(AF74),MONTH(AF74)),DATE(RIGHT(AF74,4),LEFT(AF74,2),MID(AF74,4,2))) -> 45972 | AF74: 45972 | AG74: 17.28
A75: 14 | B75: COP | C75: OXY | D75: 80931 | E75: 46175.605 | F75: 116.065 | G75: 58.52 | H75: 116.05339 | I75: 58.525852 | J75: 4.223299 | K75: 0.75386183 | L75: -861.58618 | M75: 1288.2123 | N75: SHORT | O75: 1140000000000 | P75: signal | Q75: 80950 | R75: 46175.618 | S75: 116.84 | T75: 59.015 | U75: 0.37396195 | V75: -30.064209 | W75: -65.271985 | X75: 0 | Y75: 21.497985 | Z75: -86.76997 | AA75: 1 | AB75: 0 | AC75: =INT(R75) -> 46175 | AE75: =IF(ISNUMBER(AF75),DATE(YEAR(AF75),DAY(AF75),MONTH(AF75)),DATE(RIGHT(AF75,4),LEFT(AF75,2),MID(AF75,4,2))) -> 45973 | AF75: 46002 | AG75: 17.51
A76: 14 | B76: COP | C76: OXY | D76: 81501 | E76: 46176.727 | F76: 119.52 | G76: 60.47 | H76: 119.50805 | I76: 60.476047 | J76: 3.6388854 | K76: 0.75386183 | L76: -836.68005 | M76: 1246.6708 | N76: SHORT | O76: 1200000000000 | P76: signal | Q76: 81521 | R76: 46176.741 | S76: 119.285 | T76: 60.295 | U76: 0.20365692 | V76: -21.547576 | W76: -56.583334 | X76: 0 | Y76: 20.833508 | Z76: -77.416842 | AA76: 0 | AB76: 0 | AC76: =INT(R76) -> 46176 | AE76: =IF(ISNUMBER(AF76),DATE(YEAR(AF76),DAY(AF76),MONTH(AF76)),DATE(RIGHT(AF76,4),LEFT(AF76,2),MID(AF76,4,2))) -> 45974 | AF76: 11/13/2025 | AG76: 20
A77: 14 | B77: COP | C77: OXY | D77: 81716 | E77: 46177.604 | F77: 117.95 | G77: 58.64 | H77: 117.9382 | I77: 58.645864 | J77: 3.5236732 | K77: 0.75386183 | L77: -847.81687 | M77: 1285.5761 | N77: SHORT | O77: 1500000000000 | P77: signal | Q77: 81741 | R77: 46177.622 | S77: 118.38 | T77: 58.44 | U77: 0.49579825 | V77: -621.67648 | W77: -656.76446 | X77: 0 | Y77: 21.33393 | Z77: -678.09839 | AA77: 0 | AB77: 0 | AC77: =INT(R77) -> 46177 | AE77: =IF(ISNUMBER(AF77),DATE(YEAR(AF77),DAY(AF77),MONTH(AF77)),DATE(RIGHT(AF77,4),LEFT(AF77,2),MID(AF77,4,2))) -> 45975 | AF77: 11/14/2025 | AG77: 19.83
A78: 14 | B78: COP | C78: OXY | D78: 81978 | E78: 46177.786 | F78: 118.75 | G78: 58.43 | H78: 118.76188 | I78: 58.424157 | J78: -4.1258414 | K78: 0.75386183 | L78: 842.10526 | M78: -1290.1965 | N78: LONG | O78: 1380000000000 | P78: signal | Q78: 82001 | R78: 46177.802 | S78: 118.9 | T78: 58.51 | U78: -0.054157033 | V78: 23.100068 | W78: -12.000122 | X78: 0 | Y78: 21.323018 | Z78: -33.32314 | AA78: 0 | AB78: 0 | AC78: =INT(R78) -> 46177 | AE78: =IF(ISNUMBER(AF78),DATE(YEAR(AF78),DAY(AF78),MONTH(AF78)),DATE(RIGHT(AF78,4),LEFT(AF78,2),MID(AF78,4,2))) -> 45978 | AF78: 11/17/2025 | AG78: 22.38
A79: 14 | B79: COP | C79: OXY | D79: 82497 | E79: 46181.605 | F79: 118.24 | G79: 57.45 | H79: 118.22818 | I79: 57.455745 | J79: 3.5356335 | K79: 0.75386183 | L79: -845.73748 | M79: 1312.2051 | N79: SHORT | O79: 180000000000 | P79: forced | Q79: 82500 | R79: 46181.607 | S79: 118.27 | T79: 57.335 | V79: -176.27571 | W79: -211.34039 | X79: 0 | Y79: 21.579426 | Z79: -232.91982 | AA79: 0 | AB79: 0 | AC79: =INT(R79) -> 46181 | AE79: =IF(ISNUMBER(AF79),DATE(YEAR(AF79),DAY(AF79),MONTH(AF79)),DATE(RIGHT(AF79,4),LEFT(AF79,2),MID(AF79,4,2))) -> 45979 | AF79: 11/18/2025 | AG79: 24.69
A80: 16 | B80: CVX | C80: OXY | D80: 87588 | E80: 46199.604 | F80: 171.89 | G80: 50.77 | H80: 171.87281 | I80: 50.775077 | J80: 3.83551 | K80: 0.72444379 | L80: -581.76741 | M80: 1426.9131 | N80: SHORT | O80: 660000000000 | P80: signal | Q80: 87599 | R80: 46199.612 | S80: 170.91 | T80: 50.545 | U80: 0.37643066 | V80: 249.07661 | W80: 214.67685 | X80: 0 | Y80: 20.086805 | Z80: 194.59005 | AA80: 0 | AB80: 0 | AC80: =INT(R80) -> 46199 | AE80: =IF(ISNUMBER(AF80),DATE(YEAR(AF80),DAY(AF80),MONTH(AF80)),DATE(RIGHT(AF80,4),LEFT(AF80,2),MID(AF80,4,2))) -> 45980 | AF80: 11/19/2025 | AG80: 23.66
A81: 16 | B81: CVX | C81: OXY | D81: 88142 | E81: 46202.718 | F81: 169.3 | G81: 49.85 | H81: 169.28307 | I81: 49.854985 | J81: 3.860869 | K81: 0.72444379 | L81: -590.66745 | M81: 1453.2473 | N81: SHORT | O81: 120000000000 | P81: signal | Q81: 88144 | R81: 46202.719 | S81: 169.21 | T81: 49.915 | U81: 0.2904448 | V81: 147.62115 | W81: 113.12814 | X81: 0 | Y81: 20.439148 | Z81: 92.688994 | AA81: 0 | AB81: 0 | AC81: =INT(R81) -> 46202 | AE81: =IF(ISNUMBER(AF81),DATE(YEAR(AF81),DAY(AF81),MONTH(AF81)),DATE(RIGHT(AF81,4),LEFT(AF81,2),MID(AF81,4,2))) -> 45981 | AF81: 11/20/2025 | AG81: 26.42
A82: 16 | B82: CVX | C82: OXY | D82: 88359 | E82: 46202.869 | F82: 168.88 | G82: 49.21 | H82: 168.86311 | I82: 49.214921 | J82: 3.6250364 | K82: 0.72444379 | L82: -592.13643 | M82: 1472.1475 | N82: SHORT | O82: 63840000000000 | P82: signal | Q82: 88373 | R82: 46203.608 | S82: 169.19 | T82: 49.5 | U82: -0.49331685 | V82: 243.36049 | W82: 208.81056 | X82: 0 | Y82: 20.642839 | Z82: 188.16772 | AA82: 0 | AB82: 0 | AC82: =INT(R82) -> 46203 | AE82: =IF(ISNUMBER(AF82),DATE(YEAR(AF82),DAY(AF82),MONTH(AF82)),DATE(RIGHT(AF82,4),LEFT(AF82,2),MID(AF82,4,2))) -> 45982 | AF82: 11/21/2025 | AG82: 23.43
A83: 16 | B83: CVX | C83: OXY | D83: 88760 | E83: 46204.605 | F83: 166.28 | G83: 48.45 | H83: 166.26337 | I83: 48.454845 | J83: 3.9236625 | K83: 0.72444379 | L83: -601.39524 | M83: 1495.24 | N83: SHORT | O83: 1200000000000 | P83: signal | Q83: 88780 | R83: 46204.619 | S83: 166.5 | T83: 48.445 | U83: 0.36516037 | V83: -139.78315 | W83: -174.28451 | X83: 0 | Y83: 20.966353 | Z83: -195.25086 | AA83: 0 | AB83: 0 | AC83: =INT(R83) -> 46204 | AE83: =IF(ISNUMBER(AF83),DATE(YEAR(AF83),DAY(AF83),MONTH(AF83)),DATE(RIGHT(AF83,4),LEFT(AF83,2),MID(AF83,4,2))) -> 45985 | AF83: 11/24/2025 | AG83: 20.52
A84: 16 | B84: CVX | C84: OXY | D84: 89149 | E84: 46205.604 | F84: 168.05 | G84: 48.43 | H84: 168.0332 | I84: 48.434843 | J84: 4.7332451 | K84: 0.72444379 | L84: -595.06099 | M84: 1495.8575 | N84: SHORT | O84: 1260000000000 | P84: signal | Q84: 89170 | R84: 46205.619 | S84: 169.14 | T84: 48.93 | U84: 0.4371205 | V84: 99.312274 | W84: 64.683744 | X84: 0 | Y84: 20.909185 | Z84: 43.774559 | AA84: 0 | AB84: 0 | AC84: =INT(R84) -> 46205 | AE84: =IF(ISNUMBER(AF84),DATE(YEAR(AF84),DAY(AF84),MONTH(AF84)),DATE(RIGHT(AF84,4),LEFT(AF84,2),MID(AF84,4,2))) -> 45986 | AF84: 11/25/2025 | AG84: 18.56
A85: 16 | B85: CVX | C85: OXY | D85: 89430 | E85: 46205.799 | F85: 168.04 | G85: 48.48 | H85: 168.0568 | I85: 48.475152 | J85: -4.0112115 | K85: 0.72444379 | L85: 595.09641 | M85: -1494.3148 | N85: LONG | O85: 900000000000 | P85: signal | Q85: 89445 | R85: 46205.81 | S85: 168.46 | T85: 48.57 | U85: -0.4559868 | V85: 115.45216 | W85: 80.924843 | X85: 0 | Y85: 20.894112 | Z85: 60.030732 | AA85: 0 | AB85: 0 | AC85: =INT(R85) -> 46205 | AE85: =IF(ISNUMBER(AF85),DATE(YEAR(AF85),DAY(AF85),MONTH(AF85)),DATE(RIGHT(AF85,4),LEFT(AF85,2),MID(AF85,4,2))) -> 45987 | AF85: 11/26/2025 | AG85: 17.19
A86: 16 | B86: CVX | C86: OXY | D86: 89540 | E86: 46209.604 | F86: 168.685 | G86: 48.845 | H86: 168.70187 | I86: 48.840116 | J86: -3.6460094 | K86: 0.72444379 | L86: 592.82094 | M86: -1483.1483 | N86: LONG | O86: 1440000000000 | P86: signal | Q86: 89564 | R86: 46209.621 | S86: 169.075 | T86: 49.235 | U86: -0.16300201 | V86: -347.22768 | W86: -381.79752 | X86: 0 | Y86: 20.759693 | Z86: -402.55721 | AA86: 0 | AB86: 0 | AC86: =INT(R86) -> 46209 | AE86: =IF(ISNUMBER(AF86),DATE(YEAR(AF86),DAY(AF86),MONTH(AF86)),DATE(RIGHT(AF86,4),LEFT(AF86,2),MID(AF86,4,2))) -> 45988 | AF86: 11/27/2025 | AG86: 17.21
A87: 16 | B87: CVX | C87: OXY | D87: 89880 | E87: 46209.84 | F87: 167.68 | G87: 48.725 | H87: 167.66323 | I87: 48.729872 | J87: 3.5505425 | K87: 0.72444379 | L87: -596.37405 | M87: 1486.801 | N87: SHORT | O87: 120000000000 | P87: signal | Q87: 89882 | R87: 46209.842 | S87: 167.56 | T87: 48.75 | U87: 0.18551903 | V87: 108.73491 | W87: 74.249474 | X87: 0 | Y87: 20.831751 | Z87: 53.417724 | AA87: 0 | AB87: 0 | AC87: =INT(R87) -> 46209 | AE87: =IF(ISNUMBER(AF87),DATE(YEAR(AF87),DAY(AF87),MONTH(AF87)),DATE(RIGHT(AF87,4),LEFT(AF87,2),MID(AF87,4,2))) -> 45989 | AF87: 11/28/2025 | AG87: 16.35
A88: 16 | B88: CVX | C88: OXY | D88: 89930 | E88: 46210.604 | F88: 170.925 | G88: 49.57 | H88: 170.90791 | I88: 49.574957 | J88: 4.2075241 | K88: 0.72444379 | L88: -585.05192 | M88: 1461.4561 | N88: SHORT | O88: 120000000000 | P88: signal | Q88: 89932 | R88: 46210.606 | S88: 171.37 | T88: 50.19 | U88: 0.032782292 | V88: 645.75468 | W88: 611.14916 | X88: 0 | Y88: 20.46508 | Z88: 590.68408 | AA88: 0 | AB88: 0 | AC88: =INT(R88) -> 46210 | AE88: =IF(ISNUMBER(AF88),DATE(YEAR(AF88),DAY(AF88),MONTH(AF88)),DATE(RIGHT(AF88,4),LEFT(AF88,2),MID(AF88,4,2))) -> 45992 | AF88: 45669 | AG88: 17.24
AE89: =IF(ISNUMBER(AF89),DATE(YEAR(AF89),DAY(AF89),MONTH(AF89)),DATE(RIGHT(AF89,4),LEFT(AF89,2),MID(AF89,4,2))) -> 45993 | AF89: 45700 | AG89: 16.59
AE90: =IF(ISNUMBER(AF90),DATE(YEAR(AF90),DAY(AF90),MONTH(AF90)),DATE(RIGHT(AF90,4),LEFT(AF90,2),MID(AF90,4,2))) -> 45994 | AF90: 45728 | AG90: 16.08
AE91: =IF(ISNUMBER(AF91),DATE(YEAR(AF91),DAY(AF91),MONTH(AF91)),DATE(RIGHT(AF91,4),LEFT(AF91,2),MID(AF91,4,2))) -> 45995 | AF91: 45759 | AG91: 15.78
AE92: =IF(ISNUMBER(AF92),DATE(YEAR(AF92),DAY(AF92),MONTH(AF92)),DATE(RIGHT(AF92,4),LEFT(AF92,2),MID(AF92,4,2))) -> 45996 | AF92: 45789 | AG92: 15.41
AE93: =IF(ISNUMBER(AF93),DATE(YEAR(AF93),DAY(AF93),MONTH(AF93)),DATE(RIGHT(AF93,4),LEFT(AF93,2),MID(AF93,4,2))) -> 45999 | AF93: 45881 | AG93: 16.66
AE94: =IF(ISNUMBER(AF94),DATE(YEAR(AF94),DAY(AF94),MONTH(AF94)),DATE(RIGHT(AF94,4),LEFT(AF94,2),MID(AF94,4,2))) -> 46000 | AF94: 45912 | AG94: 16.93
AE95: =IF(ISNUMBER(AF95),DATE(YEAR(AF95),DAY(AF95),MONTH(AF95)),DATE(RIGHT(AF95,4),LEFT(AF95,2),MID(AF95,4,2))) -> 46001 | AF95: 45942 | AG95: 15.77
AE96: =IF(ISNUMBER(AF96),DATE(YEAR(AF96),DAY(AF96),MONTH(AF96)),DATE(RIGHT(AF96,4),LEFT(AF96,2),MID(AF96,4,2))) -> 46002 | AF96: 45973 | AG96: 14.85
AE97: =IF(ISNUMBER(AF97),DATE(YEAR(AF97),DAY(AF97),MONTH(AF97)),DATE(RIGHT(AF97,4),LEFT(AF97,2),MID(AF97,4,2))) -> 46003 | AF97: 46003 | AG97: 15.74
AE98: =IF(ISNUMBER(AF98),DATE(YEAR(AF98),DAY(AF98),MONTH(AF98)),DATE(RIGHT(AF98,4),LEFT(AF98,2),MID(AF98,4,2))) -> 46006 | AF98: 12/15/2025 | AG98: 16.5
AE99: =IF(ISNUMBER(AF99),DATE(YEAR(AF99),DAY(AF99),MONTH(AF99)),DATE(RIGHT(AF99,4),LEFT(AF99,2),MID(AF99,4,2))) -> 46007 | AF99: 12/16/2025 | AG99: 16.48
AE100: =IF(ISNUMBER(AF100),DATE(YEAR(AF100),DAY(AF100),MONTH(AF100)),DATE(RIGHT(AF100,4),LEFT(AF100,2),MID(AF100,4,2))) -> 46008 | AF100: 12/17/2025 | AG100: 17.62
AE101: =IF(ISNUMBER(AF101),DATE(YEAR(AF101),DAY(AF101),MONTH(AF101)),DATE(RIGHT(AF101,4),LEFT(AF101,2),MID(AF101,4,2))) -> 46009 | AF101: 12/18/2025 | AG101: 16.87
AE102: =IF(ISNUMBER(AF102),DATE(YEAR(AF102),DAY(AF102),MONTH(AF102)),DATE(RIGHT(AF102,4),LEFT(AF102,2),MID(AF102,4,2))) -> 46010 | AF102: 12/19/2025 | AG102: 14.91
...

Sheet Analysis
L1: Exit timestamp | M1: Cumulative Gross PnL | N1: Cumulative Slipped PnL | O1: Cumulative Net PnL | Q1: min holding minutes | R1: max holding minutes | S1: Mean Net PnL | T1: Number of trades
B2: Rough Analysis of the baseline strategy | J2: Figures | L2: =Trades!P2 -> signal | M2: =Trades!T2 -> 138.93 | N2: =Trades!U2 -> 0.32285626 | O2: =Trades!W2 -> 166.40739 | Q2: 0 | R2: 3 | S2: =AVERAGEIFS(Trades!W:W,Trades!N:N,">="&Q2,Trades!N:N,"<="&R2) -> #DIV/0! | T2: =COUNTIFS(Trades!N:N,">="&Q2,Trades!N:N,"<="&R2) -> 0
L3: =Trades!P3 -> signal | M3: =M2+Trades!T3 -> 274.65 | N3: =N2+Trades!U3 -> 0.59790225 | O3: =O2+Trades!W3 -> 984.01731 | Q3: 4 | R3: 7 | S3: =AVERAGEIFS(Trades!W:W,Trades!N:N,">="&Q3,Trades!N:N,"<="&R3) -> #DIV/0! | T3: =COUNTIFS(Trades!N:N,">="&Q3,Trades!N:N,"<="&R3) -> 0
B4: Column1 | C4: Gross | D4: Slipped | E4: Net (Transaction costs) | L4: =Trades!P4 -> signal | M4: =M3+Trades!T4 -> 410.04 | N4: =N3+Trades!U4 -> 0.50394977 | O4: =O3+Trades!W4 -> 1455.8565 | Q4: 8 | R4: 11 | S4: =AVERAGEIFS(Trades!W:W,Trades!N:N,">="&Q4,Trades!N:N,"<="&R4) -> #DIV/0! | T4: =COUNTIFS(Trades!N:N,">="&Q4,Trades!N:N,"<="&R4) -> 0
B5: Overall PnL | C5: =SUM(Trades!T2:T9652) -> 10285.49 | D5: =SUM(Trades!U2:U9652) -> 1389.7017 | E5: =SUM(Trades!W2:W9652) -> 13126.94 | L5: =Trades!P5 -> signal | M5: =M4+Trades!T5 -> 546.08 | N5: =N4+Trades!U5 -> 0.18880804 | O5: =O4+Trades!W5 -> 1554.7248 | Q5: 12 | R5: 15 | S5: =AVERAGEIFS(Trades!W:W,Trades!N:N,">="&Q5,Trades!N:N,"<="&R5) -> #DIV/0! | T5: =COUNTIFS(Trades!N:N,">="&Q5,Trades!N:N,"<="&R5) -> 0
B6: Mean PnL | C6: =AVERAGE(Trades!T:T) -> 118.22402 | D6: =AVERAGE(Trades!U:U) -> 15.44113 | E6: =AVERAGE(Trades!W:W) -> 150.88437 | L6: =Trades!P6 -> signal | M6: =M5+Trades!T6 -> 680.53 | N6: =N5+Trades!U6 -> 0.48700868 | O6: =O5+Trades!W6 -> 1876.8777 | Q6: 16 | R6: 19 | S6: =AVERAGEIFS(Trades!W:W,Trades!N:N,">="&Q6,Trades!N:N,"<="&R6) -> #DIV/0! | T6: =COUNTIFS(Trades!N:N,">="&Q6,Trades!N:N,"<="&R6) -> 0
B7: Median PnL | C7: =MEDIAN(Trades!T:T) -> 139.61 | D7: =MEDIAN(Trades!U:U) -> 0.11686958 | E7: =MEDIAN(Trades!W:W) -> 114.35879 | L7: =Trades!P7 -> signal | M7: =M6+Trades!T7 -> 816.595 | N7: =N6+Trades!U7 -> 0.49237589 | O7: =O6+Trades!W7 -> 2171.2661 | Q7: 20 | R7: 23 | S7: =AVERAGEIFS(Trades!W:W,Trades!N:N,">="&Q7,Trades!N:N,"<="&R7) -> #DIV/0! | T7: =COUNTIFS(Trades!N:N,">="&Q7,Trades!N:N,"<="&R7) -> 0
B8: Max drawdown | C8: =MIN(Trades!T:T) -> 43.83 | D8: =MIN(Trades!U:U) -> -0.49856161 | E8: =MIN(Trades!W:W) -> -2017.4321 | L8: =Trades!P8 -> signal | M8: =M7+Trades!T8 -> 956.205 | N8: =N7+Trades!U8 -> 0.17411608 | O8: =O7+Trades!W8 -> 1963.2326 | Q8: 24 | R8: 27 | S8: =AVERAGEIFS(Trades!W:W,Trades!N:N,">="&Q8,Trades!N:N,"<="&R8) -> #DIV/0! | T8: =COUNTIFS(Trades!N:N,">="&Q8,Trades!N:N,"<="&R8) -> 0
B9: Biggest Winner | C9: =MAX(Trades!T:T) -> 187.5 | D9: =MAX(Trades!U:U) -> 1239.3579 | E9: =MAX(Trades!W:W) -> 1920.4505 | L9: =Trades!P9 -> signal | M9: =M8+Trades!T9 -> 1093.65 | N9: =N8+Trades!U9 -> 0.49821397 | O9: =O8+Trades!W9 -> 2145.6452 | Q9: 28 | R9: 34 | S9: =AVERAGEIFS(Trades!W:W,Trades!N:N,">="&Q9,Trades!N:N,"<="&R9) -> #DIV/0! | T9: =COUNTIFS(Trades!N:N,">="&Q9,Trades!N:N,"<="&R9) -> 0
B10: Win rate | C10: =COUNTIF(Trades!T:T,">0")/(COUNTIF(Trades!T:T,">0")+COUNTIF(Trades!T:T,"<0")) -> 1 | D10: =COUNTIF(Trades!U:U,">0")/(COUNTIF(Trades!U:U,">0")+COUNTIF(Trades!U:U,"<0")) -> 0.55555556 | E10: =COUNTIF(Trades!W:W,">0")/(COUNTIF(Trades!W:W,">0")+COUNTIF(Trades!W:W,"<0")) -> 0.64367816 | L10: =Trades!P10 -> signal | M10: =M9+Trades!T10 -> 1230.32 | N10: =N9+Trades!U10 -> 0.12006464 | O10: =O9+Trades!W10 -> 1704.6712 | Q10: 35 | R10: 40 | S10: =AVERAGEIFS(Trades!W:W,Trades!N:N,">="&Q10,Trades!N:N,"<="&R10) -> #DIV/0! | T10: =COUNTIFS(Trades!N:N,">="&Q10,Trades!N:N,"<="&R10) -> 0
B11: Profit Factor | C11: =SUMIF(Trades!T:T,">0",Trades!T:T)/ABS(SUMIF(Trades!T:T,"<0",Trades!T:T)) -> #DIV/0! | D11: =SUMIF(Trades!U:U,">0",Trades!U:U)/ABS(SUMIF(Trades!U:U,"<0",Trades!U:U)) -> 129.34521 | E11: =SUMIF(Trades!W:W,">0",Trades!W:W)/ABS(SUMIF(Trades!W:W,"<0",Trades!W:W)) -> 2.2161259 | L11: =Trades!P11 -> signal | M11: =M9+Trades!T11 -> 1235.98 | N11: =N9+Trades!U11 -> 0.62656582 | O11: =O9+Trades!W11 -> 2308.5078
L12: =Trades!P12 -> signal | M12: =M11+Trades!T12 -> 1376.39 | N12: =N11+Trades!U12 -> 0.35596763 | O12: =O11+Trades!W12 -> 1832.1564 | Q12: 41 | R12: 47 | S12: =AVERAGEIFS(Trades!W:W,Trades!N:N,">="&Q12,Trades!N:N,"<="&R12) -> #DIV/0! | T12: =COUNTIFS(Trades!N:N,">="&Q12,Trades!N:N,"<="&R12) -> 0
B13: Column1 | C13: Column2 | L13: =Trades!P20 -> signal | M13: =M12+Trades!T20 -> 1554.8 | N13: =N12+Trades!U20 -> 0.48279195 | O13: =O12+Trades!W20 -> 2125.7186
B14: Number of Trades | C14: =COUNTA(Trades!A:A)-1 -> 87 | L14: =Trades!P13 -> signal | M14: =M13+Trades!T13 -> 1732.51 | N14: =N13+Trades!U13 -> 0.13270712 | O14: =O13+Trades!W13 -> 2240.0774
B15: Mean holding time | C15: =AVERAGE(Trades!N:N) -> #DIV/0! | L15: =Trades!P21 -> signal | M15: =M14+Trades!T21 -> 1905.13 | N15: =N14+Trades!U21 -> -0.08857873 | O15: =O14+Trades!W21 -> 2497.5251
B16: Median holding time | C16: =MEDIAN(Trades!N:N) -> #NUM! | L16: =Trades!P22 -> signal | M16: =M15+Trades!T22 -> 2078.71 | N16: =N15+Trades!U22 -> 0.40243136 | O16: =O15+Trades!W22 -> 480.09297
B17: Max holding time | C17: =MAX(Trades!N:N) -> 0 | L17: =Trades!P23 -> signal | M17: =M16+Trades!T23 -> 2252.765 | N17: =N16+Trades!U23 -> 0.54593177 | O17: =O16+Trades!W23 -> 34.028193
L18: =Trades!P14 -> signal | M18: =M17+Trades!T14 -> 2430.195 | N18: =N17+Trades!U14 -> 0.059731094 | O18: =O17+Trades!W14 -> 46.501552
B19: Column1 | C19: Positive | D19: Negative | L19: =Trades!P15 -> signal | M19: =M18+Trades!T15 -> 2611.845 | N19: =N18+Trades!U15 -> -0.20790767 | O19: =O18+Trades!W15 -> -117.95809
B20: Mean entry z score | C20: =AVERAGEIF(Trades!I:I,">0",Trades!I:I) -> 118.11758 | D20: =AVERAGEIF(Trades!I:I,"<0",Trades!I:I) -> #DIV/0! | L20: =Trades!P24 -> signal | M20: =M19+Trades!T24 -> 2788.365 | N20: =N19+Trades!U24 -> -0.64870004 | O20: =O19+Trades!W24 -> -132.36951
B21: Median entry z score | C21: {=MEDIAN(_xlfn._xlws.FILTER(Trades!I:I,Trades!I:I>0))} -> 138.86389 | D21: {=MEDIAN(_xlfn._xlws.FILTER(Trades!I:I,Trades!I:I<0))} -> #VALUE! | L21: =Trades!P25 -> signal | M21: =M20+Trades!T25 -> 2964.395 | N21: =N20+Trades!U25 -> -0.96170555 | O21: =O20+Trades!W25 -> -47.445824
B22: max entry z score | C22: =_xlfn.MAXIFS(Trades!I:I,Trades!I:I,">0") -> 187.30627 | D22: =_xlfn.MINIFS(Trades!I:I,Trades!I:I,"<0") -> 0 | L22: =Trades!P16 -> signal | M22: =M21+Trades!T16 -> 3144.53 | N22: =N21+Trades!U16 -> -0.58933354 | O22: =O21+Trades!W16 -> 307.91451
B23: Mean exit z score | C23: =AVERAGEIF(Trades!S:S,">0",Trades!S:S) -> 172.0081 | D23: =AVERAGEIF(Trades!S:S,"<0",Trades!S:S) -> #DIV/0! | L23: =Trades!P26 -> signal | M23: =M22+Trades!T26 -> 3317.54 | N23: =N22+Trades!U26 -> -0.091670785 | O23: =O22+Trades!W26 -> 196.71395
B24: Median exit z score | C24: {=MEDIAN(_xlfn._xlws.FILTER(Trades!S:S,Trades!S:S>0))} -> 183.485 | D24: {=MEDIAN(_xlfn._xlws.FILTER(Trades!S:S,Trades!S:S<0))} -> #VALUE! | L24: =Trades!P27 -> signal | M24: =M23+Trades!T27 -> 3362.42 | N24: =N23+Trades!U27 -> -0.12266821 | O24: =O23+Trades!W27 -> 949.81716
B25: max exit z score | C25: =_xlfn.MAXIFS(Trades!S:S,Trades!S:S,">0") -> 251.31 | D25: =_xlfn.MINIFS(Trades!S:S,Trades!S:S,"<0") -> 0 | L25: =Trades!P17 -> signal | M25: =M24+Trades!T17 -> 3539.89 | N25: =N24+Trades!U17 -> -0.25282199 | O25: =O24+Trades!W17 -> 1445.0831
G26: 1 | H26: Edge is there, but wiped out by costs | L26: =Trades!P18 -> signal | M26: =M25+Trades!T18 -> 3718.46 | N26: =N25+Trades!U18 -> 0.10783599 | O26: =O25+Trades!W18 -> 2067.1296
B27: Column1 | C27: Long | D27: Short | E27: Signal | F27: Forced | L27: =Trades!P19 -> signal | M27: =M26+Trades!T19 -> 3890.7 | N27: =N26+Trades!U19 -> -0.16607106 | O27: =O26+Trades!W19 -> 2260.5068
B28: PnL (gross) | C28: =SUMIF(Trades!M:M,"LONG",Trades!T:T) -> 0 | D28: =SUMIF(Trades!M:M,"SHORT",Trades!T:T) -> 0 | E28: =SUMIF(Trades!O:O,"Signal",Trades!T:T) -> 0 | F28: =SUMIF(Trades!O:O,"Forced",Trades!T:T) -> 0 | L28: =Trades!P28 -> signal | M28: =M27+Trades!T28 -> 3935.39 | N28: =N27+Trades!U28 -> 0.218997 | O28: =O27+Trades!W28 -> 2815.8245
B29: Number | C29: =COUNTIF(Trades!M:M,"LONG") -> 0 | D29: =COUNTIF(Trades!M:M,"SHORT") -> 0 | E29: =COUNTIF(Trades!O:O,"Signal") -> 0 | F29: =COUNTIF(Trades!O:O,"Forced") -> 0 | L29: =Trades!P35 -> signal | M29: =M28+Trades!T35 -> 3982.15 | N29: =N28+Trades!U35 -> 0.49102383 | O29: =O28+Trades!W35 -> 2114.7341
L30: =Trades!P44 -> signal | M30: =M29+Trades!T44 -> 4032.25 | N30: =N29+Trades!U44 -> 0.87027993 | O30: =O29+Trades!W44 -> 1426.027
B31: min Holding time | C31: Max Holding time | D31: Win rate | L31: =Trades!P52 -> signal | M31: =M30+Trades!T52 -> 4197.31 | N31: =N30+Trades!U52 -> 0.42909392 | O31: =O30+Trades!W52 -> 2588.3466
B32: 0 | C32: 3 | D32: =COUNTIFS(Trades!N:N,">="&B32,Trades!N:N,"<="&C32,Trades!T:T,">0")/(COUNTIFS(Trades!N:N,">="&B32,Trades!N:N,"<="&C32,Trades!T:T,">0")+COUNTIFS(Trades!N:N,">="&B32,Trades!N:N,"<="&C32,Trades!T:T,"<0")) -> #DIV/0! | L32: =Trades!P36 -> signal | M32: =M31+Trades!T36 -> 4242.765 | N32: =N31+Trades!U36 -> 0.63654799 | O32: =O31+Trades!W36 -> 2847.6984
B33: 4 | C33: 7 | D33: =COUNTIFS(Trades!N:N,">="&B33,Trades!N:N,"<="&C33,Trades!T:T,">0")/(COUNTIFS(Trades!N:N,">="&B33,Trades!N:N,"<="&C33,Trades!T:T,">0")+COUNTIFS(Trades!N:N,">="&B33,Trades!N:N,"<="&C33,Trades!T:T,"<0")) -> #DIV/0! | L33: =Trades!P45 -> signal | M33: =M32+Trades!T45 -> 4428.315 | N33: =N32+Trades!U45 -> 1.1212995 | O33: =O32+Trades!W45 -> 3144.1991
B34: 8 | C34: 11 | D34: =COUNTIFS(Trades!N:N,">="&B34,Trades!N:N,"<="&C34,Trades!T:T,">0")/(COUNTIFS(Trades!N:N,">="&B34,Trades!N:N,"<="&C34,Trades!T:T,">0")+COUNTIFS(Trades!N:N,">="&B34,Trades!N:N,"<="&C34,Trades!T:T,"<0")) -> #DIV/0! | L34: =Trades!P29 -> signal | M34: =M33+Trades!T29 -> 4473.395 | N34: =N33+Trades!U29 -> 0.74932506 | O34: =O33+Trades!W29 -> 4239.821
B35: 12 | C35: 15 | D35: =COUNTIFS(Trades!N:N,">="&B35,Trades!N:N,"<="&C35,Trades!T:T,">0")/(COUNTIFS(Trades!N:N,">="&B35,Trades!N:N,"<="&C35,Trades!T:T,">0")+COUNTIFS(Trades!N:N,">="&B35,Trades!N:N,"<="&C35,Trades!T:T,"<0")) -> #DIV/0! | L35: =Trades!P30 -> signal | M35: =M34+Trades!T30 -> 4518.13 | N35: =N34+Trades!U30 -> 1.1148411 | O35: =O34+Trades!W30 -> 4967.2789
B36: 16 | C36: 1000000 | D36: =COUNTIFS(Trades!N:N,">="&B36,Trades!N:N,"<="&C36,Trades!T:T,">0")/(COUNTIFS(Trades!N:N,">="&B36,Trades!N:N,"<="&C36,Trades!T:T,">0")+COUNTIFS(Trades!N:N,">="&B36,Trades!N:N,"<="&C36,Trades!T:T,"<0")) -> #DIV/0! | L36: =Trades!P37 -> signal | M36: =M35+Trades!T37 -> 4563.73 | N36: =N35+Trades!U37 -> 0.61627952 | O36: =O35+Trades!W37 -> 5575.5009
L37: =Trades!P53 -> signal | M37: =M36+Trades!T53 -> 4724.145 | N37: =N36+Trades!U53 -> 1.0585862 | O37: =O36+Trades!W53 -> 5671.7692
L38: =Trades!P54 -> signal | M38: =M37+Trades!T54 -> 4884.765 | N38: =N37+Trades!U54 -> 0.57031584 | O38: =O37+Trades!W54 -> 5881.363
B39: Conclusion: | L39: =Trades!P31 -> signal | M39: =M38+Trades!T31 -> 4928.95 | N39: =N38+Trades!U31 -> 0.91235225 | O39: =O38+Trades!W31 -> 5655.4478
B40: does the multiple pairs strategy improve diversification and risk adjusted returns instead of just gross exposure? | L40: =Trades!P32 -> signal | M40: =M39+Trades!T32 -> 4972.78 | N40: =N39+Trades!U32 -> 1.3289206 | O40: =O39+Trades!W32 -> 6943.7943
L41: =Trades!P46 -> signal | M41: =M40+Trades!T46 -> 5160.28 | N41: =N40+Trades!U46 -> 1.1940243 | O41: =O40+Trades!W46 -> 6676.0433
L42: =Trades!P55 -> signal | M42: =M41+Trades!T55 -> 5318.88 | N42: =N41+Trades!U55 -> 1.6416909 | O42: =O41+Trades!W55 -> 6729.4435
L43: =Trades!P47 -> signal | M43: =M42+Trades!T47 -> 5504.01 | N43: =N42+Trades!U47 -> 2.1324389 | O43: =O42+Trades!W47 -> 6976.452
L44: =Trades!P38 -> signal | M44: =M43+Trades!T38 -> 5549.94 | N44: =N43+Trades!U38 -> 2.3246524 | O44: =O43+Trades!W38 -> 7032.6972
L45: =Trades!P48 -> signal | M45: =M44+Trades!T48 -> 5733.77 | N45: =N44+Trades!U48 -> 2.0313787 | O45: =O44+Trades!W48 -> 7715.5854
G46: 2 | H46: shorter trades are significantly more profitiable | L46: =Trades!P39 -> signal | M46: =M45+Trades!T39 -> 5779.56 | N46: =N45+Trades!U39 -> 1.9809282 | O46: =O45+Trades!W39 -> 7993.8685 | Y46: 3 | Z46: most trades are short, but with a long tail
L47: =Trades!P40 -> signal | M47: =M46+Trades!T40 -> 5825.83 | N47: =N46+Trades!U40 -> 1.5104066 | O47: =O46+Trades!W40 -> 8525.7023
L48: =Trades!P56 -> signal | M48: =M47+Trades!T56 -> 5986.1 | N48: =N47+Trades!U56 -> 1.888788 | O48: =O47+Trades!W56 -> 8254.0816
L49: =Trades!P49 -> signal | M49: =M48+Trades!T49 -> 6159.91 | N49: =N48+Trades!U49 -> 2.0075448 | O49: =O48+Trades!W49 -> 8519.4228
L50: =Trades!P57 -> signal | M50: =M49+Trades!T57 -> 6317.6 | N50: =N49+Trades!U57 -> 1.9702127 | O50: =O49+Trades!W57 -> 8952.0074
L51: =Trades!P50 -> signal | M51: =M50+Trades!T50 -> 6494.03 | N51: =N50+Trades!U50 -> 1.9501827 | O51: =O50+Trades!W50 -> 8903.6024
L52: =Trades!P58 -> signal | M52: =M51+Trades!T58 -> 6650.78 | N52: =N51+Trades!U58 -> 1.5355145 | O52: =O51+Trades!W58 -> 9497.2552
L53: =Trades!P33 -> signal | M53: =M52+Trades!T33 -> 6696.39 | N53: =N52+Trades!U33 -> 1.4505233 | O53: =O52+Trades!W33 -> 10277.849
L54: =Trades!P41 -> signal | M54: =M53+Trades!T41 -> 6743.615 | N54: =N53+Trades!U41 -> 1.4246953 | O54: =O53+Trades!W41 -> 10383.41
L55: =Trades!P59 -> signal | M55: =M54+Trades!T59 -> 6899.675 | N55: =N54+Trades!U59 -> 1.3556588 | O55: =O54+Trades!W59 -> 10815.635
L56: =Trades!P51 -> signal | M56: =M55+Trades!T51 -> 7076.085 | N56: =N55+Trades!U51 -> 1.7905198 | O56: =O55+Trades!W51 -> 12736.085
L57: =Trades!P60 -> signal | M57: =M56+Trades!T60 -> 7232.36 | N57: =N56+Trades!U60 -> 1.3514762 | O57: =O56+Trades!W60 -> 12608.564
L58: =Trades!P42 -> signal | M58: =M57+Trades!T42 -> 7283.74 | N58: =N57+Trades!U42 -> 1.6997354 | O58: =O57+Trades!W42 -> 13282.952
L59: =Trades!P61 -> signal | M59: =M58+Trades!T61 -> 7444.605 | N59: =N58+Trades!U61 -> 2.1503859 | O59: =O58+Trades!W61 -> 13366.317
L60: =Trades!P34 -> signal | M60: =M59+Trades!T34 -> 7490.875 | N60: =N59+Trades!U34 -> 2.5207142 | O60: =O59+Trades!W34 -> 13263.259
L61: =Trades!P43 -> signal | M61: =M60+Trades!T43 -> 7541.915 | N61: =N60+Trades!U43 -> 2.9197573 | O61: =O60+Trades!W43 -> 12849.925
L62: =Trades!P62 -> signal | M62: =M61+Trades!T62 -> 7703.965 | N62: =N61+Trades!U62 -> 2.7249478 | O62: =O61+Trades!W62 -> 13053.232
L63: =Trades!P63 -> signal | M63: =M62+Trades!T63 -> 7865.33 | N63: =N62+Trades!U63 -> 2.3173494 | O63: =O62+Trades!W63 -> 12557.371
L64: =Trades!P74 -> signal | M64: =M63+Trades!T74 -> 7924.22 | N64: =N63+Trades!U74 -> 2.1539526 | O64: =O63+Trades!W74 -> 12517.25
L65: =Trades!P85 -> signal | M65: =M64+Trades!T85 -> 7972.79 | N65: =N64+Trades!U85 -> 1.6979658 | O65: =O64+Trades!W85 -> 12598.175
L66: =Trades!P75 -> signal | M66: =M65+Trades!T75 -> 8031.805 | N66: =N65+Trades!U75 -> 2.0719277 | O66: =O65+Trades!W75 -> 12532.903
L67: =Trades!P64 -> signal | M67: =M66+Trades!T64 -> 8197.04 | N67: =N66+Trades!U64 -> 2.3631198 | O67: =O66+Trades!W64 -> 13070.696
L68: =Trades!P86 -> signal | M68: =M67+Trades!T86 -> 8246.275 | N68: =N67+Trades!U86 -> 2.2001178 | O68: =O67+Trades!W86 -> 12688.899
L69: =Trades!P65 -> signal | M69: =M68+Trades!T65 -> 8411.355 | N69: =N68+Trades!U65 -> 2.6927469 | O69: =O68+Trades!W65 -> 12134.434
L70: =Trades!P76 -> signal | M70: =M69+Trades!T76 -> 8471.65 | N70: =N69+Trades!U76 -> 2.8964038 | O70: =O69+Trades!W76 -> 12077.851
L71: =Trades!P77 -> signal | M71: =M70+Trades!T77 -> 8530.09 | N71: =N70+Trades!U77 -> 3.392202 | O71: =O70+Trades!W77 -> 11421.086
L72: =Trades!P78 -> signal | M72: =M71+Trades!T78 -> 8588.6 | N72: =N71+Trades!U78 -> 3.338045 | O72: =O71+Trades!W78 -> 11409.086
L73: =Trades!P87 -> signal | M73: =M72+Trades!T87 -> 8637.35 | N73: =N72+Trades!U87 -> 3.523564 | O73: =O72+Trades!W87 -> 11483.336
L74: =Trades!P66 -> signal | M74: =M73+Trades!T66 -> 8809.47 | N74: =N73+Trades!U66 -> 3.7106425 | O74: =O73+Trades!W66 -> 10813.367
L75: =Trades!P67 -> signal | M75: =M74+Trades!T67 -> 8985.2 | N75: =N74+Trades!U67 -> 3.2743728 | O75: =O74+Trades!W67 -> 10996.184
L76: =Trades!P88 -> signal | M76: =M75+Trades!T88 -> 9035.39 | N76: =N75+Trades!U88 -> 3.3071551 | O76: =O75+Trades!W88 -> 11607.334
L77: =Trades!P79 -> forced | M77: =M76+Trades!T79 -> 9092.725 | N77: =N76+Trades!U79 -> 3.3071551 | O77: =O76+Trades!W79 -> 11395.993
L78: =Trades!P68 -> signal | M78: =M77+Trades!T68 -> 9271.045 | N78: =N77+Trades!U68 -> 3.2690626 | O78: =O77+Trades!W68 -> 12762.587
L79: =Trades!P80 -> signal | M79: =M78+Trades!T80 -> 9321.59 | N79: =N78+Trades!U80 -> 3.6454932 | O79: =O78+Trades!W80 -> 12977.264
L80: =Trades!P69 -> signal | M80: =M79+Trades!T69 -> 9501.01 | N80: =N79+Trades!U69 -> 3.7005004 | O80: =O79+Trades!W69 -> 12947.875
L81: =Trades!P89 -> 0 | M81: =M80+Trades!T89 -> 9501.01 | N81: =N80+Trades!U89 -> 3.7005004 | O81: =O80+Trades!W89 -> 12947.875
L82: =Trades!P90 -> 0 | M82: =M81+Trades!T90 -> 9501.01 | N82: =N81+Trades!U90 -> 3.7005004 | O82: =O81+Trades!W90 -> 12947.875
L83: =Trades!P81 -> signal | M83: =M82+Trades!T81 -> 9550.925 | N83: =N82+Trades!U81 -> 3.9909452 | O83: =O82+Trades!W81 -> 13061.003
L84: =Trades!P70 -> signal | M84: =M83+Trades!T70 -> 9719.54 | N84: =N83+Trades!U70 -> 3.6136605 | O84: =O83+Trades!W70 -> 13701.828
L85: =Trades!P91 -> 0 | M85: =M84+Trades!T91 -> 9719.54 | N85: =N84+Trades!U91 -> 3.6136605 | O85: =O84+Trades!W91 -> 13701.828
L86: =Trades!P71 -> signal | M86: =M85+Trades!T71 -> 9886.74 | N86: =N85+Trades!U71 -> 3.7286429 | O86: =O85+Trades!W71 -> 14188.592
L87: =Trades!P72 -> signal | M87: =M86+Trades!T72 -> 9945.72 | N87: =N86+Trades!U72 -> 3.4149468 | O87: =O86+Trades!W72 -> 13893.529
L88: =Trades!P92 -> 0 | M88: =M87+Trades!T92 -> 9945.72 | N88: =N87+Trades!U92 -> 1242.7729 | O88: =O87+Trades!W92 -> 13893.529
L89: =Trades!P82 -> signal | M89: =M88+Trades!T82 -> 9995.22 | N89: =N88+Trades!U82 -> 1242.2795 | O89: =O88+Trades!W82 -> 14102.34
L90: =Trades!P83 -> signal | M90: =M89+Trades!T83 -> 10043.665 | N90: =N89+Trades!U83 -> 1242.6447 | O90: =O89+Trades!W83 -> 13928.055
L91: =Trades!P73 -> signal | M91: =M90+Trades!T73 -> 10099.89 | N91: =N90+Trades!U73 -> 1242.83 | O91: =O90+Trades!W73 -> 13503.23
L92: =Trades!P84 -> signal | M92: =M91+Trades!T84 -> 10148.82 | N92: =N91+Trades!U84 -> 1243.2671 | O92: =O91+Trades!W84 -> 13567.914
L93: =Trades!P93 -> 0 | M93: =M92+Trades!T93 -> 10148.82 | N93: =N92+Trades!U93 -> 1252.2671 | O93: =O92+Trades!W93 -> 13567.914
L94: =Trades!P94 -> 0 | M94: =M93+Trades!T94 -> 10148.82 | N94: =N93+Trades!U94 -> 1389.9735 | O94: =O93+Trades!W94 -> 13567.914
L95: =Trades!P105 -> 0 | M95: =M94+Trades!T105 -> 10148.82 | N95: =N94+Trades!U105 -> 1389.9735 | O95: =O94+Trades!W105 -> 13567.914
L96: =Trades!P95 -> 0 | M96: =M95+Trades!T95 -> 10148.82 | N96: =N95+Trades!U95 -> 1390.0799 | O96: =O95+Trades!W95 -> 13567.914
L97: =Trades!P106 -> 0 | M97: =M96+Trades!T106 -> 10148.82 | N97: =N96+Trades!U106 -> 1390.0799 | O97: =O96+Trades!W106 -> 13567.914
L98: =Trades!P96 -> 0 | M98: =M97+Trades!T96 -> 10148.82 | N98: =N97+Trades!U96 -> 1390.0799 | O98: =O97+Trades!W96 -> 13567.914
L99: =Trades!P97 -> 0 | M99: =M98+Trades!T97 -> 10148.82 | N99: =N98+Trades!U97 -> 1390.0799 | O99: =O98+Trades!W97 -> 13567.914
L100: =Trades!P98 -> 0 | M100: =M99+Trades!T98 -> 10148.82 | N100: =N99+Trades!U98 -> 1390.0799 | O100: =O99+Trades!W98 -> 13567.914
...

Sheet comparison with single pair
B2: Metric | C2: Value | J2: Daily PnL table
B3: Net P&L | C3: =SUM(Trades!Z2:Z9652) -> 11654.223
B4: Number of trades | C4: =COUNTA(Trades!A:A)-1 -> 87 | J4: {=_xlfn.LET( _xlpm.dates,_xlfn.SEQUENCE(DATE(2026,8,2)-DATE(2025,8,2)+1,,DATE(2025,8,2)), _xlfn._xlws.FILTER(_xlpm.dates,WEEKDAY(_xlpm.dates,2)<=5) )} -> 45873 | K4: {=SUMIFS('trades edited'!$Z$2:$Z$100000,'trades edited'!$AC$2:$AC$100000,_xlfn.ANCHORARRAY(J4))} -> 0
B5: P&L/trade | C5: =AVERAGE(Trades!W:W) -> 150.88437 | J5: 45874 | K5: 0
B6: Daily P&L volatility | C6: =_xlfn.STDEV.S(_xlfn.ANCHORARRAY(K4)) -> 322.6555 | J6: 45875 | K6: 0
B7: Sharpe-like measure | C7: =AVERAGE(_xlfn.ANCHORARRAY(K4))/_xlfn.STDEV.S(_xlfn.ANCHORARRAY(K4))*SQRT(252) -> 2.2053177 | J7: 45876 | K7: 0
B8: Max drawdown | C8: =MIN(Trades!W:W) -> -2017.4321 | J8: 45877 | K8: 0
B9: Max drawdown / total P&L | C9: =C8/C3 -> -0.17310739 | J9: 45880 | K9: 0
B10: Worst day | J10: 45881 | K10: 0
B11: Max concurrent positions | J11: 45882 | K11: 0
B12: Max gross exposure | J12: 45883 | K12: 0
J13: 45884 | K13: 0
J14: 45887 | K14: 0
J15: 45888 | K15: 0
B16: it seems like this strat might actually be WORSE for risk *potentially* than the single pair version. The main question now is how much capital we need to keep in reserves to avoid margin calling and liquidation. portfolio total P&L = cumulative realised P&L up to minute + total unrealised P&L at minute | J16: 45889 | K16: 0
J17: 45890 | K17: 0
J18: 45891 | K18: 0
J19: 45894 | K19: 0
J20: 45895 | K20: 0
J21: 45896 | K21: 0
J22: 45897 | K22: 0
J23: 45898 | K23: 0
J24: 45901 | K24: 0
J25: 45902 | K25: 0
J26: 45903 | K26: 0
J27: 45904 | K27: 0
J28: 45905 | K28: 0
... J263: 46234 | K263: 0
