Workbook

Sheet Trades
A1: window_id | B1: stock1 | C1: stock2 | D1: entry_timestamp | E1: entry_price_1 | F1: entry_price_2 | G1: entry_price_1_slipped | H1: entry_price_2_slipped | I1: entry_zscore | J1: hedge_ratio_entry | K1: position_size_1 | L1: position_size_2 | M1: direction | N1: holding_minutes | O1: exit_reason | P1: exit_timestamp | Q1: exit_price_1 | R1: exit_price_2 | S1: exit_zscore | T1: gross_pnl | U1: gross_pnl_slipped | V1: transaction_costs | W1: net_pnl | X1: exit_price_age_1 | Y1: exit_price_age_2
A2: 0 | B2: JPM | C2: GS | D2: 24207 | E2: 306.355 | F2: 782.975 | G2: 306.32436 | H2: 783.0533 | I2: 3.594531 | J2: 0.66743015 | K2: -0.03264187 | L2: 0.0085242843 | M2: SHORT | N2: 7 | O2: signal | P2: 24214 | Q2: 305.615 | R2: 782.975 | S2: 0.36824447 | T2: 0.024154984 | U2: 0.020822539 | V2: 0.0033347938 | W2: 0.017487745 | X2: 305.615 | Y2: 782.975
A3: 0 | B3: JPM | C3: GS | D3: 24601 | E3: 310.255 | F3: 784.85 | G3: 310.22397 | H3: 784.92849 | I3: 3.7200374 | J3: 0.66743015 | K3: -0.032231551 | L3: 0.0085039198 | M3: SHORT | N3: 5 | O3: signal | P3: 24606 | Q3: 309.23 | R3: 786.1 | S3: 0.45860297 | T3: 0.04366724 | U3: 0.04033462 | V3: 0.0033347938 | W3: 0.036999827 | X3: 309.23 | Y3: 786.1
A4: 0 | B4: JPM | C4: GS | D4: 24832 | E4: 309.67 | F4: 784.45 | G4: 309.63903 | H4: 784.52845 | I4: 3.979432 | J4: 0.66743015 | K4: -0.03229244 | L4: 0.0085082561 | M4: SHORT | N4: 16 | O4: signal | P4: 24848 | Q4: 309.315 | R4: 783.6 | S4: 0.38578157 | T4: 0.0042317987 | U4: 0.00089880794 | V4: 0.0033347938 | W4: -0.0024359858 | X4: 309.315 | Y4: 783.6
A5: 0 | B5: JPM | C5: GS | D5: 24987 | E5: 310.945 | F5: 792.31 | G5: 310.97609 | H5: 792.23077 | I5: -4.4660855 | J5: 0.66743015 | K5: 0.032160028 | L5: -0.0084238511 | M5: LONG | N5: 9 | O5: signal | P5: 24996 | Q5: 311.59 | R5: 790.28 | S5: 0.2672345 | T5: 0.037843636 | U5: 0.034508411 | V5: 0.0033349268 | W5: 0.031173485 | X5: 311.59 | Y5: 790.28
A6: 0 | B6: JPM | C6: GS | D6: 25380 | E6: 305.665 | F6: 775.68 | G6: 305.69557 | H6: 775.60243 | I6: -3.6905639 | J6: 0.66743015 | K6: 0.032715555 | L6: -0.0086044522 | M6: LONG | N6: 12 | O6: signal | P6: 25392 | Q6: 307.425 | R6: 778.79 | S6: 0.21702582 | T6: 0.03081953 | U6: 0.027476236 | V6: 0.0033349268 | W6: 0.024141309 | X6: 307.425 | Y6: 778.79
A7: 0 | B7: JPM | C7: GS | D7: 25694 | E7: 308.605 | F7: 791.07 | G7: 308.57414 | H7: 791.14911 | I7: 3.6289486 | J7: 0.66743015 | K7: -0.032403882 | L7: 0.0084370555 | M7: SHORT | N7: 37 | O7: signal | P7: 25731 | Q7: 309.34 | R7: 792.03 | S7: 0.21396878 | T7: -0.01571728 | U7: -0.019055332 | V7: 0.0033347938 | W7: -0.022390126 | X7: 309.34 | Y7: 792.03
A8: 0 | B8: JPM | C8: GS | D8: 25752 | E8: 310.22 | F8: 793.57 | G8: 310.18898 | H8: 793.64936 | I8: 3.587045 | J8: 0.66743015 | K8: -0.032235188 | L8: 0.0084104761 | M8: SHORT | N8: 6 | O8: signal | P8: 25758 | Q8: 309.595 | R8: 792.46 | S8: 0.10046321 | T8: 0.010811364 | U8: 0.007479452 | V8: 0.0033347938 | W8: 0.0041446582 | X8: 309.595 | Y8: 792.46
A9: 0 | B9: JPM | C9: GS | D9: 26937 | E9: 316.57 | F9: 798.58 | G9: 316.60166 | H9: 798.50014 | I9: -3.6665215 | J9: 0.66743015 | K9: 0.03158859 | L9: -0.0083577118 | M9: LONG | N9: 5 | O9: signal | P9: 26942 | Q9: 319.07 | R9: 804.4 | S9: -0.22070535 | T9: 0.030329593 | U9: 0.026981971 | V9: 0.0033349268 | W9: 0.023647044 | X9: 319.07 | Y9: 804.4
A10: 0 | B10: JPM | C10: GS | D10: 27327 | E10: 318.785 | F10: 801.62 | G10: 318.75312 | H10: 801.70016 | I10: 3.8655947 | J10: 0.66743015 | K10: -0.031369105 | L10: 0.0083260167 | M10: SHORT | N10: 5 | O10: signal | P10: 27332 | Q10: 316.99 | R10: 797.74 | S10: 0.091473395 | T10: 0.024002598 | U10: 0.020676599 | V10: 0.0033347938 | W10: 0.017341805 | X10: 316.99 | Y10: 797.74
A11: 0 | B11: JPM | C11: GS | D11: 27717 | E11: 316.63 | F11: 816.83 | G11: 316.66166 | H11: 816.74832 | I11: -4.1191154 | J11: 0.66743015 | K11: 0.031582604 | L11: -0.0081709799 | M11: LONG | N11: 8 | O11: signal | P11: 27725 | Q11: 320.43 | R11: 829.34 | S11: -0.091250949 | T11: 0.017794938 | U11: 0.014437855 | V11: 0.0033349268 | W11: 0.011102928 | X11: 320.43 | Y11: 829.34
A12: 1 | B12: JPM | C12: GS | D12: 27902 | E12: 321.54 | F12: 832.99 | G12: 321.50785 | H12: 833.0733 | I12: 3.6646559 | J12: 0.65390315 | K12: -0.03110033 | L12: 0.007850072 | M12: SHORT | N12: 22 | O12: signal | P12: 27924 | Q12: 321.12 | R12: 832.625 | S12: 0.47150671 | T12: 0.010196862 | U12: 0.0068906486 | V12: 0.0033077371 | W12: 0.0035829115 | X12: 321.12 | Y12: 832.625
A13: 1 | B13: JPM | C13: GS | D13: 28497 | E13: 305.71 | F13: 787.29 | G13: 305.67943 | H13: 787.36873 | I13: 3.9612488 | J13: 0.65390315 | K13: -0.032710739 | L13: 0.0083057469 | M13: SHORT | N13: 7 | O13: signal | P13: 28504 | Q13: 304.365 | R13: 786.38 | S13: 0.030918091 | T13: 0.036437714 | U13: 0.033135063 | V13: 0.0033077371 | W13: 0.029827326 | X13: 304.365 | Y13: 786.38
... A138: 16 | B138: BAC | C138: USB | D138: 90259 | E138: 59.24 | F138: 62.225 | G138: 59.234076 | H138: 62.231223 | I138: 3.938376 | J138: 1.2019117 | K138: -0.16880486 | L138: 0.19315576 | M138: SHORT | N138: 31 | O138: signal | P138: 90290 | Q138: 59.23 | R138: 61.88 | S138: 0.19335895 | T138: -0.06495069 | U138: -0.06934768 | V138: 0.0044038639 | W138: -0.073751544 | X138: 59.23 | Y138: 61.88

Sheet trades edited
A1: window_id | B1: stock1 | C1: stock2 | D1: entry_timestamp | E1: entry_price_1 | F1: entry_price_2 | G1: entry_price_1_slipped | H1: entry_price_2_slipped | I1: entry_zscore | J1: hedge_ratio_entry | K1: position_size_1 | L1: position_size_2 | M1: direction | N1: holding_minutes | O1: exit_reason | P1: exit_timestamp | Q1: exit_price_1 | R1: exit_price_2 | S1: exit_zscore | T1: gross_pnl | U1: gross_pnl_slipped | V1: transaction_costs | W1: net_pnl | X1: Entry day | Y1: Exit day | Z1: VIX on entry | AE1: UK Date | AF1: US DATE | AG1: VIX ON ENTRY
A2: 0 | B2: JPM | C2: GS | D2: 24207 | E2: 306.355 | F2: 782.975 | G2: 306.32436 | H2: 783.0533 | I2: 3.594531 | J2: 0.66743015 | K2: -0.03264187 | L2: 0.0085242843 | M2: SHORT | N2: 7 | O2: signal | P2: 24214 | Q2: 305.615 | R2: 782.975 | S2: 0.36824447 | T2: 0.024154984 | U2: 0.020822539 | V2: 0.0033347938 | W2: 0.017487745 | X2: =WORKDAY(DATE(2025,8,2),INT(D2/390)) -> 45958 | Y2: =WORKDAY(DATE(2025,8,2),INT(P2/390)) -> 45958 | Z2: {=_xlfn.XLOOKUP(INT(X2),INT($AE$2:$AE$1000),$AG$2:$AG$1000,"")} -> 16.42 | AE2: =IF(ISNUMBER(AF2),DATE(YEAR(AF2),DAY(AF2),MONTH(AF2)),DATE(RIGHT(AF2,4),LEFT(AF2,2),MID(AF2,4,2))) -> 45870 | AF2: 45665 | AG2: 20.38 | AJ2: VIX at entry | AK2: Net PnL | AL2: Trades | AM2: Avg Net P&L | AN2: Win rate
A3: 0 | B3: JPM | C3: GS | D3: 24601 | E3: 310.255 | F3: 784.85 | G3: 310.22397 | H3: 784.92849 | I3: 3.7200374 | J3: 0.66743015 | K3: -0.032231551 | L3: 0.0085039198 | M3: SHORT | N3: 5 | O3: signal | P3: 24606 | Q3: 309.23 | R3: 786.1 | S3: 0.45860297 | T3: 0.04366724 | U3: 0.04033462 | V3: 0.0033347938 | W3: 0.036999827 | X3: =WORKDAY(DATE(2025,8,2),INT(D3/390)) -> 45959 | Y3: =WORKDAY(DATE(2025,8,2),INT(P3/390)) -> 45959 | Z3: {=_xlfn.XLOOKUP(INT(X3),INT($AE$2:$AE$1000),$AG$2:$AG$1000,"")} -> 16.92 | AE3: =IF(ISNUMBER(AF3),DATE(YEAR(AF3),DAY(AF3),MONTH(AF3)),DATE(RIGHT(AF3,4),LEFT(AF3,2),MID(AF3,4,2))) -> 45873 | AF3: 45755 | AG3: 17.52 | AJ3: <15 | AK3: =AL3*AM3 -> -1.6896569 | AL3: =COUNTIF(Z:Z,"<15") -> 107 | AM3: =AVERAGEIF(Z:Z,"<15",W:W) -> -0.015791186 | AN3: =COUNTIFS(Z:Z,"<15",T:T,">0")/COUNTIFS(Z:Z,"<15") -> 0.62616822
A4: 0 | B4: JPM | C4: GS | D4: 24832 | E4: 309.67 | F4: 784.45 | G4: 309.63903 | H4: 784.52845 | I4: 3.979432 | J4: 0.66743015 | K4: -0.03229244 | L4: 0.0085082561 | M4: SHORT | N4: 16 | O4: signal | P4: 24848 | Q4: 309.315 | R4: 783.6 | S4: 0.38578157 | T4: 0.0042317987 | U4: 0.00089880794 | V4: 0.0033347938 | W4: -0.0024359858 | X4: =WORKDAY(DATE(2025,8,2),INT(D4/390)) -> 45959 | Y4: =WORKDAY(DATE(2025,8,2),INT(P4/390)) -> 45959 | Z4: {=_xlfn.XLOOKUP(INT(X4),INT($AE$2:$AE$1000),$AG$2:$AG$1000,"")} -> 16.92 | AE4: =IF(ISNUMBER(AF4),DATE(YEAR(AF4),DAY(AF4),MONTH(AF4)),DATE(RIGHT(AF4,4),LEFT(AF4,2),MID(AF4,4,2))) -> 45874 | AF4: 45785 | AG4: 17.85 | AJ4: 15–20 | AK4: =AL4*AM4 -> 2.2099517 | AL4: =COUNTIFS(Z:Z,">=15",Z:Z,"<20") -> 293 | AM4: =AVERAGEIFS(W:W,Z:Z,">=15",Z:Z,"<20") -> 0.0075424972 | AN4: =COUNTIFS(Z:Z,">=15",Z:Z,"<20",T:T,">0")/COUNTIFS(Z:Z,">=15",Z:Z,"<20") -> 0.72013652
A5: 0 | B5: JPM | C5: GS | D5: 24987 | E5: 310.945 | F5: 792.31 | G5: 310.97609 | H5: 792.23077 | I5: -4.4660855 | J5: 0.66743015 | K5: 0.032160028 | L5: -0.0084238511 | M5: LONG | N5: 9 | O5: signal | P5: 24996 | Q5: 311.59 | R5: 790.28 | S5: 0.2672345 | T5: 0.037843636 | U5: 0.034508411 | V5: 0.0033349268 | W5: 0.031173485 | X5: =WORKDAY(DATE(2025,8,2),INT(D5/390)) -> 45960 | Y5: =WORKDAY(DATE(2025,8,2),INT(P5/390)) -> 45960 | Z5: {=_xlfn.XLOOKUP(INT(X5),INT($AE$2:$AE$1000),$AG$2:$AG$1000,"")} -> 16.91 | AE5: =IF(ISNUMBER(AF5),DATE(YEAR(AF5),DAY(AF5),MONTH(AF5)),DATE(RIGHT(AF5,4),LEFT(AF5,2),MID(AF5,4,2))) -> 45875 | AF5: 45816 | AG5: 16.77 | AJ5: >=20 | AK5: =AL5*AM5 -> 3.2875953 | AL5: =COUNTIFS(Z:Z,">=20") -> 164 | AM5: =AVERAGEIFS(W:W,Z:Z,">=20") -> 0.020046313 | AN5: =COUNTIFS(Z:Z,">=20",T:T,">0")/COUNTIFS(Z:Z,">=20") -> 0.74390244
A6: 0 | B6: JPM | C6: GS | D6: 25380 | E6: 305.665 | F6: 775.68 | G6: 305.69557 | H6: 775.60243 | I6: -3.6905639 | J6: 0.66743015 | K6: 0.032715555 | L6: -0.0086044522 | M6: LONG | N6: 12 | O6: signal | P6: 25392 | Q6: 307.425 | R6: 778.79 | S6: 0.21702582 | T6: 0.03081953 | U6: 0.027476236 | V6: 0.0033349268 | W6: 0.024141309 | X6: =WORKDAY(DATE(2025,8,2),INT(D6/390)) -> 45961 | Y6: =WORKDAY(DATE(2025,8,2),INT(P6/390)) -> 45961 | Z6: {=_xlfn.XLOOKUP(INT(X6),INT($AE$2:$AE$1000),$AG$2:$AG$1000,"")} -> 17.44 | AE6: =IF(ISNUMBER(AF6),DATE(YEAR(AF6),DAY(AF6),MONTH(AF6)),DATE(RIGHT(AF6,4),LEFT(AF6,2),MID(AF6,4,2))) -> 45876 | AF6: 45846 | AG6: 16.57
A7: 0 | B7: JPM | C7: GS | D7: 25694 | E7: 308.605 | F7: 791.07 | G7: 308.57414 | H7: 791.14911 | I7: 3.6289486 | J7: 0.66743015 | K7: -0.032403882 | L7: 0.0084370555 | M7: SHORT | N7: 37 | O7: signal | P7: 25731 | Q7: 309.34 | R7: 792.03 | S7: 0.21396878 | T7: -0.01571728 | U7: -0.019055332 | V7: 0.0033347938 | W7: -0.022390126 | X7: =WORKDAY(DATE(2025,8,2),INT(D7/390)) -> 45961 | Y7: =WORKDAY(DATE(2025,8,2),INT(P7/390)) -> 45961 | Z7: {=_xlfn.XLOOKUP(INT(X7),INT($AE$2:$AE$1000),$AG$2:$AG$1000,"")} -> 17.44 | AE7: =IF(ISNUMBER(AF7),DATE(YEAR(AF7),DAY(AF7),MONTH(AF7)),DATE(RIGHT(AF7,4),LEFT(AF7,2),MID(AF7,4,2))) -> 45877 | AF7: 45877 | AG7: 15.15
A8: 0 | B8: JPM | C8: GS | D8: 25752 | E8: 310.22 | F8: 793.57 | G8: 310.18898 | H8: 793.64936 | I8: 3.587045 | J8: 0.66743015 | K8: -0.032235188 | L8: 0.0084104761 | M8: SHORT | N8: 6 | O8: signal | P8: 25758 | Q8: 309.595 | R8: 792.46 | S8: 0.10046321 | T8: 0.010811364 | U8: 0.007479452 | V8: 0.0033347938 | W8: 0.0041446582 | X8: =WORKDAY(DATE(2025,8,2),INT(D8/390)) -> 45964 | Y8: =WORKDAY(DATE(2025,8,2),INT(P8/390)) -> 45964 | Z8: {=_xlfn.XLOOKUP(INT(X8),INT($AE$2:$AE$1000),$AG$2:$AG$1000,"")} -> 17.17 | AE8: =IF(ISNUMBER(AF8),DATE(YEAR(AF8),DAY(AF8),MONTH(AF8)),DATE(RIGHT(AF8,4),LEFT(AF8,2),MID(AF8,4,2))) -> 45880 | AF8: 45969 | AG8: 16.25
A9: 0 | B9: JPM | C9: GS | D9: 26937 | E9: 316.57 | F9: 798.58 | G9: 316.60166 | H9: 798.50014 | I9: -3.6665215 | J9: 0.66743015 | K9: 0.03158859 | L9: -0.0083577118 | M9: LONG | N9: 5 | O9: signal | P9: 26942 | Q9: 319.07 | R9: 804.4 | S9: -0.22070535 | T9: 0.030329593 | U9: 0.026981971 | V9: 0.0033349268 | W9: 0.023647044 | X9: =WORKDAY(DATE(2025,8,2),INT(D9/390)) -> 45967 | Y9: =WORKDAY(DATE(2025,8,2),INT(P9/390)) -> 45967 | Z9: {=_xlfn.XLOOKUP(INT(X9),INT($AE$2:$AE$1000),$AG$2:$AG$1000,"")} -> 19.5 | AE9: =IF(ISNUMBER(AF9),DATE(YEAR(AF9),DAY(AF9),MONTH(AF9)),DATE(RIGHT(AF9,4),LEFT(AF9,2),MID(AF9,4,2))) -> 45881 | AF9: 45999 | AG9: 14.73
A10: 0 | B10: JPM | C10: GS | D10: 27327 | E10: 318.785 | F10: 801.62 | G10: 318.75312 | H10: 801.70016 | I10: 3.8655947 | J10: 0.66743015 | K10: -0.031369105 | L10: 0.0083260167 | M10: SHORT | N10: 5 | O10: signal | P10: 27332 | Q10: 316.99 | R10: 797.74 | S10: 0.091473395 | T10: 0.024002598 | U10: 0.020676599 | V10: 0.0033347938 | W10: 0.017341805 | X10: =WORKDAY(DATE(2025,8,2),INT(D10/390)) -> 45968 | Y10: =WORKDAY(DATE(2025,8,2),INT(P10/390)) -> 45968 | Z10: {=_xlfn.XLOOKUP(INT(X10),INT($AE$2:$AE$1000),$AG$2:$AG$1000,"")} -> 19.08 | AE10: =IF(ISNUMBER(AF10),DATE(YEAR(AF10),DAY(AF10),MONTH(AF10)),DATE(RIGHT(AF10,4),LEFT(AF10,2),MID(AF10,4,2))) -> 45882 | AF10: 08/13/2025 | AG10: 14.49 | AJ10: Metric | AK10: OOS H1 | AL10: OOS H2
A11: 0 | B11: JPM | C11: GS | D11: 27717 | E11: 316.63 | F11: 816.83 | G11: 316.66166 | H11: 816.74832 | I11: -4.1191154 | J11: 0.66743015 | K11: 0.031582604 | L11: -0.0081709799 | M11: LONG | N11: 8 | O11: signal | P11: 27725 | Q11: 320.43 | R11: 829.34 | S11: -0.091250949 | T11: 0.017794938 | U11: 0.014437855 | V11: 0.0033349268 | W11: 0.011102928 | X11: =WORKDAY(DATE(2025,8,2),INT(D11/390)) -> 45971 | Y11: =WORKDAY(DATE(2025,8,2),INT(P11/390)) -> 45971 | Z11: {=_xlfn.XLOOKUP(INT(X11),INT($AE$2:$AE$1000),$AG$2:$AG$1000,"")} -> 17.6 | AE11: =IF(ISNUMBER(AF11),DATE(YEAR(AF11),DAY(AF11),MONTH(AF11)),DATE(RIGHT(AF11,4),LEFT(AF11,2),MID(AF11,4,2))) -> 45883 | AF11: 08/14/2025 | AG11: 14.83 | AJ11: Trades
A12: 1 | B12: BAC | C12: WFC | D12: 27901 | E12: 54.27 | F12: 86.98 | G12: 54.275427 | H12: 86.971302 | I12: -5.2945043 | J12: 0.78585231 | K12: 0.18426387 | L12: -0.090348621 | M12: LONG | N12: 23 | O12: signal | P12: 27924 | Q12: 54.35 | R12: 87.09 | S12: -0.49071198 | T12: 0.0048027609 | U12: 0.0012285884 | V12: 0.0035717474 | W12: -0.0023431591 | X12: =WORKDAY(DATE(2025,8,2),INT(D12/390)) -> 45971 | Y12: =WORKDAY(DATE(2025,8,2),INT(P12/390)) -> 45971 | Z12: {=_xlfn.XLOOKUP(INT(X12),INT($AE$2:$AE$1000),$AG$2:$AG$1000,"")} -> 17.6 | AE12: =IF(ISNUMBER(AF12),DATE(YEAR(AF12),DAY(AF12),MONTH(AF12)),DATE(RIGHT(AF12,4),LEFT(AF12,2),MID(AF12,4,2))) -> 45884 | AF12: 08/15/2025 | AG12: 15.09 | AJ12: Gross P&L
A13: 1 | B13: BAC | C13: WFC | D13: 28107 | E13: 53.855 | F13: 86.21 | G13: 53.860385 | H13: 86.201379 | I13: -4.2210563 | J13: 0.78585231 | K13: 0.18568378 | L13: -0.091155586 | M13: LONG | N13: 16 | O13: signal | P13: 28123 | Q13: 53.83 | R13: 86.07 | S13: -0.46599468 | T13: 0.0081196875 | U13: 0.0045497233 | V13: 0.0035717474 | W13: 0.00097797585 | X13: =WORKDAY(DATE(2025,8,2),INT(D13/390)) -> 45972 | Y13: =WORKDAY(DATE(2025,8,2),INT(P13/390)) -> 45972 | Z13: {=_xlfn.XLOOKUP(INT(X13),INT($AE$2:$AE$1000),$AG$2:$AG$1000,"")} -> 17.28 | AE13: =IF(ISNUMBER(AF13),DATE(YEAR(AF13),DAY(AF13),MONTH(AF13)),DATE(RIGHT(AF13,4),LEFT(AF13,2),MID(AF13,4,2))) -> 45887 | AF13: 08/18/2025 | AG13: 14.99 | AJ13: Net P&L
A14: 1 | B14: BAC | C14: WFC | D14: 28839 | E14: 52.725 | F14: 85.125 | G14: 52.730272 | H14: 85.116488 | I14: -3.745894 | J14: 0.78585231 | K14: 0.18966335 | L14: -0.092317452 | M14: LONG | N14: 19 | O14: signal | P14: 28858 | Q14: 52.615 | R14: 84.855 | S14: -0.36520226 | T14: 0.0040627437 | U14: 0.00049561794 | V14: 0.0035717474 | W14: -0.0030761295 | X14: =WORKDAY(DATE(2025,8,2),INT(D14/390)) -> 45973 | Y14: =WORKDAY(DATE(2025,8,2),INT(P14/390)) -> 45973 | Z14: {=_xlfn.XLOOKUP(INT(X14),INT($AE$2:$AE$1000),$AG$2:$AG$1000,"")} -> 17.51 | AE14: =IF(ISNUMBER(AF14),DATE(YEAR(AF14),DAY(AF14),MONTH(AF14)),DATE(RIGHT(AF14,4),LEFT(AF14,2),MID(AF14,4,2))) -> 45888 | AF14: 08/19/2025 | AG14: 15.57 | AJ14: Avg gross P&L/trade
A15: 1 | B15: BAC | C15: WFC | D15: 29105 | E15: 52.09 | F15: 84.31 | G15: 52.095209 | H15: 84.301569 | I15: -4.0396526 | J15: 0.78585231 | K15: 0.19197543 | L15: -0.093209857 | M15: LONG | N15: 17 | O15: signal | P15: 29122 | Q15: 52.035 | R15: 84.14 | S15: -0.20841839 | T15: 0.0052870272 | U15: 0.0017179631 | V15: 0.0035717474 | W15: -0.0018537844 | X15: =WORKDAY(DATE(2025,8,2),INT(D15/390)) -> 45974 | Y15: =WORKDAY(DATE(2025,8,2),INT(P15/390)) -> 45974 | Z15: {=_xlfn.XLOOKUP(INT(X15),INT($AE$2:$AE$1000),$AG$2:$AG$1000,"")} -> 20 | AE15: =IF(ISNUMBER(AF15),DATE(YEAR(AF15),DAY(AF15),MONTH(AF15)),DATE(RIGHT(AF15,4),LEFT(AF15,2),MID(AF15,4,2))) -> 45889 | AF15: 08/20/2025 | AG15: 15.69 | AJ15: Avg net P&L/trade
A16: 1 | B16: BAC | C16: WFC | D16: 29668 | E16: 51.95 | F16: 84.105 | G16: 51.944805 | H16: 84.113411 | I16: 4.3006198 | J16: 0.78585231 | K16: -0.19249278 | L16: 0.09343705 | M16: SHORT | N16: 26 | O16: signal | P16: 29694 | Q16: 52.165 | R16: 84.43 | S16: 0.40318604 | T16: -0.011018907 | U16: -0.014597787 | V16: 0.0035716618 | W16: -0.018169449 | X16: =WORKDAY(DATE(2025,8,2),INT(D16/390)) -> 45978 | Y16: =WORKDAY(DATE(2025,8,2),INT(P16/390)) -> 45978 | Z16: {=_xlfn.XLOOKUP(INT(X16),INT($AE$2:$AE$1000),$AG$2:$AG$1000,"")} -> 22.38 | AE16: =IF(ISNUMBER(AF16),DATE(YEAR(AF16),DAY(AF16),MONTH(AF16)),DATE(RIGHT(AF16,4),LEFT(AF16,2),MID(AF16,4,2))) -> 45890 | AF16: 08/21/2025 | AG16: 16.6 | AJ16: Net PF
A17: 1 | B17: BAC | C17: WFC | D17: 31217 | E17: 51.96 | F17: 84.86 | G17: 51.965196 | H17: 84.851514 | I17: -3.5614788 | J17: 0.78585231 | K17: 0.19245574 | L17: -0.09260574 | M17: LONG | N17: 20 | O17: signal | P17: 31237 | Q17: 52.51 | R17: 85.14 | S17: 0.40215492 | T17: 0.079921047 | U17: 0.076336165 | V17: 0.0035717474 | W17: 0.072764417 | X17: =WORKDAY(DATE(2025,8,2),INT(D17/390)) -> 45982 | Y17: =WORKDAY(DATE(2025,8,2),INT(P17/390)) -> 45982 | Z17: {=_xlfn.XLOOKUP(INT(X17),INT($AE$2:$AE$1000),$AG$2:$AG$1000,"")} -> 23.43 | AE17: =IF(ISNUMBER(AF17),DATE(YEAR(AF17),DAY(AF17),MONTH(AF17)),DATE(RIGHT(AF17,4),LEFT(AF17,2),MID(AF17,4,2))) -> 45891 | AF17: 08/22/2025 | AG17: 14.22 | AJ17: Win rate
A18: 1 | B18: BAC | C18: WFC | D18: 31444 | E18: 52.65 | F18: 84.8 | G18: 52.655265 | H18: 84.79152 | I18: -3.5053921 | J18: 0.78585231 | K18: 0.18993352 | L18: -0.092671263 | M18: LONG | N18: 32 | O18: signal | P18: 31476 | Q18: 52.71 | R18: 85.025 | S18: -0.49317777 | T18: -0.0094550227 | U18: -0.013029952 | V18: 0.0035717474 | W18: -0.016601699 | X18: =WORKDAY(DATE(2025,8,2),INT(D18/390)) -> 45982 | Y18: =WORKDAY(DATE(2025,8,2),INT(P18/390)) -> 45982 | Z18: {=_xlfn.XLOOKUP(INT(X18),INT($AE$2:$AE$1000),$AG$2:$AG$1000,"")} -> 23.43 | AE18: =IF(ISNUMBER(AF18),DATE(YEAR(AF18),DAY(AF18),MONTH(AF18)),DATE(RIGHT(AF18,4),LEFT(AF18,2),MID(AF18,4,2))) -> 45894 | AF18: 08/25/2025 | AG18: 14.79 | AJ18: Avg winner
A19: 1 | B19: BAC | C19: WFC | D19: 31612 | E19: 52.505 | F19: 85.055 | G19: 52.510251 | H19: 85.046495 | I19: -3.5933745 | J19: 0.78585231 | K19: 0.19045805 | L19: -0.092393429 | M19: LONG | N19: 10 | O19: signal | P19: 31622 | Q19: 52.78 | R19: 85.49 | S19: -0.050359074 | T19: 0.012184823 | U19: 0.0086038615 | V19: 0.0035717474 | W19: 0.005032114 | X19: =WORKDAY(DATE(2025,8,2),INT(D19/390)) -> 45985 | Y19: =WORKDAY(DATE(2025,8,2),INT(P19/390)) -> 45985 | Z19: {=_xlfn.XLOOKUP(INT(X19),INT($AE$2:$AE$1000),$AG$2:$AG$1000,"")} -> 20.52 | AE19: =IF(ISNUMBER(AF19),DATE(YEAR(AF19),DAY(AF19),MONTH(AF19)),DATE(RIGHT(AF19,4),LEFT(AF19,2),MID(AF19,4,2))) -> 45895 | AF19: 08/26/2025 | AG19: 14.62 | AJ19: Avg loser
A20: 1 | B20: JPM | C20: GS | D20: 27901 | E20: 321.49 | F20: 832.19 | G20: 321.45785 | H20: 832.27322 | I20: 5.2946162 | J20: 0.65390315 | K20: -0.031105167 | L20: 0.0078576185 | M20: SHORT | N20: 23 | O20: signal | P20: 27924 | Q20: 321.12 | R20: 832.625 | S20: 0.48959011 | T20: 0.014926976 | U20: 0.011619978 | V20: 0.0033077371 | W20: 0.0083122414 | X20: =WORKDAY(DATE(2025,8,2),INT(D20/390)) -> 45971 | Y20: =WORKDAY(DATE(2025,8,2),INT(P20/390)) -> 45971 | Z20: {=_xlfn.XLOOKUP(INT(X20),INT($AE$2:$AE$1000),$AG$2:$AG$1000,"")} -> 17.6 | AE20: =IF(ISNUMBER(AF20),DATE(YEAR(AF20),DAY(AF20),MONTH(AF20)),DATE(RIGHT(AF20,4),LEFT(AF20,2),MID(AF20,4,2))) -> 45896 | AF20: 08/27/2025 | AG20: 14.85 | AJ20: Avg holding time
A21: 1 | B21: JPM | C21: GS | D21: 28497 | E21: 305.71 | F21: 787.29 | G21: 305.67943 | H21: 787.36873 | I21: 3.9612488 | J21: 0.65390315 | K21: -0.032710739 | L21: 0.0083057469 | M21: SHORT | N21: 7 | O21: signal | P21: 28504 | Q21: 304.365 | R21: 786.38 | S21: 0.030918091 | T21: 0.036437714 | U21: 0.033135063 | V21: 0.0033077371 | W21: 0.029827326 | X21: =WORKDAY(DATE(2025,8,2),INT(D21/390)) -> 45973 | Y21: =WORKDAY(DATE(2025,8,2),INT(P21/390)) -> 45973 | Z21: {=_xlfn.XLOOKUP(INT(X21),INT($AE$2:$AE$1000),$AG$2:$AG$1000,"")} -> 17.51 | AE21: =IF(ISNUMBER(AF21),DATE(YEAR(AF21),DAY(AF21),MONTH(AF21)),DATE(RIGHT(AF21,4),LEFT(AF21,2),MID(AF21,4,2))) -> 45897 | AF21: 08/28/2025 | AG21: 14.43 | AJ21: Avg |entry Z|
A22: 1 | B22: JPM | C22: GS | D22: 28630 | E22: 304.8 | F22: 797.315 | G22: 304.83048 | H22: 797.23527 | I22: -3.6261084 | J22: 0.65390315 | K22: 0.032808399 | L22: -0.0082013151 | M22: LONG | N22: 9 | O22: signal | P22: 28639 | Q22: 305.47 | R22: 796.03 | S22: 0.26313253 | T22: 0.032520317 | U22: 0.029211367 | V22: 0.0033078755 | W22: 0.025903491 | X22: =WORKDAY(DATE(2025,8,2),INT(D22/390)) -> 45973 | Y22: =WORKDAY(DATE(2025,8,2),INT(P22/390)) -> 45973 | Z22: {=_xlfn.XLOOKUP(INT(X22),INT($AE$2:$AE$1000),$AG$2:$AG$1000,"")} -> 17.51 | AE22: =IF(ISNUMBER(AF22),DATE(YEAR(AF22),DAY(AF22),MONTH(AF22)),DATE(RIGHT(AF22,4),LEFT(AF22,2),MID(AF22,4,2))) -> 45898 | AF22: 08/29/2025 | AG22: 15.36
A23: 1 | B23: JPM | C23: GS | D23: 28708 | E23: 304.81 | F23: 797.11 | G23: 304.84048 | H23: 797.03029 | I23: -3.55602 | J23: 0.65390315 | K23: 0.032807323 | L23: -0.0082034243 | M23: LONG | N23: 27 | O23: signal | P23: 28735 | Q23: 304.57 | R23: 796.62 | S23: 0.12160767 | T23: -0.0038540795 | U23: -0.0071606965 | V23: 0.0033078755 | W23: -0.010468572 | X23: =WORKDAY(DATE(2025,8,2),INT(D23/390)) -> 45973 | Y23: =WORKDAY(DATE(2025,8,2),INT(P23/390)) -> 45973 | Z23: {=_xlfn.XLOOKUP(INT(X23),INT($AE$2:$AE$1000),$AG$2:$AG$1000,"")} -> 17.51 | AE23: =IF(ISNUMBER(AF23),DATE(YEAR(AF23),DAY(AF23),MONTH(AF23)),DATE(RIGHT(AF23,4),LEFT(AF23,2),MID(AF23,4,2))) -> 45901 | AF23: 45666 | AG23: 16.12
A24: 1 | B24: JPM | C24: GS | D24: 29594 | E24: 301.3 | F24: 781.25 | G24: 301.26987 | H24: 781.32812 | I24: 3.5359515 | J24: 0.65390315 | K24: -0.033189512 | L24: 0.0083699603 | M24: SHORT | N24: 5 | O24: signal | P24: 29599 | Q24: 300.495 | R24: 781.25 | S24: -0.42317359 | T24: 0.026717557 | U24: 0.023412423 | V24: 0.0033077371 | W24: 0.020104686 | X24: =WORKDAY(DATE(2025,8,2),INT(D24/390)) -> 45975 | Y24: =WORKDAY(DATE(2025,8,2),INT(P24/390)) -> 45975 | Z24: {=_xlfn.XLOOKUP(INT(X24),INT($AE$2:$AE$1000),$AG$2:$AG$1000,"")} -> 19.83 | AE24: =IF(ISNUMBER(AF24),DATE(YEAR(AF24),DAY(AF24),MONTH(AF24)),DATE(RIGHT(AF24,4),LEFT(AF24,2),MID(AF24,4,2))) -> 45902 | AF24: 45697 | AG24: 17.17
A25: 1 | B25: JPM | C25: GS | D25: 29667 | E25: 300.82 | F25: 776.07 | G25: 300.78992 | H25: 776.14761 | I25: 4.3180527 | J25: 0.65390315 | K25: -0.033242471 | L25: 0.0084258269 | M25: SHORT | N25: 24 | O25: signal | P25: 29691 | Q25: 302.36 | R25: 779.065 | S25: 0.36508655 | T25: -0.025958053 | U25: -0.029273502 | V25: 0.0033077371 | W25: -0.032581239 | X25: =WORKDAY(DATE(2025,8,2),INT(D25/390)) -> 45978 | Y25: =WORKDAY(DATE(2025,8,2),INT(P25/390)) -> 45978 | Z25: {=_xlfn.XLOOKUP(INT(X25),INT($AE$2:$AE$1000),$AG$2:$AG$1000,"")} -> 22.38 | AE25: =IF(ISNUMBER(AF25),DATE(YEAR(AF25),DAY(AF25),MONTH(AF25)),DATE(RIGHT(AF25,4),LEFT(AF25,2),MID(AF25,4,2))) -> 45903 | AF25: 45725 | AG25: 16.35
A26: 1 | B26: JPM | C26: GS | D26: 30059 | E26: 307.04 | F26: 805.745 | G26: 307.0707 | H26: 805.66443 | I26: -3.8618259 | J26: 0.65390315 | K26: 0.032569046 | L26: -0.0081155099 | M26: LONG | N26: 6 | O26: signal | P26: 30065 | Q26: 308.48 | R26: 807.56 | S26: -0.319723 | T26: 0.032169776 | U26: 0.028855807 | V26: 0.0033078755 | W26: 0.025547932 | X26: =WORKDAY(DATE(2025,8,2),INT(D26/390)) -> 45979 | Y26: =WORKDAY(DATE(2025,8,2),INT(P26/390)) -> 45979 | Z26: {=_xlfn.XLOOKUP(INT(X26),INT($AE$2:$AE$1000),$AG$2:$AG$1000,"")} -> 24.69 | AE26: =IF(ISNUMBER(AF26),DATE(YEAR(AF26),DAY(AF26),MONTH(AF26)),DATE(RIGHT(AF26,4),LEFT(AF26,2),MID(AF26,4,2))) -> 45904 | AF26: 45756 | AG26: 15.3
A27: 1 | B27: JPM | C27: GS | D27: 31217 | E27: 297.97 | F27: 792.37 | G27: 297.9998 | H27: 792.29076 | I27: -3.574562 | J27: 0.65390315 | K27: 0.033560426 | L27: -0.0082524976 | M27: LONG | N27: 10 | O27: signal | P27: 31227 | Q27: 299.32 | R27: 795.235 | S27: -0.43617298 | T27: 0.021663169 | U27: 0.018348468 | V27: 0.0033078755 | W27: 0.015040592 | X27: =WORKDAY(DATE(2025,8,2),INT(D27/390)) -> 45982 | Y27: =WORKDAY(DATE(2025,8,2),INT(P27/390)) -> 45982 | Z27: {=_xlfn.XLOOKUP(INT(X27),INT($AE$2:$AE$1000),$AG$2:$AG$1000,"")} -> 23.43 | AE27: =IF(ISNUMBER(AF27),DATE(YEAR(AF27),DAY(AF27),MONTH(AF27)),DATE(RIGHT(AF27,4),LEFT(AF27,2),MID(AF27,4,2))) -> 45905 | AF27: 45786 | AG27: 15.18
A28: 2 | B28: BAC | C28: WFC | D28: 31801 | E28: 53.09 | F28: 85.965 | G28: 53.095309 | H28: 85.956404 | I28: -5.2946208 | J28: 0.73858207 | K28: 0.18835939 | L28: -0.085916602 | M28: LONG | N28: 23 | O28: signal | P28: 31824 | Q28: 53.09 | R28: 86 | S28: -0.49061199 | T28: -0.0030070811 | U28: -0.0064845459 | V28: 0.0034772164 | W28: -0.0099617624 | X28: =WORKDAY(DATE(2025,8,2),INT(D28/390)) -> 45985 | Y28: =WORKDAY(DATE(2025,8,2),INT(P28/390)) -> 45985 | Z28: {=_xlfn.XLOOKUP(INT(X28),INT($AE$2:$AE$1000),$AG$2:$AG$1000,"")} -> 20.52 | AE28: =IF(ISNUMBER(AF28),DATE(YEAR(AF28),DAY(AF28),MONTH(AF28)),DATE(RIGHT(AF28,4),LEFT(AF28,2),MID(AF28,4,2))) -> 45908 | AF28: 45878 | AG28: 15.11
A29: 2 | B29: BAC | C29: WFC | D29: 32007 | E29: 53.05 | F29: 85.48 | G29: 53.044695 | H29: 85.488548 | I29: 4.5358082 | J29: 0.73858207 | K29: -0.18850141 | L29: 0.08640408 | M29: SHORT | N29: 48 | O29: signal | P29: 32055 | Q29: 53.64 | R29: 85.89 | S29: 0.45483687 | T29: -0.075790161 | U29: -0.07928199 | V29: 0.0034771119 | W29: -0.082759102 | X29: =WORKDAY(DATE(2025,8,2),INT(D29/390)) -> 45986 | Y29: =WORKDAY(DATE(2025,8,2),INT(P29/390)) -> 45986 | Z29: {=_xlfn.XLOOKUP(INT(X29),INT($AE$2:$AE$1000),$AG$2:$AG$1000,"")} -> 18.56 | AE29: =IF(ISNUMBER(AF29),DATE(YEAR(AF29),DAY(AF29),MONTH(AF29)),DATE(RIGHT(AF29,4),LEFT(AF29,2),MID(AF29,4,2))) -> 45909 | AF29: 45909 | AG29: 15.04
A30: 2 | B30: BAC | C30: WFC | D30: 32217 | E30: 53.525 | F30: 85.885 | G30: 53.530352 | H30: 85.876412 | I30: -4.2270289 | J30: 0.73858207 | K30: 0.18682858 | L30: -0.085996632 | M30: LONG | N30: 1 | O30: signal | P30: 32218 | Q30: 53.54 | R30: 85.66 | S30: 0.16301468 | T30: 0.022151671 | U30: 0.018676161 | V30: 0.0034772164 | W30: 0.015198945 | X30: =WORKDAY(DATE(2025,8,2),INT(D30/390)) -> 45986 | Y30: =WORKDAY(DATE(2025,8,2),INT(P30/390)) -> 45986 | Z30: {=_xlfn.XLOOKUP(INT(X30),INT($AE$2:$AE$1000),$AG$2:$AG$1000,"")} -> 18.56 | AE30: =IF(ISNUMBER(AF30),DATE(YEAR(AF30),DAY(AF30),MONTH(AF30)),DATE(RIGHT(AF30,4),LEFT(AF30,2),MID(AF30,4,2))) -> 45910 | AF30: 45939 | AG30: 15.35
A31: 2 | B31: BAC | C31: WFC | D31: 32614 | E31: 53.25 | F31: 85.77 | G31: 53.255325 | H31: 85.761423 | I31: -3.6888174 | J31: 0.73858207 | K31: 0.18779343 | L31: -0.086111936 | M31: LONG | N31: 17 | O31: signal | P31: 32631 | Q31: 53.135 | R31: 85.39 | S31: -0.28159101 | T31: 0.011126291 | U31: 0.0076545592 | V31: 0.0034772164 | W31: 0.0041773427 | X31: =WORKDAY(DATE(2025,8,2),INT(D31/390)) -> 45987 | Y31: =WORKDAY(DATE(2025,8,2),INT(P31/390)) -> 45987 | Z31: {=_xlfn.XLOOKUP(INT(X31),INT($AE$2:$AE$1000),$AG$2:$AG$1000,"")} -> 17.19 | AE31: =IF(ISNUMBER(AF31),DATE(YEAR(AF31),DAY(AF31),MONTH(AF31)),DATE(RIGHT(AF31,4),LEFT(AF31,2),MID(AF31,4,2))) -> 45911 | AF31: 45970 | AG31: 14.71
A32: 2 | B32: BAC | C32: WFC | D32: 32998 | E32: 53.3 | F32: 86.31 | G32: 53.29467 | H32: 86.318631 | I32: 4.1634247 | J32: 0.73858207 | K32: -0.18761726 | L32: 0.085573175 | M32: SHORT | N32: 17 | O32: signal | P32: 33015 | Q32: 53.525 | R32: 86.83 | S32: 0.4746937 | T32: 0.0022841673 | U32: -0.0012016681 | V32: 0.0034771119 | W32: -0.0046787799 | X32: =WORKDAY(DATE(2025,8,2),INT(D32/390)) -> 45988 | Y32: =WORKDAY(DATE(2025,8,2),INT(P32/390)) -> 45988 | Z32: {=_xlfn.XLOOKUP(INT(X32),INT($AE$2:$AE$1000),$AG$2:$AG$1000,"")} -> 17.21 | AE32: =IF(ISNUMBER(AF32),DATE(YEAR(AF32),DAY(AF32),MONTH(AF32)),DATE(RIGHT(AF32,4),LEFT(AF32,2),MID(AF32,4,2))) -> 45912 | AF32: 46000 | AG32: 14.76
A33: 2 | B33: BAC | C33: WFC | D33: 34559 | E33: 54.005 | F33: 89.76 | G33: 53.9996 | H33: 89.768976 | I33: 3.5672352 | J33: 0.73858207 | K33: -0.18516804 | L33: 0.082284099 | M33: SHORT | N33: 5 | O33: signal | P33: 34564 | Q33: 53.83 | R33: 89.755 | S33: 0.11894705 | T33: 0.031992987 | U33: 0.028519104 | V33: 0.0034771119 | W33: 0.025041992 | X33: =WORKDAY(DATE(2025,8,2),INT(D33/390)) -> 45994 | Y33: =WORKDAY(DATE(2025,8,2),INT(P33/390)) -> 45994 | Z33: {=_xlfn.XLOOKUP(INT(X33),INT($AE$2:$AE$1000),$AG$2:$AG$1000,"")} -> 16.08 | AE33: =IF(ISNUMBER(AF33),DATE(YEAR(AF33),DAY(AF33),MONTH(AF33)),DATE(RIGHT(AF33,4),LEFT(AF33,2),MID(AF33,4,2))) -> 45915 | AF33: 09/15/2025 | AG33: 15.69
A34: 2 | B34: BAC | C34: WFC | D34: 35304 | E34: 53.915 | F34: 90.32 | G34: 53.920392 | H34: 90.310968 | I34: -3.5605368 | J34: 0.73858207 | K34: 0.18547714 | L34: -0.081773923 | M34: LONG | N34: 6 | O34: signal | P34: 35310 | Q34: 54.27 | R34: 90.385 | S34: 0.059936539 | T34: 0.06052908 | U34: 0.0570448 | V34: 0.0034772164 | W34: 0.053567583 | X34: =WORKDAY(DATE(2025,8,2),INT(D34/390)) -> 45996 | Y34: =WORKDAY(DATE(2025,8,2),INT(P34/390)) -> 45996 | Z34: {=_xlfn.XLOOKUP(INT(X34),INT($AE$2:$AE$1000),$AG$2:$AG$1000,"")} -> 15.41 | AE34: =IF(ISNUMBER(AF34),DATE(YEAR(AF34),DAY(AF34),MONTH(AF34)),DATE(RIGHT(AF34,4),LEFT(AF34,2),MID(AF34,4,2))) -> 45916 | AF34: 09/16/2025 | AG34: 16.36
A35: 2 | B35: MS | C35: WFC | D35: 31801 | E35: 168.27 | F35: 85.965 | G35: 168.25317 | H35: 85.973596 | I35: 5.2944766 | J35: 0.92309383 | K35: -0.0594283 | L35: 0.10738019 | M35: SHORT | N35: 23 | O35: signal | P35: 31824 | Q35: 168.29 | R35: 86 | S35: 0.49154454 | T35: 0.0025697408 | U35: -0.0012769416 | V35: 0.0038461723 | W35: -0.0051231139 | X35: =WORKDAY(DATE(2025,8,2),INT(D35/390)) -> 45985 | Y35: =WORKDAY(DATE(2025,8,2),INT(P35/390)) -> 45985 | Z35: {=_xlfn.XLOOKUP(INT(X35),INT($AE$2:$AE$1000),$AG$2:$AG$1000,"")} -> 20.52 | AE35: =IF(ISNUMBER(AF35),DATE(YEAR(AF35),DAY(AF35),MONTH(AF35)),DATE(RIGHT(AF35,4),LEFT(AF35,2),MID(AF35,4,2))) -> 45917 | AF35: 09/17/2025 | AG35: 15.72
A36: 2 | B36: MS | C36: WFC | D36: 32010 | E36: 168.395 | F36: 85.51 | G36: 168.37816 | H36: 85.518551 | I36: 4.2045657 | J36: 0.92309383 | K36: -0.059384186 | L36: 0.10795157 | M36: SHORT | N36: 8 | O36: signal | P36: 32018 | Q36: 168.17 | R36: 85.62 | S36: -0.44407293 | T36: 0.025236114 | U36: 0.021390075 | V36: 0.0038461723 | W36: 0.017543903 | X36: =WORKDAY(DATE(2025,8,2),INT(D36/390)) -> 45986 | Y36: =WORKDAY(DATE(2025,8,2),INT(P36/390)) -> 45986 | Z36: {=_xlfn.XLOOKUP(INT(X36),INT($AE$2:$AE$1000),$AG$2:$AG$1000,"")} -> 18.56 | AE36: =IF(ISNUMBER(AF36),DATE(YEAR(AF36),DAY(AF36),MONTH(AF36)),DATE(RIGHT(AF36,4),LEFT(AF36,2),MID(AF36,4,2))) -> 45918 | AF36: 09/18/2025 | AG36: 15.7
A37: 2 | B37: MS | C37: WFC | D37: 32218 | E37: 168.52 | F37: 85.66 | G37: 168.53685 | H37: 85.651434 | I37: -4.2728175 | J37: 0.92309383 | K37: 0.059340138 | L37: -0.10776253 | M37: LONG | N37: 26 | O37: signal | P37: 32244 | Q37: 169.74 | R37: 86.39 | S37: -0.37128894 | T37: -0.006271679 | U37: -0.010132973 | V37: 0.003846203 | W37: -0.013979176 | X37: =WORKDAY(DATE(2025,8,2),INT(D37/390)) -> 45986 | Y37: =WORKDAY(DATE(2025,8,2),INT(P37/390)) -> 45986 | Z37: {=_xlfn.XLOOKUP(INT(X37),INT($AE$2:$AE$1000),$AG$2:$AG$1000,"")} -> 18.56 | AE37: =IF(ISNUMBER(AF37),DATE(YEAR(AF37),DAY(AF37),MONTH(AF37)),DATE(RIGHT(AF37,4),LEFT(AF37,2),MID(AF37,4,2))) -> 45919 | AF37: 09/19/2025 | AG37: 15.45
A38: 2 | B38: MS | C38: WFC | D38: 33778 | E38: 174.92 | F38: 89.97 | G38: 174.90251 | H38: 89.978997 | I38: 3.639135 | J38: 0.92309383 | K38: -0.057168992 | L38: 0.10260018 | M38: SHORT | N38: 8 | O38: signal | P38: 33786 | Q38: 174.87 | R38: 90.22 | S38: 0.2567332 | T38: 0.028508495 | U38: 0.024660028 | V38: 0.0038461723 | W38: 0.020813856 | X38: =WORKDAY(DATE(2025,8,2),INT(D38/390)) -> 45992 | Y38: =WORKDAY(DATE(2025,8,2),INT(P38/390)) -> 45992 | Z38: {=_xlfn.XLOOKUP(INT(X38),INT($AE$2:$AE$1000),$AG$2:$AG$1000,"")} -> 17.24 | AE38: =IF(ISNUMBER(AF38),DATE(YEAR(AF38),DAY(AF38),MONTH(AF38)),DATE(RIGHT(AF38,4),LEFT(AF38,2),MID(AF38,4,2))) -> 45922 | AF38: 09/22/2025 | AG38: 16.1
A39: 2 | B39: MS | C39: WFC | D39: 34137 | E39: 176.815 | F39: 90.16 | G39: 176.79732 | H39: 90.169016 | I39: 3.7864965 | J39: 0.92309383 | K39: -0.056556288 | L39: 0.10238397 | M39: SHORT | N39: 21 | O39: signal | P39: 34158 | Q39: 176.23 | R39: 89.77 | S39: 0.31570697 | T39: -0.0068443183 | U39: -0.010683204 | V39: 0.0038461723 | W39: -0.014529377 | X39: =WORKDAY(DATE(2025,8,2),INT(D39/390)) -> 45993 | Y39: =WORKDAY(DATE(2025,8,2),INT(P39/390)) -> 45993 | Z39: {=_xlfn.XLOOKUP(INT(X39),INT($AE$2:$AE$1000),$AG$2:$AG$1000,"")} -> 16.59 | AE39: =IF(ISNUMBER(AF39),DATE(YEAR(AF39),DAY(AF39),MONTH(AF39)),DATE(RIGHT(AF39,4),LEFT(AF39,2),MID(AF39,4,2))) -> 45923 | AF39: 09/23/2025 | AG39: 16.64
A40: 2 | B40: MS | C40: WFC | D40: 34169 | E40: 176.88 | F40: 89.375 | G40: 176.86231 | H40: 89.383938 | I40: 4.0761167 | J40: 0.92309383 | K40: -0.056535504 | L40: 0.10328323 | M40: SHORT | N40: 9 | O40: signal | P40: 34178 | Q40: 177.68 | R40: 90.28 | S40: 0.25507736 | T40: 0.048242916 | U40: 0.044382859 | V40: 0.0038461723 | W40: 0.040536686 | X40: =WORKDAY(DATE(2025,8,2),INT(D40/390)) -> 45993 | Y40: =WORKDAY(DATE(2025,8,2),INT(P40/390)) -> 45993 | Z40: {=_xlfn.XLOOKUP(INT(X40),INT($AE$2:$AE$1000),$AG$2:$AG$1000,"")} -> 16.59 | AE40: =IF(ISNUMBER(AF40),DATE(YEAR(AF40),DAY(AF40),MONTH(AF40)),DATE(RIGHT(AF40,4),LEFT(AF40,2),MID(AF40,4,2))) -> 45924 | AF40: 09/24/2025 | AG40: 16.18
A41: 2 | B41: MS | C41: WFC | D41: 34559 | E41: 177.17 | F41: 89.76 | G41: 177.15228 | H41: 89.768976 | I41: 4.3355863 | J41: 0.92309383 | K41: -0.056442964 | L41: 0.10284022 | M41: SHORT | N41: 45 | O41: signal | P41: 34604 | Q41: 179.2 | R41: 89.68 | S41: 0.11069287 | T41: -0.12280644 | U41: -0.12666326 | V41: 0.0038461723 | W41: -0.13050943 | X41: =WORKDAY(DATE(2025,8,2),INT(D41/390)) -> 45994 | Y41: =WORKDAY(DATE(2025,8,2),INT(P41/390)) -> 45994 | Z41: {=_xlfn.XLOOKUP(INT(X41),INT($AE$2:$AE$1000),$AG$2:$AG$1000,"")} -> 16.08 | AE41: =IF(ISNUMBER(AF41),DATE(YEAR(AF41),DAY(AF41),MONTH(AF41)),DATE(RIGHT(AF41,4),LEFT(AF41,2),MID(AF41,4,2))) -> 45925 | AF41: 09/25/2025 | AG41: 16.74
A42: 2 | B42: MS | C42: WFC | D42: 35099 | E42: 179.37 | F42: 89.49 | G42: 179.38794 | H42: 89.481051 | I42: -3.5849633 | J42: 0.92309383 | K42: 0.055750683 | L42: -0.1031505 | M42: LONG | N42: 18 | O42: signal | P42: 35117 | Q42: 179.17 | R42: 89.595 | S42: -0.48575459 | T42: -0.021980939 | U42: -0.025827095 | V42: 0.003846203 | W42: -0.029673298 | X42: =WORKDAY(DATE(2025,8,2),INT(D42/390)) -> 45995 | Y42: =WORKDAY(DATE(2025,8,2),INT(P42/390)) -> 45996 | Z42: {=_xlfn.XLOOKUP(INT(X42),INT($AE$2:$AE$1000),$AG$2:$AG$1000,"")} -> 15.78 | AE42: =IF(ISNUMBER(AF42),DATE(YEAR(AF42),DAY(AF42),MONTH(AF42)),DATE(RIGHT(AF42,4),LEFT(AF42,2),MID(AF42,4,2))) -> 45926 | AF42: 09/26/2025 | AG42: 15.29
A43: 2 | B43: MS | C43: WFC | D43: 35419 | E43: 180.74 | F43: 91.4 | G43: 180.75807 | H43: 91.39086 | I43: -3.5943 | J43: 0.92309383 | K43: 0.055328096 | L43: -0.10099495 | M43: LONG | N43: 3 | O43: signal | P43: 35422 | Q43: 181.415 | R43: 91.52 | S43: -0.20294239 | T43: 0.025227071 | U43: 0.021375936 | V43: 0.003846203 | W43: 0.017529733 | X43: =WORKDAY(DATE(2025,8,2),INT(D43/390)) -> 45996 | Y43: =WORKDAY(DATE(2025,8,2),INT(P43/390)) -> 45996 | Z43: {=_xlfn.XLOOKUP(INT(X43),INT($AE$2:$AE$1000),$AG$2:$AG$1000,"")} -> 15.41 | AE43: =IF(ISNUMBER(AF43),DATE(YEAR(AF43),DAY(AF43),MONTH(AF43)),DATE(RIGHT(AF43,4),LEFT(AF43,2),MID(AF43,4,2))) -> 45929 | AF43: 09/29/2025 | AG43: 16.12
A44: 2 | B44: BAC | C44: MS | D44: 31801 | E44: 53.09 | F44: 168.27 | G44: 53.095309 | H44: 168.25317 | I44: -5.2945196 | J44: 0.67069501 | K44: 0.18835939 | L44: -0.039858264 | M44: LONG | N44: 23 | O44: signal | P44: 31824 | Q44: 53.09 | R44: 168.29 | S44: -0.49025798 | T44: -0.00079716528 | U44: -0.004138635 | V44: 0.0033414559 | W44: -0.0074800909 | X44: =WORKDAY(DATE(2025,8,2),INT(D44/390)) -> 45985 | Y44: =WORKDAY(DATE(2025,8,2),INT(P44/390)) -> 45985 | Z44: {=_xlfn.XLOOKUP(INT(X44),INT($AE$2:$AE$1000),$AG$2:$AG$1000,"")} -> 20.52 | AE44: =IF(ISNUMBER(AF44),DATE(YEAR(AF44),DAY(AF44),MONTH(AF44)),DATE(RIGHT(AF44,4),LEFT(AF44,2),MID(AF44,4,2))) -> 45930 | AF44: 09/30/2025 | AG44: 16.28
A45: 2 | B45: BAC | C45: MS | D45: 32007 | E45: 53.05 | F45: 168.005 | G45: 53.044695 | H45: 168.0218 | I45: 4.0851305 | J45: 0.67069501 | K45: -0.18850141 | L45: 0.039921134 | M45: SHORT | N45: 25 | O45: signal | P45: 32032 | Q45: 53.39 | R45: 168.7 | S45: 0.4195729 | T45: -0.036345293 | U45: -0.039695866 | V45: 0.0033413242 | W45: -0.04303719 | X45: =WORKDAY(DATE(2025,8,2),INT(D45/390)) -> 45986 | Y45: =WORKDAY(DATE(2025,8,2),INT(P45/390)) -> 45986 | Z45: {=_xlfn.XLOOKUP(INT(X45),INT($AE$2:$AE$1000),$AG$2:$AG$1000,"")} -> 18.56 | AE45: =IF(ISNUMBER(AF45),DATE(YEAR(AF45),DAY(AF45),MONTH(AF45)),DATE(RIGHT(AF45,4),LEFT(AF45,2),MID(AF45,4,2))) -> 45931 | AF45: 45667 | AG45: 16.29
A46: 2 | B46: BAC | C46: MS | D46: 32998 | E46: 53.3 | F46: 168.41 | G46: 53.29467 | H46: 168.42684 | I46: 4.8934434 | J46: 0.67069501 | K46: -0.18761726 | L46: 0.03982513 | M46: SHORT | N46: 17 | O46: signal | P46: 33015 | Q46: 53.525 | R46: 169.185 | S46: 0.41153323 | T46: -0.011349408 | U46: -0.014698106 | V46: 0.0033413242 | W46: -0.01803943 | X46: =WORKDAY(DATE(2025,8,2),INT(D46/390)) -> 45988 | Y46: =WORKDAY(DATE(2025,8,2),INT(P46/390)) -> 45988 | Z46: {=_xlfn.XLOOKUP(INT(X46),INT($AE$2:$AE$1000),$AG$2:$AG$1000,"")} -> 17.21 | AE46: =IF(ISNUMBER(AF46),DATE(YEAR(AF46),DAY(AF46),MONTH(AF46)),DATE(RIGHT(AF46,4),LEFT(AF46,2),MID(AF46,4,2))) -> 45932 | AF46: 45698 | AG46: 16.63
A47: 2 | B47: BAC | C47: MS | D47: 33388 | E47: 54.38 | F47: 174.265 | G47: 54.374562 | H47: 174.28243 | I47: 4.3692742 | J47: 0.67069501 | K47: -0.18389114 | L47: 0.038487075 | M47: SHORT | N47: 17 | O47: signal | P47: 33405 | Q47: 54.445 | R47: 174.3 | S47: 0.44094135 | T47: -0.010605876 | U47: -0.013948596 | V47: 0.0033413242 | W47: -0.01728992 | X47: =WORKDAY(DATE(2025,8,2),INT(D47/390)) -> 45989 | Y47: =WORKDAY(DATE(2025,8,2),INT(P47/390)) -> 45989 | Z47: {=_xlfn.XLOOKUP(INT(X47),INT($AE$2:$AE$1000),$AG$2:$AG$1000,"")} -> 16.35 | AE47: =IF(ISNUMBER(AF47),DATE(YEAR(AF47),DAY(AF47),MONTH(AF47)),DATE(RIGHT(AF47,4),LEFT(AF47,2),MID(AF47,4,2))) -> 45933 | AF47: 45726 | AG47: 16.65
A48: 2 | B48: BAC | C48: MS | D48: 33778 | E48: 53.9 | F48: 174.92 | G48: 53.90539 | H48: 174.90251 | I48: -3.8535514 | J48: 0.67069501 | K48: 0.18552876 | L48: -0.038342957 | M48: LONG | N48: 9 | O48: signal | P48: 33787 | Q48: 54.24 | R48: 175.52 | S48: 0.21764902 | T48: 0.040074003 | U48: 0.036724004 | V48: 0.0033414559 | W48: 0.033382549 | X48: =WORKDAY(DATE(2025,8,2),INT(D48/390)) -> 45992 | Y48: =WORKDAY(DATE(2025,8,2),INT(P48/390)) -> 45992 | Z48: {=_xlfn.XLOOKUP(INT(X48),INT($AE$2:$AE$1000),$AG$2:$AG$1000,"")} -> 17.24 | AE48: =IF(ISNUMBER(AF48),DATE(YEAR(AF48),DAY(AF48),MONTH(AF48)),DATE(RIGHT(AF48,4),LEFT(AF48,2),MID(AF48,4,2))) -> 45936 | AF48: 45818 | AG48: 16.37
A49: 2 | B49: BAC | C49: MS | D49: 34168 | E49: 53.62 | F49: 176.725 | G49: 53.625362 | H49: 176.70733 | I49: -4.898697 | J49: 0.67069501 | K49: 0.18649758 | L49: -0.037951337 | M49: LONG | N49: 18 | O49: signal | P49: 34186 | Q49: 54.055 | R49: 178.35 | S49: -0.4969516 | T49: 0.019455522 | U49: 0.016099853 | V49: 0.0033414559 | W49: 0.012758397 | X49: =WORKDAY(DATE(2025,8,2),INT(D49/390)) -> 45993 | Y49: =WORKDAY(DATE(2025,8,2),INT(P49/390)) -> 45993 | Z49: {=_xlfn.XLOOKUP(INT(X49),INT($AE$2:$AE$1000),$AG$2:$AG$1000,"")} -> 16.59 | AE49: =IF(ISNUMBER(AF49),DATE(YEAR(AF49),DAY(AF49),MONTH(AF49)),DATE(RIGHT(AF49,4),LEFT(AF49,2),MID(AF49,4,2))) -> 45937 | AF49: 45848 | AG49: 17.24
A50: 2 | B50: BAC | C50: MS | D50: 34528 | E50: 53.87 | F50: 176.875 | G50: 53.875387 | H50: 176.85731 | I50: -3.5067484 | J50: 0.67069501 | K50: 0.18563208 | L50: -0.037919152 | M50: LONG | N50: 27 | O50: signal | P50: 34555 | Q50: 53.86 | R50: 176.61 | S50: 0.18115973 | T50: 0.0081922546 | U50: 0.0048520551 | V50: 0.0033414559 | W50: 0.0015105992 | X50: =WORKDAY(DATE(2025,8,2),INT(D50/390)) -> 45994 | Y50: =WORKDAY(DATE(2025,8,2),INT(P50/390)) -> 45994 | Z50: {=_xlfn.XLOOKUP(INT(X50),INT($AE$2:$AE$1000),$AG$2:$AG$1000,"")} -> 16.08 | AE50: =IF(ISNUMBER(AF50),DATE(YEAR(AF50),DAY(AF50),MONTH(AF50)),DATE(RIGHT(AF50,4),LEFT(AF50,2),MID(AF50,4,2))) -> 45938 | AF50: 45879 | AG50: 16.3
A51: 2 | B51: BAC | C51: MS | D51: 34745 | E51: 53.82 | F51: 179.88 | G51: 53.825382 | H51: 179.86201 | I51: -3.9480143 | J51: 0.67069501 | K51: 0.18580453 | L51: -0.037285691 | M51: LONG | N51: 40 | O51: signal | P51: 34785 | Q51: 53.625 | R51: 179.495 | S51: -0.36336053 | T51: -0.021876893 | U51: -0.025213224 | V51: 0.0033414559 | W51: -0.02855468 | X51: =WORKDAY(DATE(2025,8,2),INT(D51/390)) -> 45995 | Y51: =WORKDAY(DATE(2025,8,2),INT(P51/390)) -> 45995 | Z51: {=_xlfn.XLOOKUP(INT(X51),INT($AE$2:$AE$1000),$AG$2:$AG$1000,"")} -> 15.78 | AE51: =IF(ISNUMBER(AF51),DATE(YEAR(AF51),DAY(AF51),MONTH(AF51)),DATE(RIGHT(AF51,4),LEFT(AF51,2),MID(AF51,4,2))) -> 45939 | AF51: 45910 | AG51: 16.43
A52: 2 | B52: C | C52: GS | D52: 31801 | E52: 102.92 | F52: 817.49 | G52: 102.93029 | H52: 817.40825 | I52: -5.2945824 | J52: 0.75132766 | K52: 0.097162845 | L52: -0.0091906649 | M52: LONG | N52: 23 | O52: signal | P52: 31824 | Q52: 102.87 | R52: 816.91 | S52: -0.49083532 | T52: 0.00047244338 | U52: -0.0030291931 | V52: 0.0035027051 | W52: -0.0065318981 | X52: =WORKDAY(DATE(2025,8,2),INT(D52/390)) -> 45985 | Y52: =WORKDAY(DATE(2025,8,2),INT(P52/390)) -> 45985 | Z52: {=_xlfn.XLOOKUP(INT(X52),INT($AE$2:$AE$1000),$AG$2:$AG$1000,"")} -> 20.52 | AE52: =IF(ISNUMBER(AF52),DATE(YEAR(AF52),DAY(AF52),MONTH(AF52)),DATE(RIGHT(AF52,4),LEFT(AF52,2),MID(AF52,4,2))) -> 45940 | AF52: 45940 | AG52: 21.66
A53: 2 | B53: C | C53: GS | D53: 32218 | E53: 103.82 | F53: 820.08 | G53: 103.80962 | H53: 820.16201 | I53: 4.5696833 | J53: 0.75132766 | K53: -0.096320555 | L53: 0.0091616386 | M53: SHORT | N53: 27 | O53: signal | P53: 32245 | Q53: 104.27 | R53: 824.22 | S53: 0.4585845 | T53: -0.0054150657 | U53: -0.0089258483 | V53: 0.0035026056 | W53: -0.012428454 | X53: =WORKDAY(DATE(2025,8,2),INT(D53/390)) -> 45986 | Y53: =WORKDAY(DATE(2025,8,2),INT(P53/390)) -> 45986 | Z53: {=_xlfn.XLOOKUP(INT(X53),INT($AE$2:$AE$1000),$AG$2:$AG$1000,"")} -> 18.56 | AE53: =IF(ISNUMBER(AF53),DATE(YEAR(AF53),DAY(AF53),MONTH(AF53)),DATE(RIGHT(AF53,4),LEFT(AF53,2),MID(AF53,4,2))) -> 45943 | AF53: 10/13/2025 | AG53: 19.03
A54: 2 | B54: C | C54: GS | D54: 32607 | E54: 103.21 | F54: 813.89 | G54: 103.19968 | H54: 813.97139 | I54: 3.7043152 | J54: 0.75132766 | K54: -0.096889836 | L54: 0.009231317 | M54: SHORT | N54: 13 | O54: signal | P54: 32620 | Q54: 103.19 | R54: 813.36 | S54: 0.28206386 | T54: -0.0029548013 | U54: -0.0064567736 | V54: 0.0035026056 | W54: -0.0099593792 | X54: =WORKDAY(DATE(2025,8,2),INT(D54/390)) -> 45987 | Y54: =WORKDAY(DATE(2025,8,2),INT(P54/390)) -> 45987 | Z54: {=_xlfn.XLOOKUP(INT(X54),INT($AE$2:$AE$1000),$AG$2:$AG$1000,"")} -> 17.19 | AE54: =IF(ISNUMBER(AF54),DATE(YEAR(AF54),DAY(AF54),MONTH(AF54)),DATE(RIGHT(AF54,4),LEFT(AF54,2),MID(AF54,4,2))) -> 45944 | AF54: 10/14/2025 | AG54: 20.81
A55: 2 | B55: C | C55: GS | D55: 33390 | E55: 107.48 | F55: 839.53 | G55: 107.46925 | H55: 839.61395 | I55: 3.9562159 | J55: 0.75132766 | K55: -0.093040566 | L55: 0.0089493843 | M55: SHORT | N55: 11 | O55: signal | P55: 33401 | Q55: 107.13 | R55: 839.285 | S55: 0.047007871 | T55: 0.030371599 | U55: 0.026872419 | V55: 0.0035026056 | W55: 0.023369814 | X55: =WORKDAY(DATE(2025,8,2),INT(D55/390)) -> 45989 | Y55: =WORKDAY(DATE(2025,8,2),INT(P55/390)) -> 45989 | Z55: {=_xlfn.XLOOKUP(INT(X55),INT($AE$2:$AE$1000),$AG$2:$AG$1000,"")} -> 16.35 | AE55: =IF(ISNUMBER(AF55),DATE(YEAR(AF55),DAY(AF55),MONTH(AF55)),DATE(RIGHT(AF55,4),LEFT(AF55,2),MID(AF55,4,2))) -> 45945 | AF55: 10/15/2025 | AG55: 20.64
A56: 2 | B56: C | C56: GS | D56: 34168 | E56: 108.89 | F56: 858.26 | G56: 108.90089 | H56: 858.17417 | I56: -3.6343757 | J56: 0.75132766 | K56: 0.091835798 | L56: -0.0087540799 | M56: LONG | N56: 11 | O56: signal | P56: 34179 | Q56: 109.59 | R56: 862.345 | S56: -0.48581821 | T56: 0.028524642 | U56: 0.025011982 | V56: 0.0035027051 | W56: 0.021509277 | X56: =WORKDAY(DATE(2025,8,2),INT(D56/390)) -> 45993 | Y56: =WORKDAY(DATE(2025,8,2),INT(P56/390)) -> 45993 | Z56: {=_xlfn.XLOOKUP(INT(X56),INT($AE$2:$AE$1000),$AG$2:$AG$1000,"")} -> 16.59 | AE56: =IF(ISNUMBER(AF56),DATE(YEAR(AF56),DAY(AF56),MONTH(AF56)),DATE(RIGHT(AF56,4),LEFT(AF56,2),MID(AF56,4,2))) -> 45946 | AF56: 10/16/2025 | AG56: 25.31
A57: 2 | B57: C | C57: GS | D57: 34331 | E57: 108.3 | F57: 862.155 | G57: 108.31083 | H57: 862.06878 | I57: -3.5630462 | J57: 0.75132766 | K57: 0.092336103 | L57: -0.0087145312 | M57: LONG | N57: 33 | O57: signal | P57: 34364 | Q57: 108.22 | R57: 862.35 | S57: -0.42040733 | T57: -0.0090862219 | U57: -0.012588308 | V57: 0.0035027051 | W57: -0.016091013 | X57: =WORKDAY(DATE(2025,8,2),INT(D57/390)) -> 45994 | Y57: =WORKDAY(DATE(2025,8,2),INT(P57/390)) -> 45994 | Z57: {=_xlfn.XLOOKUP(INT(X57),INT($AE$2:$AE$1000),$AG$2:$AG$1000,"")} -> 16.08 | AE57: =IF(ISNUMBER(AF57),DATE(YEAR(AF57),DAY(AF57),MONTH(AF57)),DATE(RIGHT(AF57,4),LEFT(AF57,2),MID(AF57,4,2))) -> 45947 | AF57: 10/17/2025 | AG57: 20.78
A58: 2 | B58: C | C58: GS | D58: 34559 | E58: 109.39 | F58: 866.78 | G58: 109.37906 | H58: 866.86668 | I58: 4.5142387 | J58: 0.75132766 | K58: -0.091416034 | L58: 0.0086680318 | M58: SHORT | N58: 3 | O58: signal | P58: 34562 | Q58: 109.035 | R58: 869.67 | S58: -0.19928957 | T58: 0.057503304 | U58: 0.054001389 | V58: 0.0035026056 | W58: 0.050498783 | X58: =WORKDAY(DATE(2025,8,2),INT(D58/390)) -> 45994 | Y58: =WORKDAY(DATE(2025,8,2),INT(P58/390)) -> 45994 | Z58: {=_xlfn.XLOOKUP(INT(X58),INT($AE$2:$AE$1000),$AG$2:$AG$1000,"")} -> 16.08 | AE58: =IF(ISNUMBER(AF58),DATE(YEAR(AF58),DAY(AF58),MONTH(AF58)),DATE(RIGHT(AF58,4),LEFT(AF58,2),MID(AF58,4,2))) -> 45950 | AF58: 10/20/2025 | AG58: 18.23
A59: 2 | B59: C | C59: GS | D59: 34740 | E59: 108.74 | F59: 879.655 | G59: 108.75087 | H59: 879.56703 | I59: -4.3476102 | J59: 0.75132766 | K59: 0.091962479 | L59: -0.0085411629 | M59: LONG | N59: 8 | O59: signal | P59: 34748 | Q59: 108.34 | R59: 873.51 | S59: -0.43288763 | T59: 0.015700454 | U59: 0.012206726 | V59: 0.0035027051 | W59: 0.0087040207 | X59: =WORKDAY(DATE(2025,8,2),INT(D59/390)) -> 45995 | Y59: =WORKDAY(DATE(2025,8,2),INT(P59/390)) -> 45995 | Z59: {=_xlfn.XLOOKUP(INT(X59),INT($AE$2:$AE$1000),$AG$2:$AG$1000,"")} -> 15.78 | AE59: =IF(ISNUMBER(AF59),DATE(YEAR(AF59),DAY(AF59),MONTH(AF59)),DATE(RIGHT(AF59,4),LEFT(AF59,2),MID(AF59,4,2))) -> 45951 | AF59: 10/21/2025 | AG59: 17.87
A60: 2 | B60: C | C60: GS | D60: 34911 | E60: 108.75 | F60: 876.11 | G60: 108.73913 | H60: 876.19761 | I60: 3.6938441 | J60: 0.75132766 | K60: -0.091954023 | L60: 0.0085757229 | M60: SHORT | N60: 51 | O60: signal | P60: 34962 | Q60: 109.84 | R60: 877 | S60: 0.096414886 | T60: -0.092597492 | U60: -0.096110933 | V60: 0.0035026056 | W60: -0.099613539 | X60: =WORKDAY(DATE(2025,8,2),INT(D60/390)) -> 45995 | Y60: =WORKDAY(DATE(2025,8,2),INT(P60/390)) -> 45995 | Z60: {=_xlfn.XLOOKUP(INT(X60),INT($AE$2:$AE$1000),$AG$2:$AG$1000,"")} -> 15.78 | AE60: =IF(ISNUMBER(AF60),DATE(YEAR(AF60),DAY(AF60),MONTH(AF60)),DATE(RIGHT(AF60,4),LEFT(AF60,2),MID(AF60,4,2))) -> 45952 | AF60: 10/22/2025 | AG60: 18.6
A61: 2 | B61: C | C61: GS | D61: 35134 | E61: 110.185 | F61: 875.68 | G61: 110.17398 | H61: 875.76757 | I61: 3.5126816 | J61: 0.75132766 | K61: -0.090756455 | L61: 0.008579934 | M61: SHORT | N61: 14 | O61: signal | P61: 35148 | Q61: 110.13 | R61: 876.85 | S61: -0.004989877 | T61: 0.015030128 | U61: 0.011526968 | V61: 0.0035026056 | W61: 0.0080243622 | X61: =WORKDAY(DATE(2025,8,2),INT(D61/390)) -> 45996 | Y61: =WORKDAY(DATE(2025,8,2),INT(P61/390)) -> 45996 | Z61: {=_xlfn.XLOOKUP(INT(X61),INT($AE$2:$AE$1000),$AG$2:$AG$1000,"")} -> 15.41 | AE61: =IF(ISNUMBER(AF61),DATE(YEAR(AF61),DAY(AF61),MONTH(AF61)),DATE(RIGHT(AF61,4),LEFT(AF61,2),MID(AF61,4,2))) -> 45953 | AF61: 10/23/2025 | AG61: 17.3
A62: 2 | B62: C | C62: GS | D62: 35618 | E62: 111.32 | F62: 910.59 | G62: 111.33113 | H62: 910.49894 | I62: -3.6638745 | J62: 0.75132766 | K62: 0.089831117 | L62: -0.0082509984 | M62: LONG | N62: 43 | O62: signal | P62: 35661 | Q62: 111.57 | R62: 916.47 | S62: -0.47184014 | T62: -0.026058091 | U62: -0.029567844 | V62: 0.0035027051 | W62: -0.033070549 | X62: =WORKDAY(DATE(2025,8,2),INT(D62/390)) -> 45999 | Y62: =WORKDAY(DATE(2025,8,2),INT(P62/390)) -> 45999 | Z62: {=_xlfn.XLOOKUP(INT(X62),INT($AE$2:$AE$1000),$AG$2:$AG$1000,"")} -> 16.66 | AE62: =IF(ISNUMBER(AF62),DATE(YEAR(AF62),DAY(AF62),MONTH(AF62)),DATE(RIGHT(AF62,4),LEFT(AF62,2),MID(AF62,4,2))) -> 45954 | AF62: 10/24/2025 | AG62: 16.37
A63: 3 | B63: JPM | C63: PNC | D63: 35701 | E63: 317.625 | F63: 211.63 | G63: 317.59324 | H63: 211.65116 | I63: 5.2946485 | J63: 0.23219592 | K63: -0.031483668 | L63: 0.010971787 | M63: SHORT | N63: 23 | O63: signal | P63: 35724 | Q63: 317.095 | R63: 211.415 | S63: 0.49115147 | T63: 0.01432741 | U63: 0.011864922 | V63: 0.0024642383 | W63: 0.0094006842 | X63: =WORKDAY(DATE(2025,8,2),INT(D63/390)) -> 45999 | Y63: =WORKDAY(DATE(2025,8,2),INT(P63/390)) -> 45999 | Z63: {=_xlfn.XLOOKUP(INT(X63),INT($AE$2:$AE$1000),$AG$2:$AG$1000,"")} -> 16.66 | AE63: =IF(ISNUMBER(AF63),DATE(YEAR(AF63),DAY(AF63),MONTH(AF63)),DATE(RIGHT(AF63,4),LEFT(AF63,2),MID(AF63,4,2))) -> 45957 | AF63: 10/27/2025 | AG63: 15.79
A64: 3 | B64: JPM | C64: PNC | D64: 36126 | E64: 321.405 | F64: 211.53 | G64: 321.37286 | H64: 211.55115 | I64: 3.591409 | J64: 0.23219592 | K64: -0.031113393 | L64: 0.010976974 | M64: SHORT | N64: 19 | O64: signal | P64: 36145 | Q64: 320.915 | R64: 211.75 | S64: 0.19573617 | T64: 0.017660497 | U64: 0.015197388 | V64: 0.0024642383 | W64: 0.01273315 | X64: =WORKDAY(DATE(2025,8,2),INT(D64/390)) -> 46000 | Y64: =WORKDAY(DATE(2025,8,2),INT(P64/390)) -> 46000 | Z64: {=_xlfn.XLOOKUP(INT(X64),INT($AE$2:$AE$1000),$AG$2:$AG$1000,"")} -> 16.93 | AE64: =IF(ISNUMBER(AF64),DATE(YEAR(AF64),DAY(AF64),MONTH(AF64)),DATE(RIGHT(AF64,4),LEFT(AF64,2),MID(AF64,4,2))) -> 45958 | AF64: 10/28/2025 | AG64: 16.42
... A67: 3 | B67: JPM | C67: PNC | D67: 37679 | E67: 314.66 | F67: 209.51 | G67: 314.62853 | H67: 209.53095 | I67: 4.989752 | J67: 0.23219592 | K67: -0.031780334 | L67: 0.011082809 | M67: SHORT | N67: 16 | O67: signal | P67: 37695 | Q67: 315.41 | R67: 211.36 | S67: 0.3167078 | T67: -0.0033320549 | U67: -0.0058008806 | V67: 0.0024642383 | W67: -0.0082651189 | X67: =WORKDAY(DATE(2025,8,2),INT(D67/390)) -> 46006 | Y67: =WORKDAY(DATE(2025,8,2),INT(P67/390)) -> 46006 | Z67: {=_xlfn.XLOOKUP(INT(X67),INT($AE$2:$AE$1000),$AG$2:$AG$1000,"")} -> 16.5 | AE67: =IF(ISNUMBER(AF67),DATE(YEAR(AF67),DAY(AF67),MONTH(AF67)),DATE(RIGHT(AF67,4),LEFT(AF67,2),MID(AF67,4,2))) -> 45961 | AF67: 10/31/2025 | AG67: 17.44
A68: 3 | B68: JPM | C68: PNC | D68: 37853 | E68: 317.285 | F68: 211.41 | G68: 317.25327 | H68: 211.43114 | I68: 3.6495207 | J68: 0.23219592 | K68: -0.031517405 | L68: 0.010983204 | M68: SHORT | N68: 11 | O68: signal | P68: 37864 | Q68: 316.985 | R68: 211.69 | S68: 0.20614605 | T68: 0.012530519 | U68: 0.010066765 | V68: 0.0024642383 | W68: 0.0076025267 | X68: =WORKDAY(DATE(2025,8,2),INT(D68/390)) -> 46007 | Y68: =WORKDAY(DATE(2025,8,2),INT(P68/390)) -> 46007 | Z68: {=_xlfn.XLOOKUP(INT(X68),INT($AE$2:$AE$1000),$AG$2:$AG$1000,"")} -> 16.48 | AE68: =IF(ISNUMBER(AF68),DATE(YEAR(AF68),DAY(AF68),MONTH(AF68)),DATE(RIGHT(AF68,4),LEFT(AF68,2),MID(AF68,4,2))) -> 45964 | AF68: 45727 | AG68: 17.17
A69: 3 | B69: JPM | C69: PNC | D69: 38069 | E69: 320.055 | F69: 210.27 | G69: 320.02299 | H69: 210.29103 | I69: 4.9682768 | J69: 0.23219592 | K69: -0.03124463 | L69: 0.011042751 | M69: SHORT | N69: 23 | O69: signal | P69: 38092 | Q69: 320.49 | R69: 212.23 | S69: 0.39257105 | T69: 0.0080523777 | U69: 0.0055844624 | V69: 0.0024642383 | W69: 0.0031202241 | X69: =WORKDAY(DATE(2025,8,2),INT(D69/390)) -> 46007 | Y69: =WORKDAY(DATE(2025,8,2),INT(P69/390)) -> 46007 | Z69: {=_xlfn.XLOOKUP(INT(X69),INT($AE$2:$AE$1000),$AG$2:$AG$1000,"")} -> 16.48 | AE69: =IF(ISNUMBER(AF69),DATE(YEAR(AF69),DAY(AF69),MONTH(AF69)),DATE(RIGHT(AF69,4),LEFT(AF69,2),MID(AF69,4,2))) -> 45965 | AF69: 45758 | AG69: 19
A70: 3 | B70: JPM | C70: PNC | D70: 38457 | E70: 322.97 | F70: 212.72 | G70: 322.9377 | H70: 212.74127 | I70: 3.5251828 | J70: 0.23219592 | K70: -0.030962628 | L70: 0.010915566 | M70: SHORT | N70: 33 | O70: signal | P70: 38490 | Q70: 324.54 | R70: 212.78 | S70: 0.34875393 | T70: -0.047956392 | U70: -0.050425711 | V70: 0.0024642383 | W70: -0.052889949 | X70: =WORKDAY(DATE(2025,8,2),INT(D70/390)) -> 46008 | Y70: =WORKDAY(DATE(2025,8,2),INT(P70/390)) -> 46008 | Z70: {=_xlfn.XLOOKUP(INT(X70),INT($AE$2:$AE$1000),$AG$2:$AG$1000,"")} -> 17.62 | AE70: =IF(ISNUMBER(AF70),DATE(YEAR(AF70),DAY(AF70),MONTH(AF70)),DATE(RIGHT(AF70,4),LEFT(AF70,2),MID(AF70,4,2))) -> 45966 | AF70: 45788 | AG70: 18.01
A71: 3 | B71: JPM | C71: PNC | D71: 38666 | E71: 327.05 | F71: 212.945 | G71: 327.01729 | H71: 212.96629 | I71: 3.504723 | J71: 0.23219592 | K71: -0.030576364 | L71: 0.010904033 | M71: SHORT | N71: 36 | O71: signal | P71: 38702 | Q71: 327.48 | R71: 213.07 | S71: 0.46013995 | T71: -0.011784833 | U71: -0.014250676 | V71: 0.0024642383 | W71: -0.016714914 | X71: =WORKDAY(DATE(2025,8,2),INT(D71/390)) -> 46009 | Y71: =WORKDAY(DATE(2025,8,2),INT(P71/390)) -> 46009 | Z71: {=_xlfn.XLOOKUP(INT(X71),INT($AE$2:$AE$1000),$AG$2:$AG$1000,"")} -> 16.87 | AE71: =IF(ISNUMBER(AF71),DATE(YEAR(AF71),DAY(AF71),MONTH(AF71)),DATE(RIGHT(AF71,4),LEFT(AF71,2),MID(AF71,4,2))) -> 45967 | AF71: 45819 | AG71: 19.5
A72: 3 | B72: JPM | C72: PNC | D72: 38824 | E72: 325.6 | F72: 212.16 | G72: 325.63256 | H72: 212.13878 | I72: -3.9340394 | J72: 0.23219592 | K72: 0.030712531 | L72: -0.010944378 | M72: LONG | N72: 15 | O72: signal | P72: 38839 | Q72: 325.72 | R72: 211.7 | S72: 0.079422187 | T72: 0.0087199175 | U72: 0.0062556606 | V72: 0.0024645454 | W72: 0.0037911152 | X72: =WORKDAY(DATE(2025,8,2),INT(D72/390)) -> 46009 | Y72: =WORKDAY(DATE(2025,8,2),INT(P72/390)) -> 46009 | Z72: {=_xlfn.XLOOKUP(INT(X72),INT($AE$2:$AE$1000),$AG$2:$AG$1000,"")} -> 16.87 | AE72: =IF(ISNUMBER(AF72),DATE(YEAR(AF72),DAY(AF72),MONTH(AF72)),DATE(RIGHT(AF72,4),LEFT(AF72,2),MID(AF72,4,2))) -> 45968 | AF72: 45849 | AG72: 19.08
A73: 3 | B73: JPM | C73: PNC | D73: 39450 | E73: 326.53 | F73: 213.86 | G73: 326.56265 | H73: 213.83861 | I73: -3.6822591 | J73: 0.23219592 | K73: 0.030625057 | L73: -0.01085738 | M73: LONG | N73: 2 | O73: signal | P73: 39452 | Q73: 327.6 | R73: 213.86 | S73: 0.28876474 | T73: 0.032768811 | U73: 0.030301143 | V73: 0.0024645454 | W73: 0.027836597 | X73: =WORKDAY(DATE(2025,8,2),INT(D73/390)) -> 46013 | Y73: =WORKDAY(DATE(2025,8,2),INT(P73/390)) -> 46013 | Z73: {=_xlfn.XLOOKUP(INT(X73),INT($AE$2:$AE$1000),$AG$2:$AG$1000,"")} -> 14.08 | AE73: =IF(ISNUMBER(AF73),DATE(YEAR(AF73),DAY(AF73),MONTH(AF73)),DATE(RIGHT(AF73,4),LEFT(AF73,2),MID(AF73,4,2))) -> 45971 | AF73: 45941 | AG73: 17.6
A74: 3 | B74: GS | C74: TFC | D74: 35701 | E74: 915.55 | F74: 49.86 | G74: 915.64155 | H74: 49.855014 | I74: -5.2946403 | J74: 1.0056626 | K74: 0.010922396 | L74: -0.20169728 | M74: LONG | N74: 23 | O74: signal | P74: 35724 | Q74: 911.93 | R74: 49.735 | S74: -0.49239969 | T74: -0.014326915 | U74: -0.018331765 | V74: 0.0040113241 | W74: -0.022343089 | X74: =WORKDAY(DATE(2025,8,2),INT(D74/390)) -> 45999 | Y74: =WORKDAY(DATE(2025,8,2),INT(P74/390)) -> 45999 | Z74: {=_xlfn.XLOOKUP(INT(X74),INT($AE$2:$AE$1000),$AG$2:$AG$1000,"")} -> 16.66 | AE74: =IF(ISNUMBER(AF74),DATE(YEAR(AF74),DAY(AF74),MONTH(AF74)),DATE(RIGHT(AF74,4),LEFT(AF74,2),MID(AF74,4,2))) -> 45972 | AF74: 45972 | AG74: 17.28
A75: 3 | B75: GS | C75: TFC | D75: 35731 | E75: 908.86 | F75: 49.83 | G75: 908.95089 | H75: 49.825017 | I75: -3.6441848 | J75: 1.0056626 | K75: 0.011002795 | L75: -0.20181871 | M75: LONG | N75: 11 | O75: signal | P75: 35742 | Q75: 908.79 | R75: 49.67 | S75: -0.09366705 | T75: 0.031520798 | U75: 0.027512779 | V75: 0.0040113241 | W75: 0.023501454 | X75: =WORKDAY(DATE(2025,8,2),INT(D75/390)) -> 45999 | Y75: =WORKDAY(DATE(2025,8,2),INT(P75/390)) -> 45999 | Z75: {=_xlfn.XLOOKUP(INT(X75),INT($AE$2:$AE$1000),$AG$2:$AG$1000,"")} -> 16.66 | AE75: =IF(ISNUMBER(AF75),DATE(YEAR(AF75),DAY(AF75),MONTH(AF75)),DATE(RIGHT(AF75,4),LEFT(AF75,2),MID(AF75,4,2))) -> 45973 | AF75: 46002 | AG75: 17.51
A76: 3 | B76: GS | C76: TFC | D76: 36843 | E76: 880.93 | F76: 49.675 | G76: 881.01809 | H76: 49.670032 | I76: -4.5580958 | J76: 1.0056626 | K76: 0.01135164 | L76: -0.20244844 | M76: LONG | N76: 10 | O76: signal | P76: 36853 | Q76: 882.23 | R76: 49.495 | S76: -0.19344711 | T76: 0.051197851 | U76: 0.047188694 | V76: 0.0040113241 | W76: 0.04317737 | X76: =WORKDAY(DATE(2025,8,2),INT(D76/390)) -> 46002 | Y76: =WORKDAY(DATE(2025,8,2),INT(P76/390)) -> 46002 | Z76: {=_xlfn.XLOOKUP(INT(X76),INT($AE$2:$AE$1000),$AG$2:$AG$1000,"")} -> 14.85 | AE76: =IF(ISNUMBER(AF76),DATE(YEAR(AF76),DAY(AF76),MONTH(AF76)),DATE(RIGHT(AF76,4),LEFT(AF76,2),MID(AF76,4,2))) -> 45974 | AF76: 11/13/2025 | AG76: 20
A77: 3 | B77: GS | C77: TFC | D77: 37260 | E77: 870.79 | F77: 50.055 | G77: 870.70292 | H77: 50.060006 | I77: 3.5231039 | J77: 1.0056626 | K77: -0.011483825 | L77: 0.20091152 | M77: SHORT | N77: 19 | O77: signal | P77: 37279 | Q77: 872.05 | R77: 50.21 | S77: 0.00095208527 | T77: 0.016671666 | U77: 0.01265578 | V77: 0.0040113264 | W77: 0.0086444537 | X77: =WORKDAY(DATE(2025,8,2),INT(D77/390)) -> 46003 | Y77: =WORKDAY(DATE(2025,8,2),INT(P77/390)) -> 46003 | Z77: {=_xlfn.XLOOKUP(INT(X77),INT($AE$2:$AE$1000),$AG$2:$AG$1000,"")} -> 15.74 | AE77: =IF(ISNUMBER(AF77),DATE(YEAR(AF77),DAY(AF77),MONTH(AF77)),DATE(RIGHT(AF77,4),LEFT(AF77,2),MID(AF77,4,2))) -> 45975 | AF77: 11/14/2025 | AG77: 19.83
A78: 3 | B78: GS | C78: TFC | D78: 37289 | E78: 884.51 | F78: 50.245 | G78: 884.42155 | H78: 50.250024 | I78: 5.1381237 | J78: 1.0056626 | K78: -0.011305695 | L78: 0.20015178 | M78: SHORT | N78: 26 | O78: signal | P78: 37315 | Q78: 885.7 | R78: 50.145 | S78: 0.44876964 | T78: -0.033468955 | U78: -0.037479624 | V78: 0.0040113264 | W78: -0.04149095 | X78: =WORKDAY(DATE(2025,8,2),INT(D78/390)) -> 46003 | Y78: =WORKDAY(DATE(2025,8,2),INT(P78/390)) -> 46003 | Z78: {=_xlfn.XLOOKUP(INT(X78),INT($AE$2:$AE$1000),$AG$2:$AG$1000,"")} -> 15.74 | AE78: =IF(ISNUMBER(AF78),DATE(YEAR(AF78),DAY(AF78),MONTH(AF78)),DATE(RIGHT(AF78,4),LEFT(AF78,2),MID(AF78,4,2))) -> 45978 | AF78: 11/17/2025 | AG78: 22.38
A79: 3 | B79: GS | C79: TFC | D79: 37679 | E79: 883.68 | F79: 50 | G79: 883.59163 | H79: 50.005 | I79: 4.5849355 | J79: 1.0056626 | K79: -0.011316314 | L79: 0.20113252 | M79: SHORT | N79: 36 | O79: signal | P79: 37715 | Q79: 891.16 | R79: 50.11 | S79: 0.39585257 | T79: -0.062521448 | U79: -0.06654345 | V79: 0.0040113264 | W79: -0.070554777 | X79: =WORKDAY(DATE(2025,8,2),INT(D79/390)) -> 46006 | Y79: =WORKDAY(DATE(2025,8,2),INT(P79/390)) -> 46006 | Z79: {=_xlfn.XLOOKUP(INT(X79),INT($AE$2:$AE$1000),$AG$2:$AG$1000,"")} -> 16.5 | AE79: =IF(ISNUMBER(AF79),DATE(YEAR(AF79),DAY(AF79),MONTH(AF79)),DATE(RIGHT(AF79,4),LEFT(AF79,2),MID(AF79,4,2))) -> 45979 | AF79: 11/18/2025 | AG79: 24.69
A80: 3 | B80: GS | C80: TFC | D80: 38059 | E80: 893.32 | F80: 50.025 | G80: 893.40933 | H80: 50.019998 | I80: -3.6561726 | J80: 1.0056626 | K80: 0.011194197 | L80: -0.20103201 | M80: LONG | N80: 10 | O80: signal | P80: 38069 | Q80: 899.46 | R80: 50.215 | S80: 0.15582032 | T80: 0.030536287 | U80: 0.026514269 | V80: 0.0040113241 | W80: 0.022502945 | X80: =WORKDAY(DATE(2025,8,2),INT(D80/390)) -> 46007 | Y80: =WORKDAY(DATE(2025,8,2),INT(P80/390)) -> 46007 | Z80: {=_xlfn.XLOOKUP(INT(X80),INT($AE$2:$AE$1000),$AG$2:$AG$1000,"")} -> 16.48 | AE80: =IF(ISNUMBER(AF80),DATE(YEAR(AF80),DAY(AF80),MONTH(AF80)),DATE(RIGHT(AF80,4),LEFT(AF80,2),MID(AF80,4,2))) -> 45980 | AF80: 11/19/2025 | AG80: 23.66
A81: 3 | B81: GS | C81: TFC | D81: 38463 | E81: 894.825 | F81: 50.665 | G81: 894.91448 | H81: 50.659934 | I81: -3.9756674 | J81: 1.0056626 | K81: 0.011175369 | L81: -0.19849257 | M81: LONG | N81: 24 | O81: signal | P81: 38487 | Q81: 897.08 | R81: 50.72 | S81: -0.40826683 | T81: 0.014283367 | U81: 0.01026843 | V81: 0.0040113241 | W81: 0.0062571055 | X81: =WORKDAY(DATE(2025,8,2),INT(D81/390)) -> 46008 | Y81: =WORKDAY(DATE(2025,8,2),INT(P81/390)) -> 46008 | Z81: {=_xlfn.XLOOKUP(INT(X81),INT($AE$2:$AE$1000),$AG$2:$AG$1000,"")} -> 17.62 | AE81: =IF(ISNUMBER(AF81),DATE(YEAR(AF81),DAY(AF81),MONTH(AF81)),DATE(RIGHT(AF81,4),LEFT(AF81,2),MID(AF81,4,2))) -> 45981 | AF81: 11/20/2025 | AG81: 26.42
A82: 3 | B82: GS | C82: TFC | D82: 39214 | E82: 907.96 | F82: 50.415 | G82: 907.8692 | H82: 50.420042 | I82: 3.7328139 | J82: 1.0056626 | K82: -0.011013701 | L82: 0.19947687 | M82: SHORT | N82: 12 | O82: signal | P82: 39226 | Q82: 907.33 | R82: 50.435 | S82: -0.083456284 | T82: 0.010928169 | U82: 0.0069171387 | V82: 0.0040113264 | W82: 0.0029058123 | X82: =WORKDAY(DATE(2025,8,2),INT(D82/390)) -> 46010 | Y82: =WORKDAY(DATE(2025,8,2),INT(P82/390)) -> 46010 | Z82: {=_xlfn.XLOOKUP(INT(X82),INT($AE$2:$AE$1000),$AG$2:$AG$1000,"")} -> 14.91 | AE82: =IF(ISNUMBER(AF82),DATE(YEAR(AF82),DAY(AF82),MONTH(AF82)),DATE(RIGHT(AF82,4),LEFT(AF82,2),MID(AF82,4,2))) -> 45982 | AF82: 11/21/2025 | AG82: 23.43
A83: 3 | B83: GS | C83: TFC | D83: 39278 | E83: 907.55 | F83: 50.43 | G83: 907.45925 | H83: 50.435043 | I83: 4.0552674 | J83: 1.0056626 | K83: -0.011018677 | L83: 0.19941753 | M83: SHORT | N83: 18 | O83: signal | P83: 39296 | Q83: 906.87 | R83: 50.455 | S83: -0.18415414 | T83: 0.012478138 | U83: 0.008467064 | V83: 0.0040113264 | W83: 0.0044557376 | X83: =WORKDAY(DATE(2025,8,2),INT(D83/390)) -> 46010 | Y83: =WORKDAY(DATE(2025,8,2),INT(P83/390)) -> 46010 | Z83: {=_xlfn.XLOOKUP(INT(X83),INT($AE$2:$AE$1000),$AG$2:$AG$1000,"")} -> 14.91 | AE83: =IF(ISNUMBER(AF83),DATE(YEAR(AF83),DAY(AF83),MONTH(AF83)),DATE(RIGHT(AF83,4),LEFT(AF83,2),MID(AF83,4,2))) -> 45985 | AF83: 11/24/2025 | AG83: 20.52
A84: 3 | B84: GS | C84: TFC | D84: 39449 | E84: 905.24 | F84: 50.62 | G84: 905.33052 | H84: 50.614938 | I84: -3.9662588 | J84: 1.0056626 | K84: 0.011046794 | L84: -0.19866903 | M84: LONG | N84: 8 | O84: signal | P84: 39457 | Q84: 904.66 | R84: 50.47 | S84: -0.203274 | T84: 0.023393214 | U84: 0.019385509 | V84: 0.0040113241 | W84: 0.015374185 | X84: =WORKDAY(DATE(2025,8,2),INT(D84/390)) -> 46013 | Y84: =WORKDAY(DATE(2025,8,2),INT(P84/390)) -> 46013 | Z84: {=_xlfn.XLOOKUP(INT(X84),INT($AE$2:$AE$1000),$AG$2:$AG$1000,"")} -> 14.08 | AE84: =IF(ISNUMBER(AF84),DATE(YEAR(AF84),DAY(AF84),MONTH(AF84)),DATE(RIGHT(AF84,4),LEFT(AF84,2),MID(AF84,4,2))) -> 45986 | AF84: 11/25/2025 | AG84: 18.56
A85: 3 | B85: BAC | C85: WFC | D85: 35701 | E85: 54.63 | F85: 93.25 | G85: 54.635463 | H85: 93.240675 | I85: -5.2946374 | J85: 0.67544695 | K85: 0.18304961 | L85: -0.072433989 | M85: LONG | N85: 23 | O85: signal | P85: 35724 | Q85: 54.54 | R85: 92.695 | S85: -0.49011655 | T85: 0.023726399 | U85: 0.020381173 | V85: 0.0033509588 | W85: 0.017030214 | X85: =WORKDAY(DATE(2025,8,2),INT(D85/390)) -> 45999 | Y85: =WORKDAY(DATE(2025,8,2),INT(P85/390)) -> 45999 | Z85: {=_xlfn.XLOOKUP(INT(X85),INT($AE$2:$AE$1000),$AG$2:$AG$1000,"")} -> 16.66 | AE85: =IF(ISNUMBER(AF85),DATE(YEAR(AF85),DAY(AF85),MONTH(AF85)),DATE(RIGHT(AF85,4),LEFT(AF85,2),MID(AF85,4,2))) -> 45987 | AF85: 11/26/2025 | AG85: 17.19
A86: 3 | B86: BAC | C86: WFC | D86: 36509 | E86: 54.965 | F86: 93.105 | G86: 54.970497 | H86: 93.09569 | I86: -4.8712868 | J86: 0.67544695 | K86: 0.18193396 | L86: -0.072546796 | M86: LONG | N86: 7 | O86: signal | P86: 36516 | Q86: 55.35 | R86: 93.03 | S86: -0.41313051 | T86: 0.075485584 | U86: 0.072128229 | V86: 0.0033509588 | W86: 0.06877727 | X86: =WORKDAY(DATE(2025,8,2),INT(D86/390)) -> 46001 | Y86: =WORKDAY(DATE(2025,8,2),INT(P86/390)) -> 46001 | Z86: {=_xlfn.XLOOKUP(INT(X86),INT($AE$2:$AE$1000),$AG$2:$AG$1000,"")} -> 15.77 | AE86: =IF(ISNUMBER(AF86),DATE(YEAR(AF86),DAY(AF86),MONTH(AF86)),DATE(RIGHT(AF86,4),LEFT(AF86,2),MID(AF86,4,2))) -> 45988 | AF86: 11/27/2025 | AG86: 17.21
A87: 3 | B87: BAC | C87: WFC | D87: 37290 | E87: 54.595 | F87: 93.11 | G87: 54.600459 | H87: 93.100689 | I87: -3.9272584 | J87: 0.67544695 | K87: 0.18316696 | L87: -0.0725429 | M87: LONG | N87: 25 | O87: signal | P87: 37315 | Q87: 55.1 | R87: 93.705 | S87: 0.14678068 | T87: 0.049336287 | U87: 0.045971827 | V87: 0.0033509588 | W87: 0.042620868 | X87: =WORKDAY(DATE(2025,8,2),INT(D87/390)) -> 46003 | Y87: =WORKDAY(DATE(2025,8,2),INT(P87/390)) -> 46003 | Z87: {=_xlfn.XLOOKUP(INT(X87),INT($AE$2:$AE$1000),$AG$2:$AG$1000,"")} -> 15.74 | AE87: =IF(ISNUMBER(AF87),DATE(YEAR(AF87),DAY(AF87),MONTH(AF87)),DATE(RIGHT(AF87,4),LEFT(AF87,2),MID(AF87,4,2))) -> 45989 | AF87: 11/28/2025 | AG87: 16.35
A88: 3 | B88: BAC | C88: WFC | D88: 37679 | E88: 54.57 | F88: 91.7 | G88: 54.564543 | H88: 91.70917 | I88: 4.6807257 | J88: 0.67544695 | K88: -0.18325087 | L88: 0.073658336 | M88: SHORT | N88: 22 | O88: signal | P88: 37701 | Q88: 54.75 | R88: 92.075 | S88: 0.41292147 | T88: -0.0053632805 | U88: -0.0087202351 | V88: 0.003350829 | W88: -0.012071064 | X88: =WORKDAY(DATE(2025,8,2),INT(D88/390)) -> 46006 | Y88: =WORKDAY(DATE(2025,8,2),INT(P88/390)) -> 46006 | Z88: {=_xlfn.XLOOKUP(INT(X88),INT($AE$2:$AE$1000),$AG$2:$AG$1000,"")} -> 16.5 | AE88: =IF(ISNUMBER(AF88),DATE(YEAR(AF88),DAY(AF88),MONTH(AF88)),DATE(RIGHT(AF88,4),LEFT(AF88,2),MID(AF88,4,2))) -> 45992 | AF88: 45669 | AG88: 17.24
A89: 3 | B89: BAC | C89: WFC | D89: 38190 | E89: 55.87 | F89: 94.01 | G89: 55.864413 | H89: 94.019401 | I89: 3.6342178 | J89: 0.67544695 | K89: -0.17898693 | L89: 0.071848415 | M89: SHORT | N89: 16 | O89: signal | P89: 38206 | Q89: 55.915 | R89: 94.115 | S89: 0.48719907 | T89: -0.0005103285 | U89: -0.0038627822 | V89: 0.003350829 | W89: -0.0072136112 | X89: =WORKDAY(DATE(2025,8,2),INT(D89/390)) -> 46007 | Y89: =WORKDAY(DATE(2025,8,2),INT(P89/390)) -> 46007 | Z89: {=_xlfn.XLOOKUP(INT(X89),INT($AE$2:$AE$1000),$AG$2:$AG$1000,"")} -> 16.48 | AE89: =IF(ISNUMBER(AF89),DATE(YEAR(AF89),DAY(AF89),MONTH(AF89)),DATE(RIGHT(AF89,4),LEFT(AF89,2),MID(AF89,4,2))) -> 45993 | AF89: 45700 | AG89: 16.59
A90: 3 | B90: BAC | C90: WFC | D90: 38306 | E90: 55.98 | F90: 93.99 | G90: 55.985598 | H90: 93.980601 | I90: -4.0638487 | J90: 0.67544695 | K90: 0.17863523 | L90: -0.071863703 | M90: LONG | N90: 27 | O90: signal | P90: 38333 | Q90: 55.955 | R90: 93.96 | S90: 0.017472686 | T90: -0.0023099696 | U90: -0.0056602013 | V90: 0.0033509588 | W90: -0.0090111601 | X90: =WORKDAY(DATE(2025,8,2),INT(D90/390)) -> 46008 | Y90: =WORKDAY(DATE(2025,8,2),INT(P90/390)) -> 46008 | Z90: {=_xlfn.XLOOKUP(INT(X90),INT($AE$2:$AE$1000),$AG$2:$AG$1000,"")} -> 17.62 | AE90: =IF(ISNUMBER(AF90),DATE(YEAR(AF90),DAY(AF90),MONTH(AF90)),DATE(RIGHT(AF90,4),LEFT(AF90,2),MID(AF90,4,2))) -> 45994 | AF90: 45728 | AG90: 16.08
A91: 3 | B91: BAC | C91: WFC | D91: 38659 | E91: 55.95 | F91: 94.22 | G91: 55.955595 | H91: 94.210578 | I91: -3.6283825 | J91: 0.67544695 | K91: 0.17873101 | L91: -0.071688277 | M91: LONG | N91: 15 | O91: signal | P91: 38674 | Q91: 56.025 | R91: 94.29 | S91: 0.17646003 | T91: 0.0083866464 | U91: 0.0050339102 | V91: 0.0033509588 | W91: 0.0016829514 | X91: =WORKDAY(DATE(2025,8,2),INT(D91/390)) -> 46009 | Y91: =WORKDAY(DATE(2025,8,2),INT(P91/390)) -> 46009 | Z91: {=_xlfn.XLOOKUP(INT(X91),INT($AE$2:$AE$1000),$AG$2:$AG$1000,"")} -> 16.87 | AE91: =IF(ISNUMBER(AF91),DATE(YEAR(AF91),DAY(AF91),MONTH(AF91)),DATE(RIGHT(AF91,4),LEFT(AF91,2),MID(AF91,4,2))) -> 45995 | AF91: 45759 | AG91: 15.78
A92: 3 | B92: BAC | C92: WFC | D92: 39059 | E92: 56.42 | F92: 95.27 | G92: 56.414358 | H92: 95.279527 | I92: 3.7111055 | J92: 0.67544695 | K92: -0.17724211 | L92: 0.070898178 | M92: SHORT | N92: 9 | O92: signal | P92: 39068 | Q92: 56.34 | R92: 95.295 | S92: 0.16521923 | T92: 0.015951823 | U92: 0.01260217 | V92: 0.003350829 | W92: 0.0092513413 | X92: =WORKDAY(DATE(2025,8,2),INT(D92/390)) -> 46010 | Y92: =WORKDAY(DATE(2025,8,2),INT(P92/390)) -> 46010 | Z92: {=_xlfn.XLOOKUP(INT(X92),INT($AE$2:$AE$1000),$AG$2:$AG$1000,"")} -> 14.91 | AE92: =IF(ISNUMBER(AF92),DATE(YEAR(AF92),DAY(AF92),MONTH(AF92)),DATE(RIGHT(AF92,4),LEFT(AF92,2),MID(AF92,4,2))) -> 45996 | AF92: 45789 | AG92: 15.41
A93: 3 | B93: BAC | C93: WFC | D93: 39449 | E93: 56.095 | F93: 95.37 | G93: 56.100609 | H93: 95.360463 | I93: -3.6509999 | J93: 0.67544695 | K93: 0.17826901 | L93: -0.070823838 | M93: LONG | N93: 23 | O93: signal | P93: 39472 | Q93: 55.91 | R93: 94.92 | S93: -0.48824636 | T93: -0.0011090393 | U93: -0.0044534481 | V93: 0.0033509588 | W93: -0.0078044069 | X93: =WORKDAY(DATE(2025,8,2),INT(D93/390)) -> 46013 | Y93: =WORKDAY(DATE(2025,8,2),INT(P93/390)) -> 46013 | Z93: {=_xlfn.XLOOKUP(INT(X93),INT($AE$2:$AE$1000),$AG$2:$AG$1000,"")} -> 14.08 | AE93: =IF(ISNUMBER(AF93),DATE(YEAR(AF93),DAY(AF93),MONTH(AF93)),DATE(RIGHT(AF93,4),LEFT(AF93,2),MID(AF93,4,2))) -> 45999 | AF93: 45881 | AG93: 16.66
A94: 4 | B94: GS | C94: TFC | D94: 39601 | E94: 895.93 | F94: 50.02 | G94: 895.84041 | H94: 50.025002 | I94: 5.2946487 | J94: 1.0629441 | K94: -0.011161586 | L94: 0.21250383 | M94: SHORT | N94: 23 | O94: signal | P94: 39624 | Q94: 894.24 | R94: 50.03 | S94: 0.49073309 | T94: 0.020988119 | U94: 0.016863905 | V94: 0.0041259009 | W94: 0.012738004 | X94: =WORKDAY(DATE(2025,8,2),INT(D94/390)) -> 46013 | Y94: =WORKDAY(DATE(2025,8,2),INT(P94/390)) -> 46013 | Z94: {=_xlfn.XLOOKUP(INT(X94),INT($AE$2:$AE$1000),$AG$2:$AG$1000,"")} -> 14.08 | AE94: =IF(ISNUMBER(AF94),DATE(YEAR(AF94),DAY(AF94),MONTH(AF94)),DATE(RIGHT(AF94,4),LEFT(AF94,2),MID(AF94,4,2))) -> 46000 | AF94: 45912 | AG94: 16.93
A95: 4 | B95: GS | C95: TFC | D95: 39647 | E95: 895.29 | F95: 50 | G95: 895.20047 | H95: 50.005 | I95: 3.8187621 | J95: 1.0629441 | K95: -0.011169565 | L95: 0.21258883 | M95: SHORT | N95: 2 | O95: signal | P95: 39649 | Q95: 894.235 | R95: 50.005 | S95: 0.42425148 | T95: 0.012846835 | U95: 0.0087220192 | V95: 0.0041259009 | W95: 0.0045961183 | X95: =WORKDAY(DATE(2025,8,2),INT(D95/390)) -> 46013 | Y95: =WORKDAY(DATE(2025,8,2),INT(P95/390)) -> 46013 | Z95: {=_xlfn.XLOOKUP(INT(X95),INT($AE$2:$AE$1000),$AG$2:$AG$1000,"")} -> 14.08 | AE95: =IF(ISNUMBER(AF95),DATE(YEAR(AF95),DAY(AF95),MONTH(AF95)),DATE(RIGHT(AF95,4),LEFT(AF95,2),MID(AF95,4,2))) -> 46001 | AF95: 45942 | AG95: 15.77
A96: 4 | B96: GS | C96: TFC | D96: 39843 | E96: 886.02 | F96: 49.89 | G96: 886.1086 | H96: 49.885011 | I96: -3.536177 | J96: 1.0629441 | K96: 0.011286427 | L96: -0.21305756 | M96: LONG | N96: 16 | O96: signal | P96: 39859 | Q96: 885.94 | R96: 49.84 | S96: -0.14096291 | T96: 0.0097499636 | U96: 0.0056252309 | V96: 0.0041258757 | W96: 0.0014993552 | X96: =WORKDAY(DATE(2025,8,2),INT(D96/390)) -> 46014 | Y96: =WORKDAY(DATE(2025,8,2),INT(P96/390)) -> 46014 | Z96: {=_xlfn.XLOOKUP(INT(X96),INT($AE$2:$AE$1000),$AG$2:$AG$1000,"")} -> 14 | AE96: =IF(ISNUMBER(AF96),DATE(YEAR(AF96),DAY(AF96),MONTH(AF96)),DATE(RIGHT(AF96,4),LEFT(AF96,2),MID(AF96,4,2))) -> 46002 | AF96: 45973 | AG96: 14.85
A97: 4 | B97: GS | C97: TFC | D97: 40091 | E97: 883.72 | F97: 49.485 | G97: 883.63163 | H97: 49.489948 | I97: 3.521877 | J97: 1.0629441 | K97: -0.011315801 | L97: 0.21480128 | M97: SHORT | N97: 13 | O97: signal | P97: 40104 | Q97: 883.24 | R97: 49.5 | S97: 0.12975943 | T97: 0.0086536039 | U97: 0.0045279366 | V97: 0.0041259009 | W97: 0.00040203568 | X97: =WORKDAY(DATE(2025,8,2),INT(D97/390)) -> 46014 | Y97: =WORKDAY(DATE(2025,8,2),INT(P97/390)) -> 46014 | Z97: {=_xlfn.XLOOKUP(INT(X97),INT($AE$2:$AE$1000),$AG$2:$AG$1000,"")} -> 14 | AE97: =IF(ISNUMBER(AF97),DATE(YEAR(AF97),DAY(AF97),MONTH(AF97)),DATE(RIGHT(AF97,4),LEFT(AF97,2),MID(AF97,4,2))) -> 46003 | AF97: 46003 | AG97: 15.74
A98: 4 | B98: GS | C98: TFC | D98: 40619 | E98: 884.99 | F98: 49.34 | G98: 884.9015 | H98: 49.344934 | I98: 4.4671721 | J98: 1.0629441 | K98: -0.011299563 | L98: 0.21543254 | M98: SHORT | N98: 21 | O98: signal | P98: 40640 | Q98: 883.295 | R98: 49.01 | S98: 0.46766326 | T98: -0.051939979 | U98: -0.056056843 | V98: 0.0041259009 | W98: -0.060182744 | X98: =WORKDAY(DATE(2025,8,2),INT(D98/390)) -> 46016 | Y98: =WORKDAY(DATE(2025,8,2),INT(P98/390)) -> 46016 | Z98: {=_xlfn.XLOOKUP(INT(X98),INT($AE$2:$AE$1000),$AG$2:$AG$1000,"")} | AE98: =IF(ISNUMBER(AF98),DATE(YEAR(AF98),DAY(AF98),MONTH(AF98)),DATE(RIGHT(AF98,4),LEFT(AF98,2),MID(AF98,4,2))) -> 46006 | AF98: 12/15/2025 | AG98: 16.5
A99: 4 | B99: GS | C99: TFC | D99: 41009 | E99: 923.475 | F99: 49.94 | G99: 923.38265 | H99: 49.944994 | I99: 4.2141691 | J99: 1.0629441 | K99: -0.010828663 | L99: 0.21284424 | M99: SHORT | N99: 48 | O99: signal | P99: 41057 | Q99: 955.77 | R99: 50.555 | S99: 0.46868178 | T99: -0.21881248 | U99: -0.22298643 | V99: 0.0041259009 | W99: -0.22711233 | X99: =WORKDAY(DATE(2025,8,2),INT(D99/390)) -> 46017 | Y99: =WORKDAY(DATE(2025,8,2),INT(P99/390)) -> 46017 | Z99: {=_xlfn.XLOOKUP(INT(X99),INT($AE$2:$AE$1000),$AG$2:$AG$1000,"")} -> 13.6 | AE99: =IF(ISNUMBER(AF99),DATE(YEAR(AF99),DAY(AF99),MONTH(AF99)),DATE(RIGHT(AF99,4),LEFT(AF99,2),MID(AF99,4,2))) -> 46007 | AF99: 12/16/2025 | AG99: 16.48
A100: 4 | B100: GS | C100: TFC | D100: 41392 | E100: 949.11 | F100: 50.51 | G100: 949.20491 | H100: 50.504949 | I100: -3.7224256 | J100: 1.0629441 | K100: 0.010536187 | L100: -0.21044232 | M100: LONG | N100: 10 | O100: signal | P100: 41402 | Q100: 950.53 | R100: 50.455 | S100: 0.1679916 | T100: 0.026535712 | U100: 0.022409485 | V100: 0.0041258757 | W100: 0.01828361 | X100: =WORKDAY(DATE(2025,8,2),INT(D100/390)) -> 46020 | Y100: =WORKDAY(DATE(2025,8,2),INT(P100/390)) -> 46020 | Z100: {=_xlfn.XLOOKUP(INT(X100),INT($AE$2:$AE$1000),$AG$2:$AG$1000,"")} -> 14.2 | AE100: =IF(ISNUMBER(AF100),DATE(YEAR(AF100),DAY(AF100),MONTH(AF100)),DATE(RIGHT(AF100,4),LEFT(AF100,2),MID(AF100,4,2))) -> 46008 | AF100: 12/17/2025 | AG100: 17.62
A101: 4 | B101: GS | C101: TFC | D101: 42179 | E101: 940.25 | F101: 50.585 | G101: 940.15598 | H101: 50.590058 | I101: 3.8176291 | J101: 1.0629441 | K101: -0.010635469 | L101: 0.2101303 | M101: SHORT | N101: 1 | O101: signal | P101: 42180 | Q101: 935.86 | R101: 50.53 | S101: 0.28810109 | T101: 0.035132543 | U101: 0.03101248 | V101: 0.0041259009 | W101: 0.026886579 | X101: =WORKDAY(DATE(2025,8,2),INT(D101/390)) -> 46022 | Y101: =WORKDAY(DATE(2025,8,2),INT(P101/390)) -> 46022 | Z101: {=_xlfn.XLOOKUP(INT(X101),INT($AE$2:$AE$1000),$AG$2:$AG$1000,"")} -> 14.95 | AE101: =IF(ISNUMBER(AF101),DATE(YEAR(AF101),DAY(AF101),MONTH(AF101)),DATE(RIGHT(AF101,4),LEFT(AF101,2),MID(AF101,4,2))) -> 46009 | AF101: 12/18/2025 | AG101: 16.87
A102: 4 | B102: GS | C102: TFC | D102: 42576 | E102: 943.565 | F102: 51.15 | G102: 943.47064 | H102: 51.155115 | I102: 3.5316794 | J102: 1.0629441 | K102: -0.010598104 | L102: 0.20780922 | M102: SHORT | N102: 7 | O102: signal | P102: 42583 | Q102: 937.48 | R102: 50.97 | S102: 0.43288673 | T102: 0.027083804 | U102: 0.022968105 | V102: 0.0041259009 | W102: 0.018842204 | X102: =WORKDAY(DATE(2025,8,2),INT(D102/390)) -> 46023 | Y102: =WORKDAY(DATE(2025,8,2),INT(P102/390)) -> 46023 | Z102: {=_xlfn.XLOOKUP(INT(X102),INT($AE$2:$AE$1000),$AG$2:$AG$1000,"")} | AE102: =IF(ISNUMBER(AF102),DATE(YEAR(AF102),DAY(AF102),MONTH(AF102)),DATE(RIGHT(AF102,4),LEFT(AF102,2),MID(AF102,4,2))) -> 46010 | AF102: 12/19/2025 | AG102: 14.91
...

Sheet Analysis
L1: Exit timestamp | M1: Cumulative Gross PnL | N1: Cumulative Slipped PnL | O1: Cumulative Net PnL | Q1: min holding minutes | R1: max holding minutes | S1: Mean Net PnL | T1: Number of trades
B2: Rough Analysis of the baseline strategy | J2: Figures | L2: =Trades!P2 -> 24214 | M2: =Trades!T2 -> 0.024154984 | N2: =Trades!U2 -> 0.020822539 | O2: =Trades!W2 -> 0.017487745 | Q2: 0 | R2: 3 | S2: =AVERAGEIFS(Trades!W:W,Trades!N:N,">="&Q2,Trades!N:N,"<="&R2) -> 0.03153191 | T2: =COUNTIFS(Trades!N:N,">="&Q2,Trades!N:N,"<="&R2) -> 9
L3: =Trades!P3 -> 24606 | M3: =M2+Trades!T3 -> 0.067822224 | N3: =N2+Trades!U3 -> 0.061157159 | O3: =O2+Trades!W3 -> 0.054487572 | Q3: 4 | R3: 7 | S3: =AVERAGEIFS(Trades!W:W,Trades!N:N,">="&Q3,Trades!N:N,"<="&R3) -> 0.02589914 | T3: =COUNTIFS(Trades!N:N,">="&Q3,Trades!N:N,"<="&R3) -> 21
B4: Column1 | C4: Gross | D4: Slipped | E4: Net (Transaction costs) | L4: =Trades!P4 -> 24848 | M4: =M3+Trades!T4 -> 0.072054022 | N4: =N3+Trades!U4 -> 0.062055967 | O4: =O3+Trades!W4 -> 0.052051586 | Q4: 8 | R4: 11 | S4: =AVERAGEIFS(Trades!W:W,Trades!N:N,">="&Q4,Trades!N:N,"<="&R4) -> 0.023782929 | T4: =COUNTIFS(Trades!N:N,">="&Q4,Trades!N:N,"<="&R4) -> 19
B5: Overall PnL | C5: =SUM(Trades!T2:T9652) -> 1.3885918 | D5: =SUM(Trades!U2:U9652) -> 0.882144 | E5: =SUM(Trades!W2:W9652) -> 0.3758623 | L5: =Trades!P5 -> 24996 | M5: =M4+Trades!T5 -> 0.10989766 | N5: =N4+Trades!U5 -> 0.096564379 | O5: =O4+Trades!W5 -> 0.083225071 | Q5: 12 | R5: 15 | S5: =AVERAGEIFS(Trades!W:W,Trades!N:N,">="&Q5,Trades!N:N,"<="&R5) -> 0.014300093 | T5: =COUNTIFS(Trades!N:N,">="&Q5,Trades!N:N,"<="&R5) -> 19
B6: Mean PnL | C6: =AVERAGE(Trades!T:T) -> 0.010135706 | D6: =AVERAGE(Trades!U:U) -> 0.0064390073 | E6: =AVERAGE(Trades!W:W) -> 0.0027435204 | L6: =Trades!P6 -> 25392 | M6: =M5+Trades!T6 -> 0.14071719 | N6: =N5+Trades!U6 -> 0.12404061 | O6: =O5+Trades!W6 -> 0.10736638 | Q6: 16 | R6: 19 | S6: =AVERAGEIFS(Trades!W:W,Trades!N:N,">="&Q6,Trades!N:N,"<="&R6) -> -0.0045318448 | T6: =COUNTIFS(Trades!N:N,">="&Q6,Trades!N:N,"<="&R6) -> 16
B7: Median PnL | C7: =MEDIAN(Trades!T:T) -> 0.011783975 | D7: =MEDIAN(Trades!U:U) -> 0.0084181991 | E7: =MEDIAN(Trades!W:W) -> 0.0047335944 | L7: =Trades!P7 -> 25731 | M7: =M6+Trades!T7 -> 0.12499991 | N7: =N6+Trades!U7 -> 0.10498528 | O7: =O6+Trades!W7 -> 0.084976254 | Q7: 20 | R7: 23 | S7: =AVERAGEIFS(Trades!W:W,Trades!N:N,">="&Q7,Trades!N:N,"<="&R7) -> -0.012857903 | T7: =COUNTIFS(Trades!N:N,">="&Q7,Trades!N:N,"<="&R7) -> 24
B8: Max drawdown | C8: =MIN(Trades!T:T) -> -0.087068107 | D8: =MIN(Trades!U:U) -> -0.091191822 | E8: =MIN(Trades!W:W) -> -0.095289891 | L8: =Trades!P8 -> 25758 | M8: =M7+Trades!T8 -> 0.13581127 | N8: =N7+Trades!U8 -> 0.11246473 | O8: =O7+Trades!W8 -> 0.089120912 | Q8: 24 | R8: 27 | S8: =AVERAGEIFS(Trades!W:W,Trades!N:N,">="&Q8,Trades!N:N,"<="&R8) -> -0.024624317 | T8: =COUNTIFS(Trades!N:N,">="&Q8,Trades!N:N,"<="&R8) -> 15
B9: Biggest Winner | C9: =MAX(Trades!T:T) -> 0.09558224 | D9: =MAX(Trades!U:U) -> 0.091738669 | E9: =MAX(Trades!W:W) -> 0.087869742 | L9: =Trades!P9 -> 26942 | M9: =M8+Trades!T9 -> 0.16614087 | N9: =N8+Trades!U9 -> 0.13944671 | O9: =O8+Trades!W9 -> 0.11276796 | Q9: 28 | R9: 34 | S9: =AVERAGEIFS(Trades!W:W,Trades!N:N,">="&Q9,Trades!N:N,"<="&R9) -> -0.016174126 | T9: =COUNTIFS(Trades!N:N,">="&Q9,Trades!N:N,"<="&R9) -> 8
B10: Win rate | C10: =COUNTIF(Trades!T:T,">0")/(COUNTIF(Trades!T:T,">0")+COUNTIF(Trades!T:T,"<0")) -> 0.69343066 | D10: =COUNTIF(Trades!U:U,">0")/(COUNTIF(Trades!U:U,">0")+COUNTIF(Trades!U:U,"<0")) -> 0.6350365 | E10: =COUNTIF(Trades!W:W,">0")/(COUNTIF(Trades!W:W,">0")+COUNTIF(Trades!W:W,"<0")) -> 0.58394161 | L10: =Trades!P10 -> 27332 | M10: =M9+Trades!T10 -> 0.19014346 | N10: =N9+Trades!U10 -> 0.1601233 | O10: =O9+Trades!W10 -> 0.13010976 | Q10: 35 | R10: 40 | S10: =AVERAGEIFS(Trades!W:W,Trades!N:N,">="&Q10,Trades!N:N,"<="&R10) -> -0.045173001 | T10: =COUNTIFS(Trades!N:N,">="&Q10,Trades!N:N,"<="&R10) -> 4
B11: Profit Factor | C11: =SUMIF(Trades!T:T,">0",Trades!T:T)/ABS(SUMIF(Trades!T:T,"<0",Trades!T:T)) -> 2.2631106 | D11: =SUMIF(Trades!U:U,">0",Trades!U:U)/ABS(SUMIF(Trades!U:U,"<0",Trades!U:U)) -> 1.694162 | E11: =SUMIF(Trades!W:W,">0",Trades!W:W)/ABS(SUMIF(Trades!W:W,"<0",Trades!W:W)) -> 1.2550328 | L11: =Trades!P11 -> 27725 | M11: =M9+Trades!T11 -> 0.1839358 | N11: =N9+Trades!U11 -> 0.15388456 | O11: =O9+Trades!W11 -> 0.12387088
L12: =Trades!P12 -> 27924 | M12: =M11+Trades!T12 -> 0.19413267 | N12: =N11+Trades!U12 -> 0.16077521 | O12: =O11+Trades!W12 -> 0.1274538 | Q12: 41 | R12: 47 | S12: =AVERAGEIFS(Trades!W:W,Trades!N:N,">="&Q12,Trades!N:N,"<="&R12) -> -0.032076202 | T12: =COUNTIFS(Trades!N:N,">="&Q12,Trades!N:N,"<="&R12) -> 1
B13: Column1 | C13: Column2 | L13: =Trades!P20 -> 32055 | M13: =M12+Trades!T20 -> 0.1183425 | N13: =N12+Trades!U20 -> 0.081493219 | O13: =O12+Trades!W20 -> 0.044694694
B14: Number of Trades | C14: =COUNTA(Trades!A:A)-1 -> 137 | L14: =Trades!P13 -> 28504 | M14: =M13+Trades!T13 -> 0.15478022 | N14: =N13+Trades!U13 -> 0.11462828 | O14: =O13+Trades!W13 -> 0.07452202
B15: Mean holding time | C15: =AVERAGE(Trades!N:N) -> 16.321168 | L15: =Trades!P21 -> 32218 | M15: =M14+Trades!T21 -> 0.17693189 | N15: =N14+Trades!U21 -> 0.13330444 | O15: =O14+Trades!W21 -> 0.089720965
B16: Median holding time | C16: =MEDIAN(Trades!N:N) -> 16 | L16: =Trades!P22 -> 32631 | M16: =M15+Trades!T22 -> 0.18805818 | N16: =N15+Trades!U22 -> 0.140959 | O16: =O15+Trades!W22 -> 0.093898308
B17: Max holding time | C17: =MAX(Trades!N:N) -> 48 | L17: =Trades!P23 -> 33015 | M17: =M16+Trades!T23 -> 0.19034235 | N17: =N16+Trades!U23 -> 0.13975733 | O17: =O16+Trades!W23 -> 0.089219528
L18: =Trades!P14 -> 28639 | M18: =M17+Trades!T14 -> 0.22286266 | N18: =N17+Trades!U14 -> 0.1689687 | O18: =O17+Trades!W14 -> 0.11512302
B19: Column1 | C19: Positive | D19: Negative | L19: =Trades!P15 -> 28735 | M19: =M18+Trades!T15 -> 0.21900859 | N19: =N18+Trades!U15 -> 0.161808 | O19: =O18+Trades!W15 -> 0.10465445
B20: Mean entry z score | C20: =AVERAGEIF(Trades!I:I,">0",Trades!I:I) -> 4.1060707 | D20: =AVERAGEIF(Trades!I:I,"<0",Trades!I:I) -> -4.0699518 | L20: =Trades!P24 -> 34564 | M20: =M19+Trades!T24 -> 0.25100157 | N20: =N19+Trades!U24 -> 0.19032711 | O20: =O19+Trades!W24 -> 0.12969644
B21: Median entry z score | C21: {=MEDIAN(_xlfn._xlws.FILTER(Trades!I:I,Trades!I:I>0))} -> 3.9061094 | D21: {=MEDIAN(_xlfn._xlws.FILTER(Trades!I:I,Trades!I:I<0))} -> -3.8781857 | L21: =Trades!P25 -> 35310 | M21: =M20+Trades!T25 -> 0.31153065 | N21: =N20+Trades!U25 -> 0.24737191 | O21: =O20+Trades!W25 -> 0.18326402
B22: max entry z score | C22: =_xlfn.MAXIFS(Trades!I:I,Trades!I:I,">0") -> 5.2946422 | D22: =_xlfn.MINIFS(Trades!I:I,Trades!I:I,"<0") -> -5.29465 | L22: =Trades!P16 -> 29691 | M22: =M21+Trades!T16 -> 0.2855726 | N22: =N21+Trades!U16 -> 0.21809841 | O22: =O21+Trades!W16 -> 0.15068278
B23: Mean exit z score | C23: =AVERAGEIF(Trades!S:S,">0",Trades!S:S) -> 0.28568269 | D23: =AVERAGEIF(Trades!S:S,"<0",Trades!S:S) -> -0.31373434 | L23: =Trades!P26 -> 35725 | M23: =M22+Trades!T26 -> 0.25803359 | N23: =N22+Trades!U26 -> 0.18721437 | O23: =O22+Trades!W26 -> 0.11644792
B24: Median exit z score | C24: {=MEDIAN(_xlfn._xlws.FILTER(Trades!S:S,Trades!S:S>0))} -> 0.28678401 | D24: {=MEDIAN(_xlfn._xlws.FILTER(Trades!S:S,Trades!S:S<0))} -> -0.32318646 | L24: =Trades!P27 -> 36516 | M24: =M23+Trades!T27 -> 0.33351918 | N24: =N23+Trades!U27 -> 0.2593426 | O24: =O23+Trades!W27 -> 0.18522519
B25: max exit z score | C25: =_xlfn.MAXIFS(Trades!S:S,Trades!S:S,">0") -> 0.49471769 | D25: =_xlfn.MINIFS(Trades!S:S,Trades!S:S,"<0") -> -0.49528239 | L25: =Trades!P17 -> 30065 | M25: =M24+Trades!T17 -> 0.36568895 | N25: =N24+Trades!U17 -> 0.28819841 | O25: =O24+Trades!W17 -> 0.21077312
G26: 1 | H26: Edge is there, but wiped out by costs | L26: =Trades!P18 -> 31227 | M26: =M25+Trades!T18 -> 0.38735212 | N26: =N25+Trades!U18 -> 0.30654688 | O26: =O25+Trades!W18 -> 0.22581371
B27: Column1 | C27: Long | D27: Short | E27: Signal | F27: Forced | L27: =Trades!P19 -> 31824 | M27: =M26+Trades!T19 -> 0.38434504 | N27: =N26+Trades!U19 -> 0.30006233 | O27: =O26+Trades!W19 -> 0.21585195
B28: PnL (gross) | C28: =SUMIF(Trades!M:M,"LONG",Trades!T:T) -> 0.83313468 | D28: =SUMIF(Trades!M:M,"SHORT",Trades!T:T) -> 0.5554571 | E28: =SUMIF(Trades!O:O,"Signal",Trades!T:T) -> 1.3885918 | F28: =SUMIF(Trades!O:O,"Forced",Trades!T:T) -> 0 | L28: =Trades!P28 -> 37315 | M28: =M27+Trades!T28 -> 0.43368133 | N28: =N27+Trades!U28 -> 0.34603416 | O28: =O27+Trades!W28 -> 0.25847282
B29: Number | C29: =COUNTIF(Trades!M:M,"LONG") -> 60 | D29: =COUNTIF(Trades!M:M,"SHORT") -> 77 | E29: =COUNTIF(Trades!O:O,"Signal") -> 137 | F29: =COUNTIF(Trades!O:O,"Forced") -> 0 | L29: =Trades!P35 -> 39624 | M29: =M28+Trades!T35 -> 0.43411723 | N29: =N28+Trades!U35 -> 0.34316461 | O29: =O28+Trades!W35 -> 0.25229668
L30: =Trades!P44 -> 44024 | M30: =M29+Trades!T44 -> 0.415339 | N30: =N29+Trades!U44 -> 0.32116928 | O30: =O29+Trades!W44 -> 0.22708743
B31: min Holding time | C31: Max Holding time | D31: Win rate | L31: =Trades!P52 -> 47424 | M31: =M30+Trades!T52 -> 0.42008468 | N31: =N30+Trades!U52 -> 0.32181636 | O31: =O30+Trades!W52 -> 0.22363644
B32: 0 | C32: 3 | D32: =COUNTIFS(Trades!N:N,">="&B32,Trades!N:N,"<="&C32,Trades!T:T,">0")/(COUNTIFS(Trades!N:N,">="&B32,Trades!N:N,"<="&C32,Trades!T:T,">0")+COUNTIFS(Trades!N:N,">="&B32,Trades!N:N,"<="&C32,Trades!T:T,"<0")) -> 1 | L32: =Trades!P36 -> 39854 | M32: =M31+Trades!T36 -> 0.43647186 | N32: =N31+Trades!U36 -> 0.33490512 | O32: =O31+Trades!W36 -> 0.2334186
B33: 4 | C33: 7 | D33: =COUNTIFS(Trades!N:N,">="&B33,Trades!N:N,"<="&C33,Trades!T:T,">0")/(COUNTIFS(Trades!N:N,">="&B33,Trades!N:N,"<="&C33,Trades!T:T,">0")+COUNTIFS(Trades!N:N,">="&B33,Trades!N:N,"<="&C33,Trades!T:T,"<0")) -> 1 | L33: =Trades!P45 -> 44544 | M33: =M32+Trades!T45 -> 0.47445826 | N33: =N32+Trades!U45 -> 0.36968772 | O33: =O32+Trades!W45 -> 0.26498728
B34: 8 | C34: 11 | D34: =COUNTIFS(Trades!N:N,">="&B34,Trades!N:N,"<="&C34,Trades!T:T,">0")/(COUNTIFS(Trades!N:N,">="&B34,Trades!N:N,"<="&C34,Trades!T:T,">0")+COUNTIFS(Trades!N:N,">="&B34,Trades!N:N,"<="&C34,Trades!T:T,"<0")) -> 1 | L34: =Trades!P29 -> 37701 | M34: =M33+Trades!T29 -> 0.46909498 | N34: =N33+Trades!U29 -> 0.36096748 | O34: =O33+Trades!W29 -> 0.25291621
B35: 12 | C35: 15 | D35: =COUNTIFS(Trades!N:N,">="&B35,Trades!N:N,"<="&C35,Trades!T:T,">0")/(COUNTIFS(Trades!N:N,">="&B35,Trades!N:N,"<="&C35,Trades!T:T,">0")+COUNTIFS(Trades!N:N,">="&B35,Trades!N:N,"<="&C35,Trades!T:T,"<0")) -> 0.94736842 | L35: =Trades!P30 -> 38206 | M35: =M34+Trades!T30 -> 0.46858465 | N35: =N34+Trades!U30 -> 0.3571047 | O35: =O34+Trades!W30 -> 0.2457026
B36: 16 | C36: 1000000 | D36: =COUNTIFS(Trades!N:N,">="&B36,Trades!N:N,"<="&C36,Trades!T:T,">0")/(COUNTIFS(Trades!N:N,">="&B36,Trades!N:N,"<="&C36,Trades!T:T,">0")+COUNTIFS(Trades!N:N,">="&B36,Trades!N:N,"<="&C36,Trades!T:T,"<0")) -> 0.4057971 | L36: =Trades!P37 -> 41036 | M36: =M35+Trades!T37 -> 0.39856519 | N36: =N35+Trades!U37 -> 0.28375323 | O36: =O35+Trades!W37 -> 0.16904454
L37: =Trades!P53 -> 47667 | M37: =M36+Trades!T53 -> 0.38252126 | N37: =N36+Trades!U53 -> 0.26358278 | O37: =O36+Trades!W53 -> 0.14477603
L38: =Trades!P54 -> 47973 | M38: =M37+Trades!T54 -> 0.40939771 | N38: =N37+Trades!U54 -> 0.28635789 | O38: =O37+Trades!W54 -> 0.16345309
B39: Conclusion: | L39: =Trades!P31 -> 38333 | M39: =M38+Trades!T31 -> 0.40708774 | N39: =N38+Trades!U31 -> 0.28069769 | O39: =O38+Trades!W31 -> 0.15444193
B40: does the multiple pairs strategy improve diversification and risk adjusted returns instead of just gross exposure? | L40: =Trades!P32 -> 38674 | M40: =M39+Trades!T32 -> 0.41547439 | N40: =N39+Trades!U32 -> 0.2857316 | O40: =O39+Trades!W32 -> 0.15612489
L41: =Trades!P46 -> 44948 | M41: =M40+Trades!T46 -> 0.43741562 | N41: =N40+Trades!U46 -> 0.30444689 | O41: =O40+Trades!W46 -> 0.17162611
L42: =Trades!P55 -> 48243 | M42: =M41+Trades!T55 -> 0.44370108 | N42: =N41+Trades!U55 -> 0.30663643 | O42: =O41+Trades!W55 -> 0.1697176
L43: =Trades!P47 -> 45534 | M43: =M42+Trades!T47 -> 0.44869265 | N43: =N42+Trades!U47 -> 0.30841542 | O43: =O42+Trades!W47 -> 0.16828267
L44: =Trades!P38 -> 41209 | M44: =M43+Trades!T38 -> 0.46455655 | N44: =N43+Trades!U38 -> 0.32097316 | O44: =O43+Trades!W38 -> 0.17753381
L45: =Trades!P48 -> 45725 | M45: =M44+Trades!T48 -> 0.49941287 | N45: =N44+Trades!U48 -> 0.35260535 | O45: =O44+Trades!W48 -> 0.20595208
G46: 2 | H46: shorter trades are significantly more profitiable | L46: =Trades!P39 -> 41414 | M46: =M45+Trades!T39 -> 0.54392988 | N46: =N45+Trades!U39 -> 0.39382103 | O46: =O45+Trades!W39 -> 0.24386116 | Y46: 3 | Z46: most trades are short, but with a long tail
L47: =Trades!P40 -> 41825 | M47: =M46+Trades!T40 -> 0.52143744 | N47: =N46+Trades!U40 -> 0.36803803 | O47: =O46+Trades!W40 -> 0.21477142
L48: =Trades!P56 -> 48835 | M48: =M47+Trades!T56 -> 0.56420742 | N48: =N47+Trades!U56 -> 0.4067173 | O48: =O47+Trades!W56 -> 0.24935263
L49: =Trades!P49 -> 45815 | M49: =M48+Trades!T49 -> 0.5759914 | N49: =N48+Trades!U49 -> 0.41528667 | O49: =O48+Trades!W49 -> 0.25470808
L50: =Trades!P57 -> 49254 | M50: =M49+Trades!T57 -> 0.51955842 | N50: =N49+Trades!U57 -> 0.35475461 | O50: =O49+Trades!W57 -> 0.19007797
L51: =Trades!P50 -> 46118 | M51: =M50+Trades!T50 -> 0.50067165 | N51: =N50+Trades!U50 -> 0.33265426 | O51: =O50+Trades!W50 -> 0.16476355
L52: =Trades!P58 -> 49618 | M52: =M51+Trades!T58 -> 0.53967356 | N52: =N51+Trades!U58 -> 0.36756667 | O52: =O51+Trades!W58 -> 0.19557791
L53: =Trades!P33 -> 39068 | M53: =M52+Trades!T33 -> 0.55562539 | N53: =N52+Trades!U33 -> 0.38016884 | O53: =O52+Trades!W33 -> 0.20482925
L54: =Trades!P41 -> 42181 | M54: =M53+Trades!T41 -> 0.58842631 | N54: =N53+Trades!U41 -> 0.40965954 | O54: =O53+Trades!W41 -> 0.23101321
L55: =Trades!P59 -> 50031 | M55: =M54+Trades!T59 -> 0.5013582 | N55: =N54+Trades!U59 -> 0.31846771 | O55: =O54+Trades!W59 -> 0.13572332
L56: =Trades!P51 -> 47299 | M56: =M55+Trades!T51 -> 0.48588942 | N56: =N55+Trades!U51 -> 0.2997832 | O56: =O55+Trades!W51 -> 0.11382472
L57: =Trades!P60 -> 50395 | M57: =M56+Trades!T60 -> 0.52222826 | N57: =N56+Trades!U60 -> 0.33202758 | O57: =O56+Trades!W60 -> 0.14197106
L58: =Trades!P42 -> 43338 | M58: =M57+Trades!T42 -> 0.53357426 | N58: =N57+Trades!U42 -> 0.34006778 | O58: =O57+Trades!W42 -> 0.14670465
L59: =Trades!P61 -> 50810 | M59: =M58+Trades!T61 -> 0.51689124 | N59: =N58+Trades!U61 -> 0.31929112 | O59: =O58+Trades!W61 -> 0.12182993
L60: =Trades!P34 -> 39472 | M60: =M59+Trades!T34 -> 0.5157822 | N60: =N59+Trades!U34 -> 0.31483768 | O60: =O59+Trades!W34 -> 0.11402553
L61: =Trades!P43 -> 43524 | M61: =M60+Trades!T43 -> 0.52975856 | N61: =N60+Trades!U43 -> 0.32560156 | O61: =O60+Trades!W43 -> 0.1215755
L62: =Trades!P62 -> 51195 | M62: =M61+Trades!T62 -> 0.49312368 | N62: =N61+Trades!U62 -> 0.28488747 | O62: =O61+Trades!W62 -> 0.076763336
L63: =Trades!P63 -> 51324 | M63: =M62+Trades!T63 -> 0.50204586 | N63: =N62+Trades!U63 -> 0.28979524 | O63: =O62+Trades!W63 -> 0.07765081
L64: =Trades!P74 -> 56647 | M64: =M63+Trades!T74 -> 0.52897178 | N64: =N63+Trades!U74 -> 0.31278863 | O64: =O63+Trades!W74 -> 0.096706645
L65: =Trades!P85 -> 61358 | M65: =M64+Trades!T85 -> 0.54013034 | N65: =N64+Trades!U85 -> 0.32032027 | O65: =O64+Trades!W85 -> 0.10060936
L66: =Trades!P75 -> 57049 | M66: =M65+Trades!T75 -> 0.54344737 | N66: =N65+Trades!U75 -> 0.31969641 | O66: =O65+Trades!W75 -> 0.096047948
L67: =Trades!P64 -> 51579 | M67: =M66+Trades!T64 -> 0.56103303 | N67: =N66+Trades!U64 -> 0.33325976 | O67: =O66+Trades!W64 -> 0.105591
L68: =Trades!P86 -> 61737 | M68: =M67+Trades!T86 -> 0.601887 | N68: =N67+Trades!U86 -> 0.37044394 | O68: =O67+Trades!W86 -> 0.13914625
L69: =Trades!P65 -> 52356 | M69: =M68+Trades!T65 -> 0.66140079 | N69: =N68+Trades!U65 -> 0.42593016 | O69: =O68+Trades!W65 -> 0.19061218
L70: =Trades!P76 -> 57831 | M70: =M69+Trades!T76 -> 0.6927172 | N70: =N69+Trades!U76 -> 0.45331682 | O70: =O69+Trades!W76 -> 0.21406129
L71: =Trades!P77 -> 58222 | M71: =M70+Trades!T77 -> 0.72319272 | N71: =N70+Trades!U77 -> 0.47986097 | O71: =O70+Trades!W77 -> 0.23666788
L72: =Trades!P78 -> 58490 | M72: =M71+Trades!T78 -> 0.74389785 | N72: =N71+Trades!U78 -> 0.49662983 | O72: =O71+Trades!W78 -> 0.24949917
L73: =Trades!P87 -> 62130 | M73: =M72+Trades!T87 -> 0.75429914 | N73: =N72+Trades!U87 -> 0.50339121 | O73: =O72+Trades!W87 -> 0.25263162
L74: =Trades!P66 -> 53145 | M74: =M73+Trades!T66 -> 0.78940262 | N74: =N73+Trades!U66 -> 0.53446706 | O74: =O73+Trades!W66 -> 0.27968718
L75: =Trades!P67 -> 53383 | M75: =M74+Trades!T67 -> 0.80241799 | N75: =N74+Trades!U67 -> 0.54345407 | O75: =O74+Trades!W67 -> 0.2846539
L76: =Trades!P88 -> 62597 | M76: =M75+Trades!T88 -> 0.81456124 | N76: =N75+Trades!U88 -> 0.55197214 | O76: =O75+Trades!W88 -> 0.28954311
L77: =Trades!P79 -> 58607 | M77: =M76+Trades!T79 -> 0.85176152 | N77: =N76+Trades!U79 -> 0.58523398 | O77: =O76+Trades!W79 -> 0.3188674
L78: =Trades!P68 -> 53535 | M78: =M77+Trades!T68 -> 0.83540249 | N78: =N77+Trades!U68 -> 0.5648669 | O78: =O77+Trades!W68 -> 0.29448002
L79: =Trades!P80 -> 59003 | M79: =M78+Trades!T80 -> 0.85239538 | N79: =N78+Trades!U80 -> 0.57793086 | O79: =O78+Trades!W80 -> 0.30360643
L80: =Trades!P69 -> 53791 | M80: =M79+Trades!T69 -> 0.89007127 | N80: =N79+Trades!U69 -> 0.61157814 | O80: =O79+Trades!W69 -> 0.33323342
L81: =Trades!P89 -> 62907 | M81: =M80+Trades!T89 -> 0.91671374 | N81: =N80+Trades!U89 -> 0.63458805 | O81: =O80+Trades!W89 -> 0.3526144
L82: =Trades!P90 -> 63024 | M82: =M81+Trades!T90 -> 0.8932615 | N82: =N81+Trades!U90 -> 0.6073282 | O82: =O81+Trades!W90 -> 0.32154617
L83: =Trades!P81 -> 59124 | M83: =M82+Trades!T81 -> 0.88002966 | N83: =N82+Trades!U81 -> 0.59045783 | O83: =O82+Trades!W81 -> 0.30104694
L84: =Trades!P70 -> 53929 | M84: =M83+Trades!T70 -> 0.85961403 | N84: =N83+Trades!U70 -> 0.56604298 | O84: =O83+Trades!W70 -> 0.27261179
L85: =Trades!P91 -> 63477 | M85: =M84+Trades!T91 -> 0.87796396 | N85: =N84+Trades!U91 -> 0.58058487 | O85: =O84+Trades!W91 -> 0.28334535
L86: =Trades!P71 -> 54324 | M86: =M85+Trades!T71 -> 0.81553799 | N86: =N85+Trades!U71 -> 0.51415247 | O86: =O85+Trades!W71 -> 0.21289265
L87: =Trades!P72 -> 55224 | M87: =M86+Trades!T72 -> 0.81275929 | N87: =N86+Trades!U72 -> 0.50744374 | O87: =O86+Trades!W72 -> 0.20224637
L88: =Trades!P92 -> 64258 | M88: =M87+Trades!T92 -> 0.84268592 | N88: =N87+Trades!U92 -> 0.53355476 | O88: =O87+Trades!W92 -> 0.22454904
L89: =Trades!P82 -> 60167 | M89: =M88+Trades!T82 -> 0.85845217 | N89: =N88+Trades!U82 -> 0.54568104 | O89: =O88+Trades!W82 -> 0.23304646
L90: =Trades!P83 -> 60519 | M90: =M89+Trades!T83 -> 0.8665069 | N90: =N89+Trades!U83 -> 0.55010779 | O90: =O89+Trades!W83 -> 0.23384429
L91: =Trades!P73 -> 55503 | M91: =M90+Trades!T73 -> 0.83013574 | N91: =N90+Trades!U73 -> 0.50983767 | O91: =O90+Trades!W73 -> 0.18963662
L92: =Trades!P84 -> 60566 | M92: =M91+Trades!T84 -> 0.85680327 | N92: =N91+Trades!U84 -> 0.53286935 | O92: =O91+Trades!W84 -> 0.20903937
L93: =Trades!P93 -> 65251 | M93: =M92+Trades!T93 -> 0.89274127 | N93: =N92+Trades!U93 -> 0.56499746 | O93: =O92+Trades!W93 -> 0.23735913
L94: =Trades!P94 -> 65806 | M94: =M93+Trades!T94 -> 0.89496557 | N94: =N93+Trades!U94 -> 0.56341429 | O94: =O93+Trades!W94 -> 0.23196762
L95: =Trades!P105 -> 71516 | M95: =M94+Trades!T105 -> 0.90299343 | N95: =N94+Trades!U105 -> 0.56755219 | O95: =O94+Trades!W105 -> 0.23221741
L96: =Trades!P95 -> 66028 | M96: =M95+Trades!T95 -> 0.87471826 | N96: =N95+Trades!U95 -> 0.53540713 | O96: =O95+Trades!W95 -> 0.19626401
L97: =Trades!P106 -> 71897 | M97: =M96+Trades!T106 -> 0.91743809 | N97: =N96+Trades!U106 -> 0.57423458 | O97: =O96+Trades!W106 -> 0.23120334
L98: =Trades!P96 -> 67621 | M98: =M97+Trades!T96 -> 0.87811104 | N98: =N97+Trades!U96 -> 0.5310533 | O98: =O97+Trades!W96 -> 0.18415314
L99: =Trades!P97 -> 68021 | M99: =M98+Trades!T97 -> 0.97369328 | N99: =N98+Trades!U97 -> 0.62279197 | O99: =O98+Trades!W97 -> 0.27202288
L100: =Trades!P98 -> 68392 | M100: =M99+Trades!T98 -> 1.0562279 | N100: =N99+Trades!U98 -> 0.70144704 | O100: =O99+Trades!W98 -> 0.34680902
...

Sheet comparison with single pair
B2: Metric | C2: Value | J2: Daily PnL table
B3: Net P&L | C3: =SUM(Trades!W2:W9652) -> 0.3758623
B4: Number of trades | C4: =COUNTA(Trades!A:A)-1 -> 137 | J4: {=_xlfn.LET( _xlpm.dates,_xlfn.SEQUENCE(DATE(2026,8,2)-DATE(2025,8,2)+1,,DATE(2025,8,2)), _xlfn._xlws.FILTER(_xlpm.dates,WEEKDAY(_xlpm.dates,2)<=5) )} -> 45873 | K4: {=SUMIFS('trades edited'!$W$2:$W$100000,'trades edited'!$Y$2:$Y$100000,_xlfn.ANCHORARRAY(J4))} -> 0
B5: P&L/trade | C5: =AVERAGE(Trades!W:W) -> 0.0027435204 | J5: 45874 | K5: 0
B6: Daily P&L volatility | C6: =_xlfn.STDEV.S(_xlfn.ANCHORARRAY(K4)) -> 0.1838488 | J6: 45875 | K6: 0
B7: Sharpe-like measure | C7: =AVERAGE(_xlfn.ANCHORARRAY(K4))/_xlfn.STDEV.S(_xlfn.ANCHORARRAY(K4))*SQRT(252) -> 2.5235284 | J7: 45876 | K7: 0
B8: Max drawdown | C8: =MIN(Trades!W:W) -> -0.095289891 | J8: 45877 | K8: 0
B9: Max drawdown / total P&L | C9: =C8/C3 -> -0.25352341 | J9: 45880 | K9: 0
B10: Worst day | J10: 45881 | K10: 0
B11: Max concurrent positions | J11: 45882 | K11: 0
B12: Max gross exposure | J12: 45883 | K12: 0
J13: 45884 | K13: 0
J14: 45887 | K14: 0
J15: 45888 | K15: 0
B16: it seems like this strat might actually be WORSE for risk *potentially* than the single pair version. The main question now is how much capital we need to keep in reserves to avoid margin calling and liquidation. portfolio total P&L = cumulative realised P&L up to minute + total unrealised P&L at minute | J16: 45889 | K16: 0
J17: 45890 | K17: 0
J18: 45891 | K18: 0
J19: 45894 | K19: 0
J20: 45895 | K20: 0
J21: 45896 | K21: 0
J22: 45897 | K22: 0
J23: 45898 | K23: 0
J24: 45901 | K24: 0
J25: 45902 | K25: 0
J26: 45903 | K26: 0
J27: 45904 | K27: 0
J28: 45905 | K28: 0
... J263: 46234 | K263: 0
