Workbook

Sheet Trades
A1: window_id | B1: stock1 | C1: stock2 | D1: entry_timestamp | E1: entry_price_1 | F1: entry_price_2 | G1: entry_price_1_slipped | H1: entry_price_2_slipped | I1: entry_zscore | J1: hedge_ratio_entry | K1: position_size_1 | L1: position_size_2 | M1: direction | N1: holding_minutes | O1: exit_reason | P1: exit_timestamp | Q1: exit_price_1 | R1: exit_price_2 | S1: exit_zscore | T1: gross_pnl | U1: gross_pnl_slipped | V1: transaction_costs | W1: net_pnl | X1: exit_price_age_1 | Y1: exit_price_age_2
A2: 0 | B2: JPM | C2: GS | D2: 24207 | E2: 306.355 | F2: 782.975 | G2: 306.32436 | H2: 783.0533 | I2: 3.594531 | J2: 0.66743015 | K2: -0.03264187 | L2: 0.0085242843 | M2: SHORT | N2: 7 | O2: signal | P2: 24214 | Q2: 305.615 | R2: 782.975 | S2: 0.36824447 | T2: 0.024154984 | U2: 0.020822539 | V2: 0.0033347938 | W2: 0.017487745 | X2: 305.615 | Y2: 782.975
A3: 0 | B3: JPM | C3: GS | D3: 24601 | E3: 310.255 | F3: 784.85 | G3: 310.22397 | H3: 784.92849 | I3: 3.7200374 | J3: 0.66743015 | K3: -0.032231551 | L3: 0.0085039198 | M3: SHORT | N3: 5 | O3: signal | P3: 24606 | Q3: 309.23 | R3: 786.1 | S3: 0.45860297 | T3: 0.04366724 | U3: 0.04033462 | V3: 0.0033347938 | W3: 0.036999827 | X3: 309.23 | Y3: 786.1
A4: 0 | B4: JPM | C4: GS | D4: 24832 | E4: 309.67 | F4: 784.45 | G4: 309.63903 | H4: 784.52845 | I4: 3.979432 | J4: 0.66743015 | K4: -0.03229244 | L4: 0.0085082561 | M4: SHORT | N4: 16 | O4: signal | P4: 24848 | Q4: 309.315 | R4: 783.6 | S4: 0.38578157 | T4: 0.0042317987 | U4: 0.00089880794 | V4: 0.0033347938 | W4: -0.0024359858 | X4: 309.315 | Y4: 783.6
A5: 0 | B5: JPM | C5: GS | D5: 24987 | E5: 310.945 | F5: 792.31 | G5: 310.97609 | H5: 792.23077 | I5: -4.4660855 | J5: 0.66743015 | K5: 0.032160028 | L5: -0.0084238511 | M5: LONG | N5: 9 | O5: signal | P5: 24996 | Q5: 311.59 | R5: 790.28 | S5: 0.2672345 | T5: 0.037843636 | U5: 0.034508411 | V5: 0.0033349268 | W5: 0.031173485 | X5: 311.59 | Y5: 790.28
A6: 0 | B6: JPM | C6: GS | D6: 25380 | E6: 305.665 | F6: 775.68 | G6: 305.69557 | H6: 775.60243 | I6: -3.6905639 | J6: 0.66743015 | K6: 0.032715555 | L6: -0.0086044522 | M6: LONG | N6: 12 | O6: signal | P6: 25392 | Q6: 307.425 | R6: 778.79 | S6: 0.21702582 | T6: 0.03081953 | U6: 0.027476236 | V6: 0.0033349268 | W6: 0.024141309 | X6: 307.425 | Y6: 778.79
A7: 0 | B7: JPM | C7: GS | D7: 25694 | E7: 308.605 | F7: 791.07 | G7: 308.57414 | H7: 791.14911 | I7: 3.6289486 | J7: 0.66743015 | K7: -0.032403882 | L7: 0.0084370555 | M7: SHORT | N7: 37 | O7: signal | P7: 25731 | Q7: 309.34 | R7: 792.03 | S7: 0.21396878 | T7: -0.01571728 | U7: -0.019055332 | V7: 0.0033347938 | W7: -0.022390126 | X7: 309.34 | Y7: 792.03
A8: 0 | B8: JPM | C8: GS | D8: 25752 | E8: 310.22 | F8: 793.57 | G8: 310.18898 | H8: 793.64936 | I8: 3.587045 | J8: 0.66743015 | K8: -0.032235188 | L8: 0.0084104761 | M8: SHORT | N8: 6 | O8: signal | P8: 25758 | Q8: 309.595 | R8: 792.46 | S8: 0.10046321 | T8: 0.010811364 | U8: 0.007479452 | V8: 0.0033347938 | W8: 0.0041446582 | X8: 309.595 | Y8: 792.46
A9: 0 | B9: JPM | C9: GS | D9: 26937 | E9: 316.57 | F9: 798.58 | G9: 316.60166 | H9: 798.50014 | I9: -3.6665215 | J9: 0.66743015 | K9: 0.03158859 | L9: -0.0083577118 | M9: LONG | N9: 5 | O9: signal | P9: 26942 | Q9: 319.07 | R9: 804.4 | S9: -0.22070535 | T9: 0.030329593 | U9: 0.026981971 | V9: 0.0033349268 | W9: 0.023647044 | X9: 319.07 | Y9: 804.4
A10: 0 | B10: JPM | C10: GS | D10: 27327 | E10: 318.785 | F10: 801.62 | G10: 318.75312 | H10: 801.70016 | I10: 3.8655947 | J10: 0.66743015 | K10: -0.031369105 | L10: 0.0083260167 | M10: SHORT | N10: 5 | O10: signal | P10: 27332 | Q10: 316.99 | R10: 797.74 | S10: 0.091473395 | T10: 0.024002598 | U10: 0.020676599 | V10: 0.0033347938 | W10: 0.017341805 | X10: 316.99 | Y10: 797.74
A11: 0 | B11: JPM | C11: GS | D11: 27717 | E11: 316.63 | F11: 816.83 | G11: 316.66166 | H11: 816.74832 | I11: -4.1191154 | J11: 0.66743015 | K11: 0.031582604 | L11: -0.0081709799 | M11: LONG | N11: 8 | O11: signal | P11: 27725 | Q11: 320.43 | R11: 829.34 | S11: -0.091250949 | T11: 0.017794938 | U11: 0.014437855 | V11: 0.0033349268 | W11: 0.011102928 | X11: 320.43 | Y11: 829.34
A12: 1 | B12: JPM | C12: GS | D12: 28497 | E12: 305.71 | F12: 787.29 | G12: 305.67943 | H12: 787.36873 | I12: 3.9612488 | J12: 0.65390315 | K12: -0.032710739 | L12: 0.0083057469 | M12: SHORT | N12: 7 | O12: signal | P12: 28504 | Q12: 304.365 | R12: 786.38 | S12: 0.030918091 | T12: 0.036437714 | U12: 0.033135063 | V12: 0.0033077371 | W12: 0.029827326 | X12: 304.365 | Y12: 786.38
A13: 1 | B13: JPM | C13: GS | D13: 28630 | E13: 304.8 | F13: 797.315 | G13: 304.83048 | H13: 797.23527 | I13: -3.6261084 | J13: 0.65390315 | K13: 0.032808399 | L13: -0.0082013151 | M13: LONG | N13: 9 | O13: signal | P13: 28639 | Q13: 305.47 | R13: 796.03 | S13: 0.26313253 | T13: 0.032520317 | U13: 0.029211367 | V13: 0.0033078755 | W13: 0.025903491 | X13: 305.47 | Y13: 796.03
... A133: 16 | B133: BAC | C133: USB | D133: 90259 | E133: 59.24 | F133: 62.225 | G133: 59.234076 | H133: 62.231223 | I133: 3.938376 | J133: 1.2019117 | K133: -0.16880486 | L133: 0.19315576 | M133: SHORT | N133: 31 | O133: signal | P133: 90290 | Q133: 59.23 | R133: 61.88 | S133: 0.19335895 | T133: -0.06495069 | U133: -0.06934768 | V133: 0.0044038639 | W133: -0.073751544 | X133: 59.23 | Y133: 61.88

Sheet trades edited
A1: window_id | B1: stock1 | C1: stock2 | D1: entry_timestamp | E1: entry_price_1 | F1: entry_price_2 | G1: entry_price_1_slipped | H1: entry_price_2_slipped | I1: entry_zscore | J1: hedge_ratio_entry | K1: position_size_1 | L1: position_size_2 | M1: direction | N1: holding_minutes | O1: exit_reason | P1: exit_timestamp | Q1: exit_price_1 | R1: exit_price_2 | S1: exit_zscore | T1: gross_pnl | U1: gross_pnl_slipped | V1: transaction_costs | W1: net_pnl | X1: Entry day | Y1: Exit day | AB1: timestamp | AC1: minute | AE1: UK Date | AF1: US DATE | AG1: VIX ON ENTRY
A2: 0 | B2: JPM | C2: GS | D2: 24207 | E2: 306.355 | F2: 782.975 | G2: 306.32436 | H2: 783.0533 | I2: 3.594531 | J2: 0.66743015 | K2: -0.03264187 | L2: 0.0085242843 | M2: SHORT | N2: 7 | O2: signal | P2: 24214 | Q2: 305.615 | R2: 782.975 | S2: 0.36824447 | T2: 0.024154984 | U2: 0.020822539 | V2: 0.0033347938 | W2: 0.017487745 | X2: =WORKDAY(DATE(2025,8,2),INT(D2/390)) -> 45958 | Y2: =WORKDAY(DATE(2025,8,2),INT(P2/390)) -> 45958 | AB2: 45873.562 | AC2: 0 | AE2: =IF(ISNUMBER(AF2),DATE(YEAR(AF2),DAY(AF2),MONTH(AF2)),DATE(RIGHT(AF2,4),LEFT(AF2,2),MID(AF2,4,2))) -> 45870 | AF2: 45665 | AG2: 20.38 | AJ2: VIX at entry | AK2: Net PnL | AL2: Trades | AM2: Avg Net P&L | AN2: Win rate
A3: 0 | B3: JPM | C3: GS | D3: 24601 | E3: 310.255 | F3: 784.85 | G3: 310.22397 | H3: 784.92849 | I3: 3.7200374 | J3: 0.66743015 | K3: -0.032231551 | L3: 0.0085039198 | M3: SHORT | N3: 5 | O3: signal | P3: 24606 | Q3: 309.23 | R3: 786.1 | S3: 0.45860297 | T3: 0.04366724 | U3: 0.04033462 | V3: 0.0033347938 | W3: 0.036999827 | X3: =WORKDAY(DATE(2025,8,2),INT(D3/390)) -> 45959 | Y3: =WORKDAY(DATE(2025,8,2),INT(P3/390)) -> 45959 | AB3: 45873.563 | AC3: 1 | AE3: =IF(ISNUMBER(AF3),DATE(YEAR(AF3),DAY(AF3),MONTH(AF3)),DATE(RIGHT(AF3,4),LEFT(AF3,2),MID(AF3,4,2))) -> 45873 | AF3: 45755 | AG3: 17.52 | AJ3: <15 | AK3: =AL3*AM3 -> #DIV/0! | AL3: =COUNTIF(Z:Z,"<15") -> 0 | AM3: =AVERAGEIF(Z:Z,"<15",W:W) -> #DIV/0! | AN3: =COUNTIFS(Z:Z,"<15",T:T,">0")/COUNTIFS(Z:Z,"<15") -> #DIV/0!
A4: 0 | B4: JPM | C4: GS | D4: 24832 | E4: 309.67 | F4: 784.45 | G4: 309.63903 | H4: 784.52845 | I4: 3.979432 | J4: 0.66743015 | K4: -0.03229244 | L4: 0.0085082561 | M4: SHORT | N4: 16 | O4: signal | P4: 24848 | Q4: 309.315 | R4: 783.6 | S4: 0.38578157 | T4: 0.0042317987 | U4: 0.00089880794 | V4: 0.0033347938 | W4: -0.0024359858 | X4: =WORKDAY(DATE(2025,8,2),INT(D4/390)) -> 45959 | Y4: =WORKDAY(DATE(2025,8,2),INT(P4/390)) -> 45959 | AB4: 45873.564 | AC4: 2 | AE4: =IF(ISNUMBER(AF4),DATE(YEAR(AF4),DAY(AF4),MONTH(AF4)),DATE(RIGHT(AF4,4),LEFT(AF4,2),MID(AF4,4,2))) -> 45874 | AF4: 45785 | AG4: 17.85 | AJ4: 15–20 | AK4: =AL4*AM4 -> #DIV/0! | AL4: =COUNTIFS(Z:Z,">=15",Z:Z,"<20") -> 0 | AM4: =AVERAGEIFS(W:W,Z:Z,">=15",Z:Z,"<20") -> #DIV/0! | AN4: =COUNTIFS(Z:Z,">=15",Z:Z,"<20",T:T,">0")/COUNTIFS(Z:Z,">=15",Z:Z,"<20") -> #DIV/0!
A5: 0 | B5: JPM | C5: GS | D5: 24987 | E5: 310.945 | F5: 792.31 | G5: 310.97609 | H5: 792.23077 | I5: -4.4660855 | J5: 0.66743015 | K5: 0.032160028 | L5: -0.0084238511 | M5: LONG | N5: 9 | O5: signal | P5: 24996 | Q5: 311.59 | R5: 790.28 | S5: 0.2672345 | T5: 0.037843636 | U5: 0.034508411 | V5: 0.0033349268 | W5: 0.031173485 | X5: =WORKDAY(DATE(2025,8,2),INT(D5/390)) -> 45960 | Y5: =WORKDAY(DATE(2025,8,2),INT(P5/390)) -> 45960 | AB5: 45873.565 | AC5: 3 | AE5: =IF(ISNUMBER(AF5),DATE(YEAR(AF5),DAY(AF5),MONTH(AF5)),DATE(RIGHT(AF5,4),LEFT(AF5,2),MID(AF5,4,2))) -> 45875 | AF5: 45816 | AG5: 16.77 | AJ5: >=20 | AK5: =AL5*AM5 -> #DIV/0! | AL5: =COUNTIFS(Z:Z,">=20") -> 0 | AM5: =AVERAGEIFS(W:W,Z:Z,">=20") -> #DIV/0! | AN5: =COUNTIFS(Z:Z,">=20",T:T,">0")/COUNTIFS(Z:Z,">=20") -> #DIV/0!
A6: 0 | B6: JPM | C6: GS | D6: 25380 | E6: 305.665 | F6: 775.68 | G6: 305.69557 | H6: 775.60243 | I6: -3.6905639 | J6: 0.66743015 | K6: 0.032715555 | L6: -0.0086044522 | M6: LONG | N6: 12 | O6: signal | P6: 25392 | Q6: 307.425 | R6: 778.79 | S6: 0.21702582 | T6: 0.03081953 | U6: 0.027476236 | V6: 0.0033349268 | W6: 0.024141309 | X6: =WORKDAY(DATE(2025,8,2),INT(D6/390)) -> 45961 | Y6: =WORKDAY(DATE(2025,8,2),INT(P6/390)) -> 45961 | AB6: 45873.565 | AC6: 4 | AE6: =IF(ISNUMBER(AF6),DATE(YEAR(AF6),DAY(AF6),MONTH(AF6)),DATE(RIGHT(AF6,4),LEFT(AF6,2),MID(AF6,4,2))) -> 45876 | AF6: 45846 | AG6: 16.57
A7: 0 | B7: JPM | C7: GS | D7: 25694 | E7: 308.605 | F7: 791.07 | G7: 308.57414 | H7: 791.14911 | I7: 3.6289486 | J7: 0.66743015 | K7: -0.032403882 | L7: 0.0084370555 | M7: SHORT | N7: 37 | O7: signal | P7: 25731 | Q7: 309.34 | R7: 792.03 | S7: 0.21396878 | T7: -0.01571728 | U7: -0.019055332 | V7: 0.0033347938 | W7: -0.022390126 | X7: =WORKDAY(DATE(2025,8,2),INT(D7/390)) -> 45961 | Y7: =WORKDAY(DATE(2025,8,2),INT(P7/390)) -> 45961 | AB7: 45873.566 | AC7: 5 | AE7: =IF(ISNUMBER(AF7),DATE(YEAR(AF7),DAY(AF7),MONTH(AF7)),DATE(RIGHT(AF7,4),LEFT(AF7,2),MID(AF7,4,2))) -> 45877 | AF7: 45877 | AG7: 15.15
A8: 0 | B8: JPM | C8: GS | D8: 25752 | E8: 310.22 | F8: 793.57 | G8: 310.18898 | H8: 793.64936 | I8: 3.587045 | J8: 0.66743015 | K8: -0.032235188 | L8: 0.0084104761 | M8: SHORT | N8: 6 | O8: signal | P8: 25758 | Q8: 309.595 | R8: 792.46 | S8: 0.10046321 | T8: 0.010811364 | U8: 0.007479452 | V8: 0.0033347938 | W8: 0.0041446582 | X8: =WORKDAY(DATE(2025,8,2),INT(D8/390)) -> 45964 | Y8: =WORKDAY(DATE(2025,8,2),INT(P8/390)) -> 45964 | AB8: 45873.567 | AC8: 6 | AE8: =IF(ISNUMBER(AF8),DATE(YEAR(AF8),DAY(AF8),MONTH(AF8)),DATE(RIGHT(AF8,4),LEFT(AF8,2),MID(AF8,4,2))) -> 45880 | AF8: 45969 | AG8: 16.25
A9: 0 | B9: JPM | C9: GS | D9: 26937 | E9: 316.57 | F9: 798.58 | G9: 316.60166 | H9: 798.50014 | I9: -3.6665215 | J9: 0.66743015 | K9: 0.03158859 | L9: -0.0083577118 | M9: LONG | N9: 5 | O9: signal | P9: 26942 | Q9: 319.07 | R9: 804.4 | S9: -0.22070535 | T9: 0.030329593 | U9: 0.026981971 | V9: 0.0033349268 | W9: 0.023647044 | X9: =WORKDAY(DATE(2025,8,2),INT(D9/390)) -> 45967 | Y9: =WORKDAY(DATE(2025,8,2),INT(P9/390)) -> 45967 | AB9: 45873.567 | AC9: 7 | AE9: =IF(ISNUMBER(AF9),DATE(YEAR(AF9),DAY(AF9),MONTH(AF9)),DATE(RIGHT(AF9,4),LEFT(AF9,2),MID(AF9,4,2))) -> 45881 | AF9: 45999 | AG9: 14.73
A10: 0 | B10: JPM | C10: GS | D10: 27327 | E10: 318.785 | F10: 801.62 | G10: 318.75312 | H10: 801.70016 | I10: 3.8655947 | J10: 0.66743015 | K10: -0.031369105 | L10: 0.0083260167 | M10: SHORT | N10: 5 | O10: signal | P10: 27332 | Q10: 316.99 | R10: 797.74 | S10: 0.091473395 | T10: 0.024002598 | U10: 0.020676599 | V10: 0.0033347938 | W10: 0.017341805 | X10: =WORKDAY(DATE(2025,8,2),INT(D10/390)) -> 45968 | Y10: =WORKDAY(DATE(2025,8,2),INT(P10/390)) -> 45968 | AB10: 45873.568 | AC10: 8 | AE10: =IF(ISNUMBER(AF10),DATE(YEAR(AF10),DAY(AF10),MONTH(AF10)),DATE(RIGHT(AF10,4),LEFT(AF10,2),MID(AF10,4,2))) -> 45882 | AF10: 08/13/2025 | AG10: 14.49 | AJ10: Metric | AK10: OOS H1 | AL10: OOS H2
A11: 0 | B11: JPM | C11: GS | D11: 27717 | E11: 316.63 | F11: 816.83 | G11: 316.66166 | H11: 816.74832 | I11: -4.1191154 | J11: 0.66743015 | K11: 0.031582604 | L11: -0.0081709799 | M11: LONG | N11: 8 | O11: signal | P11: 27725 | Q11: 320.43 | R11: 829.34 | S11: -0.091250949 | T11: 0.017794938 | U11: 0.014437855 | V11: 0.0033349268 | W11: 0.011102928 | X11: =WORKDAY(DATE(2025,8,2),INT(D11/390)) -> 45971 | Y11: =WORKDAY(DATE(2025,8,2),INT(P11/390)) -> 45971 | AB11: 45873.569 | AC11: 9 | AE11: =IF(ISNUMBER(AF11),DATE(YEAR(AF11),DAY(AF11),MONTH(AF11)),DATE(RIGHT(AF11,4),LEFT(AF11,2),MID(AF11,4,2))) -> 45883 | AF11: 08/14/2025 | AG11: 14.83 | AJ11: Trades
A12: 1 | B12: JPM | C12: GS | D12: 28497 | E12: 305.71 | F12: 787.29 | G12: 305.67943 | H12: 787.36873 | I12: 3.9612488 | J12: 0.65390315 | K12: -0.032710739 | L12: 0.0083057469 | M12: SHORT | N12: 7 | O12: signal | P12: 28504 | Q12: 304.365 | R12: 786.38 | S12: 0.030918091 | T12: 0.036437714 | U12: 0.033135063 | V12: 0.0033077371 | W12: 0.029827326 | X12: =WORKDAY(DATE(2025,8,2),INT(D12/390)) -> 45973 | Y12: =WORKDAY(DATE(2025,8,2),INT(P12/390)) -> 45973 | AB12: 45873.569 | AC12: 10 | AE12: =IF(ISNUMBER(AF12),DATE(YEAR(AF12),DAY(AF12),MONTH(AF12)),DATE(RIGHT(AF12,4),LEFT(AF12,2),MID(AF12,4,2))) -> 45884 | AF12: 08/15/2025 | AG12: 15.09 | AJ12: Gross P&L
A13: 1 | B13: JPM | C13: GS | D13: 28630 | E13: 304.8 | F13: 797.315 | G13: 304.83048 | H13: 797.23527 | I13: -3.6261084 | J13: 0.65390315 | K13: 0.032808399 | L13: -0.0082013151 | M13: LONG | N13: 9 | O13: signal | P13: 28639 | Q13: 305.47 | R13: 796.03 | S13: 0.26313253 | T13: 0.032520317 | U13: 0.029211367 | V13: 0.0033078755 | W13: 0.025903491 | X13: =WORKDAY(DATE(2025,8,2),INT(D13/390)) -> 45973 | Y13: =WORKDAY(DATE(2025,8,2),INT(P13/390)) -> 45973 | AB13: 45873.57 | AC13: 11 | AE13: =IF(ISNUMBER(AF13),DATE(YEAR(AF13),DAY(AF13),MONTH(AF13)),DATE(RIGHT(AF13,4),LEFT(AF13,2),MID(AF13,4,2))) -> 45887 | AF13: 08/18/2025 | AG13: 14.99 | AJ13: Net P&L
A14: 1 | B14: JPM | C14: GS | D14: 28708 | E14: 304.81 | F14: 797.11 | G14: 304.84048 | H14: 797.03029 | I14: -3.55602 | J14: 0.65390315 | K14: 0.032807323 | L14: -0.0082034243 | M14: LONG | N14: 27 | O14: signal | P14: 28735 | Q14: 304.57 | R14: 796.62 | S14: 0.12160767 | T14: -0.0038540795 | U14: -0.0071606965 | V14: 0.0033078755 | W14: -0.010468572 | X14: =WORKDAY(DATE(2025,8,2),INT(D14/390)) -> 45973 | Y14: =WORKDAY(DATE(2025,8,2),INT(P14/390)) -> 45973 | AB14: 45873.571 | AC14: 12 | AE14: =IF(ISNUMBER(AF14),DATE(YEAR(AF14),DAY(AF14),MONTH(AF14)),DATE(RIGHT(AF14,4),LEFT(AF14,2),MID(AF14,4,2))) -> 45888 | AF14: 08/19/2025 | AG14: 15.57 | AJ14: Avg gross P&L/trade
A15: 1 | B15: JPM | C15: GS | D15: 29594 | E15: 301.3 | F15: 781.25 | G15: 301.26987 | H15: 781.32812 | I15: 3.5359515 | J15: 0.65390315 | K15: -0.033189512 | L15: 0.0083699603 | M15: SHORT | N15: 5 | O15: signal | P15: 29599 | Q15: 300.495 | R15: 781.25 | S15: -0.42317359 | T15: 0.026717557 | U15: 0.023412423 | V15: 0.0033077371 | W15: 0.020104686 | X15: =WORKDAY(DATE(2025,8,2),INT(D15/390)) -> 45975 | Y15: =WORKDAY(DATE(2025,8,2),INT(P15/390)) -> 45975 | AB15: 45873.572 | AC15: 13 | AE15: =IF(ISNUMBER(AF15),DATE(YEAR(AF15),DAY(AF15),MONTH(AF15)),DATE(RIGHT(AF15,4),LEFT(AF15,2),MID(AF15,4,2))) -> 45889 | AF15: 08/20/2025 | AG15: 15.69 | AJ15: Avg net P&L/trade
A16: 1 | B16: JPM | C16: GS | D16: 29667 | E16: 300.82 | F16: 776.07 | G16: 300.78992 | H16: 776.14761 | I16: 4.3180527 | J16: 0.65390315 | K16: -0.033242471 | L16: 0.0084258269 | M16: SHORT | N16: 24 | O16: signal | P16: 29691 | Q16: 302.36 | R16: 779.065 | S16: 0.36508655 | T16: -0.025958053 | U16: -0.029273502 | V16: 0.0033077371 | W16: -0.032581239 | X16: =WORKDAY(DATE(2025,8,2),INT(D16/390)) -> 45978 | Y16: =WORKDAY(DATE(2025,8,2),INT(P16/390)) -> 45978 | AB16: 45873.572 | AC16: 14 | AE16: =IF(ISNUMBER(AF16),DATE(YEAR(AF16),DAY(AF16),MONTH(AF16)),DATE(RIGHT(AF16,4),LEFT(AF16,2),MID(AF16,4,2))) -> 45890 | AF16: 08/21/2025 | AG16: 16.6 | AJ16: Net PF
A17: 1 | B17: JPM | C17: GS | D17: 30059 | E17: 307.04 | F17: 805.745 | G17: 307.0707 | H17: 805.66443 | I17: -3.8618259 | J17: 0.65390315 | K17: 0.032569046 | L17: -0.0081155099 | M17: LONG | N17: 6 | O17: signal | P17: 30065 | Q17: 308.48 | R17: 807.56 | S17: -0.319723 | T17: 0.032169776 | U17: 0.028855807 | V17: 0.0033078755 | W17: 0.025547932 | X17: =WORKDAY(DATE(2025,8,2),INT(D17/390)) -> 45979 | Y17: =WORKDAY(DATE(2025,8,2),INT(P17/390)) -> 45979 | AB17: 45873.573 | AC17: 15 | AE17: =IF(ISNUMBER(AF17),DATE(YEAR(AF17),DAY(AF17),MONTH(AF17)),DATE(RIGHT(AF17,4),LEFT(AF17,2),MID(AF17,4,2))) -> 45891 | AF17: 08/22/2025 | AG17: 14.22 | AJ17: Win rate
A18: 1 | B18: JPM | C18: GS | D18: 31217 | E18: 297.97 | F18: 792.37 | G18: 297.9998 | H18: 792.29076 | I18: -3.574562 | J18: 0.65390315 | K18: 0.033560426 | L18: -0.0082524976 | M18: LONG | N18: 10 | O18: signal | P18: 31227 | Q18: 299.32 | R18: 795.235 | S18: -0.43617298 | T18: 0.021663169 | U18: 0.018348468 | V18: 0.0033078755 | W18: 0.015040592 | X18: =WORKDAY(DATE(2025,8,2),INT(D18/390)) -> 45982 | Y18: =WORKDAY(DATE(2025,8,2),INT(P18/390)) -> 45982 | AB18: 45873.574 | AC18: 16 | AE18: =IF(ISNUMBER(AF18),DATE(YEAR(AF18),DAY(AF18),MONTH(AF18)),DATE(RIGHT(AF18,4),LEFT(AF18,2),MID(AF18,4,2))) -> 45894 | AF18: 08/25/2025 | AG18: 14.79 | AJ18: Avg winner
A19: 2 | B19: BAC | C19: WFC | D19: 32007 | E19: 53.05 | F19: 85.48 | G19: 53.044695 | H19: 85.488548 | I19: 4.5358082 | J19: 0.73858207 | K19: -0.18850141 | L19: 0.08640408 | M19: SHORT | N19: 48 | O19: signal | P19: 32055 | Q19: 53.64 | R19: 85.89 | S19: 0.45483687 | T19: -0.075790161 | U19: -0.07928199 | V19: 0.0034771119 | W19: -0.082759102 | X19: =WORKDAY(DATE(2025,8,2),INT(D19/390)) -> 45986 | Y19: =WORKDAY(DATE(2025,8,2),INT(P19/390)) -> 45986 | AB19: 45873.574 | AC19: 17 | AE19: =IF(ISNUMBER(AF19),DATE(YEAR(AF19),DAY(AF19),MONTH(AF19)),DATE(RIGHT(AF19,4),LEFT(AF19,2),MID(AF19,4,2))) -> 45895 | AF19: 08/26/2025 | AG19: 14.62 | AJ19: Avg loser
A20: 2 | B20: BAC | C20: WFC | D20: 32217 | E20: 53.525 | F20: 85.885 | G20: 53.530352 | H20: 85.876412 | I20: -4.2270289 | J20: 0.73858207 | K20: 0.18682858 | L20: -0.085996632 | M20: LONG | N20: 1 | O20: signal | P20: 32218 | Q20: 53.54 | R20: 85.66 | S20: 0.16301468 | T20: 0.022151671 | U20: 0.018676161 | V20: 0.0034772164 | W20: 0.015198945 | X20: =WORKDAY(DATE(2025,8,2),INT(D20/390)) -> 45986 | Y20: =WORKDAY(DATE(2025,8,2),INT(P20/390)) -> 45986 | AB20: 45873.575 | AC20: 18 | AE20: =IF(ISNUMBER(AF20),DATE(YEAR(AF20),DAY(AF20),MONTH(AF20)),DATE(RIGHT(AF20,4),LEFT(AF20,2),MID(AF20,4,2))) -> 45896 | AF20: 08/27/2025 | AG20: 14.85 | AJ20: Avg holding time
A21: 2 | B21: BAC | C21: WFC | D21: 32614 | E21: 53.25 | F21: 85.77 | G21: 53.255325 | H21: 85.761423 | I21: -3.6888174 | J21: 0.73858207 | K21: 0.18779343 | L21: -0.086111936 | M21: LONG | N21: 17 | O21: signal | P21: 32631 | Q21: 53.135 | R21: 85.39 | S21: -0.28159101 | T21: 0.011126291 | U21: 0.0076545592 | V21: 0.0034772164 | W21: 0.0041773427 | X21: =WORKDAY(DATE(2025,8,2),INT(D21/390)) -> 45987 | Y21: =WORKDAY(DATE(2025,8,2),INT(P21/390)) -> 45987 | AB21: 45873.576 | AC21: 19 | AE21: =IF(ISNUMBER(AF21),DATE(YEAR(AF21),DAY(AF21),MONTH(AF21)),DATE(RIGHT(AF21,4),LEFT(AF21,2),MID(AF21,4,2))) -> 45897 | AF21: 08/28/2025 | AG21: 14.43 | AJ21: Avg |entry Z|
A22: 2 | B22: BAC | C22: WFC | D22: 32998 | E22: 53.3 | F22: 86.31 | G22: 53.29467 | H22: 86.318631 | I22: 4.1634247 | J22: 0.73858207 | K22: -0.18761726 | L22: 0.085573175 | M22: SHORT | N22: 17 | O22: signal | P22: 33015 | Q22: 53.525 | R22: 86.83 | S22: 0.4746937 | T22: 0.0022841673 | U22: -0.0012016681 | V22: 0.0034771119 | W22: -0.0046787799 | X22: =WORKDAY(DATE(2025,8,2),INT(D22/390)) -> 45988 | Y22: =WORKDAY(DATE(2025,8,2),INT(P22/390)) -> 45988 | AB22: 45873.576 | AC22: 20 | AE22: =IF(ISNUMBER(AF22),DATE(YEAR(AF22),DAY(AF22),MONTH(AF22)),DATE(RIGHT(AF22,4),LEFT(AF22,2),MID(AF22,4,2))) -> 45898 | AF22: 08/29/2025 | AG22: 15.36
A23: 2 | B23: BAC | C23: WFC | D23: 34559 | E23: 54.005 | F23: 89.76 | G23: 53.9996 | H23: 89.768976 | I23: 3.5672352 | J23: 0.73858207 | K23: -0.18516804 | L23: 0.082284099 | M23: SHORT | N23: 5 | O23: signal | P23: 34564 | Q23: 53.83 | R23: 89.755 | S23: 0.11894705 | T23: 0.031992987 | U23: 0.028519104 | V23: 0.0034771119 | W23: 0.025041992 | X23: =WORKDAY(DATE(2025,8,2),INT(D23/390)) -> 45994 | Y23: =WORKDAY(DATE(2025,8,2),INT(P23/390)) -> 45994 | AB23: 45873.577 | AC23: 21 | AE23: =IF(ISNUMBER(AF23),DATE(YEAR(AF23),DAY(AF23),MONTH(AF23)),DATE(RIGHT(AF23,4),LEFT(AF23,2),MID(AF23,4,2))) -> 45901 | AF23: 45666 | AG23: 16.12
A24: 2 | B24: BAC | C24: WFC | D24: 35304 | E24: 53.915 | F24: 90.32 | G24: 53.920392 | H24: 90.310968 | I24: -3.5605368 | J24: 0.73858207 | K24: 0.18547714 | L24: -0.081773923 | M24: LONG | N24: 6 | O24: signal | P24: 35310 | Q24: 54.27 | R24: 90.385 | S24: 0.059936539 | T24: 0.06052908 | U24: 0.0570448 | V24: 0.0034772164 | W24: 0.053567583 | X24: =WORKDAY(DATE(2025,8,2),INT(D24/390)) -> 45996 | Y24: =WORKDAY(DATE(2025,8,2),INT(P24/390)) -> 45996 | AB24: 45873.578 | AC24: 22 | AE24: =IF(ISNUMBER(AF24),DATE(YEAR(AF24),DAY(AF24),MONTH(AF24)),DATE(RIGHT(AF24,4),LEFT(AF24,2),MID(AF24,4,2))) -> 45902 | AF24: 45697 | AG24: 17.17
A25: 3 | B25: BAC | C25: WFC | D25: 36509 | E25: 54.965 | F25: 93.105 | G25: 54.970497 | H25: 93.09569 | I25: -4.8712868 | J25: 0.67544695 | K25: 0.18193396 | L25: -0.072546796 | M25: LONG | N25: 7 | O25: signal | P25: 36516 | Q25: 55.35 | R25: 93.03 | S25: -0.41313051 | T25: 0.075485584 | U25: 0.072128229 | V25: 0.0033509588 | W25: 0.06877727 | X25: =WORKDAY(DATE(2025,8,2),INT(D25/390)) -> 46001 | Y25: =WORKDAY(DATE(2025,8,2),INT(P25/390)) -> 46001 | AB25: 45873.578 | AC25: 23 | AE25: =IF(ISNUMBER(AF25),DATE(YEAR(AF25),DAY(AF25),MONTH(AF25)),DATE(RIGHT(AF25,4),LEFT(AF25,2),MID(AF25,4,2))) -> 45903 | AF25: 45725 | AG25: 16.35
A26: 3 | B26: BAC | C26: WFC | D26: 37290 | E26: 54.595 | F26: 93.11 | G26: 54.600459 | H26: 93.100689 | I26: -3.9272584 | J26: 0.67544695 | K26: 0.18316696 | L26: -0.0725429 | M26: LONG | N26: 25 | O26: signal | P26: 37315 | Q26: 55.1 | R26: 93.705 | S26: 0.14678068 | T26: 0.049336287 | U26: 0.045971827 | V26: 0.0033509588 | W26: 0.042620868 | X26: =WORKDAY(DATE(2025,8,2),INT(D26/390)) -> 46003 | Y26: =WORKDAY(DATE(2025,8,2),INT(P26/390)) -> 46003 | AB26: 45873.579 | AC26: 24 | AE26: =IF(ISNUMBER(AF26),DATE(YEAR(AF26),DAY(AF26),MONTH(AF26)),DATE(RIGHT(AF26,4),LEFT(AF26,2),MID(AF26,4,2))) -> 45904 | AF26: 45756 | AG26: 15.3
A27: 3 | B27: BAC | C27: WFC | D27: 37679 | E27: 54.57 | F27: 91.7 | G27: 54.564543 | H27: 91.70917 | I27: 4.6807257 | J27: 0.67544695 | K27: -0.18325087 | L27: 0.073658336 | M27: SHORT | N27: 22 | O27: signal | P27: 37701 | Q27: 54.75 | R27: 92.075 | S27: 0.41292147 | T27: -0.0053632805 | U27: -0.0087202351 | V27: 0.003350829 | W27: -0.012071064 | X27: =WORKDAY(DATE(2025,8,2),INT(D27/390)) -> 46006 | Y27: =WORKDAY(DATE(2025,8,2),INT(P27/390)) -> 46006 | AB27: 45873.58 | AC27: 25 | AE27: =IF(ISNUMBER(AF27),DATE(YEAR(AF27),DAY(AF27),MONTH(AF27)),DATE(RIGHT(AF27,4),LEFT(AF27,2),MID(AF27,4,2))) -> 45905 | AF27: 45786 | AG27: 15.18
A28: 3 | B28: BAC | C28: WFC | D28: 38190 | E28: 55.87 | F28: 94.01 | G28: 55.864413 | H28: 94.019401 | I28: 3.6342178 | J28: 0.67544695 | K28: -0.17898693 | L28: 0.071848415 | M28: SHORT | N28: 16 | O28: signal | P28: 38206 | Q28: 55.915 | R28: 94.115 | S28: 0.48719907 | T28: -0.0005103285 | U28: -0.0038627822 | V28: 0.003350829 | W28: -0.0072136112 | X28: =WORKDAY(DATE(2025,8,2),INT(D28/390)) -> 46007 | Y28: =WORKDAY(DATE(2025,8,2),INT(P28/390)) -> 46007 | AB28: 45873.581 | AC28: 26 | AE28: =IF(ISNUMBER(AF28),DATE(YEAR(AF28),DAY(AF28),MONTH(AF28)),DATE(RIGHT(AF28,4),LEFT(AF28,2),MID(AF28,4,2))) -> 45908 | AF28: 45878 | AG28: 15.11
A29: 3 | B29: BAC | C29: WFC | D29: 38306 | E29: 55.98 | F29: 93.99 | G29: 55.985598 | H29: 93.980601 | I29: -4.0638487 | J29: 0.67544695 | K29: 0.17863523 | L29: -0.071863703 | M29: LONG | N29: 27 | O29: signal | P29: 38333 | Q29: 55.955 | R29: 93.96 | S29: 0.017472686 | T29: -0.0023099696 | U29: -0.0056602013 | V29: 0.0033509588 | W29: -0.0090111601 | X29: =WORKDAY(DATE(2025,8,2),INT(D29/390)) -> 46008 | Y29: =WORKDAY(DATE(2025,8,2),INT(P29/390)) -> 46008 | AB29: 45873.581 | AC29: 27 | AE29: =IF(ISNUMBER(AF29),DATE(YEAR(AF29),DAY(AF29),MONTH(AF29)),DATE(RIGHT(AF29,4),LEFT(AF29,2),MID(AF29,4,2))) -> 45909 | AF29: 45909 | AG29: 15.04
A30: 3 | B30: BAC | C30: WFC | D30: 38659 | E30: 55.95 | F30: 94.22 | G30: 55.955595 | H30: 94.210578 | I30: -3.6283825 | J30: 0.67544695 | K30: 0.17873101 | L30: -0.071688277 | M30: LONG | N30: 15 | O30: signal | P30: 38674 | Q30: 56.025 | R30: 94.29 | S30: 0.17646003 | T30: 0.0083866464 | U30: 0.0050339102 | V30: 0.0033509588 | W30: 0.0016829514 | X30: =WORKDAY(DATE(2025,8,2),INT(D30/390)) -> 46009 | Y30: =WORKDAY(DATE(2025,8,2),INT(P30/390)) -> 46009 | AB30: 45873.582 | AC30: 28 | AE30: =IF(ISNUMBER(AF30),DATE(YEAR(AF30),DAY(AF30),MONTH(AF30)),DATE(RIGHT(AF30,4),LEFT(AF30,2),MID(AF30,4,2))) -> 45910 | AF30: 45939 | AG30: 15.35
A31: 3 | B31: BAC | C31: WFC | D31: 39059 | E31: 56.42 | F31: 95.27 | G31: 56.414358 | H31: 95.279527 | I31: 3.7111055 | J31: 0.67544695 | K31: -0.17724211 | L31: 0.070898178 | M31: SHORT | N31: 9 | O31: signal | P31: 39068 | Q31: 56.34 | R31: 95.295 | S31: 0.16521923 | T31: 0.015951823 | U31: 0.01260217 | V31: 0.003350829 | W31: 0.0092513413 | X31: =WORKDAY(DATE(2025,8,2),INT(D31/390)) -> 46010 | Y31: =WORKDAY(DATE(2025,8,2),INT(P31/390)) -> 46010 | AB31: 45873.583 | AC31: 29 | AE31: =IF(ISNUMBER(AF31),DATE(YEAR(AF31),DAY(AF31),MONTH(AF31)),DATE(RIGHT(AF31,4),LEFT(AF31,2),MID(AF31,4,2))) -> 45911 | AF31: 45970 | AG31: 14.71
A32: 3 | B32: BAC | C32: WFC | D32: 39449 | E32: 56.095 | F32: 95.37 | G32: 56.100609 | H32: 95.360463 | I32: -3.6509999 | J32: 0.67544695 | K32: 0.17826901 | L32: -0.070823838 | M32: LONG | N32: 23 | O32: signal | P32: 39472 | Q32: 55.91 | R32: 94.92 | S32: -0.48824636 | T32: -0.0011090393 | U32: -0.0044534481 | V32: 0.0033509588 | W32: -0.0078044069 | X32: =WORKDAY(DATE(2025,8,2),INT(D32/390)) -> 46013 | Y32: =WORKDAY(DATE(2025,8,2),INT(P32/390)) -> 46013 | AB32: 45873.583 | AC32: 30 | AE32: =IF(ISNUMBER(AF32),DATE(YEAR(AF32),DAY(AF32),MONTH(AF32)),DATE(RIGHT(AF32,4),LEFT(AF32,2),MID(AF32,4,2))) -> 45912 | AF32: 46000 | AG32: 14.76
A33: 4 | B33: BAC | C33: WFC | D33: 39839 | E33: 55.6 | F33: 94.82 | G33: 55.59444 | H33: 94.829482 | I33: 5.0316061 | J33: 0.65333461 | K33: -0.17985612 | L33: 0.068902616 | M33: SHORT | N33: 15 | O33: signal | P33: 39854 | Q33: 55.325 | R33: 94.34 | S33: -0.086236821 | T33: 0.016387176 | U33: 0.01308876 | V33: 0.0033065999 | W33: 0.0097821602 | X33: =WORKDAY(DATE(2025,8,2),INT(D33/390)) -> 46014 | Y33: =WORKDAY(DATE(2025,8,2),INT(P33/390)) -> 46014 | AB33: 45873.584 | AC33: 31 | AE33: =IF(ISNUMBER(AF33),DATE(YEAR(AF33),DAY(AF33),MONTH(AF33)),DATE(RIGHT(AF33,4),LEFT(AF33,2),MID(AF33,4,2))) -> 45915 | AF33: 09/15/2025 | AG33: 15.69
A34: 4 | B34: BAC | C34: WFC | D34: 41009 | E34: 56.28 | F34: 95.5 | G34: 56.274372 | H34: 95.50955 | I34: 5.0228281 | J34: 0.65333461 | K34: -0.17768301 | L34: 0.068412001 | M34: SHORT | N34: 27 | O34: signal | P34: 41036 | Q34: 57.19 | R34: 96.84 | S34: 0.39209777 | T34: -0.070019462 | U34: -0.073351467 | V34: 0.0033065999 | W34: -0.076658067 | X34: =WORKDAY(DATE(2025,8,2),INT(D34/390)) -> 46017 | Y34: =WORKDAY(DATE(2025,8,2),INT(P34/390)) -> 46017 | AB34: 45873.585 | AC34: 32 | AE34: =IF(ISNUMBER(AF34),DATE(YEAR(AF34),DAY(AF34),MONTH(AF34)),DATE(RIGHT(AF34,4),LEFT(AF34,2),MID(AF34,4,2))) -> 45916 | AF34: 09/16/2025 | AG34: 16.36
A35: 4 | B35: BAC | C35: WFC | D35: 41201 | E35: 57.27 | F35: 97.02 | G35: 57.264273 | H35: 97.029702 | I35: 3.6553078 | J35: 0.65333461 | K35: -0.17461149 | L35: 0.067340198 | M35: SHORT | N35: 8 | O35: signal | P35: 41209 | Q35: 57.21 | R35: 97.1 | S35: 0.10476352 | T35: 0.015863905 | U35: 0.012557745 | V35: 0.0033065999 | W35: 0.0092511451 | X35: =WORKDAY(DATE(2025,8,2),INT(D35/390)) -> 46017 | Y35: =WORKDAY(DATE(2025,8,2),INT(P35/390)) -> 46017 | AB35: 45873.585 | AC35: 33 | AE35: =IF(ISNUMBER(AF35),DATE(YEAR(AF35),DAY(AF35),MONTH(AF35)),DATE(RIGHT(AF35,4),LEFT(AF35,2),MID(AF35,4,2))) -> 45917 | AF35: 09/17/2025 | AG35: 15.72
A36: 4 | B36: BAC | C36: WFC | D36: 41399 | E36: 57.19 | F36: 95.59 | G36: 57.184281 | H36: 95.599559 | I36: 5.0111564 | J36: 0.65333461 | K36: -0.17485574 | L36: 0.068347589 | M36: SHORT | N36: 15 | O36: signal | P36: 41414 | Q36: 56.91 | R36: 95.525 | S36: 0.46103593 | T36: 0.044517015 | U36: 0.041215686 | V36: 0.0033065999 | W36: 0.037909086 | X36: =WORKDAY(DATE(2025,8,2),INT(D36/390)) -> 46020 | Y36: =WORKDAY(DATE(2025,8,2),INT(P36/390)) -> 46020 | AB36: 45873.586 | AC36: 34 | AE36: =IF(ISNUMBER(AF36),DATE(YEAR(AF36),DAY(AF36),MONTH(AF36)),DATE(RIGHT(AF36,4),LEFT(AF36,2),MID(AF36,4,2))) -> 45918 | AF36: 09/18/2025 | AG36: 15.7
A37: 4 | B37: BAC | C37: WFC | D37: 41790 | E37: 56.665 | F37: 95.725 | G37: 56.670667 | H37: 95.715427 | I37: -4.5347559 | J37: 0.65333461 | K37: 0.17647578 | L37: -0.068251199 | M37: LONG | N37: 35 | O37: signal | P37: 41825 | Q37: 56.145 | R37: 94.71 | S37: -0.064708702 | T37: -0.022492438 | U37: -0.025783003 | V37: 0.0033067385 | W37: -0.029089741 | X37: =WORKDAY(DATE(2025,8,2),INT(D37/390)) -> 46021 | Y37: =WORKDAY(DATE(2025,8,2),INT(P37/390)) -> 46021 | AB37: 45873.587 | AC37: 35 | AE37: =IF(ISNUMBER(AF37),DATE(YEAR(AF37),DAY(AF37),MONTH(AF37)),DATE(RIGHT(AF37,4),LEFT(AF37,2),MID(AF37,4,2))) -> 45919 | AF37: 09/19/2025 | AG37: 15.45
A38: 4 | B38: BAC | C38: WFC | D38: 42180 | E38: 55.58 | F38: 94.41 | G38: 55.585558 | H38: 94.400559 | I38: -4.0714174 | J38: 0.65333461 | K38: 0.17992083 | L38: -0.069201844 | M38: LONG | N38: 1 | O38: signal | P38: 42181 | Q38: 55.77 | R38: 94.43 | S38: 0.11846267 | T38: 0.032800922 | U38: 0.029490696 | V38: 0.0033067385 | W38: 0.026183957 | X38: =WORKDAY(DATE(2025,8,2),INT(D38/390)) -> 46022 | Y38: =WORKDAY(DATE(2025,8,2),INT(P38/390)) -> 46022 | AB38: 45873.588 | AC38: 36 | AE38: =IF(ISNUMBER(AF38),DATE(YEAR(AF38),DAY(AF38),MONTH(AF38)),DATE(RIGHT(AF38,4),LEFT(AF38,2),MID(AF38,4,2))) -> 45922 | AF38: 09/22/2025 | AG38: 16.1
A39: 4 | B39: BAC | C39: WFC | D39: 43332 | E39: 55.17 | F39: 94.905 | G39: 55.164483 | H39: 94.91449 | I39: 3.7294972 | J39: 0.65333461 | K39: -0.18125793 | L39: 0.068840905 | M39: SHORT | N39: 6 | O39: signal | P39: 43338 | Q39: 55.115 | R39: 94.925 | S39: 0.19387848 | T39: 0.011346004 | U39: 0.0080401943 | V39: 0.0033065999 | W39: 0.0047335944 | X39: =WORKDAY(DATE(2025,8,2),INT(D39/390)) -> 46027 | Y39: =WORKDAY(DATE(2025,8,2),INT(P39/390)) -> 46027 | AB39: 45873.588 | AC39: 37 | AE39: =IF(ISNUMBER(AF39),DATE(YEAR(AF39),DAY(AF39),MONTH(AF39)),DATE(RIGHT(AF39,4),LEFT(AF39,2),MID(AF39,4,2))) -> 45923 | AF39: 09/23/2025 | AG39: 16.64
A40: 5 | B40: BAC | C40: WFC | D40: 44003 | E40: 52.16 | F40: 88.9 | G40: 52.154784 | H40: 88.90889 | I40: 3.5004358 | J40: 0.60699764 | K40: -0.19171779 | L40: 0.068278699 | M40: SHORT | N40: 21 | O40: signal | P40: 44024 | Q40: 52.29 | R40: 88.99 | S40: 0.49471769 | T40: -0.01877823 | U40: -0.021995332 | V40: 0.0032139167 | W40: -0.025209249 | X40: =WORKDAY(DATE(2025,8,2),INT(D40/390)) -> 46028 | Y40: =WORKDAY(DATE(2025,8,2),INT(P40/390)) -> 46028 | AB40: 45873.589 | AC40: 38 | AE40: =IF(ISNUMBER(AF40),DATE(YEAR(AF40),DAY(AF40),MONTH(AF40)),DATE(RIGHT(AF40,4),LEFT(AF40,2),MID(AF40,4,2))) -> 45924 | AF40: 09/24/2025 | AG40: 16.18
A41: 5 | B41: BAC | C41: WFC | D41: 44541 | E41: 52.91 | F41: 89.31 | G41: 52.904709 | H41: 89.318931 | I41: 4.4053722 | J41: 0.60699764 | K41: -0.18900019 | L41: 0.067965249 | M41: SHORT | N41: 3 | O41: signal | P41: 44544 | Q41: 52.54 | R41: 88.84 | S41: -0.031865356 | T41: 0.037986403 | U41: 0.034782595 | V41: 0.0032139167 | W41: 0.031568678 | X41: =WORKDAY(DATE(2025,8,2),INT(D41/390)) -> 46030 | Y41: =WORKDAY(DATE(2025,8,2),INT(P41/390)) -> 46030 | AB41: 45873.59 | AC41: 39 | AE41: =IF(ISNUMBER(AF41),DATE(YEAR(AF41),DAY(AF41),MONTH(AF41)),DATE(RIGHT(AF41,4),LEFT(AF41,2),MID(AF41,4,2))) -> 45925 | AF41: 09/25/2025 | AG41: 16.74
A42: 5 | B42: BAC | C42: WFC | D42: 44934 | E42: 52.345 | F42: 87.17 | G42: 52.350234 | H42: 87.161283 | I42: -3.7539575 | J42: 0.60699764 | K42: 0.19104021 | L42: -0.069633777 | M42: LONG | N42: 14 | O42: signal | P42: 44948 | Q42: 52.715 | R42: 87.87 | S42: -0.18276601 | T42: 0.021941235 | U42: 0.018715297 | V42: 0.0032140739 | W42: 0.015501223 | X42: =WORKDAY(DATE(2025,8,2),INT(D42/390)) -> 46031 | Y42: =WORKDAY(DATE(2025,8,2),INT(P42/390)) -> 46031 | AB42: 45873.59 | AC42: 40 | AE42: =IF(ISNUMBER(AF42),DATE(YEAR(AF42),DAY(AF42),MONTH(AF42)),DATE(RIGHT(AF42,4),LEFT(AF42,2),MID(AF42,4,2))) -> 45926 | AF42: 09/26/2025 | AG42: 15.29
A43: 5 | B43: BAC | C43: WFC | D43: 45515 | E43: 52.44 | F43: 86.845 | G43: 52.434756 | H43: 86.853684 | I43: 3.7192284 | J43: 0.60699764 | K43: -0.19069413 | L43: 0.069894368 | M43: SHORT | N43: 19 | O43: signal | P43: 45534 | Q43: 52.39 | R43: 86.78 | S43: 0.22693364 | T43: 0.0049915724 | U43: 0.0017789849 | V43: 0.0032139167 | W43: -0.0014349318 | X43: =WORKDAY(DATE(2025,8,2),INT(D43/390)) -> 46034 | Y43: =WORKDAY(DATE(2025,8,2),INT(P43/390)) -> 46034 | AB43: 45873.591 | AC43: 41 | AE43: =IF(ISNUMBER(AF43),DATE(YEAR(AF43),DAY(AF43),MONTH(AF43)),DATE(RIGHT(AF43,4),LEFT(AF43,2),MID(AF43,4,2))) -> 45929 | AF43: 09/29/2025 | AG43: 16.12
A44: 5 | B44: BAC | C44: WFC | D44: 45712 | E44: 52.63 | F44: 86.45 | G44: 52.624737 | H44: 86.458645 | I44: 4.7581025 | J44: 0.60699764 | K44: -0.1900057 | L44: 0.070213723 | M44: SHORT | N44: 13 | O44: signal | P44: 45725 | Q44: 52.805 | R44: 87.42 | S44: 0.28526969 | T44: 0.034856314 | U44: 0.031632183 | V44: 0.0032139167 | W44: 0.028418266 | X44: =WORKDAY(DATE(2025,8,2),INT(D44/390)) -> 46035 | Y44: =WORKDAY(DATE(2025,8,2),INT(P44/390)) -> 46035 | AB44: 45873.592 | AC44: 42 | AE44: =IF(ISNUMBER(AF44),DATE(YEAR(AF44),DAY(AF44),MONTH(AF44)),DATE(RIGHT(AF44,4),LEFT(AF44,2),MID(AF44,4,2))) -> 45930 | AF44: 09/30/2025 | AG44: 16.28
A45: 5 | B45: BAC | C45: WFC | D45: 45806 | E45: 52.82 | F45: 88.225 | G45: 52.814718 | H45: 88.233822 | I45: 3.5419216 | J45: 0.60699764 | K45: -0.18932223 | L45: 0.068801092 | M45: SHORT | N45: 9 | O45: signal | P45: 45815 | Q45: 52.805 | R45: 88.355 | S45: 0.26943153 | T45: 0.011783975 | U45: 0.0085693697 | V45: 0.0032139167 | W45: 0.005355453 | X45: =WORKDAY(DATE(2025,8,2),INT(D45/390)) -> 46035 | Y45: =WORKDAY(DATE(2025,8,2),INT(P45/390)) -> 46035 | AB45: 45873.592 | AC45: 43 | AE45: =IF(ISNUMBER(AF45),DATE(YEAR(AF45),DAY(AF45),MONTH(AF45)),DATE(RIGHT(AF45,4),LEFT(AF45,2),MID(AF45,4,2))) -> 45931 | AF45: 45667 | AG45: 16.29
A46: 5 | B46: BAC | C46: WFC | D46: 46105 | E46: 51.88 | F46: 87.05 | G46: 51.885188 | H46: 87.041295 | I46: -3.8454865 | J46: 0.60699764 | K46: 0.19275251 | L46: -0.069729769 | M46: LONG | N46: 13 | O46: signal | P46: 46118 | Q46: 51.82 | R46: 87.155 | S46: -0.46359032 | T46: -0.018886776 | U46: -0.022100347 | V46: 0.0032140739 | W46: -0.025314421 | X46: =WORKDAY(DATE(2025,8,2),INT(D46/390)) -> 46036 | Y46: =WORKDAY(DATE(2025,8,2),INT(P46/390)) -> 46036 | AB46: 45873.593 | AC46: 44 | AE46: =IF(ISNUMBER(AF46),DATE(YEAR(AF46),DAY(AF46),MONTH(AF46)),DATE(RIGHT(AF46,4),LEFT(AF46,2),MID(AF46,4,2))) -> 45932 | AF46: 45698 | AG46: 16.63
A47: 5 | B47: BAC | C47: WFC | D47: 47273 | E47: 51.95 | F47: 88.66 | G47: 51.955195 | H47: 88.651134 | I47: -4.0212474 | J47: 0.60699764 | K47: 0.19249278 | L47: -0.068463528 | M47: LONG | N47: 26 | O47: signal | P47: 47299 | Q47: 51.955 | R47: 88.9 | S47: -0.30297441 | T47: -0.015468783 | U47: -0.018684517 | V47: 0.0032140739 | W47: -0.021898591 | X47: =WORKDAY(DATE(2025,8,2),INT(D47/390)) -> 46041 | Y47: =WORKDAY(DATE(2025,8,2),INT(P47/390)) -> 46041 | AB47: 45873.594 | AC47: 45 | AE47: =IF(ISNUMBER(AF47),DATE(YEAR(AF47),DAY(AF47),MONTH(AF47)),DATE(RIGHT(AF47,4),LEFT(AF47,2),MID(AF47,4,2))) -> 45933 | AF47: 45726 | AG47: 16.65
A48: 6 | B48: JPM | C48: BAC | D48: 47638 | E48: 300.86 | F48: 51.64 | G48: 300.89009 | H48: 51.634836 | I48: -3.5518788 | J48: 1.0490293 | K48: 0.033238051 | L48: -0.20314279 | M48: LONG | N48: 29 | O48: signal | P48: 47667 | Q48: 304.9 | R48: 52.38 | S48: 0.14843383 | T48: -0.016043936 | U48: -0.020170455 | V48: 0.0040980489 | W48: -0.024268504 | X48: =WORKDAY(DATE(2025,8,2),INT(D48/390)) -> 46042 | Y48: =WORKDAY(DATE(2025,8,2),INT(P48/390)) -> 46042 | AB48: 45873.594 | AC48: 46 | AE48: =IF(ISNUMBER(AF48),DATE(YEAR(AF48),DAY(AF48),MONTH(AF48)),DATE(RIGHT(AF48,4),LEFT(AF48,2),MID(AF48,4,2))) -> 45936 | AF48: 45818 | AG48: 16.37
A49: 6 | B49: JPM | C49: BAC | D49: 47964 | E49: 304.83 | F49: 52.87 | G49: 304.86048 | H49: 52.864713 | I49: -4.1516297 | J49: 1.0490293 | K49: 0.03280517 | L49: -0.19841675 | M49: LONG | N49: 9 | O49: signal | P49: 47973 | Q49: 305.74 | R49: 52.885 | S49: 0.40576484 | T49: 0.026876454 | U49: 0.022775112 | V49: 0.0040980489 | W49: 0.018677063 | X49: =WORKDAY(DATE(2025,8,2),INT(D49/390)) -> 46042 | Y49: =WORKDAY(DATE(2025,8,2),INT(P49/390)) -> 46043 | AB49: 45873.595 | AC49: 47 | AE49: =IF(ISNUMBER(AF49),DATE(YEAR(AF49),DAY(AF49),MONTH(AF49)),DATE(RIGHT(AF49,4),LEFT(AF49,2),MID(AF49,4,2))) -> 45937 | AF49: 45848 | AG49: 17.24
A50: 6 | B50: JPM | C50: BAC | D50: 48224 | E50: 303.74 | F50: 52.99 | G50: 303.77037 | H50: 52.984701 | I50: -3.5960148 | J50: 1.0490293 | K50: 0.032922895 | L50: -0.19796742 | M50: LONG | N50: 19 | O50: signal | P50: 48243 | Q50: 303.51 | R50: 52.92 | S50: 0.029467072 | T50: 0.0062854535 | U50: 0.0021895378 | V50: 0.0040980489 | W50: -0.0019085111 | X50: =WORKDAY(DATE(2025,8,2),INT(D50/390)) -> 46043 | Y50: =WORKDAY(DATE(2025,8,2),INT(P50/390)) -> 46043 | AB50: 45873.596 | AC50: 48 | AE50: =IF(ISNUMBER(AF50),DATE(YEAR(AF50),DAY(AF50),MONTH(AF50)),DATE(RIGHT(AF50,4),LEFT(AF50,2),MID(AF50,4,2))) -> 45938 | AF50: 45879 | AG50: 16.3
A51: 6 | B51: JPM | C51: BAC | D51: 48834 | E51: 312.99 | F51: 54.57 | G51: 312.9587 | H51: 54.575457 | I51: 3.5632041 | J51: 1.0490293 | K51: -0.031949903 | L51: 0.19223554 | M51: SHORT | N51: 1 | O51: signal | P51: 48835 | Q51: 311.17 | R51: 54.49 | S51: 0.029694549 | T51: 0.042769979 | U51: 0.038679273 | V51: 0.0040980685 | W51: 0.034581205 | X51: =WORKDAY(DATE(2025,8,2),INT(D51/390)) -> 46045 | Y51: =WORKDAY(DATE(2025,8,2),INT(P51/390)) -> 46045 | AB51: 45873.597 | AC51: 49 | AE51: =IF(ISNUMBER(AF51),DATE(YEAR(AF51),DAY(AF51),MONTH(AF51)),DATE(RIGHT(AF51,4),LEFT(AF51,2),MID(AF51,4,2))) -> 45939 | AF51: 45910 | AG51: 16.43
A52: 6 | B52: JPM | C52: BAC | D52: 49223 | E52: 316.18 | F52: 55.055 | G52: 316.21162 | H52: 55.049495 | I52: -4.859089 | J52: 1.0490293 | K52: 0.031627554 | L52: -0.19054207 | M52: LONG | N52: 31 | O52: signal | P52: 49254 | Q52: 315.45 | R52: 55.23 | S52: -0.18965137 | T52: -0.056432976 | U52: -0.06053206 | V52: 0.0040980489 | W52: -0.064630109 | X52: =WORKDAY(DATE(2025,8,2),INT(D52/390)) -> 46048 | Y52: =WORKDAY(DATE(2025,8,2),INT(P52/390)) -> 46048 | AB52: 45873.597 | AC52: 50 | AE52: =IF(ISNUMBER(AF52),DATE(YEAR(AF52),DAY(AF52),MONTH(AF52)),DATE(RIGHT(AF52,4),LEFT(AF52,2),MID(AF52,4,2))) -> 45940 | AF52: 45940 | AG52: 21.66
A53: 6 | B53: JPM | C53: BAC | D53: 49616 | E53: 311.875 | F53: 54.77 | G53: 311.90619 | H53: 54.764523 | I53: -3.8976025 | J53: 1.0490293 | K53: 0.032064128 | L53: -0.19153357 | M53: LONG | N53: 2 | O53: signal | P53: 49618 | Q53: 311.15 | R53: 54.445 | S53: -0.18436969 | T53: 0.039001916 | U53: 0.034912407 | V53: 0.0040980489 | W53: 0.030814358 | X53: =WORKDAY(DATE(2025,8,2),INT(D53/390)) -> 46049 | Y53: =WORKDAY(DATE(2025,8,2),INT(P53/390)) -> 46049 | AB53: 45873.598 | AC53: 51 | AE53: =IF(ISNUMBER(AF53),DATE(YEAR(AF53),DAY(AF53),MONTH(AF53)),DATE(RIGHT(AF53,4),LEFT(AF53,2),MID(AF53,4,2))) -> 45943 | AF53: 10/13/2025 | AG53: 19.03
A54: 6 | B54: JPM | C54: BAC | D54: 50004 | E54: 316.03 | F54: 55.7 | G54: 315.9984 | H54: 55.70557 | I54: 3.6230947 | J54: 1.0490293 | K54: -0.031642566 | L54: 0.18833561 | M54: SHORT | N54: 27 | O54: signal | P54: 50031 | Q54: 321.46 | R54: 56.15 | S54: 0.17975244 | T54: -0.087068107 | U54: -0.091191822 | V54: 0.0040980685 | W54: -0.095289891 | X54: =WORKDAY(DATE(2025,8,2),INT(D54/390)) -> 46050 | Y54: =WORKDAY(DATE(2025,8,2),INT(P54/390)) -> 46050 | AB54: 45873.599 | AC54: 52 | AE54: =IF(ISNUMBER(AF54),DATE(YEAR(AF54),DAY(AF54),MONTH(AF54)),DATE(RIGHT(AF54,4),LEFT(AF54,2),MID(AF54,4,2))) -> 45944 | AF54: 10/14/2025 | AG54: 20.81
A55: 6 | B55: JPM | C55: BAC | D55: 50394 | E55: 320.89 | F55: 56.535 | G55: 320.92209 | H55: 56.529347 | I55: -4.3146824 | J55: 1.0490293 | K55: 0.031163327 | L55: -0.18555397 | M55: LONG | N55: 1 | O55: signal | P55: 50395 | Q55: 320.895 | R55: 56.34 | S55: -0.46827257 | T55: 0.03633884 | U55: 0.032244384 | V55: 0.0040980489 | W55: 0.028146335 | X55: =WORKDAY(DATE(2025,8,2),INT(D55/390)) -> 46051 | Y55: =WORKDAY(DATE(2025,8,2),INT(P55/390)) -> 46051 | AB55: 45873.599 | AC55: 53 | AE55: =IF(ISNUMBER(AF55),DATE(YEAR(AF55),DAY(AF55),MONTH(AF55)),DATE(RIGHT(AF55,4),LEFT(AF55,2),MID(AF55,4,2))) -> 45945 | AF55: 10/15/2025 | AG55: 20.64
A56: 6 | B56: JPM | C56: BAC | D56: 50785 | E56: 325.55 | F56: 56.74 | G56: 325.51745 | H56: 56.745674 | I56: 4.0609214 | J56: 1.0490293 | K56: -0.030717248 | L56: 0.18488356 | M56: SHORT | N56: 25 | O56: signal | P56: 50810 | Q56: 325.1 | R56: 56.575 | S56: 0.3065808 | T56: -0.016683027 | U56: -0.020776653 | V56: 0.0040980685 | W56: -0.024874721 | X56: =WORKDAY(DATE(2025,8,2),INT(D56/390)) -> 46052 | Y56: =WORKDAY(DATE(2025,8,2),INT(P56/390)) -> 46052 | AB56: 45873.6 | AC56: 54 | AE56: =IF(ISNUMBER(AF56),DATE(YEAR(AF56),DAY(AF56),MONTH(AF56)),DATE(RIGHT(AF56,4),LEFT(AF56,2),MID(AF56,4,2))) -> 45946 | AF56: 10/16/2025 | AG56: 25.31
A57: 6 | B57: JPM | C57: BAC | D57: 51174 | E57: 323.53 | F57: 55.94 | G57: 323.49765 | H57: 55.945594 | I57: 4.6345613 | J57: 1.0490293 | K57: -0.030909035 | L57: 0.18752759 | M57: SHORT | N57: 21 | O57: signal | P57: 51195 | Q57: 321.075 | R57: 55.34 | S57: 0.29875456 | T57: -0.036634875 | U57: -0.040714093 | V57: 0.0040980685 | W57: -0.044812162 | X57: =WORKDAY(DATE(2025,8,2),INT(D57/390)) -> 46055 | Y57: =WORKDAY(DATE(2025,8,2),INT(P57/390)) -> 46055 | AB57: 45873.601 | AC57: 55 | AE57: =IF(ISNUMBER(AF57),DATE(YEAR(AF57),DAY(AF57),MONTH(AF57)),DATE(RIGHT(AF57,4),LEFT(AF57,2),MID(AF57,4,2))) -> 45947 | AF57: 10/17/2025 | AG57: 20.78
A58: 7 | B58: JPM | C58: BAC | D58: 51565 | E58: 310.43 | F58: 53.52 | G58: 310.39896 | H58: 53.525352 | I58: 4.0755687 | J58: 1.010147 | K58: -0.032213381 | L58: 0.18874196 | M58: SHORT | N58: 14 | O58: signal | P58: 51579 | Q58: 310.47 | R58: 53.62 | S58: 0.077876738 | T58: 0.017585661 | U58: 0.013563351 | V58: 0.004020296 | W58: 0.0095430548 | X58: =WORKDAY(DATE(2025,8,2),INT(D58/390)) -> 46056 | Y58: =WORKDAY(DATE(2025,8,2),INT(P58/390)) -> 46056 | AB58: 45873.601 | AC58: 56 | AE58: =IF(ISNUMBER(AF58),DATE(YEAR(AF58),DAY(AF58),MONTH(AF58)),DATE(RIGHT(AF58,4),LEFT(AF58,2),MID(AF58,4,2))) -> 45950 | AF58: 10/20/2025 | AG58: 18.23
A59: 7 | B59: JPM | C59: BAC | D59: 52344 | E59: 304.59 | F59: 53.24 | G59: 304.62046 | H59: 53.234676 | I59: -4.9584327 | J59: 1.010147 | K59: 0.032831019 | L59: -0.18973459 | M59: LONG | N59: 12 | O59: signal | P59: 52356 | Q59: 306.605 | R59: 53.275 | S59: -0.14343059 | T59: 0.059513792 | U59: 0.055486218 | V59: 0.0040202919 | W59: 0.051465927 | X59: =WORKDAY(DATE(2025,8,2),INT(D59/390)) -> 46058 | Y59: =WORKDAY(DATE(2025,8,2),INT(P59/390)) -> 46058 | AB59: 45873.602 | AC59: 57 | AE59: =IF(ISNUMBER(AF59),DATE(YEAR(AF59),DAY(AF59),MONTH(AF59)),DATE(RIGHT(AF59,4),LEFT(AF59,2),MID(AF59,4,2))) -> 45951 | AF59: 10/21/2025 | AG59: 17.87
A60: 7 | B60: JPM | C60: BAC | D60: 53127 | E60: 306.26 | F60: 52.18 | G60: 306.22937 | H60: 52.185218 | I60: 4.6566311 | J60: 1.010147 | K60: -0.032651995 | L60: 0.19358892 | M60: SHORT | N60: 18 | O60: signal | P60: 53145 | Q60: 306.845 | R60: 52.46 | S60: 0.36883765 | T60: 0.03510348 | U60: 0.031075856 | V60: 0.004020296 | W60: 0.02705556 | X60: =WORKDAY(DATE(2025,8,2),INT(D60/390)) -> 46062 | Y60: =WORKDAY(DATE(2025,8,2),INT(P60/390)) -> 46062 | AB60: 45873.603 | AC60: 58 | AE60: =IF(ISNUMBER(AF60),DATE(YEAR(AF60),DAY(AF60),MONTH(AF60)),DATE(RIGHT(AF60,4),LEFT(AF60,2),MID(AF60,4,2))) -> 45952 | AF60: 10/22/2025 | AG60: 18.6
A61: 7 | B61: JPM | C61: BAC | D61: 53372 | E61: 305.2 | F61: 52.24 | G61: 305.23052 | H61: 52.234776 | I61: -3.7749882 | J61: 1.010147 | K61: 0.0327654 | L61: -0.19336657 | M61: LONG | N61: 11 | O61: signal | P61: 53383 | Q61: 306.63 | R61: 52.415 | S61: -0.25681307 | T61: 0.013015371 | U61: 0.0089870078 | V61: 0.0040202919 | W61: 0.0049667159 | X61: =WORKDAY(DATE(2025,8,2),INT(D61/390)) -> 46062 | Y61: =WORKDAY(DATE(2025,8,2),INT(P61/390)) -> 46062 | AB61: 45873.603 | AC61: 59 | AE61: =IF(ISNUMBER(AF61),DATE(YEAR(AF61),DAY(AF61),MONTH(AF61)),DATE(RIGHT(AF61,4),LEFT(AF61,2),MID(AF61,4,2))) -> 45953 | AF61: 10/23/2025 | AG61: 17.3
A62: 7 | B62: JPM | C62: BAC | D62: 53517 | E62: 307.62 | F62: 52.44 | G62: 307.58924 | H62: 52.445244 | I62: 4.0646379 | J62: 1.010147 | K62: -0.032507639 | L62: 0.1926291 | M62: SHORT | N62: 18 | O62: signal | P62: 53535 | Q62: 305.99 | R62: 52.08 | S62: 0.27083471 | T62: -0.016359023 | U62: -0.020367083 | V62: 0.004020296 | W62: -0.024387379 | X62: =WORKDAY(DATE(2025,8,2),INT(D62/390)) -> 46063 | Y62: =WORKDAY(DATE(2025,8,2),INT(P62/390)) -> 46063 | AB62: 45873.604 | AC62: 60 | AE62: =IF(ISNUMBER(AF62),DATE(YEAR(AF62),DAY(AF62),MONTH(AF62)),DATE(RIGHT(AF62,4),LEFT(AF62,2),MID(AF62,4,2))) -> 45954 | AF62: 10/24/2025 | AG62: 16.37
A63: 7 | B63: JPM | C63: BAC | D63: 53762 | E63: 309.985 | F63: 52.665 | G63: 309.954 | H63: 52.670266 | I63: 4.2167222 | J63: 1.010147 | K63: -0.032259625 | L63: 0.19180613 | M63: SHORT | N63: 29 | O63: signal | P63: 53791 | Q63: 310.69 | R63: 52.98 | S63: -0.45026262 | T63: 0.037675895 | U63: 0.033647285 | V63: 0.004020296 | W63: 0.029626989 | X63: =WORKDAY(DATE(2025,8,2),INT(D63/390)) -> 46063 | Y63: =WORKDAY(DATE(2025,8,2),INT(P63/390)) -> 46063 | AB63: 45873.605 | AC63: 61 | AE63: =IF(ISNUMBER(AF63),DATE(YEAR(AF63),DAY(AF63),MONTH(AF63)),DATE(RIGHT(AF63,4),LEFT(AF63,2),MID(AF63,4,2))) -> 45957 | AF63: 10/27/2025 | AG63: 15.79
A64: 7 | B64: JPM | C64: BAC | D64: 53907 | E64: 309.82 | F64: 53.09 | G64: 309.85098 | H64: 53.084691 | I64: -4.387853 | J64: 1.010147 | K64: 0.032276806 | L64: -0.19027067 | M64: LONG | N64: 22 | O64: signal | P64: 53929 | Q64: 306.24 | R64: 52.59 | S64: -0.28515227 | T64: -0.02041563 | U64: -0.024414856 | V64: 0.0040202919 | W64: -0.028435148 | X64: =WORKDAY(DATE(2025,8,2),INT(D64/390)) -> 46064 | Y64: =WORKDAY(DATE(2025,8,2),INT(P64/390)) -> 46064 | AB64: 45873.606 | AC64: 62 | AE64: =IF(ISNUMBER(AF64),DATE(YEAR(AF64),DAY(AF64),MONTH(AF64)),DATE(RIGHT(AF64,4),LEFT(AF64,2),MID(AF64,4,2))) -> 45958 | AF64: 10/28/2025 | AG64: 16.42
... A67: 8 | B67: JPM | C67: BAC | D67: 56633 | E67: 300.68 | F67: 49.88 | G67: 300.64993 | H67: 49.884988 | I67: 3.5957734 | J67: 0.96877792 | K67: -0.033257949 | L67: 0.19422172 | M67: SHORT | N67: 14 | O67: signal | P67: 56647 | Q67: 299.52 | R67: 49.82 | S67: 0.37164098 | T67: 0.026925917 | U67: 0.022993385 | V67: 0.0039375496 | W67: 0.019055835 | X67: =WORKDAY(DATE(2025,8,2),INT(D67/390)) -> 46073 | Y67: =WORKDAY(DATE(2025,8,2),INT(P67/390)) -> 46073 | AB67: 45873.608 | AC67: 65 | AE67: =IF(ISNUMBER(AF67),DATE(YEAR(AF67),DAY(AF67),MONTH(AF67)),DATE(RIGHT(AF67,4),LEFT(AF67,2),MID(AF67,4,2))) -> 45961 | AF67: 10/31/2025 | AG67: 17.44
A68: 8 | B68: JPM | C68: BAC | D68: 57037 | E68: 298.98 | F68: 50.105 | G68: 298.9501 | H68: 50.11001 | I68: 4.0336134 | J68: 0.96877792 | K68: -0.033447053 | L68: 0.19334955 | M68: SHORT | N68: 12 | O68: signal | P68: 57049 | Q68: 299.43 | R68: 50.2 | S68: 0.18966687 | T68: 0.0033170333 | U68: -0.00062386447 | V68: 0.0039375496 | W68: -0.0045614141 | X68: =WORKDAY(DATE(2025,8,2),INT(D68/390)) -> 46076 | Y68: =WORKDAY(DATE(2025,8,2),INT(P68/390)) -> 46076 | AB68: 45873.608 | AC68: 66 | AE68: =IF(ISNUMBER(AF68),DATE(YEAR(AF68),DAY(AF68),MONTH(AF68)),DATE(RIGHT(AF68,4),LEFT(AF68,2),MID(AF68,4,2))) -> 45964 | AF68: 45727 | AG68: 17.17
A69: 8 | B69: JPM | C69: BAC | D69: 57818 | E69: 286.095 | F69: 47.64 | G69: 286.06639 | H69: 47.644764 | I69: 4.8158247 | J69: 0.96877792 | K69: -0.034953425 | L69: 0.20335389 | M69: SHORT | N69: 13 | O69: signal | P69: 57831 | Q69: 284.53 | R69: 47.525 | S69: 0.3567766 | T69: 0.031316412 | U69: 0.027386665 | V69: 0.0039375496 | W69: 0.023449116 | X69: =WORKDAY(DATE(2025,8,2),INT(D69/390)) -> 46078 | Y69: =WORKDAY(DATE(2025,8,2),INT(P69/390)) -> 46078 | AB69: 45873.609 | AC69: 67 | AE69: =IF(ISNUMBER(AF69),DATE(YEAR(AF69),DAY(AF69),MONTH(AF69)),DATE(RIGHT(AF69,4),LEFT(AF69,2),MID(AF69,4,2))) -> 45965 | AF69: 45758 | AG69: 19
A70: 8 | B70: JPM | C70: BAC | D70: 58208 | E70: 290.255 | F70: 48.28 | G70: 290.28403 | H70: 48.275172 | I70: -4.345525 | J70: 0.96877792 | K70: 0.034452464 | L70: -0.20065823 | M70: LONG | N70: 14 | O70: signal | P70: 58222 | Q70: 289.8 | R70: 48.05 | S70: -0.45764643 | T70: 0.030475521 | U70: 0.026544148 | V70: 0.0039375621 | W70: 0.022606586 | X70: =WORKDAY(DATE(2025,8,2),INT(D70/390)) -> 46079 | Y70: =WORKDAY(DATE(2025,8,2),INT(P70/390)) -> 46079 | AB70: 45873.61 | AC70: 68 | AE70: =IF(ISNUMBER(AF70),DATE(YEAR(AF70),DAY(AF70),MONTH(AF70)),DATE(RIGHT(AF70,4),LEFT(AF70,2),MID(AF70,4,2))) -> 45966 | AF70: 45788 | AG70: 18.01
A71: 8 | B71: JPM | C71: BAC | D71: 58467 | E71: 291.815 | F71: 49.12 | G71: 291.84418 | H71: 49.115088 | I71: -3.7275362 | J71: 0.96877792 | K71: 0.034268286 | L71: -0.19722678 | M71: LONG | N71: 23 | O71: signal | P71: 58490 | Q71: 291.93 | R71: 49.035 | S71: -0.2378893 | T71: 0.020705129 | U71: 0.016768855 | V71: 0.0039375621 | W71: 0.012831293 | X71: =WORKDAY(DATE(2025,8,2),INT(D71/390)) -> 46079 | Y71: =WORKDAY(DATE(2025,8,2),INT(P71/390)) -> 46079 | AB71: 45873.61 | AC71: 69 | AE71: =IF(ISNUMBER(AF71),DATE(YEAR(AF71),DAY(AF71),MONTH(AF71)),DATE(RIGHT(AF71,4),LEFT(AF71,2),MID(AF71,4,2))) -> 45967 | AF71: 45819 | AG71: 19.5
A72: 8 | B72: JPM | C72: BAC | D72: 58598 | E72: 289.2 | F72: 48.39 | G72: 289.17108 | H72: 48.394839 | I72: 3.9891903 | J72: 0.96877792 | K72: -0.034578147 | L72: 0.20020209 | M72: SHORT | N72: 9 | O72: signal | P72: 58607 | Q72: 288.79 | R72: 48.505 | S72: -0.0091354239 | T72: 0.037200281 | U72: 0.03326184 | V72: 0.0039375496 | W72: 0.029324291 | X72: =WORKDAY(DATE(2025,8,2),INT(D72/390)) -> 46080 | Y72: =WORKDAY(DATE(2025,8,2),INT(P72/390)) -> 46080 | AB72: 45873.611 | AC72: 70 | AE72: =IF(ISNUMBER(AF72),DATE(YEAR(AF72),DAY(AF72),MONTH(AF72)),DATE(RIGHT(AF72,4),LEFT(AF72,2),MID(AF72,4,2))) -> 45968 | AF72: 45849 | AG72: 19.08
A73: 8 | B73: JPM | C73: BAC | D73: 58990 | E73: 282.65 | F73: 47.515 | G73: 282.62174 | H73: 47.519751 | I73: 3.5310655 | J73: 0.96877792 | K73: -0.035379445 | L73: 0.20388886 | M73: SHORT | N73: 13 | O73: signal | P73: 59003 | Q73: 281.19 | R73: 47.345 | S73: 0.24275072 | T73: 0.016992883 | U73: 0.013063958 | V73: 0.0039375496 | W73: 0.0091264087 | X73: =WORKDAY(DATE(2025,8,2),INT(D73/390)) -> 46083 | Y73: =WORKDAY(DATE(2025,8,2),INT(P73/390)) -> 46083 | AB73: 45873.612 | AC73: 71 | AE73: =IF(ISNUMBER(AF73),DATE(YEAR(AF73),DAY(AF73),MONTH(AF73)),DATE(RIGHT(AF73,4),LEFT(AF73,2),MID(AF73,4,2))) -> 45971 | AF73: 45941 | AG73: 17.6
A74: 9 | B74: JPM | C74: BAC | D74: 60161 | E74: 289.625 | F74: 47.65 | G74: 289.59604 | H74: 47.654765 | I74: 3.6825555 | J74: 0.81444705 | K74: -0.034527406 | L74: 0.17092278 | M74: SHORT | N74: 6 | O74: signal | P74: 60167 | Q74: 291 | R74: 48.02 | S74: 0.39314071 | T74: 0.015766245 | U74: 0.01212628 | V74: 0.003628857 | W74: 0.0084974227 | X74: =WORKDAY(DATE(2025,8,2),INT(D74/390)) -> 46086 | Y74: =WORKDAY(DATE(2025,8,2),INT(P74/390)) -> 46086 | AB74: 45873.613 | AC74: 72 | AE74: =IF(ISNUMBER(AF74),DATE(YEAR(AF74),DAY(AF74),MONTH(AF74)),DATE(RIGHT(AF74,4),LEFT(AF74,2),MID(AF74,4,2))) -> 45972 | AF74: 45972 | AG74: 17.28
A75: 9 | B75: JPM | C75: BAC | D75: 60506 | E75: 286.86 | F75: 47.475 | G75: 286.88869 | H75: 47.470253 | I75: -4.4312396 | J75: 0.81444705 | K75: 0.034860211 | L75: -0.17155283 | M75: LONG | N75: 13 | O75: signal | P75: 60519 | Q75: 286.845 | R75: 47.425 | S75: -0.23845242 | T75: 0.0080547382 | U75: 0.0044267542 | V75: 0.0036289312 | W75: 0.00079782298 | X75: =WORKDAY(DATE(2025,8,2),INT(D75/390)) -> 46087 | Y75: =WORKDAY(DATE(2025,8,2),INT(P75/390)) -> 46087 | AB75: 45873.613 | AC75: 73 | AE75: =IF(ISNUMBER(AF75),DATE(YEAR(AF75),DAY(AF75),MONTH(AF75)),DATE(RIGHT(AF75,4),LEFT(AF75,2),MID(AF75,4,2))) -> 45973 | AF75: 46002 | AG75: 17.51
A76: 9 | B76: JPM | C76: BAC | D76: 60554 | E76: 285.525 | F76: 47.375 | G76: 285.55355 | H76: 47.370263 | I76: -3.7668691 | J76: 0.81444705 | K76: 0.035023203 | L76: -0.17191494 | M76: LONG | N76: 12 | O76: signal | P76: 60566 | Q76: 286.9 | R76: 47.5 | S76: -0.36593962 | T76: 0.026667536 | U76: 0.023031677 | V76: 0.0036289312 | W76: 0.019402746 | X76: =WORKDAY(DATE(2025,8,2),INT(D76/390)) -> 46087 | Y76: =WORKDAY(DATE(2025,8,2),INT(P76/390)) -> 46087 | AB76: 45873.614 | AC76: 74 | AE76: =IF(ISNUMBER(AF76),DATE(YEAR(AF76),DAY(AF76),MONTH(AF76)),DATE(RIGHT(AF76,4),LEFT(AF76,2),MID(AF76,4,2))) -> 45974 | AF76: 11/13/2025 | AG76: 20
A77: 9 | B77: JPM | C77: BAC | D77: 61331 | E77: 288.13 | F77: 47.3 | G77: 288.15881 | H77: 47.29527 | I77: -4.7969416 | J77: 0.81444705 | K77: 0.034706556 | L77: -0.17218754 | M77: LONG | N77: 27 | O77: signal | P77: 61358 | Q77: 288.005 | R77: 47.21 | S77: 0.0056809218 | T77: 0.011158559 | U77: 0.0075316482 | V77: 0.0036289312 | W77: 0.003902717 | X77: =WORKDAY(DATE(2025,8,2),INT(D77/390)) -> 46091 | Y77: =WORKDAY(DATE(2025,8,2),INT(P77/390)) -> 46091 | AB77: 45873.615 | AC77: 75 | AE77: =IF(ISNUMBER(AF77),DATE(YEAR(AF77),DAY(AF77),MONTH(AF77)),DATE(RIGHT(AF77,4),LEFT(AF77,2),MID(AF77,4,2))) -> 45975 | AF77: 11/14/2025 | AG77: 19.83
A78: 9 | B78: JPM | C78: BAC | D78: 61711 | E78: 285.695 | F78: 46.91 | G78: 285.72357 | H78: 46.905309 | I78: -3.7985191 | J78: 0.81444705 | K78: 0.035002363 | L78: -0.17361907 | M78: LONG | N78: 26 | O78: signal | P78: 61737 | Q78: 292.12 | R78: 47.97 | S78: 0.010318509 | T78: 0.040853968 | U78: 0.037184181 | V78: 0.0036289312 | W78: 0.03355525 | X78: =WORKDAY(DATE(2025,8,2),INT(D78/390)) -> 46092 | Y78: =WORKDAY(DATE(2025,8,2),INT(P78/390)) -> 46092 | AB78: 45873.615 | AC78: 76 | AE78: =IF(ISNUMBER(AF78),DATE(YEAR(AF78),DAY(AF78),MONTH(AF78)),DATE(RIGHT(AF78,4),LEFT(AF78,2),MID(AF78,4,2))) -> 45978 | AF78: 11/17/2025 | AG78: 22.38
A79: 9 | B79: JPM | C79: BAC | D79: 62112 | E79: 286.98 | F79: 47.35 | G79: 287.0087 | H79: 47.345265 | I79: -4.3256654 | J79: 0.81444705 | K79: 0.034845634 | L79: -0.17200571 | M79: LONG | N79: 18 | O79: signal | P79: 62130 | Q79: 288.71 | R79: 47.64 | S79: -0.34533234 | T79: 0.01040129 | U79: 0.0067613793 | V79: 0.0036289312 | W79: 0.0031324481 | X79: =WORKDAY(DATE(2025,8,2),INT(D79/390)) -> 46093 | Y79: =WORKDAY(DATE(2025,8,2),INT(P79/390)) -> 46093 | AB79: 45873.616 | AC79: 77 | AE79: =IF(ISNUMBER(AF79),DATE(YEAR(AF79),DAY(AF79),MONTH(AF79)),DATE(RIGHT(AF79,4),LEFT(AF79,2),MID(AF79,4,2))) -> 45979 | AF79: 11/18/2025 | AG79: 24.69
A80: 9 | B80: JPM | C80: BAC | D80: 62589 | E80: 295.59 | F80: 48.66 | G80: 295.56044 | H80: 48.664866 | I80: 3.5881352 | J80: 0.81444705 | K80: -0.033830644 | L80: 0.16737506 | M80: SHORT | N80: 8 | O80: signal | P80: 62597 | Q80: 294.86 | R80: 48.585 | S80: 0.082929969 | T80: 0.01214324 | U80: 0.0085180712 | V80: 0.003628857 | W80: 0.0048892142 | X80: =WORKDAY(DATE(2025,8,2),INT(D80/390)) -> 46094 | Y80: =WORKDAY(DATE(2025,8,2),INT(P80/390)) -> 46094 | AB80: 45873.617 | AC80: 78 | AE80: =IF(ISNUMBER(AF80),DATE(YEAR(AF80),DAY(AF80),MONTH(AF80)),DATE(RIGHT(AF80,4),LEFT(AF80,2),MID(AF80,4,2))) -> 45980 | AF80: 11/19/2025 | AG80: 23.66
A81: 9 | B81: JPM | C81: BAC | D81: 62894 | E81: 293.85 | F81: 48.805 | G81: 293.87939 | H81: 48.80012 | I81: -4.2488124 | J81: 0.81444705 | K81: 0.034030968 | L81: -0.16687779 | M81: LONG | N81: 13 | O81: signal | P81: 62907 | Q81: 294.78 | R81: 48.835 | S81: -0.49528239 | T81: 0.026642467 | U81: 0.023009907 | V81: 0.0036289312 | W81: 0.019380976 | X81: =WORKDAY(DATE(2025,8,2),INT(D81/390)) -> 46097 | Y81: =WORKDAY(DATE(2025,8,2),INT(P81/390)) -> 46097 | AB81: 45873.617 | AC81: 79 | AE81: =IF(ISNUMBER(AF81),DATE(YEAR(AF81),DAY(AF81),MONTH(AF81)),DATE(RIGHT(AF81,4),LEFT(AF81,2),MID(AF81,4,2))) -> 45981 | AF81: 11/20/2025 | AG81: 26.42
A82: 10 | B82: USB | C82: PNC | D82: 63459 | E82: 51.03 | F82: 203 | G82: 51.024897 | H82: 203.0203 | I82: 3.5523459 | J82: 0.90418155 | K82: -0.19596316 | L82: 0.044540963 | M82: SHORT | N82: 18 | O82: signal | P82: 63477 | Q82: 50.975 | R82: 203.17 | S82: 0.13381963 | T82: 0.018349937 | U82: 0.014541895 | V82: 0.0038083439 | W82: 0.010733551 | X82: =WORKDAY(DATE(2025,8,2),INT(D82/390)) -> 46098 | Y82: =WORKDAY(DATE(2025,8,2),INT(P82/390)) -> 46098 | AB82: 45873.618 | AC82: 80 | AE82: =IF(ISNUMBER(AF82),DATE(YEAR(AF82),DAY(AF82),MONTH(AF82)),DATE(RIGHT(AF82,4),LEFT(AF82,2),MID(AF82,4,2))) -> 45982 | AF82: 11/21/2025 | AG82: 23.43
A83: 10 | B83: USB | C83: PNC | D83: 64254 | E83: 51.725 | F83: 205.765 | G83: 51.719828 | H83: 205.78558 | I83: 3.8820923 | J83: 0.90418155 | K83: -0.19333011 | L83: 0.043942437 | M83: SHORT | N83: 4 | O83: signal | P83: 64258 | Q83: 51.835 | R83: 206.93 | S83: 0.21192775 | T83: 0.029926627 | U83: 0.026111018 | V83: 0.0038083439 | W83: 0.022302674 | X83: =WORKDAY(DATE(2025,8,2),INT(D83/390)) -> 46100 | Y83: =WORKDAY(DATE(2025,8,2),INT(P83/390)) -> 46100 | AB83: 45873.619 | AC83: 81 | AE83: =IF(ISNUMBER(AF83),DATE(YEAR(AF83),DAY(AF83),MONTH(AF83)),DATE(RIGHT(AF83,4),LEFT(AF83,2),MID(AF83,4,2))) -> 45985 | AF83: 11/24/2025 | AG83: 20.52
A84: 10 | B84: USB | C84: PNC | D84: 64722 | E84: 52.865 | F84: 210.84 | G84: 52.870286 | H84: 210.81892 | I84: -3.8590103 | J84: 0.90418155 | K84: 0.18916107 | L84: -0.042884725 | M84: LONG | N84: 4 | O84: signal | P84: 64726 | Q84: 52.88 | R84: 210.47 | S84: 0.054271451 | T84: 0.018704764 | U84: 0.014897704 | V84: 0.0038083823 | W84: 0.011089322 | X84: =WORKDAY(DATE(2025,8,2),INT(D84/390)) -> 46101 | Y84: =WORKDAY(DATE(2025,8,2),INT(P84/390)) -> 46101 | AB84: 45873.619 | AC84: 82 | AE84: =IF(ISNUMBER(AF84),DATE(YEAR(AF84),DAY(AF84),MONTH(AF84)),DATE(RIGHT(AF84,4),LEFT(AF84,2),MID(AF84,4,2))) -> 45986 | AF84: 11/25/2025 | AG84: 18.56
A85: 10 | B85: USB | C85: PNC | D85: 65242 | E85: 53.325 | F85: 211.72 | G85: 53.319668 | H85: 211.74117 | I85: 3.5283095 | J85: 0.90418155 | K85: -0.1875293 | L85: 0.042706478 | M85: SHORT | N85: 9 | O85: signal | P85: 65251 | Q85: 53.27 | R85: 212.32 | S85: 0.40382194 | T85: 0.035937998 | U85: 0.032128104 | V85: 0.0038083439 | W85: 0.02831976 | X85: =WORKDAY(DATE(2025,8,2),INT(D85/390)) -> 46105 | Y85: =WORKDAY(DATE(2025,8,2),INT(P85/390)) -> 46105 | AB85: 45873.62 | AC85: 83 | AE85: =IF(ISNUMBER(AF85),DATE(YEAR(AF85),DAY(AF85),MONTH(AF85)),DATE(RIGHT(AF85,4),LEFT(AF85,2),MID(AF85,4,2))) -> 45987 | AF85: 11/26/2025 | AG85: 17.19
A86: 10 | B86: USB | C86: PNC | D86: 65779 | E86: 53.425 | F86: 213.31 | G86: 53.419657 | H86: 213.33133 | I86: 3.5378143 | J86: 0.90418155 | K86: -0.18717829 | L86: 0.042388146 | M86: SHORT | N86: 27 | O86: signal | P86: 65806 | Q86: 53.395 | R86: 213.23 | S86: 0.46336471 | T86: 0.0022242969 | U86: -0.0015831655 | V86: 0.0038083439 | W86: -0.0053915095 | X86: =WORKDAY(DATE(2025,8,2),INT(D86/390)) -> 46106 | Y86: =WORKDAY(DATE(2025,8,2),INT(P86/390)) -> 46106 | AB86: 45873.621 | AC86: 84 | AE86: =IF(ISNUMBER(AF86),DATE(YEAR(AF86),DAY(AF86),MONTH(AF86)),DATE(RIGHT(AF86,4),LEFT(AF86,2),MID(AF86,4,2))) -> 45988 | AF86: 11/27/2025 | AG86: 17.21
A87: 10 | B87: USB | C87: PNC | D87: 65872 | E87: 53.575 | F87: 213.33 | G87: 53.569643 | H87: 213.35133 | I87: 3.633571 | J87: 0.90418155 | K87: -0.18665422 | L87: 0.042384172 | M87: SHORT | N87: 5 | O87: signal | P87: 65877 | Q87: 53.51 | R87: 213.78 | S87: -0.42482071 | T87: 0.031205402 | U87: 0.027396345 | V87: 0.0038083439 | W87: 0.023588001 | X87: =WORKDAY(DATE(2025,8,2),INT(D87/390)) -> 46106 | Y87: =WORKDAY(DATE(2025,8,2),INT(P87/390)) -> 46106 | AB87: 45873.622 | AC87: 85 | AE87: =IF(ISNUMBER(AF87),DATE(YEAR(AF87),DAY(AF87),MONTH(AF87)),DATE(RIGHT(AF87,4),LEFT(AF87,2),MID(AF87,4,2))) -> 45989 | AF87: 11/28/2025 | AG87: 16.35
A88: 10 | B88: USB | C88: PNC | D88: 66010 | E88: 53.77 | F88: 214.595 | G88: 53.764623 | H88: 214.61646 | I88: 3.6411829 | J88: 0.90418155 | K88: -0.18597731 | L88: 0.042134325 | M88: SHORT | N88: 18 | O88: signal | P88: 66028 | Q88: 55.5 | R88: 221.56 | S88: 0.26064238 | T88: -0.028275173 | U88: -0.032145057 | V88: 0.0038083439 | W88: -0.035953401 | X88: =WORKDAY(DATE(2025,8,2),INT(D88/390)) -> 46107 | Y88: =WORKDAY(DATE(2025,8,2),INT(P88/390)) -> 46107 | AB88: 45873.622 | AC88: 86 | AE88: =IF(ISNUMBER(AF88),DATE(YEAR(AF88),DAY(AF88),MONTH(AF88)),DATE(RIGHT(AF88,4),LEFT(AF88,2),MID(AF88,4,2))) -> 45992 | AF88: 45669 | AG88: 17.24
A89: 10 | B89: USB | C89: PNC | D89: 66538 | E89: 56.18 | F89: 222.24 | G89: 56.174382 | H89: 222.26222 | I89: 4.0678942 | J89: 0.90418155 | K89: -0.17799929 | L89: 0.040684915 | M89: SHORT | N89: 13 | O89: signal | P89: 66551 | Q89: 56.18 | R89: 222.67 | S89: 0.38411161 | T89: 0.017494513 | U89: 0.013684401 | V89: 0.0038083439 | W89: 0.0098760569 | X89: =WORKDAY(DATE(2025,8,2),INT(D89/390)) -> 46108 | Y89: =WORKDAY(DATE(2025,8,2),INT(P89/390)) -> 46108 | AB89: 45873.623 | AC89: 87 | AE89: =IF(ISNUMBER(AF89),DATE(YEAR(AF89),DAY(AF89),MONTH(AF89)),DATE(RIGHT(AF89,4),LEFT(AF89,2),MID(AF89,4,2))) -> 45993 | AF89: 45700 | AG89: 16.59
A90: 11 | B90: USB | C90: PNC | D90: 67199 | E90: 55.06 | F90: 219.55 | G90: 55.065506 | H90: 219.52804 | I90: -3.842663 | J90: 0.93445707 | K90: 0.18162005 | L90: -0.042562381 | M90: LONG | N90: 4 | O90: signal | P90: 67203 | Q90: 55.06 | R90: 218.84 | S90: 0.13244998 | T90: 0.030219291 | U90: 0.026353398 | V90: 0.0038689273 | W90: 0.022484471 | X90: =WORKDAY(DATE(2025,8,2),INT(D90/390)) -> 46112 | Y90: =WORKDAY(DATE(2025,8,2),INT(P90/390)) -> 46112 | AB90: 45873.624 | AC90: 88 | AE90: =IF(ISNUMBER(AF90),DATE(YEAR(AF90),DAY(AF90),MONTH(AF90)),DATE(RIGHT(AF90,4),LEFT(AF90,2),MID(AF90,4,2))) -> 45994 | AF90: 45728 | AG90: 16.08
A91: 11 | B91: USB | C91: PNC | D91: 67526 | E91: 56.06 | F91: 220.795 | G91: 56.054394 | H91: 220.81708 | I91: 3.6632249 | J91: 0.93445707 | K91: -0.17838031 | L91: 0.042322384 | M91: SHORT | N91: 2 | O91: signal | P91: 67528 | Q91: 56.055 | R91: 221.02 | S91: 0.12602292 | T91: 0.010414438 | U91: 0.0065446607 | V91: 0.003868901 | W91: 0.0026757597 | X91: =WORKDAY(DATE(2025,8,2),INT(D91/390)) -> 46113 | Y91: =WORKDAY(DATE(2025,8,2),INT(P91/390)) -> 46113 | AB91: 45873.624 | AC91: 89 | AE91: =IF(ISNUMBER(AF91),DATE(YEAR(AF91),DAY(AF91),MONTH(AF91)),DATE(RIGHT(AF91,4),LEFT(AF91,2),MID(AF91,4,2))) -> 45995 | AF91: 45759 | AG91: 15.78
A92: 11 | B92: USB | C92: PNC | D92: 67596 | E92: 55.86 | F92: 220.74 | G92: 55.865586 | H92: 220.71793 | I92: -3.6861653 | J92: 0.93445707 | K92: 0.17901898 | L92: -0.042332929 | M92: LONG | N92: 25 | O92: signal | P92: 67621 | Q92: 55.34 | R92: 219.47 | S92: -0.18402809 | T92: -0.039327048 | U92: -0.043181277 | V92: 0.0038689273 | W92: -0.047050204 | X92: =WORKDAY(DATE(2025,8,2),INT(D92/390)) -> 46113 | Y92: =WORKDAY(DATE(2025,8,2),INT(P92/390)) -> 46113 | AB92: 45873.625 | AC92: 90 | AE92: =IF(ISNUMBER(AF92),DATE(YEAR(AF92),DAY(AF92),MONTH(AF92)),DATE(RIGHT(AF92,4),LEFT(AF92,2),MID(AF92,4,2))) -> 45996 | AF92: 45789 | AG92: 15.41
A93: 11 | B93: USB | C93: PNC | D93: 67988 | E93: 56.38 | F93: 224.095 | G93: 56.385638 | H93: 224.07259 | I93: -4.8642061 | J93: 0.93445707 | K93: 0.17736786 | L93: -0.041699149 | M93: LONG | N93: 33 | O93: signal | P93: 68021 | Q93: 55.935 | R93: 219.91 | S93: 0.49306683 | T93: 0.09558224 | U93: 0.091738669 | V93: 0.0038689273 | W93: 0.087869742 | X93: =WORKDAY(DATE(2025,8,2),INT(D93/390)) -> 46114 | Y93: =WORKDAY(DATE(2025,8,2),INT(P93/390)) -> 46114 | AB93: 45873.626 | AC93: 91 | AE93: =IF(ISNUMBER(AF93),DATE(YEAR(AF93),DAY(AF93),MONTH(AF93)),DATE(RIGHT(AF93,4),LEFT(AF93,2),MID(AF93,4,2))) -> 45999 | AF93: 45881 | AG93: 16.66
A94: 11 | B94: USB | C94: PNC | D94: 68382 | E94: 55.565 | F94: 222.875 | G94: 55.570557 | H94: 222.85271 | I94: -3.5660628 | J94: 0.93445707 | K94: 0.17996941 | L94: -0.041927407 | M94: LONG | N94: 10 | O94: signal | P94: 68392 | Q94: 56.09 | R94: 223.16 | S94: -0.37483929 | T94: 0.082534627 | U94: 0.078655069 | V94: 0.0038689273 | W94: 0.074786142 | X94: =WORKDAY(DATE(2025,8,2),INT(D94/390)) -> 46115 | Y94: =WORKDAY(DATE(2025,8,2),INT(P94/390)) -> 46115 | AB94: 45873.626 | AC94: 92 | AE94: =IF(ISNUMBER(AF94),DATE(YEAR(AF94),DAY(AF94),MONTH(AF94)),DATE(RIGHT(AF94,4),LEFT(AF94,2),MID(AF94,4,2))) -> 46000 | AF94: 45912 | AG94: 16.93
A95: 11 | B95: USB | C95: PNC | D95: 69317 | E95: 57.375 | F95: 226.42 | G95: 57.369262 | H95: 226.44264 | I95: 3.6364574 | J95: 0.93445707 | K95: -0.17429194 | L95: 0.04127096 | M95: SHORT | N95: 2 | O95: signal | P95: 69319 | Q95: 57.25 | R95: 226.3 | S95: 0.20311599 | T95: 0.016833977 | U95: 0.012967737 | V95: 0.003868901 | W95: 0.0090988359 | X95: =WORKDAY(DATE(2025,8,2),INT(D95/390)) -> 46119 | Y95: =WORKDAY(DATE(2025,8,2),INT(P95/390)) -> 46119 | AB95: 45873.627 | AC95: 93 | AE95: =IF(ISNUMBER(AF95),DATE(YEAR(AF95),DAY(AF95),MONTH(AF95)),DATE(RIGHT(AF95,4),LEFT(AF95,2),MID(AF95,4,2))) -> 46001 | AF95: 45942 | AG95: 15.77
A96: 11 | B96: USB | C96: PNC | D96: 69392 | E96: 57.23 | F96: 227.22 | G96: 57.235723 | H96: 227.19728 | I96: -3.6486711 | J96: 0.93445707 | K96: 0.17473353 | L96: -0.041125652 | M96: LONG | N96: 8 | O96: signal | P96: 69400 | Q96: 57.215 | R96: 226.755 | S96: 0.35772578 | T96: 0.016502425 | U96: 0.012635686 | V96: 0.0038689273 | W96: 0.0087667585 | X96: =WORKDAY(DATE(2025,8,2),INT(D96/390)) -> 46119 | Y96: =WORKDAY(DATE(2025,8,2),INT(P96/390)) -> 46119 | AB96: 45873.628 | AC96: 94 | AE96: =IF(ISNUMBER(AF96),DATE(YEAR(AF96),DAY(AF96),MONTH(AF96)),DATE(RIGHT(AF96,4),LEFT(AF96,2),MID(AF96,4,2))) -> 46002 | AF96: 45973 | AG96: 14.85
A97: 11 | B97: USB | C97: PNC | D97: 69500 | E97: 57.235 | F97: 227.77 | G97: 57.240724 | H97: 227.74722 | I97: -3.7803757 | J97: 0.93445707 | K97: 0.17471827 | L97: -0.041026346 | M97: LONG | N97: 18 | O97: signal | P97: 69518 | Q97: 57.21 | R97: 227.52 | S97: -0.3124889 | T97: 0.0058886297 | U97: 0.002021178 | V97: 0.0038689273 | W97: -0.0018477492 | X97: =WORKDAY(DATE(2025,8,2),INT(D97/390)) -> 46120 | Y97: =WORKDAY(DATE(2025,8,2),INT(P97/390)) -> 46120 | AB97: 45873.628 | AC97: 95 | AE97: =IF(ISNUMBER(AF97),DATE(YEAR(AF97),DAY(AF97),MONTH(AF97)),DATE(RIGHT(AF97,4),LEFT(AF97,2),MID(AF97,4,2))) -> 46003 | AF97: 46003 | AG97: 15.74
A98: 11 | B98: USB | C98: PNC | D98: 70545 | E98: 56.67 | F98: 225.825 | G98: 56.675667 | H98: 225.80242 | I98: -3.5201154 | J98: 0.93445707 | K98: 0.17646021 | L98: -0.0413797 | M98: LONG | N98: 9 | O98: signal | P98: 70554 | Q98: 56.58 | R98: 224.85 | S98: 0.0086757078 | T98: 0.024463789 | U98: 0.020600497 | V98: 0.0038689273 | W98: 0.01673157 | X98: =WORKDAY(DATE(2025,8,2),INT(D98/390)) -> 46122 | Y98: =WORKDAY(DATE(2025,8,2),INT(P98/390)) -> 46122 | AB98: 45873.629 | AC98: 96 | AE98: =IF(ISNUMBER(AF98),DATE(YEAR(AF98),DAY(AF98),MONTH(AF98)),DATE(RIGHT(AF98,4),LEFT(AF98,2),MID(AF98,4,2))) -> 46006 | AF98: 12/15/2025 | AG98: 16.5
A99: 11 | B99: USB | C99: PNC | D99: 70726 | E99: 56.59 | F99: 223.49 | G99: 56.584341 | H99: 223.51235 | I99: 4.7001284 | J99: 0.93445707 | K99: -0.17670967 | L99: 0.041812031 | M99: SHORT | N99: 9 | O99: signal | P99: 70735 | Q99: 56.47 | R99: 223.91 | S99: 0.21187709 | T99: 0.038766213 | U99: 0.034897663 | V99: 0.003868901 | W99: 0.031028762 | X99: =WORKDAY(DATE(2025,8,2),INT(D99/390)) -> 46125 | Y99: =WORKDAY(DATE(2025,8,2),INT(P99/390)) -> 46125 | AB99: 45873.63 | AC99: 97 | AE99: =IF(ISNUMBER(AF99),DATE(YEAR(AF99),DAY(AF99),MONTH(AF99)),DATE(RIGHT(AF99,4),LEFT(AF99,2),MID(AF99,4,2))) -> 46007 | AF99: 12/16/2025 | AG99: 16.48
A100: 12 | B100: USB | C100: PNC | D100: 71114 | E100: 55.95 | F100: 220.35 | G100: 55.944405 | H100: 220.37204 | I100: 3.8584048 | J100: 0.94405449 | K100: -0.17873101 | L100: 0.042843408 | M100: SHORT | N100: 7 | O100: signal | P100: 71121 | Q100: 56.1 | R100: 221.92 | S100: -0.2046109 | T100: 0.040454499 | U100: 0.036556982 | V100: 0.0038880978 | W100: 0.032668885 | X100: =WORKDAY(DATE(2025,8,2),INT(D100/390)) -> 46126 | Y100: =WORKDAY(DATE(2025,8,2),INT(P100/390)) -> 46126 | AB100: 45873.631 | AC100: 98 | AE100: =IF(ISNUMBER(AF100),DATE(YEAR(AF100),DAY(AF100),MONTH(AF100)),DATE(RIGHT(AF100,4),LEFT(AF100,2),MID(AF100,4,2))) -> 46008 | AF100: 12/17/2025 | AG100: 17.62
A101: 12 | B101: USB | C101: PNC | D101: 71504 | E101: 56.55 | F101: 223.04 | G101: 56.544345 | H101: 223.0623 | I101: 3.7118362 | J101: 0.94405449 | K101: -0.17683466 | L101: 0.04232669 | M101: SHORT | N101: 12 | O101: signal | P101: 71516 | Q101: 56.58 | R101: 223.355 | S101: 0.28678401 | T101: 0.0080278675 | U101: 0.0041378947 | V101: 0.0038880978 | W101: 0.00024979695 | X101: =WORKDAY(DATE(2025,8,2),INT(D101/390)) -> 46127 | Y101: =WORKDAY(DATE(2025,8,2),INT(P101/390)) -> 46127 | AB101: 45873.631 | AC101: 99 | AE101: =IF(ISNUMBER(AF101),DATE(YEAR(AF101),DAY(AF101),MONTH(AF101)),DATE(RIGHT(AF101,4),LEFT(AF101,2),MID(AF101,4,2))) -> 46009 | AF101: 12/18/2025 | AG101: 16.87
A102: 12 | B102: USB | C102: PNC | D102: 71896 | E102: 56.18 | F102: 221.73 | G102: 56.185618 | H102: 221.70783 | I102: -3.7173685 | J102: 0.94405449 | K102: 0.17799929 | L102: -0.04257676 | M102: LONG | N102: 1 | O102: signal | P102: 71897 | Q102: 56.42 | R102: 221.73 | S102: 0.30732377 | T102: 0.042719829 | U102: 0.038827448 | V102: 0.0038881202 | W102: 0.034939328 | X102: =WORKDAY(DATE(2025,8,2),INT(D102/390)) -> 46128 | Y102: =WORKDAY(DATE(2025,8,2),INT(P102/390)) -> 46128 | AB102: 45873.632 | AC102: 100 | AE102: =IF(ISNUMBER(AF102),DATE(YEAR(AF102),DAY(AF102),MONTH(AF102)),DATE(RIGHT(AF102,4),LEFT(AF102,2),MID(AF102,4,2))) -> 46010 | AF102: 12/19/2025 | AG102: 14.91
...

Sheet capital utilisation
B2: only 2% of time are we holding any position

Sheet Analysis
L1: Exit timestamp | M1: Cumulative Gross PnL | N1: Cumulative Slipped PnL | O1: Cumulative Net PnL | Q1: min holding minutes | R1: max holding minutes | S1: Mean Net PnL | T1: Number of trades
B2: Rough Analysis of the baseline strategy | J2: Figures | L2: =Trades!P2 -> 24214 | M2: =Trades!T2 -> 0.024154984 | N2: =Trades!U2 -> 0.020822539 | O2: =Trades!W2 -> 0.017487745 | Q2: 0 | R2: 3 | S2: =AVERAGEIFS(Trades!W:W,Trades!N:N,">="&Q2,Trades!N:N,"<="&R2) -> 0.028497814 | T2: =COUNTIFS(Trades!N:N,">="&Q2,Trades!N:N,"<="&R2) -> 11
L3: =Trades!P3 -> 24606 | M3: =M2+Trades!T3 -> 0.067822224 | N3: =N2+Trades!U3 -> 0.061157159 | O3: =O2+Trades!W3 -> 0.054487572 | Q3: 4 | R3: 7 | S3: =AVERAGEIFS(Trades!W:W,Trades!N:N,">="&Q3,Trades!N:N,"<="&R3) -> 0.024845937 | T3: =COUNTIFS(Trades!N:N,">="&Q3,Trades!N:N,"<="&R3) -> 25
B4: Column1 | C4: Gross | D4: Slipped | E4: Net (Transaction costs) | L4: =Trades!P4 -> 24848 | M4: =M3+Trades!T4 -> 0.072054022 | N4: =N3+Trades!U4 -> 0.062055967 | O4: =O3+Trades!W4 -> 0.052051586 | Q4: 8 | R4: 11 | S4: =AVERAGEIFS(Trades!W:W,Trades!N:N,">="&Q4,Trades!N:N,"<="&R4) -> 0.022591354 | T4: =COUNTIFS(Trades!N:N,">="&Q4,Trades!N:N,"<="&R4) -> 21
B5: Overall PnL | C5: =SUM(Trades!T2:T9652) -> 1.6777784 | D5: =SUM(Trades!U2:U9652) -> 1.1888885 | E5: =SUM(Trades!W2:W9652) -> 0.70017553 | L5: =Trades!P5 -> 24996 | M5: =M4+Trades!T5 -> 0.10989766 | N5: =N4+Trades!U5 -> 0.096564379 | O5: =O4+Trades!W5 -> 0.083225071 | Q5: 12 | R5: 15 | S5: =AVERAGEIFS(Trades!W:W,Trades!N:N,">="&Q5,Trades!N:N,"<="&R5) -> 0.014078891 | T5: =COUNTIFS(Trades!N:N,">="&Q5,Trades!N:N,"<="&R5) -> 20
B6: Mean PnL | C6: =AVERAGE(Trades!T:T) -> 0.012710442 | D6: =AVERAGE(Trades!U:U) -> 0.0090067312 | E6: =AVERAGE(Trades!W:W) -> 0.0053043601 | L6: =Trades!P6 -> 25392 | M6: =M5+Trades!T6 -> 0.14071719 | N6: =N5+Trades!U6 -> 0.12404061 | O6: =O5+Trades!W6 -> 0.10736638 | Q6: 16 | R6: 19 | S6: =AVERAGEIFS(Trades!W:W,Trades!N:N,">="&Q6,Trades!N:N,"<="&R6) -> -0.0045318448 | T6: =COUNTIFS(Trades!N:N,">="&Q6,Trades!N:N,"<="&R6) -> 16
B7: Median PnL | C7: =MEDIAN(Trades!T:T) -> 0.0161695 | D7: =MEDIAN(Trades!U:U) -> 0.012618928 | E7: =MEDIAN(Trades!W:W) -> 0.0091126223 | L7: =Trades!P7 -> 25731 | M7: =M6+Trades!T7 -> 0.12499991 | N7: =N6+Trades!U7 -> 0.10498528 | O7: =O6+Trades!W7 -> 0.084976254 | Q7: 20 | R7: 23 | S7: =AVERAGEIFS(Trades!W:W,Trades!N:N,">="&Q7,Trades!N:N,"<="&R7) -> -0.014353217 | T7: =COUNTIFS(Trades!N:N,">="&Q7,Trades!N:N,"<="&R7) -> 11
B8: Max drawdown | C8: =MIN(Trades!T:T) -> -0.087068107 | D8: =MIN(Trades!U:U) -> -0.091191822 | E8: =MIN(Trades!W:W) -> -0.095289891 | L8: =Trades!P8 -> 25758 | M8: =M7+Trades!T8 -> 0.13581127 | N8: =N7+Trades!U8 -> 0.11246473 | O8: =O7+Trades!W8 -> 0.089120912 | Q8: 24 | R8: 27 | S8: =AVERAGEIFS(Trades!W:W,Trades!N:N,">="&Q8,Trades!N:N,"<="&R8) -> -0.023937849 | T8: =COUNTIFS(Trades!N:N,">="&Q8,Trades!N:N,"<="&R8) -> 14
B9: Biggest Winner | C9: =MAX(Trades!T:T) -> 0.09558224 | D9: =MAX(Trades!U:U) -> 0.091738669 | E9: =MAX(Trades!W:W) -> 0.087869742 | L9: =Trades!P9 -> 26942 | M9: =M8+Trades!T9 -> 0.16614087 | N9: =N8+Trades!U9 -> 0.13944671 | O9: =O8+Trades!W9 -> 0.11276796 | Q9: 28 | R9: 34 | S9: =AVERAGEIFS(Trades!W:W,Trades!N:N,">="&Q9,Trades!N:N,"<="&R9) -> -0.016174126 | T9: =COUNTIFS(Trades!N:N,">="&Q9,Trades!N:N,"<="&R9) -> 8
B10: Win rate | C10: =COUNTIF(Trades!T:T,">0")/(COUNTIF(Trades!T:T,">0")+COUNTIF(Trades!T:T,"<0")) -> 0.74242424 | D10: =COUNTIF(Trades!U:U,">0")/(COUNTIF(Trades!U:U,">0")+COUNTIF(Trades!U:U,"<0")) -> 0.68939394 | E10: =COUNTIF(Trades!W:W,">0")/(COUNTIF(Trades!W:W,">0")+COUNTIF(Trades!W:W,"<0")) -> 0.65151515 | L10: =Trades!P10 -> 27332 | M10: =M9+Trades!T10 -> 0.19014346 | N10: =N9+Trades!U10 -> 0.1601233 | O10: =O9+Trades!W10 -> 0.13010976 | Q10: 35 | R10: 40 | S10: =AVERAGEIFS(Trades!W:W,Trades!N:N,">="&Q10,Trades!N:N,"<="&R10) -> -0.045173001 | T10: =COUNTIFS(Trades!N:N,">="&Q10,Trades!N:N,"<="&R10) -> 4
B11: Profit Factor | C11: =SUMIF(Trades!T:T,">0",Trades!T:T)/ABS(SUMIF(Trades!T:T,"<0",Trades!T:T)) -> 2.7198882 | D11: =SUMIF(Trades!U:U,">0",Trades!U:U)/ABS(SUMIF(Trades!U:U,"<0",Trades!U:U)) -> 2.0670501 | E11: =SUMIF(Trades!W:W,">0",Trades!W:W)/ABS(SUMIF(Trades!W:W,"<0",Trades!W:W)) -> 1.5483743 | L11: =Trades!P11 -> 27725 | M11: =M9+Trades!T11 -> 0.1839358 | N11: =N9+Trades!U11 -> 0.15388456 | O11: =O9+Trades!W11 -> 0.12387088
L12: =Trades!P12 -> 28504 | M12: =M11+Trades!T12 -> 0.22037352 | N12: =N11+Trades!U12 -> 0.18701962 | O12: =O11+Trades!W12 -> 0.15369821 | Q12: 41 | R12: 47 | S12: =AVERAGEIFS(Trades!W:W,Trades!N:N,">="&Q12,Trades!N:N,"<="&R12) -> -0.032076202 | T12: =COUNTIFS(Trades!N:N,">="&Q12,Trades!N:N,"<="&R12) -> 1
B13: Column1 | C13: Column2 | L13: =Trades!P20 -> 32218 | M13: =M12+Trades!T20 -> 0.24252519 | N13: =N12+Trades!U20 -> 0.20569578 | O13: =O12+Trades!W20 -> 0.16889716
B14: Number of Trades | C14: =COUNTA(Trades!A:A)-1 -> 132 | L14: =Trades!P13 -> 28639 | M14: =M13+Trades!T13 -> 0.27504551 | N14: =N13+Trades!U13 -> 0.23490715 | O14: =O13+Trades!W13 -> 0.19480065
B15: Mean holding time | C15: =AVERAGE(Trades!N:N) -> 14.909091 | L15: =Trades!P21 -> 32631 | M15: =M14+Trades!T21 -> 0.2861718 | N15: =N14+Trades!U21 -> 0.24256171 | O15: =O14+Trades!W21 -> 0.19897799
B16: Median holding time | C16: =MEDIAN(Trades!N:N) -> 13 | L16: =Trades!P22 -> 33015 | M16: =M15+Trades!T22 -> 0.28845596 | N16: =N15+Trades!U22 -> 0.24136004 | O16: =O15+Trades!W22 -> 0.19429921
B17: Max holding time | C17: =MAX(Trades!N:N) -> 48 | L17: =Trades!P23 -> 34564 | M17: =M16+Trades!T23 -> 0.32044895 | N17: =N16+Trades!U23 -> 0.26987915 | O17: =O16+Trades!W23 -> 0.2193412
L18: =Trades!P14 -> 28735 | M18: =M17+Trades!T14 -> 0.31659487 | N18: =N17+Trades!U14 -> 0.26271845 | O18: =O17+Trades!W14 -> 0.20887263
B19: Column1 | C19: Positive | D19: Negative | L19: =Trades!P15 -> 29599 | M19: =M18+Trades!T15 -> 0.34331243 | N19: =N18+Trades!U15 -> 0.28613087 | O19: =O18+Trades!W15 -> 0.22897731
B20: Mean entry z score | C20: =AVERAGEIF(Trades!I:I,">0",Trades!I:I) -> 3.9561553 | D20: =AVERAGEIF(Trades!I:I,"<0",Trades!I:I) -> -3.9684066 | L20: =Trades!P24 -> 35310 | M20: =M19+Trades!T24 -> 0.40384151 | N20: =N19+Trades!U24 -> 0.34317567 | O20: =O19+Trades!W24 -> 0.2825449
B21: Median entry z score | C21: {=MEDIAN(_xlfn._xlws.FILTER(Trades!I:I,Trades!I:I>0))} -> 3.8036455 | D21: {=MEDIAN(_xlfn._xlws.FILTER(Trades!I:I,Trades!I:I<0))} -> -3.842663 | L21: =Trades!P25 -> 36516 | M21: =M20+Trades!T25 -> 0.47932709 | N21: =N20+Trades!U25 -> 0.4153039 | O21: =O20+Trades!W25 -> 0.35132217
B22: max entry z score | C22: =_xlfn.MAXIFS(Trades!I:I,Trades!I:I,">0") -> 5.0316061 | D22: =_xlfn.MINIFS(Trades!I:I,Trades!I:I,"<0") -> -4.9584327 | L22: =Trades!P16 -> 29691 | M22: =M21+Trades!T16 -> 0.45336904 | N22: =N21+Trades!U16 -> 0.3860304 | O22: =O21+Trades!W16 -> 0.31874093
B23: Mean exit z score | C23: =AVERAGEIF(Trades!S:S,">0",Trades!S:S) -> 0.25490692 | D23: =AVERAGEIF(Trades!S:S,"<0",Trades!S:S) -> -0.29230905 | L23: =Trades!P26 -> 37315 | M23: =M22+Trades!T26 -> 0.50270533 | N23: =N22+Trades!U26 -> 0.43200223 | O23: =O22+Trades!W26 -> 0.3613618
B24: Median exit z score | C24: {=MEDIAN(_xlfn._xlws.FILTER(Trades!S:S,Trades!S:S>0))} -> 0.26064238 | D24: {=MEDIAN(_xlfn._xlws.FILTER(Trades!S:S,Trades!S:S<0))} -> -0.30297441 | L24: =Trades!P27 -> 37701 | M24: =M23+Trades!T27 -> 0.49734205 | N24: =N23+Trades!U27 -> 0.42328199 | O24: =O23+Trades!W27 -> 0.34929073
B25: max exit z score | C25: =_xlfn.MAXIFS(Trades!S:S,Trades!S:S,">0") -> 0.49471769 | D25: =_xlfn.MINIFS(Trades!S:S,Trades!S:S,"<0") -> -0.49528239 | L25: =Trades!P17 -> 30065 | M25: =M24+Trades!T17 -> 0.52951182 | N25: =N24+Trades!U17 -> 0.4521378 | O25: =O24+Trades!W17 -> 0.37483867
G26: 1 | H26: Edge is there, but wiped out by costs | L26: =Trades!P18 -> 31227 | M26: =M25+Trades!T18 -> 0.55117499 | N26: =N25+Trades!U18 -> 0.47048627 | O26: =O25+Trades!W18 -> 0.38987926
B27: Column1 | C27: Long | D27: Short | E27: Signal | F27: Forced | L27: =Trades!P19 -> 32055 | M27: =M26+Trades!T19 -> 0.47538483 | N27: =N26+Trades!U19 -> 0.39120428 | O27: =O26+Trades!W19 -> 0.30712016
B28: PnL (gross) | C28: =SUMIF(Trades!M:M,"LONG",Trades!T:T) -> 0.97162033 | D28: =SUMIF(Trades!M:M,"SHORT",Trades!T:T) -> 0.70615807 | E28: =SUMIF(Trades!O:O,"Signal",Trades!T:T) -> 1.6777784 | F28: =SUMIF(Trades!O:O,"Forced",Trades!T:T) -> 0 | L28: =Trades!P28 -> 38206 | M28: =M27+Trades!T28 -> 0.4748745 | N28: =N27+Trades!U28 -> 0.38734149 | O28: =O27+Trades!W28 -> 0.29990654
B29: Number | C29: =COUNTIF(Trades!M:M,"LONG") -> 59 | D29: =COUNTIF(Trades!M:M,"SHORT") -> 73 | E29: =COUNTIF(Trades!O:O,"Signal") -> 132 | F29: =COUNTIF(Trades!O:O,"Forced") -> 0 | L29: =Trades!P35 -> 41209 | M29: =M28+Trades!T35 -> 0.49073841 | N29: =N28+Trades!U35 -> 0.39989924 | O29: =O28+Trades!W35 -> 0.30915769
L30: =Trades!P44 -> 45725 | M30: =M29+Trades!T44 -> 0.52559472 | N30: =N29+Trades!U44 -> 0.43153142 | O30: =O29+Trades!W44 -> 0.33757596
B31: min Holding time | C31: Max Holding time | D31: Win rate | L31: =Trades!P52 -> 49254 | M31: =M30+Trades!T52 -> 0.46916174 | N31: =N30+Trades!U52 -> 0.37099936 | O31: =O30+Trades!W52 -> 0.27294585
B32: 0 | C32: 3 | D32: =COUNTIFS(Trades!N:N,">="&B32,Trades!N:N,"<="&C32,Trades!T:T,">0")/(COUNTIFS(Trades!N:N,">="&B32,Trades!N:N,"<="&C32,Trades!T:T,">0")+COUNTIFS(Trades!N:N,">="&B32,Trades!N:N,"<="&C32,Trades!T:T,"<0")) -> 1 | L32: =Trades!P36 -> 41414 | M32: =M31+Trades!T36 -> 0.51367876 | N32: =N31+Trades!U36 -> 0.41221505 | O32: =O31+Trades!W36 -> 0.31085493
B33: 4 | C33: 7 | D33: =COUNTIFS(Trades!N:N,">="&B33,Trades!N:N,"<="&C33,Trades!T:T,">0")/(COUNTIFS(Trades!N:N,">="&B33,Trades!N:N,"<="&C33,Trades!T:T,">0")+COUNTIFS(Trades!N:N,">="&B33,Trades!N:N,"<="&C33,Trades!T:T,"<0")) -> 1 | L33: =Trades!P45 -> 45815 | M33: =M32+Trades!T45 -> 0.52546273 | N33: =N32+Trades!U45 -> 0.42078442 | O33: =O32+Trades!W45 -> 0.31621039
B34: 8 | C34: 11 | D34: =COUNTIFS(Trades!N:N,">="&B34,Trades!N:N,"<="&C34,Trades!T:T,">0")/(COUNTIFS(Trades!N:N,">="&B34,Trades!N:N,"<="&C34,Trades!T:T,">0")+COUNTIFS(Trades!N:N,">="&B34,Trades!N:N,"<="&C34,Trades!T:T,"<0")) -> 1 | L34: =Trades!P29 -> 38333 | M34: =M33+Trades!T29 -> 0.52315276 | N34: =N33+Trades!U29 -> 0.41512422 | O34: =O33+Trades!W29 -> 0.30719923
B35: 12 | C35: 15 | D35: =COUNTIFS(Trades!N:N,">="&B35,Trades!N:N,"<="&C35,Trades!T:T,">0")/(COUNTIFS(Trades!N:N,">="&B35,Trades!N:N,"<="&C35,Trades!T:T,">0")+COUNTIFS(Trades!N:N,">="&B35,Trades!N:N,"<="&C35,Trades!T:T,"<0")) -> 0.95 | L35: =Trades!P30 -> 38674 | M35: =M34+Trades!T30 -> 0.53153941 | N35: =N34+Trades!U30 -> 0.42015813 | O35: =O34+Trades!W30 -> 0.30888218
B36: 16 | C36: 1000000 | D36: =COUNTIFS(Trades!N:N,">="&B36,Trades!N:N,"<="&C36,Trades!T:T,">0")/(COUNTIFS(Trades!N:N,">="&B36,Trades!N:N,"<="&C36,Trades!T:T,">0")+COUNTIFS(Trades!N:N,">="&B36,Trades!N:N,"<="&C36,Trades!T:T,"<0")) -> 0.4 | L36: =Trades!P37 -> 41825 | M36: =M35+Trades!T37 -> 0.50904697 | N36: =N35+Trades!U37 -> 0.39437512 | O36: =O35+Trades!W37 -> 0.27979244
L37: =Trades!P53 -> 49618 | M37: =M36+Trades!T53 -> 0.54804889 | N37: =N36+Trades!U53 -> 0.42928753 | O37: =O36+Trades!W53 -> 0.31060679
L38: =Trades!P54 -> 50031 | M38: =M37+Trades!T54 -> 0.46098078 | N38: =N37+Trades!U54 -> 0.33809571 | O38: =O37+Trades!W54 -> 0.2153169
B39: Conclusion: | L39: =Trades!P31 -> 39068 | M39: =M38+Trades!T31 -> 0.47693261 | N39: =N38+Trades!U31 -> 0.35069788 | O39: =O38+Trades!W31 -> 0.22456824
B40: does the multiple pairs strategy improve diversification and risk adjusted returns instead of just gross exposure? | L40: =Trades!P32 -> 39472 | M40: =M39+Trades!T32 -> 0.47582357 | N40: =N39+Trades!U32 -> 0.34624443 | O40: =O39+Trades!W32 -> 0.21676384
L41: =Trades!P46 -> 46118 | M41: =M40+Trades!T46 -> 0.45693679 | N41: =N40+Trades!U46 -> 0.32414408 | O41: =O40+Trades!W46 -> 0.19144942
L42: =Trades!P55 -> 50395 | M42: =M41+Trades!T55 -> 0.49327563 | N42: =N41+Trades!U55 -> 0.35638847 | O42: =O41+Trades!W55 -> 0.21959575
L43: =Trades!P47 -> 47299 | M43: =M42+Trades!T47 -> 0.47780685 | N43: =N42+Trades!U47 -> 0.33770395 | O43: =O42+Trades!W47 -> 0.19769716
L44: =Trades!P38 -> 42181 | M44: =M43+Trades!T38 -> 0.51060777 | N44: =N43+Trades!U38 -> 0.36719465 | O44: =O43+Trades!W38 -> 0.22388112
L45: =Trades!P48 -> 47667 | M45: =M44+Trades!T48 -> 0.49456383 | N45: =N44+Trades!U48 -> 0.34702419 | O45: =O44+Trades!W48 -> 0.19961261
G46: 2 | H46: shorter trades are significantly more profitiable | L46: =Trades!P39 -> 43338 | M46: =M45+Trades!T39 -> 0.50590984 | N46: =N45+Trades!U39 -> 0.35506438 | O46: =O45+Trades!W39 -> 0.20434621 | Y46: 3 | Z46: most trades are short, but with a long tail
L47: =Trades!P40 -> 44024 | M47: =M46+Trades!T40 -> 0.48713161 | N47: =N46+Trades!U40 -> 0.33306905 | O47: =O46+Trades!W40 -> 0.17913696
L48: =Trades!P56 -> 50810 | M48: =M47+Trades!T56 -> 0.47044858 | N48: =N47+Trades!U56 -> 0.3122924 | O48: =O47+Trades!W56 -> 0.15426224
L49: =Trades!P49 -> 47973 | M49: =M48+Trades!T49 -> 0.49732504 | N49: =N48+Trades!U49 -> 0.33506751 | O49: =O48+Trades!W49 -> 0.1729393
L50: =Trades!P57 -> 51195 | M50: =M49+Trades!T57 -> 0.46069016 | N50: =N49+Trades!U57 -> 0.29435342 | O50: =O49+Trades!W57 -> 0.12812714
L51: =Trades!P50 -> 48243 | M51: =M50+Trades!T50 -> 0.46697561 | N51: =N50+Trades!U50 -> 0.29654296 | O51: =O50+Trades!W50 -> 0.12621863
L52: =Trades!P58 -> 51579 | M52: =M51+Trades!T58 -> 0.48456128 | N52: =N51+Trades!U58 -> 0.31010631 | O52: =O51+Trades!W58 -> 0.13576168
L53: =Trades!P33 -> 39854 | M53: =M52+Trades!T33 -> 0.50094845 | N53: =N52+Trades!U33 -> 0.32319507 | O53: =O52+Trades!W33 -> 0.14554384
L54: =Trades!P41 -> 44544 | M54: =M53+Trades!T41 -> 0.53893485 | N54: =N53+Trades!U41 -> 0.35797766 | O54: =O53+Trades!W41 -> 0.17711252
L55: =Trades!P59 -> 52356 | M55: =M54+Trades!T59 -> 0.59844865 | N55: =N54+Trades!U59 -> 0.41346388 | O55: =O54+Trades!W59 -> 0.22857845
L56: =Trades!P51 -> 48835 | M56: =M55+Trades!T51 -> 0.64121863 | N56: =N55+Trades!U51 -> 0.45214315 | O56: =O55+Trades!W51 -> 0.26315965
L57: =Trades!P60 -> 53145 | M57: =M56+Trades!T60 -> 0.67632211 | N57: =N56+Trades!U60 -> 0.48321901 | O57: =O56+Trades!W60 -> 0.29021521
L58: =Trades!P42 -> 44948 | M58: =M57+Trades!T42 -> 0.69826334 | N58: =N57+Trades!U42 -> 0.50193431 | O58: =O57+Trades!W42 -> 0.30571644
L59: =Trades!P61 -> 53383 | M59: =M58+Trades!T61 -> 0.71127871 | N59: =N58+Trades!U61 -> 0.51092131 | O59: =O58+Trades!W61 -> 0.31068315
L60: =Trades!P34 -> 41036 | M60: =M59+Trades!T34 -> 0.64125925 | N60: =N59+Trades!U34 -> 0.43756985 | O60: =O59+Trades!W34 -> 0.23402508
L61: =Trades!P43 -> 45534 | M61: =M60+Trades!T43 -> 0.64625082 | N61: =N60+Trades!U43 -> 0.43934883 | O61: =O60+Trades!W43 -> 0.23259015
L62: =Trades!P62 -> 53535 | M62: =M61+Trades!T62 -> 0.6298918 | N62: =N61+Trades!U62 -> 0.41898175 | O62: =O61+Trades!W62 -> 0.20820277
L63: =Trades!P63 -> 53791 | M63: =M62+Trades!T63 -> 0.6675677 | N63: =N62+Trades!U63 -> 0.45262903 | O63: =O62+Trades!W63 -> 0.23782976
L64: =Trades!P74 -> 60167 | M64: =M63+Trades!T74 -> 0.68333394 | N64: =N63+Trades!U74 -> 0.46475531 | O64: =O63+Trades!W74 -> 0.24632718
L65: =Trades!P85 -> 65251 | M65: =M64+Trades!T85 -> 0.71927194 | N65: =N64+Trades!U85 -> 0.49688342 | O65: =O64+Trades!W85 -> 0.27464695
L66: =Trades!P75 -> 60519 | M66: =M65+Trades!T75 -> 0.72732668 | N66: =N65+Trades!U75 -> 0.50131017 | O66: =O65+Trades!W75 -> 0.27544477
L67: =Trades!P64 -> 53929 | M67: =M66+Trades!T64 -> 0.70691105 | N67: =N66+Trades!U64 -> 0.47689532 | O67: =O66+Trades!W64 -> 0.24700962
L68: =Trades!P86 -> 65806 | M68: =M67+Trades!T86 -> 0.70913534 | N68: =N67+Trades!U86 -> 0.47531215 | O68: =O67+Trades!W86 -> 0.24161811
L69: =Trades!P65 -> 54324 | M69: =M68+Trades!T65 -> 0.64670938 | N69: =N68+Trades!U65 -> 0.40887975 | O69: =O68+Trades!W65 -> 0.17116541
L70: =Trades!P76 -> 60566 | M70: =M69+Trades!T76 -> 0.67337691 | N70: =N69+Trades!U76 -> 0.43191143 | O70: =O69+Trades!W76 -> 0.19056816
L71: =Trades!P77 -> 61358 | M71: =M70+Trades!T77 -> 0.68453547 | N71: =N70+Trades!U77 -> 0.43944307 | O71: =O70+Trades!W77 -> 0.19447088
L72: =Trades!P78 -> 61737 | M72: =M71+Trades!T78 -> 0.72538944 | N72: =N71+Trades!U78 -> 0.47662726 | O72: =O71+Trades!W78 -> 0.22802613
L73: =Trades!P87 -> 65877 | M73: =M72+Trades!T87 -> 0.75659484 | N73: =N72+Trades!U87 -> 0.5040236 | O73: =O72+Trades!W87 -> 0.25161413
L74: =Trades!P66 -> 55503 | M74: =M73+Trades!T66 -> 0.72022367 | N74: =N73+Trades!U66 -> 0.46375348 | O74: =O73+Trades!W66 -> 0.20740646
L75: =Trades!P67 -> 56647 | M75: =M74+Trades!T67 -> 0.74714959 | N75: =N74+Trades!U67 -> 0.48674687 | O75: =O74+Trades!W67 -> 0.22646229
L76: =Trades!P88 -> 66028 | M76: =M75+Trades!T88 -> 0.71887442 | N76: =N75+Trades!U88 -> 0.45460181 | O76: =O75+Trades!W88 -> 0.19050889
L77: =Trades!P79 -> 62130 | M77: =M76+Trades!T79 -> 0.72927571 | N77: =N76+Trades!U79 -> 0.46136319 | O77: =O76+Trades!W79 -> 0.19364134
L78: =Trades!P68 -> 57049 | M78: =M77+Trades!T68 -> 0.73259274 | N78: =N77+Trades!U68 -> 0.46073932 | O78: =O77+Trades!W68 -> 0.18907993
L79: =Trades!P80 -> 62597 | M79: =M78+Trades!T80 -> 0.74473598 | N79: =N78+Trades!U80 -> 0.4692574 | O79: =O78+Trades!W80 -> 0.19396914
L80: =Trades!P69 -> 57831 | M80: =M79+Trades!T69 -> 0.77605239 | N80: =N79+Trades!U69 -> 0.49664406 | O80: =O79+Trades!W69 -> 0.21741826
L81: =Trades!P89 -> 66551 | M81: =M80+Trades!T89 -> 0.7935469 | N81: =N80+Trades!U89 -> 0.51032846 | O81: =O80+Trades!W89 -> 0.22729431
L82: =Trades!P90 -> 67203 | M82: =M81+Trades!T90 -> 0.8237662 | N82: =N81+Trades!U90 -> 0.53668186 | O82: =O81+Trades!W90 -> 0.24977879
L83: =Trades!P81 -> 62907 | M83: =M82+Trades!T81 -> 0.85040866 | N83: =N82+Trades!U81 -> 0.55969177 | O83: =O82+Trades!W81 -> 0.26915976
L84: =Trades!P70 -> 58222 | M84: =M83+Trades!T70 -> 0.88088418 | N84: =N83+Trades!U70 -> 0.58623592 | O84: =O83+Trades!W70 -> 0.29176635
L85: =Trades!P91 -> 67528 | M85: =M84+Trades!T91 -> 0.89129862 | N85: =N84+Trades!U91 -> 0.59278058 | O85: =O84+Trades!W91 -> 0.29444211
L86: =Trades!P71 -> 58490 | M86: =M85+Trades!T71 -> 0.91200375 | N86: =N85+Trades!U71 -> 0.60954943 | O86: =O85+Trades!W71 -> 0.3072734
L87: =Trades!P72 -> 58607 | M87: =M86+Trades!T72 -> 0.94920403 | N87: =N86+Trades!U72 -> 0.64281127 | O87: =O86+Trades!W72 -> 0.33659769
L88: =Trades!P92 -> 67621 | M88: =M87+Trades!T92 -> 0.90987698 | N88: =N87+Trades!U92 -> 0.59963 | O88: =O87+Trades!W92 -> 0.28954749
L89: =Trades!P82 -> 63477 | M89: =M88+Trades!T82 -> 0.92822692 | N89: =N88+Trades!U82 -> 0.61417189 | O89: =O88+Trades!W82 -> 0.30028104
L90: =Trades!P83 -> 64258 | M90: =M89+Trades!T83 -> 0.95815355 | N90: =N89+Trades!U83 -> 0.64028291 | O90: =O89+Trades!W83 -> 0.32258371
L91: =Trades!P73 -> 59003 | M91: =M90+Trades!T73 -> 0.97514643 | N91: =N90+Trades!U73 -> 0.65334687 | O91: =O90+Trades!W73 -> 0.33171012
L92: =Trades!P84 -> 64726 | M92: =M91+Trades!T84 -> 0.99385119 | N92: =N91+Trades!U84 -> 0.66824457 | O92: =O91+Trades!W84 -> 0.34279944
L93: =Trades!P93 -> 68021 | M93: =M92+Trades!T93 -> 1.0894334 | N93: =N92+Trades!U93 -> 0.75998324 | O93: =O92+Trades!W93 -> 0.43066918
L94: =Trades!P94 -> 68392 | M94: =M93+Trades!T94 -> 1.1719681 | N94: =N93+Trades!U94 -> 0.83863831 | O94: =O93+Trades!W94 -> 0.50545533
L95: =Trades!P105 -> 73088 | M95: =M94+Trades!T105 -> 1.1807444 | N95: =N94+Trades!U105 -> 0.84352021 | O95: =O94+Trades!W105 -> 0.50644911
L96: =Trades!P95 -> 69319 | M96: =M95+Trades!T95 -> 1.1975784 | N96: =N95+Trades!U95 -> 0.85648795 | O96: =O95+Trades!W95 -> 0.51554794
L97: =Trades!P106 -> 75628 | M97: =M96+Trades!T106 -> 1.1975933 | N97: =N96+Trades!U106 -> 0.85256657 | O97: =O96+Trades!W106 -> 0.50769654
L98: =Trades!P96 -> 69400 | M98: =M97+Trades!T96 -> 1.2140957 | N98: =N97+Trades!U96 -> 0.86520226 | O98: =O97+Trades!W96 -> 0.51646329
L99: =Trades!P97 -> 69518 | M99: =M98+Trades!T97 -> 1.2199843 | N99: =N98+Trades!U97 -> 0.86722343 | O99: =O98+Trades!W97 -> 0.51461554
L100: =Trades!P98 -> 70554 | M100: =M99+Trades!T98 -> 1.2444481 | N100: =N99+Trades!U98 -> 0.88782393 | O100: =O99+Trades!W98 -> 0.53134711
...

Sheet comparison with single pair
B2: Metric | C2: Value | J2: Daily PnL table
B3: Net P&L | C3: =SUM(Trades!W2:W9652) -> 0.70017553
B4: Number of trades | C4: =COUNTA(Trades!A:A)-1 -> 132 | J4: {=_xlfn.LET( _xlpm.dates,_xlfn.SEQUENCE(DATE(2026,8,2)-DATE(2025,8,2)+1,,DATE(2025,8,2)), _xlfn._xlws.FILTER(_xlpm.dates,WEEKDAY(_xlpm.dates,2)<=5) )} -> 45873 | K4: {=SUMIFS('trades edited'!$W$2:$W$100000,'trades edited'!$Y$2:$Y$100000,_xlfn.ANCHORARRAY(J4))} -> 0
B5: P&L/trade | C5: =AVERAGE(Trades!W:W) -> 0.0053043601 | J5: 45874 | K5: 0
B6: Daily P&L volatility | C6: =_xlfn.STDEV.S(_xlfn.ANCHORARRAY(K4)) -> 0.02256984 | J6: 45875 | K6: 0
B7: Sharpe-like measure | C7: =AVERAGE(_xlfn.ANCHORARRAY(K4))/_xlfn.STDEV.S(_xlfn.ANCHORARRAY(K4))*SQRT(252) -> 1.8941108 | J7: 45876 | K7: 0
B8: Max drawdown | C8: =MIN(Trades!W:W) -> -0.095289891 | J8: 45877 | K8: 0
B9: Max drawdown / total P&L | C9: =C8/C3 -> -0.13609429 | J9: 45880 | K9: 0
B10: Worst day | J10: 45881 | K10: 0
B11: Max concurrent positions | J11: 45882 | K11: 0
B12: Max gross exposure | J12: 45883 | K12: 0
J13: 45884 | K13: 0
J14: 45887 | K14: 0
J15: 45888 | K15: 0
B16: it seems like this strat might actually be WORSE for risk *potentially* than the single pair version. The main question now is how much capital we need to keep in reserves to avoid margin calling and liquidation. portfolio total P&L = cumulative realised P&L up to minute + total unrealised P&L at minute | J16: 45889 | K16: 0
J17: 45890 | K17: 0
J18: 45891 | K18: 0
J19: 45894 | K19: 0
J20: 45895 | K20: 0
J21: 45896 | K21: 0
J22: 45897 | K22: 0
J23: 45898 | K23: 0
J24: 45901 | K24: 0
J25: 45902 | K25: 0
J26: 45903 | K26: 0
J27: 45904 | K27: 0
J28: 45905 | K28: 0
... J263: 46234 | K263: 0
